Workbook
Name ChartCFADS: 决策看板!$E$121:INDEX(决策看板!$E$121:$E$151,核心参数输入!$B$9+1)
Name ChartCum: 决策看板!$G$121:INDEX(决策看板!$G$121:$G$151,核心参数输入!$B$9+1)
Name ChartDebt: 决策看板!$F$121:INDEX(决策看板!$F$121:$F$151,核心参数输入!$B$9+1)
Name ChartDiscounted: 决策看板!$H$121:INDEX(决策看板!$H$121:$H$151,核心参数输入!$B$9+1)
Name ChartOther: 决策看板!$D$121:INDEX(决策看板!$D$121:$D$151,核心参数输入!$B$9+1)
Name ChartRent: 决策看板!$C$121:INDEX(决策看板!$C$121:$C$151,核心参数输入!$B$9+1)
Name ChartSales: 决策看板!$B$121:INDEX(决策看板!$B$121:$B$151,核心参数输入!$B$9+1)
Name ChartYear: 决策看板!$A$121:INDEX(决策看板!$A$121:$A$151,核心参数输入!$B$9+1)

Sheet 使用说明
A2: 使用说明 · 模拟数据
A5: 模型用途 | B5: 拿地前的租售结合产业园学习测算。所有默认数据及投资阈值均为模拟值。年度模型覆盖第0年、第1—N年，最多30年；后续年末现金流，建设投资及运营作年度简化。
A9: 使用步骤 | B9: 1 在“核心参数输入”修改黄色单元格；2 同步调整建设和销售年度计划；3 在Excel中自动重算；4 查看“决策看板”的校验、指标及原因；5 在计算表核对各年变化。
A13: 工作表结构 | B13: 使用说明 → 核心参数输入 → 建筑面积与开发计划 → 投资与资金安排 → 销售与出租收入 → 运营成本与税费 → 融资与还本付息 → 利润与现金流 → 指标与情景测算 → 决策看板。
A17: 颜色与编辑 | B17: 浅黄色底蓝色文字＝手动输入；中性色＝公式及结果；绿色＝通过，红色＝未通过或待判断，灰色＝不适用。所有公式可查看编辑，无保护、宏和外部链接。
A21: 单位 | B21: 金额万元；面积平方米；地价、建安及售价元/平方米；租金元/平方米/月。面积×单价÷10000；年租金＝面积×月租金×12÷10000。百分比输入10%=0.10；出租率压力10个百分点输入10。
A25: 收益与资金条件 | B25: IRR越高越好，NPV≥0，回收期越短越好，DSCR越高越好。收益达标不代表资金充足：资本金总额度、资金缺口和到期本金也必须满足。NPV第0年不折现。
A29: 两类现金流 | B29: 项目投资现金流排除贷款、股东出资及全部本息、建设期融资费用，所得税按无融资利润；资本金现金流＝完整出资下留存后股东分配－按需股东投入。项目总投资另包含建设期融资费用。
A33: 状态说明 | B33: “无法计算”＝IRR无解或必要条件不足，不用0冒充；“测算期内未回收”＝对应累计现金流在期内没有由负转非负，视为未达标；“不适用”＝无贷款或未覆盖辅助稳定观察年等。必要收益指标无解时待判断。
A37: 建设与分摊 | B37: 土地第0年支付；其余非土地支出第1—K年按输入比例分配。建安、配套、前期、管理各范围不重叠；预备费以非土地上述成本为基数。共同开发成本按销售/持有经营面积比例分摊，非经营面积及地下成本一起分摊。
A41: 收入与免租 | B41: 销售部分出售前也不出租，出售后不再贡献租金；持有部分出租。年度销售占总可售面积比例，当年收款。出租年内面积视为全年占用，只对本年增加的出租面积扣一次免租，不模拟租户更替，故爬坡率不得下降。租金按收缴后现金口径确认收入，其他收入按实收租金比例。
A45: 税务与成本简化 | B45: 收入均为简化含税实收口径，销售及运营综合税费也按该口径；不建立增值税抵扣、土地增值税及复杂税制。所得税＝max(年度利润,0)×税率，不结转亏损。固定成本由持有部分承担，自K+1年即支付，空置不豁免；变动成本仅按持有收入；维护更新当年费用化并税前扣除，不重复资本化或折旧。
A49: 非现金成本 | B49: 销售成本按年度销售比例结转，未售保留存货；建设期间在建及存货按累计已支付成本显示。持有建筑非土地成本直线折旧，土地不折旧。融资利润将建设利息分摊至销售成本及持有折旧；项目口径剔除融资利息。建设成本只在支付年扣现金，结转与折旧不再次扣现金。
... A81: 生成与重算 | B81: 代码仅初始化默认示例；重新运行不读取或保留旧Excel中手改参数，同名文件自动加时间标识。Excel设置打开自动重算。可在Windows安装Excel后运行--recalculate；未实际重算的新文件有完整公式但缓存初始值不代表结果。验证详情见同目录“验证说明.md”。

Sheet 核心参数输入
A2: 核心参数输入 · 模拟数据
A5: 参数名称 | B5: 输入值 | C5: 单位 | D5: 说明
A6: 基础与建筑参数
A7: 项目名称 | B7: 模拟产业园 · 租售结合 | C7: 文本 | D7: 全部数据为虚构模拟数据
A8: 测算起始年份 | B8: 2026 | C8: 年 | D8: 第0年的日历年份；年度支出采用年末时点
A9: 测算期限 | B9: 20 | C9: 年 | D9: 实际范围第0年至第N年，预留至30年；须覆盖贷款到期
A10: 土地面积 | B10: 100000 | C10: 平方米 | D10: 地上面积＝土地面积×容积率
A11: 容积率 | B11: 1.5 | C11: 倍 | D11: 地上总建筑面积口径
A12: 地上可经营面积占比 | B12: 0.9 | C12: % | D12: 其余为公共及非经营空间；共同成本仍计入
A13: 地下建筑面积 | B13: 15000 | C13: 平方米 | D13: 地下空间不独立产生收入
A14: 可经营面积销售占比 | B14: 0.55 | C14: % | D14: 严格大于0且小于100%；销售部分出售前也不出租
A15: 出租占比（自动） | B15: =1-核心参数输入!$B$14 -> 0.45 | C15: % | D15: 自动＝1－销售占比
A16: 建设年限 | B16: 3 | C16: 年 | D16: 第1年至第K年；土地在第0年支付
A17: 销售开始年份 | B17: 4 | C17: 项目第几年 | D17: 必须晚于建设完成年；年度销售比例在下方输入
A18: 出租开始年份 | B18: 4 | C18: 项目第几年 | D18: 必须晚于建设完成年；运营固定成本从K+1年开始
A20: 投资参数
A21: 土地单价 | B21: 800 | C21: 元/平方米 | D21: 仅土地取得价款；不计入建筑折旧
A22: 地上单方建安成本 | B22: 2400 | C22: 元/平方米 | D22: 不含下列配套、前期、管理费用
A23: 地下单方建安成本 | B23: 3000 | C23: 元/平方米 | D23: 地下工程；不与地上重复
A24: 园区配套工程费用 | B24: 4500 | C24: 万元 | D24: 园区道路、管网、公共配套；不含建安主体
A25: 勘察设计咨询前期费用 | B25: 1800 | C25: 万元 | D25: 不含建安及管理费用
A26: 管理及其他建设费用 | B26: 2200 | C26: 万元 | D26: 建设管理等；不含融资利息和运营成本
A27: 预备费比例 | B27: 0.08 | C27: % | D27: 基数＝全部非土地建设费用（建安、配套、前期、管理）
A28: 初始运营周转资金 | B28: 500 | C28: 万元 | D28: K+1年投入，期末全额回收；不计入费用及折旧
A30: 销售参数
A31: 销售均价 | B31: 6500 | C31: 元/平方米 | D31: 简化含税成交/实收口径；销售当年全额收款
A32: 销售费用率 | B32: 0.025 | C32: % | D32: 销售回款×费用率
A33: 简化销售相关税费率 | B33: 0.08 | C33: % | D33: 含税回款×综合率；不另行建立增值税抵扣
A35: 出租参数
A36: 初始月租金 | B36: 26 | C36: 元/平方米/月 | D36: 出租首年价格；按12个月换算后除10000为万元
A37: 年租金增长率 | B37: 0.015 | C37: % | D37: 从出租开始年递增
A38: 出租第1年出租率 | B38: 0.5 | C38: % | D38: 全年占用面积比例；新增面积仅当年一次免租
A39: 出租第2年出租率 | B39: 0.7 | C39: % | D39: 前期爬坡参数集中输入
A40: 出租第3年出租率 | B40: 0.85 | C40: % | D40: 出租率须不下降；不模拟租户更替
A41: 第4年起稳定出租率 | B41: 0.9 | C41: % | D41: 稳定出租率直接驱动第4个出租年度以后
A42: 新增出租面积平均免租月数 | B42: 3 | C42: 月 | D42: 0—12月；同一面积不重复免租
A43: 租金收缴率 | B43: 0.98 | C43: % | D43: 实收租金，同时作为简化收入确认口径
A44: 其他经营收入比例 | B44: 0.05 | C44: % | D44: 实收租金×比例；属于持有经营收入
A46: 运营与税费参数
A47: 运营首年固定成本 | B47: 300 | C47: 万元/年 | D47: 仅持有部分：人员、管理、保险等；K+1年即承担
A48: 固定成本年度增长率 | B48: 0.02 | C48: % | D48: 自K+1年起递增，与是否出租无关
A49: 变动运营成本率 | B49: 0.12 | C49: % | D49: 实收租金及其他经营收入×比例；不含维护更新
A50: 年度维护更新支出 | B50: 180 | C50: 万元/年 | D50: K+1年起每年发生；费用化并当期税前扣除，不再折旧
A51: 简化运营相关税费率 | B51: 0.06 | C51: % | D51: 租金及其他经营收入×综合率；不另计复杂税种
A52: 企业所得税率 | B52: 0.25 | C52: % | D52: 年度正利润缴税；负利润不缴，不模拟亏损结转
A53: 持有建筑物折旧年限 | B53: 30 | C53: 年 | D53: K+1年起直线法；项目口径不含融资利息，资本金口径含资本化利息
A54: 建筑物残值率 | B54: 0.05 | C54: % | D54: 仅影响账面价值，不能自动变成现金收入
A56: 融资与资本金参数
A57: 贷款金额 | B57: 30000 | C57: 万元 | D57: 一笔贷款；按年度建设投资比例提款，不能超过非土地建设支出
A58: 贷款年利率 | B58: 0.042 | C58: % | D58: 利息＝（期初本金＋当年提款/2－当年还本/2）×利率
A59: 贷款期限 | B59: 10 | C59: 年 | D59: 从首次提款年算起：到期年＝首次提款年＋期限－1
A60: 开始偿还本金年份 | B60: 4 | C60: 项目第几年 | D60: 晚于建设完成年；到期前等额本金；不主动额外提前还款
A61: 可投入资本金总额度 | B61: 33000 | C61: 万元 | D61: 按需投入且不突破额度；缺口单列，不作为真实资金
A63: 期末处置参数
A64: 是否计入期末处置 | B64: 0 | C64: 0关闭/1开启 | D64: 默认关闭；仅处置持有物业，未售存货不自动变现
A65: 持有物业期末处置价值 | B65: 30000 | C65: 万元 | D65: 直接给定第N年的持有物业含税总售价，非账面值
A66: 期末处置费用率 | B66: 0.03 | C66: % | D66: 处置价×综合交易费用率（含简化交易税费）；处置净收益另纳入所得税
A68: 决策阈值（模拟判断标准，可自行修改）
A69: 项目税后IRR最低值 | B69: 0.08 | C69: % | D69: 模拟阈值，非实际投资标准
A70: 资本金IRR最低值 | B70: 0.1 | C70: % | D70: 资金不足时仅为完整出资的理论结果
A71: 项目折现率 | B71: 0.08 | C71: % | D71: 项目NPV及动态回收期折现率
A72: 资本金折现率 | B72: 0.1 | C72: % | D72: 资本金NPV折现率
A73: 静态投资回收期上限 | B73: 15 | C73: 年 | D73: 含第0年及建设期；项目投资现金流口径
A74: 动态投资回收期上限 | B74: 20 | C74: 年 | D74: 按项目折现率；测算期内未回收视为不达标
A75: 最低偿债覆盖倍数 | B75: 1.2 | C75: 倍 | D75: 仅统计建成以后存在本息偿付的年度
A77: 组合压力情景参数
A78: 销售价格下降比例 | B78: 0.1 | C78: % | D78: 基准售价×(1－下降比例)
A79: 租金下降比例 | B79: 0.1 | C79: % | D79: 基准各年租金×(1－下降比例)
A80: 出租率下降百分点 | B80: 10 | C80: 百分点 | D80: 10表示下降10个百分点，按10/100扣减，不是乘90%
A81: 非土地建设成本增加比例 | B81: 0.1 | C81: % | D81: 作用于建安、配套、前期、管理及对应预备费；土地不变
A82: 是否要求压力情景也通过 | B82: 0 | C82: 0否/1是 | D82: 默认仅观察；开启后两种情景都必须通过
A85: 年度计划：建设及销售比例均以项目总量为基数；年度索引为第0年至第30年
D87: 0 | E87: 1 | F87: 2 | G87: 3 | H87: 4 | I87: 5 | J87: 6 | K87: 7 | L87: 8 | M87: 9 | N87: 10 | O87: 11 | P87: 12 | Q87: 13 | R87: 14 | S87: 15 | T87: 16 | U87: 17 | V87: 18 | W87: 19 | X87: 20 | Y87: 21 | Z87: 22 | AA87: 23 | AB87: 24 | AC87: 25 | AD87: 26 | AE87: 27 | AF87: 28 | AG87: 29 | AH87: 30
A88: 年度非土地建设投资比例 | B88: 合计见看板 | C88: % | D88: 0 | E88: 0.3 | F88: 0.4 | G88: 0.3 | H88: 0 | I88: 0 | J88: 0 | K88: 0 | L88: 0 | M88: 0 | N88: 0 | O88: 0 | P88: 0 | Q88: 0 | R88: 0 | S88: 0 | T88: 0 | U88: 0 | V88: 0 | W88: 0 | X88: 0 | Y88: 0 | Z88: 0 | AA88: 0 | AB88: 0 | AC88: 0 | AD88: 0 | AE88: 0 | AF88: 0 | AG88: 0 | AH88: 0
A89: 年度销售比例 | B89: 合计见看板 | C89: % | D89: 0 | E89: 0 | F89: 0 | G89: 0 | H89: 0.3 | I89: 0.4 | J89: 0.3 | K89: 0 | L89: 0 | M89: 0 | N89: 0 | O89: 0 | P89: 0 | Q89: 0 | R89: 0 | S89: 0 | T89: 0 | U89: 0 | V89: 0 | W89: 0 | X89: 0 | Y89: 0 | Z89: 0 | AA89: 0 | AB89: 0 | AC89: 0 | AD89: 0 | AE89: 0 | AF89: 0 | AG89: 0 | AH89: 0
A92: 提示：调整建设/销售时点时，请同步调整黄色年度计划；出租率由出租模块的首3年及稳定期参数自动形成。

Sheet 建筑面积与开发计划
A2: 建筑面积与开发计划 · 模拟数据
A4: 项目年度 / 日历年份 | D4: =核心参数输入!D87 -> 0 | E4: =核心参数输入!E87 -> 1 | F4: =核心参数输入!F87 -> 2 | G4: =核心参数输入!G87 -> 3 | H4: =核心参数输入!H87 -> 4 | I4: =核心参数输入!I87 -> 5 | J4: =核心参数输入!J87 -> 6 | K4: =核心参数输入!K87 -> 7 | ... AH4: =核心参数输入!AH87 -> 30
D5: =核心参数输入!$B$8+D4 -> 2026 | E5: =核心参数输入!$B$8+E4 -> 2027 | F5: =核心参数输入!$B$8+F4 -> 2028 | G5: =核心参数输入!$B$8+G4 -> 2029 | H5: =核心参数输入!$B$8+H4 -> 2030 | I5: =核心参数输入!$B$8+I4 -> 2031 | J5: =核心参数输入!$B$8+J4 -> 2032 | K5: =核心参数输入!$B$8+K4 -> 2033 | ... AH5: =核心参数输入!$B$8+AH4 -> 2056
A6: 土地面积 | B6: =核心参数输入!$B$10 -> 100000 | C6: 平方米
A7: 地上建筑面积 | B7: =核心参数输入!$B$10*核心参数输入!$B$11 -> 150000 | C7: 平方米
A8: 地上可经营面积 | B8: =$B$7*核心参数输入!$B$12 -> 135000 | C8: 平方米
A9: 总可售面积 | B9: =$B$8*核心参数输入!$B$14 -> 74250 | C9: 平方米
A10: 总持有出租面积 | B10: =$B$8*核心参数输入!$B$15 -> 60750 | C10: 平方米
A11: 地下建筑面积 | B11: =核心参数输入!$B$13 -> 15000 | C11: 平方米
A18: 基准情景 · 年度开发与租售计划
A20: 建设分配比例 | B20: % | D20: =IF(D$4<=核心参数输入!$B$9,IF(AND(D$4>=1,D$4<=核心参数输入!$B$16),核心参数输入!D88,0),0) -> 0 | E20: =IF(E$4<=核心参数输入!$B$9,IF(AND(E$4>=1,E$4<=核心参数输入!$B$16),核心参数输入!E88,0),0) -> 0.3 | F20: =IF(F$4<=核心参数输入!$B$9,IF(AND(F$4>=1,F$4<=核心参数输入!$B$16),核心参数输入!F88,0),0) -> 0.4 | G20: =IF(G$4<=核心参数输入!$B$9,IF(AND(G$4>=1,G$4<=核心参数输入!$B$16),核心参数输入!G88,0),0) -> 0.3 | H20: =IF(H$4<=核心参数输入!$B$9,IF(AND(H$4>=1,H$4<=核心参数输入!$B$16),核心参数输入!H88,0),0) -> 0 | I20: =IF(I$4<=核心参数输入!$B$9,IF(AND(I$4>=1,I$4<=核心参数输入!$B$16),核心参数输入!I88,0),0) -> 0 | J20: =IF(J$4<=核心参数输入!$B$9,IF(AND(J$4>=1,J$4<=核心参数输入!$B$16),核心参数输入!J88,0),0) -> 0 | K20: =IF(K$4<=核心参数输入!$B$9,IF(AND(K$4>=1,K$4<=核心参数输入!$B$16),核心参数输入!K88,0),0) -> 0 | ... AH20: =IF(AH$4<=核心参数输入!$B$9,IF(AND(AH$4>=1,AH$4<=核心参数输入!$B$16),核心参数输入!AH88,0),0) -> 0
A21: 销售比例 | B21: % | D21: =IF(D$4<=核心参数输入!$B$9,IF(D$4>=核心参数输入!$B$17,核心参数输入!D89,0),0) -> 0 | E21: =IF(E$4<=核心参数输入!$B$9,IF(E$4>=核心参数输入!$B$17,核心参数输入!E89,0),0) -> 0 | F21: =IF(F$4<=核心参数输入!$B$9,IF(F$4>=核心参数输入!$B$17,核心参数输入!F89,0),0) -> 0 | G21: =IF(G$4<=核心参数输入!$B$9,IF(G$4>=核心参数输入!$B$17,核心参数输入!G89,0),0) -> 0 | H21: =IF(H$4<=核心参数输入!$B$9,IF(H$4>=核心参数输入!$B$17,核心参数输入!H89,0),0) -> 0.3 | I21: =IF(I$4<=核心参数输入!$B$9,IF(I$4>=核心参数输入!$B$17,核心参数输入!I89,0),0) -> 0.4 | J21: =IF(J$4<=核心参数输入!$B$9,IF(J$4>=核心参数输入!$B$17,核心参数输入!J89,0),0) -> 0.3 | K21: =IF(K$4<=核心参数输入!$B$9,IF(K$4>=核心参数输入!$B$17,核心参数输入!K89,0),0) -> 0 | ... AH21: =IF(AH$4<=核心参数输入!$B$9,IF(AH$4>=核心参数输入!$B$17,核心参数输入!AH89,0),0) -> 0
A22: 累计销售去化率 | B22: % | D22: =IF(D$4<=核心参数输入!$B$9,SUM($D21:D21),0) -> 0 | E22: =IF(E$4<=核心参数输入!$B$9,SUM($D21:E21),0) -> 0 | F22: =IF(F$4<=核心参数输入!$B$9,SUM($D21:F21),0) -> 0 | G22: =IF(G$4<=核心参数输入!$B$9,SUM($D21:G21),0) -> 0 | H22: =IF(H$4<=核心参数输入!$B$9,SUM($D21:H21),0) -> 0.3 | I22: =IF(I$4<=核心参数输入!$B$9,SUM($D21:I21),0) -> 0.7 | J22: =IF(J$4<=核心参数输入!$B$9,SUM($D21:J21),0) -> 1 | K22: =IF(K$4<=核心参数输入!$B$9,SUM($D21:K21),0) -> 1 | ... AH22: =IF(AH$4<=核心参数输入!$B$9,SUM($D21:AH21),0) -> 0
A23: 当年出售面积 | B23: 平方米 | D23: =IF(D$4<=核心参数输入!$B$9,D21*$B$9,0) -> 0 | E23: =IF(E$4<=核心参数输入!$B$9,E21*$B$9,0) -> 0 | F23: =IF(F$4<=核心参数输入!$B$9,F21*$B$9,0) -> 0 | G23: =IF(G$4<=核心参数输入!$B$9,G21*$B$9,0) -> 0 | H23: =IF(H$4<=核心参数输入!$B$9,H21*$B$9,0) -> 22275 | I23: =IF(I$4<=核心参数输入!$B$9,I21*$B$9,0) -> 29700 | J23: =IF(J$4<=核心参数输入!$B$9,J21*$B$9,0) -> 22275 | K23: =IF(K$4<=核心参数输入!$B$9,K21*$B$9,0) -> 0 | ... AH23: =IF(AH$4<=核心参数输入!$B$9,AH21*$B$9,0) -> 0
A24: 期末未售面积 | B24: 平方米 | D24: =IF(D$4<=核心参数输入!$B$9,$B$9*(1-D22),0) -> 74250 | E24: =IF(E$4<=核心参数输入!$B$9,$B$9*(1-E22),0) -> 74250 | F24: =IF(F$4<=核心参数输入!$B$9,$B$9*(1-F22),0) -> 74250 | G24: =IF(G$4<=核心参数输入!$B$9,$B$9*(1-G22),0) -> 74250 | H24: =IF(H$4<=核心参数输入!$B$9,$B$9*(1-H22),0) -> 51975 | I24: =IF(I$4<=核心参数输入!$B$9,$B$9*(1-I22),0) -> 22275 | J24: =IF(J$4<=核心参数输入!$B$9,$B$9*(1-J22),0) -> 0 | K24: =IF(K$4<=核心参数输入!$B$9,$B$9*(1-K22),0) -> 0 | ... AH24: =IF(AH$4<=核心参数输入!$B$9,$B$9*(1-AH22),0) -> 0
A25: 出租第几个年度 | B25: 年 | D25: =IF(D$4<=核心参数输入!$B$9,IF(D$4>=核心参数输入!$B$18,D$4-核心参数输入!$B$18+1,0),0) -> 0 | E25: =IF(E$4<=核心参数输入!$B$9,IF(E$4>=核心参数输入!$B$18,E$4-核心参数输入!$B$18+1,0),0) -> 0 | F25: =IF(F$4<=核心参数输入!$B$9,IF(F$4>=核心参数输入!$B$18,F$4-核心参数输入!$B$18+1,0),0) -> 0 | G25: =IF(G$4<=核心参数输入!$B$9,IF(G$4>=核心参数输入!$B$18,G$4-核心参数输入!$B$18+1,0),0) -> 0 | H25: =IF(H$4<=核心参数输入!$B$9,IF(H$4>=核心参数输入!$B$18,H$4-核心参数输入!$B$18+1,0),0) -> 1 | I25: =IF(I$4<=核心参数输入!$B$9,IF(I$4>=核心参数输入!$B$18,I$4-核心参数输入!$B$18+1,0),0) -> 2 | J25: =IF(J$4<=核心参数输入!$B$9,IF(J$4>=核心参数输入!$B$18,J$4-核心参数输入!$B$18+1,0),0) -> 3 | K25: =IF(K$4<=核心参数输入!$B$9,IF(K$4>=核心参数输入!$B$18,K$4-核心参数输入!$B$18+1,0),0) -> 4 | ... AH25: =IF(AH$4<=核心参数输入!$B$9,IF(AH$4>=核心参数输入!$B$18,AH$4-核心参数输入!$B$18+1,0),0) -> 0
A26: 实际出租率 | B26: % | D26: =IF(D$4<=核心参数输入!$B$9,IF(D25=0,0,MAX(0,IF(D25=1,核心参数输入!$B$38,IF(D25=2,核心参数输入!$B$39,IF(D25=3,核心参数输入!$B$40,核心参数输入!$B$41)))-0)),0) -> 0 | E26: =IF(E$4<=核心参数输入!$B$9,IF(E25=0,0,MAX(0,IF(E25=1,核心参数输入!$B$38,IF(E25=2,核心参数输入!$B$39,IF(E25=3,核心参数输入!$B$40,核心参数输入!$B$41)))-0)),0) -> 0 | F26: =IF(F$4<=核心参数输入!$B$9,IF(F25=0,0,MAX(0,IF(F25=1,核心参数输入!$B$38,IF(F25=2,核心参数输入!$B$39,IF(F25=3,核心参数输入!$B$40,核心参数输入!$B$41)))-0)),0) -> 0 | G26: =IF(G$4<=核心参数输入!$B$9,IF(G25=0,0,MAX(0,IF(G25=1,核心参数输入!$B$38,IF(G25=2,核心参数输入!$B$39,IF(G25=3,核心参数输入!$B$40,核心参数输入!$B$41)))-0)),0) -> 0 | H26: =IF(H$4<=核心参数输入!$B$9,IF(H25=0,0,MAX(0,IF(H25=1,核心参数输入!$B$38,IF(H25=2,核心参数输入!$B$39,IF(H25=3,核心参数输入!$B$40,核心参数输入!$B$41)))-0)),0) -> 0.5 | I26: =IF(I$4<=核心参数输入!$B$9,IF(I25=0,0,MAX(0,IF(I25=1,核心参数输入!$B$38,IF(I25=2,核心参数输入!$B$39,IF(I25=3,核心参数输入!$B$40,核心参数输入!$B$41)))-0)),0) -> 0.7 | J26: =IF(J$4<=核心参数输入!$B$9,IF(J25=0,0,MAX(0,IF(J25=1,核心参数输入!$B$38,IF(J25=2,核心参数输入!$B$39,IF(J25=3,核心参数输入!$B$40,核心参数输入!$B$41)))-0)),0) -> 0.85 | K26: =IF(K$4<=核心参数输入!$B$9,IF(K25=0,0,MAX(0,IF(K25=1,核心参数输入!$B$38,IF(K25=2,核心参数输入!$B$39,IF(K25=3,核心参数输入!$B$40,核心参数输入!$B$41)))-0)),0) -> 0.9 | ... AH26: =IF(AH$4<=核心参数输入!$B$9,IF(AH25=0,0,MAX(0,IF(AH25=1,核心参数输入!$B$38,IF(AH25=2,核心参数输入!$B$39,IF(AH25=3,核心参数输入!$B$40,核心参数输入!$B$41)))-0)),0) -> 0
A27: 已出租面积 | B27: 平方米 | D27: =IF(D$4<=核心参数输入!$B$9,$B$10*D26,0) -> 0 | E27: =IF(E$4<=核心参数输入!$B$9,$B$10*E26,0) -> 0 | F27: =IF(F$4<=核心参数输入!$B$9,$B$10*F26,0) -> 0 | G27: =IF(G$4<=核心参数输入!$B$9,$B$10*G26,0) -> 0 | H27: =IF(H$4<=核心参数输入!$B$9,$B$10*H26,0) -> 30375 | I27: =IF(I$4<=核心参数输入!$B$9,$B$10*I26,0) -> 42525 | J27: =IF(J$4<=核心参数输入!$B$9,$B$10*J26,0) -> 51637.5 | K27: =IF(K$4<=核心参数输入!$B$9,$B$10*K26,0) -> 54675 | ... AH27: =IF(AH$4<=核心参数输入!$B$9,$B$10*AH26,0) -> 0
A28: 新增出租面积 | B28: 平方米 | D28: =IF(D$4<=核心参数输入!$B$9,MAX(0,D27-0),0) -> 0 | E28: =IF(E$4<=核心参数输入!$B$9,MAX(0,E27-D27),0) -> 0 | F28: =IF(F$4<=核心参数输入!$B$9,MAX(0,F27-E27),0) -> 0 | G28: =IF(G$4<=核心参数输入!$B$9,MAX(0,G27-F27),0) -> 0 | H28: =IF(H$4<=核心参数输入!$B$9,MAX(0,H27-G27),0) -> 30375 | I28: =IF(I$4<=核心参数输入!$B$9,MAX(0,I27-H27),0) -> 12150 | J28: =IF(J$4<=核心参数输入!$B$9,MAX(0,J27-I27),0) -> 9112.5 | K28: =IF(K$4<=核心参数输入!$B$9,MAX(0,K27-J27),0) -> 3037.5 | L28: =IF(L$4<=核心参数输入!$B$9,MAX(0,L27-K27),0) -> 0 | ... AH28: =IF(AH$4<=核心参数输入!$B$9,MAX(0,AH27-AG27),0) -> 0
A29: 累计销售完成标记 | B29: 0/1 | D29: =IF(D$4<=核心参数输入!$B$9,IF(D22>=0.999999,1,0),0) -> 0 | E29: =IF(E$4<=核心参数输入!$B$9,IF(E22>=0.999999,1,0),0) -> 0 | F29: =IF(F$4<=核心参数输入!$B$9,IF(F22>=0.999999,1,0),0) -> 0 | G29: =IF(G$4<=核心参数输入!$B$9,IF(G22>=0.999999,1,0),0) -> 0 | H29: =IF(H$4<=核心参数输入!$B$9,IF(H22>=0.999999,1,0),0) -> 0 | I29: =IF(I$4<=核心参数输入!$B$9,IF(I22>=0.999999,1,0),0) -> 0 | J29: =IF(J$4<=核心参数输入!$B$9,IF(J22>=0.999999,1,0),0) -> 1 | K29: =IF(K$4<=核心参数输入!$B$9,IF(K22>=0.999999,1,0),0) -> 1 | ... AH29: =IF(AH$4<=核心参数输入!$B$9,IF(AH22>=0.999999,1,0),0) -> 0
A98: 组合压力情景 · 年度开发与租售计划（共用面积及销售比例）
A100: 建设分配比例 | B100: % | D100: =IF(D$4<=核心参数输入!$B$9,IF(AND(D$4>=1,D$4<=核心参数输入!$B$16),核心参数输入!D88,0),0) -> 0 | E100: =IF(E$4<=核心参数输入!$B$9,IF(AND(E$4>=1,E$4<=核心参数输入!$B$16),核心参数输入!E88,0),0) -> 0.3 | F100: =IF(F$4<=核心参数输入!$B$9,IF(AND(F$4>=1,F$4<=核心参数输入!$B$16),核心参数输入!F88,0),0) -> 0.4 | G100: =IF(G$4<=核心参数输入!$B$9,IF(AND(G$4>=1,G$4<=核心参数输入!$B$16),核心参数输入!G88,0),0) -> 0.3 | H100: =IF(H$4<=核心参数输入!$B$9,IF(AND(H$4>=1,H$4<=核心参数输入!$B$16),核心参数输入!H88,0),0) -> 0 | I100: =IF(I$4<=核心参数输入!$B$9,IF(AND(I$4>=1,I$4<=核心参数输入!$B$16),核心参数输入!I88,0),0) -> 0 | J100: =IF(J$4<=核心参数输入!$B$9,IF(AND(J$4>=1,J$4<=核心参数输入!$B$16),核心参数输入!J88,0),0) -> 0 | K100: =IF(K$4<=核心参数输入!$B$9,IF(AND(K$4>=1,K$4<=核心参数输入!$B$16),核心参数输入!K88,0),0) -> 0 | ... AH100: =IF(AH$4<=核心参数输入!$B$9,IF(AND(AH$4>=1,AH$4<=核心参数输入!$B$16),核心参数输入!AH88,0),0) -> 0
A101: 销售比例 | B101: % | D101: =IF(D$4<=核心参数输入!$B$9,IF(D$4>=核心参数输入!$B$17,核心参数输入!D89,0),0) -> 0 | E101: =IF(E$4<=核心参数输入!$B$9,IF(E$4>=核心参数输入!$B$17,核心参数输入!E89,0),0) -> 0 | F101: =IF(F$4<=核心参数输入!$B$9,IF(F$4>=核心参数输入!$B$17,核心参数输入!F89,0),0) -> 0 | G101: =IF(G$4<=核心参数输入!$B$9,IF(G$4>=核心参数输入!$B$17,核心参数输入!G89,0),0) -> 0 | H101: =IF(H$4<=核心参数输入!$B$9,IF(H$4>=核心参数输入!$B$17,核心参数输入!H89,0),0) -> 0.3 | I101: =IF(I$4<=核心参数输入!$B$9,IF(I$4>=核心参数输入!$B$17,核心参数输入!I89,0),0) -> 0.4 | J101: =IF(J$4<=核心参数输入!$B$9,IF(J$4>=核心参数输入!$B$17,核心参数输入!J89,0),0) -> 0.3 | K101: =IF(K$4<=核心参数输入!$B$9,IF(K$4>=核心参数输入!$B$17,核心参数输入!K89,0),0) -> 0 | ... AH101: =IF(AH$4<=核心参数输入!$B$9,IF(AH$4>=核心参数输入!$B$17,核心参数输入!AH89,0),0) -> 0
A102: 累计销售去化率 | B102: % | D102: =IF(D$4<=核心参数输入!$B$9,SUM($D101:D101),0) -> 0 | E102: =IF(E$4<=核心参数输入!$B$9,SUM($D101:E101),0) -> 0 | F102: =IF(F$4<=核心参数输入!$B$9,SUM($D101:F101),0) -> 0 | G102: =IF(G$4<=核心参数输入!$B$9,SUM($D101:G101),0) -> 0 | H102: =IF(H$4<=核心参数输入!$B$9,SUM($D101:H101),0) -> 0.3 | I102: =IF(I$4<=核心参数输入!$B$9,SUM($D101:I101),0) -> 0.7 | J102: =IF(J$4<=核心参数输入!$B$9,SUM($D101:J101),0) -> 1 | K102: =IF(K$4<=核心参数输入!$B$9,SUM($D101:K101),0) -> 1 | ... AH102: =IF(AH$4<=核心参数输入!$B$9,SUM($D101:AH101),0) -> 0
A103: 当年出售面积 | B103: 平方米 | D103: =IF(D$4<=核心参数输入!$B$9,D101*$B$9,0) -> 0 | E103: =IF(E$4<=核心参数输入!$B$9,E101*$B$9,0) -> 0 | F103: =IF(F$4<=核心参数输入!$B$9,F101*$B$9,0) -> 0 | G103: =IF(G$4<=核心参数输入!$B$9,G101*$B$9,0) -> 0 | H103: =IF(H$4<=核心参数输入!$B$9,H101*$B$9,0) -> 22275 | I103: =IF(I$4<=核心参数输入!$B$9,I101*$B$9,0) -> 29700 | J103: =IF(J$4<=核心参数输入!$B$9,J101*$B$9,0) -> 22275 | K103: =IF(K$4<=核心参数输入!$B$9,K101*$B$9,0) -> 0 | ... AH103: =IF(AH$4<=核心参数输入!$B$9,AH101*$B$9,0) -> 0
A104: 期末未售面积 | B104: 平方米 | D104: =IF(D$4<=核心参数输入!$B$9,$B$9*(1-D102),0) -> 74250 | E104: =IF(E$4<=核心参数输入!$B$9,$B$9*(1-E102),0) -> 74250 | F104: =IF(F$4<=核心参数输入!$B$9,$B$9*(1-F102),0) -> 74250 | G104: =IF(G$4<=核心参数输入!$B$9,$B$9*(1-G102),0) -> 74250 | H104: =IF(H$4<=核心参数输入!$B$9,$B$9*(1-H102),0) -> 51975 | I104: =IF(I$4<=核心参数输入!$B$9,$B$9*(1-I102),0) -> 22275 | J104: =IF(J$4<=核心参数输入!$B$9,$B$9*(1-J102),0) -> 0 | K104: =IF(K$4<=核心参数输入!$B$9,$B$9*(1-K102),0) -> 0 | ... AH104: =IF(AH$4<=核心参数输入!$B$9,$B$9*(1-AH102),0) -> 0
A105: 出租第几个年度 | B105: 年 | D105: =IF(D$4<=核心参数输入!$B$9,IF(D$4>=核心参数输入!$B$18,D$4-核心参数输入!$B$18+1,0),0) -> 0 | E105: =IF(E$4<=核心参数输入!$B$9,IF(E$4>=核心参数输入!$B$18,E$4-核心参数输入!$B$18+1,0),0) -> 0 | F105: =IF(F$4<=核心参数输入!$B$9,IF(F$4>=核心参数输入!$B$18,F$4-核心参数输入!$B$18+1,0),0) -> 0 | G105: =IF(G$4<=核心参数输入!$B$9,IF(G$4>=核心参数输入!$B$18,G$4-核心参数输入!$B$18+1,0),0) -> 0 | H105: =IF(H$4<=核心参数输入!$B$9,IF(H$4>=核心参数输入!$B$18,H$4-核心参数输入!$B$18+1,0),0) -> 1 | I105: =IF(I$4<=核心参数输入!$B$9,IF(I$4>=核心参数输入!$B$18,I$4-核心参数输入!$B$18+1,0),0) -> 2 | J105: =IF(J$4<=核心参数输入!$B$9,IF(J$4>=核心参数输入!$B$18,J$4-核心参数输入!$B$18+1,0),0) -> 3 | K105: =IF(K$4<=核心参数输入!$B$9,IF(K$4>=核心参数输入!$B$18,K$4-核心参数输入!$B$18+1,0),0) -> 4 | ... AH105: =IF(AH$4<=核心参数输入!$B$9,IF(AH$4>=核心参数输入!$B$18,AH$4-核心参数输入!$B$18+1,0),0) -> 0
A106: 实际出租率 | B106: % | D106: =IF(D$4<=核心参数输入!$B$9,IF(D105=0,0,MAX(0,IF(D105=1,核心参数输入!$B$38,IF(D105=2,核心参数输入!$B$39,IF(D105=3,核心参数输入!$B$40,核心参数输入!$B$41)))-核心参数输入!$B$80/100)),0) -> 0 | E106: =IF(E$4<=核心参数输入!$B$9,IF(E105=0,0,MAX(0,IF(E105=1,核心参数输入!$B$38,IF(E105=2,核心参数输入!$B$39,IF(E105=3,核心参数输入!$B$40,核心参数输入!$B$41)))-核心参数输入!$B$80/100)),0) -> 0 | F106: =IF(F$4<=核心参数输入!$B$9,IF(F105=0,0,MAX(0,IF(F105=1,核心参数输入!$B$38,IF(F105=2,核心参数输入!$B$39,IF(F105=3,核心参数输入!$B$40,核心参数输入!$B$41)))-核心参数输入!$B$80/100)),0) -> 0 | G106: =IF(G$4<=核心参数输入!$B$9,IF(G105=0,0,MAX(0,IF(G105=1,核心参数输入!$B$38,IF(G105=2,核心参数输入!$B$39,IF(G105=3,核心参数输入!$B$40,核心参数输入!$B$41)))-核心参数输入!$B$80/100)),0) -> 0 | H106: =IF(H$4<=核心参数输入!$B$9,IF(H105=0,0,MAX(0,IF(H105=1,核心参数输入!$B$38,IF(H105=2,核心参数输入!$B$39,IF(H105=3,核心参数输入!$B$40,核心参数输入!$B$41)))-核心参数输入!$B$80/100)),0) -> 0.4 | I106: =IF(I$4<=核心参数输入!$B$9,IF(I105=0,0,MAX(0,IF(I105=1,核心参数输入!$B$38,IF(I105=2,核心参数输入!$B$39,IF(I105=3,核心参数输入!$B$40,核心参数输入!$B$41)))-核心参数输入!$B$80/100)),0) -> 0.6 | J106: =IF(J$4<=核心参数输入!$B$9,IF(J105=0,0,MAX(0,IF(J105=1,核心参数输入!$B$38,IF(J105=2,核心参数输入!$B$39,IF(J105=3,核心参数输入!$B$40,核心参数输入!$B$41)))-核心参数输入!$B$80/100)),0) -> 0.75 | K106: =IF(K$4<=核心参数输入!$B$9,IF(K105=0,0,MAX(0,IF(K105=1,核心参数输入!$B$38,IF(K105=2,核心参数输入!$B$39,IF(K105=3,核心参数输入!$B$40,核心参数输入!$B$41)))-核心参数输入!$B$80/100)),0) -> 0.8 | ... AH106: =IF(AH$4<=核心参数输入!$B$9,IF(AH105=0,0,MAX(0,IF(AH105=1,核心参数输入!$B$38,IF(AH105=2,核心参数输入!$B$39,IF(AH105=3,核心参数输入!$B$40,核心参数输入!$B$41)))-核心参数输入!$B$80/100)),0) -> 0
A107: 已出租面积 | B107: 平方米 | D107: =IF(D$4<=核心参数输入!$B$9,$B$10*D106,0) -> 0 | E107: =IF(E$4<=核心参数输入!$B$9,$B$10*E106,0) -> 0 | F107: =IF(F$4<=核心参数输入!$B$9,$B$10*F106,0) -> 0 | G107: =IF(G$4<=核心参数输入!$B$9,$B$10*G106,0) -> 0 | H107: =IF(H$4<=核心参数输入!$B$9,$B$10*H106,0) -> 24300 | I107: =IF(I$4<=核心参数输入!$B$9,$B$10*I106,0) -> 36450 | J107: =IF(J$4<=核心参数输入!$B$9,$B$10*J106,0) -> 45562.5 | K107: =IF(K$4<=核心参数输入!$B$9,$B$10*K106,0) -> 48600 | ... AH107: =IF(AH$4<=核心参数输入!$B$9,$B$10*AH106,0) -> 0
A108: 新增出租面积 | B108: 平方米 | D108: =IF(D$4<=核心参数输入!$B$9,MAX(0,D107-0),0) -> 0 | E108: =IF(E$4<=核心参数输入!$B$9,MAX(0,E107-D107),0) -> 0 | F108: =IF(F$4<=核心参数输入!$B$9,MAX(0,F107-E107),0) -> 0 | G108: =IF(G$4<=核心参数输入!$B$9,MAX(0,G107-F107),0) -> 0 | H108: =IF(H$4<=核心参数输入!$B$9,MAX(0,H107-G107),0) -> 24300 | I108: =IF(I$4<=核心参数输入!$B$9,MAX(0,I107-H107),0) -> 12150 | J108: =IF(J$4<=核心参数输入!$B$9,MAX(0,J107-I107),0) -> 9112.5 | K108: =IF(K$4<=核心参数输入!$B$9,MAX(0,K107-J107),0) -> 3037.5 | L108: =IF(L$4<=核心参数输入!$B$9,MAX(0,L107-K107),0) -> 0 | ... AH108: =IF(AH$4<=核心参数输入!$B$9,MAX(0,AH107-AG107),0) -> 0
A109: 累计销售完成标记 | B109: 0/1 | D109: =IF(D$4<=核心参数输入!$B$9,IF(D102>=0.999999,1,0),0) -> 0 | E109: =IF(E$4<=核心参数输入!$B$9,IF(E102>=0.999999,1,0),0) -> 0 | F109: =IF(F$4<=核心参数输入!$B$9,IF(F102>=0.999999,1,0),0) -> 0 | G109: =IF(G$4<=核心参数输入!$B$9,IF(G102>=0.999999,1,0),0) -> 0 | H109: =IF(H$4<=核心参数输入!$B$9,IF(H102>=0.999999,1,0),0) -> 0 | I109: =IF(I$4<=核心参数输入!$B$9,IF(I102>=0.999999,1,0),0) -> 0 | J109: =IF(J$4<=核心参数输入!$B$9,IF(J102>=0.999999,1,0),0) -> 1 | K109: =IF(K$4<=核心参数输入!$B$9,IF(K102>=0.999999,1,0),0) -> 1 | ... AH109: =IF(AH$4<=核心参数输入!$B$9,IF(AH102>=0.999999,1,0),0) -> 0

Sheet 投资与资金安排
A2: 投资与资金安排 · 模拟数据
A3: 基准情景
A4: 项目年度 / 日历年份 | D4: =核心参数输入!D87 -> 0 | E4: =核心参数输入!E87 -> 1 | F4: =核心参数输入!F87 -> 2 | G4: =核心参数输入!G87 -> 3 | H4: =核心参数输入!H87 -> 4 | I4: =核心参数输入!I87 -> 5 | J4: =核心参数输入!J87 -> 6 | K4: =核心参数输入!K87 -> 7 | ... AH4: =核心参数输入!AH87 -> 30
D5: =核心参数输入!$B$8+D4 -> 2026 | E5: =核心参数输入!$B$8+E4 -> 2027 | F5: =核心参数输入!$B$8+F4 -> 2028 | G5: =核心参数输入!$B$8+G4 -> 2029 | H5: =核心参数输入!$B$8+H4 -> 2030 | I5: =核心参数输入!$B$8+I4 -> 2031 | J5: =核心参数输入!$B$8+J4 -> 2032 | K5: =核心参数输入!$B$8+K4 -> 2033 | ... AH5: =核心参数输入!$B$8+AH4 -> 2056
A6: 土地取得费用 | B6: =核心参数输入!$B$10*核心参数输入!$B$21/10000 -> 8000 | C6: 万元
A7: 地上建安费用 | B7: =建筑面积与开发计划!$B$7*核心参数输入!$B$22/10000*1 -> 36000 | C7: 万元
A8: 地下建安费用 | B8: =核心参数输入!$B$13*核心参数输入!$B$23/10000*1 -> 4500 | C8: 万元
A9: 配套工程费用 | B9: =核心参数输入!$B$24*1 -> 4500 | C9: 万元
A10: 前期费用 | B10: =核心参数输入!$B$25*1 -> 1800 | C10: 万元
A11: 管理及其他建设费用 | B11: =核心参数输入!$B$26*1 -> 2200 | C11: 万元
A12: 非土地建设费用小计 | B12: =SUM(B7:B11) -> 49000 | C12: 万元
A13: 预备费 | B13: =B12*核心参数输入!$B$27 -> 3920 | C13: 万元
A14: 非土地建设费用含预备费 | B14: =SUM(B12:B13) -> 52920 | C14: 万元
A15: 建设期融资费用（资本金支付） | B15: =SUM(融资与还本付息!$D$16:$AH$16) -> 1890 | C15: 万元
A16: 开发总成本含融资费用 | B16: =B6+B14+B15 -> 62810 | C16: 万元
A17: 初始运营周转资金 | B17: =核心参数输入!$B$28 -> 500 | C17: 万元
A18: 项目总投资含建设期融资费用 | B18: =SUM(B16:B17) -> 63310 | C18: 万元
A19: 销售成本基数（项目口径） | B19: =(B6+B14)*核心参数输入!$B$14 -> 33506 | C19: 万元
A20: 持有折旧基数（项目口径） | B20: =B14*核心参数输入!$B$15 -> 23814 | C20: 万元
A21: 持有分摊土地成本 | B21: =B6*核心参数输入!$B$15 -> 3600 | C21: 万元
A22: 销售成本基数（融资口径） | B22: =B16*核心参数输入!$B$14 -> 34545.5 | C22: 万元
A23: 持有折旧基数（融资口径） | B23: =(B14+B15)*核心参数输入!$B$15 -> 24664.5 | C23: 万元
A24: 持有分摊总投资含周转资金 | B24: =B16*核心参数输入!$B$15+B17 -> 28764.5 | C24: 万元
A26: 年度现金支出（成本结转与折旧不在此再次支付）
A28: 土地款 | B28: 万元 | D28: =IF(D$4<=核心参数输入!$B$9,IF(D$4=0,$B$6,0),0) -> 8000 | E28: =IF(E$4<=核心参数输入!$B$9,IF(E$4=0,$B$6,0),0) -> 0 | F28: =IF(F$4<=核心参数输入!$B$9,IF(F$4=0,$B$6,0),0) -> 0 | G28: =IF(G$4<=核心参数输入!$B$9,IF(G$4=0,$B$6,0),0) -> 0 | H28: =IF(H$4<=核心参数输入!$B$9,IF(H$4=0,$B$6,0),0) -> 0 | I28: =IF(I$4<=核心参数输入!$B$9,IF(I$4=0,$B$6,0),0) -> 0 | J28: =IF(J$4<=核心参数输入!$B$9,IF(J$4=0,$B$6,0),0) -> 0 | K28: =IF(K$4<=核心参数输入!$B$9,IF(K$4=0,$B$6,0),0) -> 0 | ... AH28: =IF(AH$4<=核心参数输入!$B$9,IF(AH$4=0,$B$6,0),0) -> 0
A29: 非土地建设现金支出 | B29: 万元 | D29: =IF(D$4<=核心参数输入!$B$9,$B$14*建筑面积与开发计划!D20,0) -> 0 | E29: =IF(E$4<=核心参数输入!$B$9,$B$14*建筑面积与开发计划!E20,0) -> 15876 | F29: =IF(F$4<=核心参数输入!$B$9,$B$14*建筑面积与开发计划!F20,0) -> 21168 | G29: =IF(G$4<=核心参数输入!$B$9,$B$14*建筑面积与开发计划!G20,0) -> 15876 | H29: =IF(H$4<=核心参数输入!$B$9,$B$14*建筑面积与开发计划!H20,0) -> 0 | I29: =IF(I$4<=核心参数输入!$B$9,$B$14*建筑面积与开发计划!I20,0) -> 0 | J29: =IF(J$4<=核心参数输入!$B$9,$B$14*建筑面积与开发计划!J20,0) -> 0 | K29: =IF(K$4<=核心参数输入!$B$9,$B$14*建筑面积与开发计划!K20,0) -> 0 | ... AH29: =IF(AH$4<=核心参数输入!$B$9,$B$14*建筑面积与开发计划!AH20,0) -> 0
A30: 年度建设支出合计 | B30: 万元 | D30: =IF(D$4<=核心参数输入!$B$9,SUM(D28:D29),0) -> 8000 | E30: =IF(E$4<=核心参数输入!$B$9,SUM(E28:E29),0) -> 15876 | F30: =IF(F$4<=核心参数输入!$B$9,SUM(F28:F29),0) -> 21168 | G30: =IF(G$4<=核心参数输入!$B$9,SUM(G28:G29),0) -> 15876 | H30: =IF(H$4<=核心参数输入!$B$9,SUM(H28:H29),0) -> 0 | I30: =IF(I$4<=核心参数输入!$B$9,SUM(I28:I29),0) -> 0 | J30: =IF(J$4<=核心参数输入!$B$9,SUM(J28:J29),0) -> 0 | K30: =IF(K$4<=核心参数输入!$B$9,SUM(K28:K29),0) -> 0 | ... AH30: =IF(AH$4<=核心参数输入!$B$9,SUM(AH28:AH29),0) -> 0
A31: 运营周转资金投入 | B31: 万元 | D31: =IF(D$4<=核心参数输入!$B$9,IF(D$4=核心参数输入!$B$16+1,核心参数输入!$B$28,0),0) -> 0 | E31: =IF(E$4<=核心参数输入!$B$9,IF(E$4=核心参数输入!$B$16+1,核心参数输入!$B$28,0),0) -> 0 | F31: =IF(F$4<=核心参数输入!$B$9,IF(F$4=核心参数输入!$B$16+1,核心参数输入!$B$28,0),0) -> 0 | G31: =IF(G$4<=核心参数输入!$B$9,IF(G$4=核心参数输入!$B$16+1,核心参数输入!$B$28,0),0) -> 0 | H31: =IF(H$4<=核心参数输入!$B$9,IF(H$4=核心参数输入!$B$16+1,核心参数输入!$B$28,0),0) -> 500 | I31: =IF(I$4<=核心参数输入!$B$9,IF(I$4=核心参数输入!$B$16+1,核心参数输入!$B$28,0),0) -> 0 | J31: =IF(J$4<=核心参数输入!$B$9,IF(J$4=核心参数输入!$B$16+1,核心参数输入!$B$28,0),0) -> 0 | K31: =IF(K$4<=核心参数输入!$B$9,IF(K$4=核心参数输入!$B$16+1,核心参数输入!$B$28,0),0) -> 0 | ... AH31: =IF(AH$4<=核心参数输入!$B$9,IF(AH$4=核心参数输入!$B$16+1,核心参数输入!$B$28,0),0) -> 0
A32: 运营周转资金收回 | B32: 万元 | D32: =IF(D$4<=核心参数输入!$B$9,IF(AND(D$4=核心参数输入!$B$9,核心参数输入!$B$9>核心参数输入!$B$16),核心参数输入!$B$28,0),0) -> 0 | E32: =IF(E$4<=核心参数输入!$B$9,IF(AND(E$4=核心参数输入!$B$9,核心参数输入!$B$9>核心参数输入!$B$16),核心参数输入!$B$28,0),0) -> 0 | F32: =IF(F$4<=核心参数输入!$B$9,IF(AND(F$4=核心参数输入!$B$9,核心参数输入!$B$9>核心参数输入!$B$16),核心参数输入!$B$28,0),0) -> 0 | G32: =IF(G$4<=核心参数输入!$B$9,IF(AND(G$4=核心参数输入!$B$9,核心参数输入!$B$9>核心参数输入!$B$16),核心参数输入!$B$28,0),0) -> 0 | H32: =IF(H$4<=核心参数输入!$B$9,IF(AND(H$4=核心参数输入!$B$9,核心参数输入!$B$9>核心参数输入!$B$16),核心参数输入!$B$28,0),0) -> 0 | I32: =IF(I$4<=核心参数输入!$B$9,IF(AND(I$4=核心参数输入!$B$9,核心参数输入!$B$9>核心参数输入!$B$16),核心参数输入!$B$28,0),0) -> 0 | J32: =IF(J$4<=核心参数输入!$B$9,IF(AND(J$4=核心参数输入!$B$9,核心参数输入!$B$9>核心参数输入!$B$16),核心参数输入!$B$28,0),0) -> 0 | K32: =IF(K$4<=核心参数输入!$B$9,IF(AND(K$4=核心参数输入!$B$9,核心参数输入!$B$9>核心参数输入!$B$16),核心参数输入!$B$28,0),0) -> 0 | ... AH32: =IF(AH$4<=核心参数输入!$B$9,IF(AND(AH$4=核心参数输入!$B$9,核心参数输入!$B$9>核心参数输入!$B$16),核心参数输入!$B$28,0),0) -> 0
A33: 项目口径年度投资支出 | B33: 万元 | D33: =IF(D$4<=核心参数输入!$B$9,D30+D31,0) -> 8000 | E33: =IF(E$4<=核心参数输入!$B$9,E30+E31,0) -> 15876 | F33: =IF(F$4<=核心参数输入!$B$9,F30+F31,0) -> 21168 | G33: =IF(G$4<=核心参数输入!$B$9,G30+G31,0) -> 15876 | H33: =IF(H$4<=核心参数输入!$B$9,H30+H31,0) -> 500 | I33: =IF(I$4<=核心参数输入!$B$9,I30+I31,0) -> 0 | J33: =IF(J$4<=核心参数输入!$B$9,J30+J31,0) -> 0 | K33: =IF(K$4<=核心参数输入!$B$9,K30+K31,0) -> 0 | ... AH33: =IF(AH$4<=核心参数输入!$B$9,AH30+AH31,0) -> 0
A34: 建设期利息现金支付 | B34: 万元 | D34: =IF(D$4<=核心参数输入!$B$9,融资与还本付息!D16,0) -> 0 | E34: =IF(E$4<=核心参数输入!$B$9,融资与还本付息!E16,0) -> 189 | F34: =IF(F$4<=核心参数输入!$B$9,融资与还本付息!F16,0) -> 630 | G34: =IF(G$4<=核心参数输入!$B$9,融资与还本付息!G16,0) -> 1071 | H34: =IF(H$4<=核心参数输入!$B$9,融资与还本付息!H16,0) -> 0 | I34: =IF(I$4<=核心参数输入!$B$9,融资与还本付息!I16,0) -> 0 | J34: =IF(J$4<=核心参数输入!$B$9,融资与还本付息!J16,0) -> 0 | K34: =IF(K$4<=核心参数输入!$B$9,融资与还本付息!K16,0) -> 0 | ... AH34: =IF(AH$4<=核心参数输入!$B$9,融资与还本付息!AH16,0) -> 0
A35: 含融资费用年度投资支出 | B35: 万元 | D35: =IF(D$4<=核心参数输入!$B$9,D33+D34,0) -> 8000 | E35: =IF(E$4<=核心参数输入!$B$9,E33+E34,0) -> 16065 | F35: =IF(F$4<=核心参数输入!$B$9,F33+F34,0) -> 21798 | G35: =IF(G$4<=核心参数输入!$B$9,G33+G34,0) -> 16947 | H35: =IF(H$4<=核心参数输入!$B$9,H33+H34,0) -> 500 | I35: =IF(I$4<=核心参数输入!$B$9,I33+I34,0) -> 0 | J35: =IF(J$4<=核心参数输入!$B$9,J33+J34,0) -> 0 | K35: =IF(K$4<=核心参数输入!$B$9,K33+K34,0) -> 0 | ... AH35: =IF(AH$4<=核心参数输入!$B$9,AH33+AH34,0) -> 0
A83: 组合压力情景
A86: 土地取得费用 | B86: =核心参数输入!$B$10*核心参数输入!$B$21/10000 -> 8000 | C86: 万元
A87: 地上建安费用 | B87: =建筑面积与开发计划!$B$7*核心参数输入!$B$22/10000*(1+核心参数输入!$B$81) -> 39600 | C87: 万元
A88: 地下建安费用 | B88: =核心参数输入!$B$13*核心参数输入!$B$23/10000*(1+核心参数输入!$B$81) -> 4950 | C88: 万元
A89: 配套工程费用 | B89: =核心参数输入!$B$24*(1+核心参数输入!$B$81) -> 4950 | C89: 万元
A90: 前期费用 | B90: =核心参数输入!$B$25*(1+核心参数输入!$B$81) -> 1980 | C90: 万元
A91: 管理及其他建设费用 | B91: =核心参数输入!$B$26*(1+核心参数输入!$B$81) -> 2420 | C91: 万元
A92: 非土地建设费用小计 | B92: =SUM(B87:B91) -> 53900 | C92: 万元
A93: 预备费 | B93: =B92*核心参数输入!$B$27 -> 4312 | C93: 万元
A94: 非土地建设费用含预备费 | B94: =SUM(B92:B93) -> 58212 | C94: 万元
A95: 建设期融资费用（资本金支付） | B95: =SUM(融资与还本付息!$D$96:$AH$96) -> 1890 | C95: 万元
A96: 开发总成本含融资费用 | B96: =B86+B94+B95 -> 68102 | C96: 万元
A97: 初始运营周转资金 | B97: =核心参数输入!$B$28 -> 500 | C97: 万元
A98: 项目总投资含建设期融资费用 | B98: =SUM(B96:B97) -> 68602 | C98: 万元
A99: 销售成本基数（项目口径） | B99: =(B86+B94)*核心参数输入!$B$14 -> 36416.6 | C99: 万元
A100: 持有折旧基数（项目口径） | B100: =B94*核心参数输入!$B$15 -> 26195.4 | C100: 万元
A101: 持有分摊土地成本 | B101: =B86*核心参数输入!$B$15 -> 3600 | C101: 万元
A102: 销售成本基数（融资口径） | B102: =B96*核心参数输入!$B$14 -> 37456.1 | C102: 万元
A103: 持有折旧基数（融资口径） | B103: =(B94+B95)*核心参数输入!$B$15 -> 27045.9 | C103: 万元
A104: 持有分摊总投资含周转资金 | B104: =B96*核心参数输入!$B$15+B97 -> 31145.9 | C104: 万元
A106: 年度现金支出（成本结转与折旧不在此再次支付）
A108: 土地款 | B108: 万元 | D108: =IF(D$4<=核心参数输入!$B$9,IF(D$4=0,$B$86,0),0) -> 8000 | E108: =IF(E$4<=核心参数输入!$B$9,IF(E$4=0,$B$86,0),0) -> 0 | F108: =IF(F$4<=核心参数输入!$B$9,IF(F$4=0,$B$86,0),0) -> 0 | G108: =IF(G$4<=核心参数输入!$B$9,IF(G$4=0,$B$86,0),0) -> 0 | H108: =IF(H$4<=核心参数输入!$B$9,IF(H$4=0,$B$86,0),0) -> 0 | I108: =IF(I$4<=核心参数输入!$B$9,IF(I$4=0,$B$86,0),0) -> 0 | J108: =IF(J$4<=核心参数输入!$B$9,IF(J$4=0,$B$86,0),0) -> 0 | K108: =IF(K$4<=核心参数输入!$B$9,IF(K$4=0,$B$86,0),0) -> 0 | ... AH108: =IF(AH$4<=核心参数输入!$B$9,IF(AH$4=0,$B$86,0),0) -> 0
A109: 非土地建设现金支出 | B109: 万元 | D109: =IF(D$4<=核心参数输入!$B$9,$B$94*建筑面积与开发计划!D100,0) -> 0 | E109: =IF(E$4<=核心参数输入!$B$9,$B$94*建筑面积与开发计划!E100,0) -> 17463.6 | F109: =IF(F$4<=核心参数输入!$B$9,$B$94*建筑面积与开发计划!F100,0) -> 23284.8 | G109: =IF(G$4<=核心参数输入!$B$9,$B$94*建筑面积与开发计划!G100,0) -> 17463.6 | H109: =IF(H$4<=核心参数输入!$B$9,$B$94*建筑面积与开发计划!H100,0) -> 0 | I109: =IF(I$4<=核心参数输入!$B$9,$B$94*建筑面积与开发计划!I100,0) -> 0 | J109: =IF(J$4<=核心参数输入!$B$9,$B$94*建筑面积与开发计划!J100,0) -> 0 | K109: =IF(K$4<=核心参数输入!$B$9,$B$94*建筑面积与开发计划!K100,0) -> 0 | ... AH109: =IF(AH$4<=核心参数输入!$B$9,$B$94*建筑面积与开发计划!AH100,0) -> 0
A110: 年度建设支出合计 | B110: 万元 | D110: =IF(D$4<=核心参数输入!$B$9,SUM(D108:D109),0) -> 8000 | E110: =IF(E$4<=核心参数输入!$B$9,SUM(E108:E109),0) -> 17463.6 | F110: =IF(F$4<=核心参数输入!$B$9,SUM(F108:F109),0) -> 23284.8 | G110: =IF(G$4<=核心参数输入!$B$9,SUM(G108:G109),0) -> 17463.6 | H110: =IF(H$4<=核心参数输入!$B$9,SUM(H108:H109),0) -> 0 | I110: =IF(I$4<=核心参数输入!$B$9,SUM(I108:I109),0) -> 0 | J110: =IF(J$4<=核心参数输入!$B$9,SUM(J108:J109),0) -> 0 | K110: =IF(K$4<=核心参数输入!$B$9,SUM(K108:K109),0) -> 0 | ... AH110: =IF(AH$4<=核心参数输入!$B$9,SUM(AH108:AH109),0) -> 0
A111: 运营周转资金投入 | B111: 万元 | D111: =IF(D$4<=核心参数输入!$B$9,IF(D$4=核心参数输入!$B$16+1,核心参数输入!$B$28,0),0) -> 0 | E111: =IF(E$4<=核心参数输入!$B$9,IF(E$4=核心参数输入!$B$16+1,核心参数输入!$B$28,0),0) -> 0 | F111: =IF(F$4<=核心参数输入!$B$9,IF(F$4=核心参数输入!$B$16+1,核心参数输入!$B$28,0),0) -> 0 | G111: =IF(G$4<=核心参数输入!$B$9,IF(G$4=核心参数输入!$B$16+1,核心参数输入!$B$28,0),0) -> 0 | H111: =IF(H$4<=核心参数输入!$B$9,IF(H$4=核心参数输入!$B$16+1,核心参数输入!$B$28,0),0) -> 500 | I111: =IF(I$4<=核心参数输入!$B$9,IF(I$4=核心参数输入!$B$16+1,核心参数输入!$B$28,0),0) -> 0 | J111: =IF(J$4<=核心参数输入!$B$9,IF(J$4=核心参数输入!$B$16+1,核心参数输入!$B$28,0),0) -> 0 | K111: =IF(K$4<=核心参数输入!$B$9,IF(K$4=核心参数输入!$B$16+1,核心参数输入!$B$28,0),0) -> 0 | ... AH111: =IF(AH$4<=核心参数输入!$B$9,IF(AH$4=核心参数输入!$B$16+1,核心参数输入!$B$28,0),0) -> 0
A112: 运营周转资金收回 | B112: 万元 | D112: =IF(D$4<=核心参数输入!$B$9,IF(AND(D$4=核心参数输入!$B$9,核心参数输入!$B$9>核心参数输入!$B$16),核心参数输入!$B$28,0),0) -> 0 | E112: =IF(E$4<=核心参数输入!$B$9,IF(AND(E$4=核心参数输入!$B$9,核心参数输入!$B$9>核心参数输入!$B$16),核心参数输入!$B$28,0),0) -> 0 | F112: =IF(F$4<=核心参数输入!$B$9,IF(AND(F$4=核心参数输入!$B$9,核心参数输入!$B$9>核心参数输入!$B$16),核心参数输入!$B$28,0),0) -> 0 | G112: =IF(G$4<=核心参数输入!$B$9,IF(AND(G$4=核心参数输入!$B$9,核心参数输入!$B$9>核心参数输入!$B$16),核心参数输入!$B$28,0),0) -> 0 | H112: =IF(H$4<=核心参数输入!$B$9,IF(AND(H$4=核心参数输入!$B$9,核心参数输入!$B$9>核心参数输入!$B$16),核心参数输入!$B$28,0),0) -> 0 | I112: =IF(I$4<=核心参数输入!$B$9,IF(AND(I$4=核心参数输入!$B$9,核心参数输入!$B$9>核心参数输入!$B$16),核心参数输入!$B$28,0),0) -> 0 | J112: =IF(J$4<=核心参数输入!$B$9,IF(AND(J$4=核心参数输入!$B$9,核心参数输入!$B$9>核心参数输入!$B$16),核心参数输入!$B$28,0),0) -> 0 | K112: =IF(K$4<=核心参数输入!$B$9,IF(AND(K$4=核心参数输入!$B$9,核心参数输入!$B$9>核心参数输入!$B$16),核心参数输入!$B$28,0),0) -> 0 | ... AH112: =IF(AH$4<=核心参数输入!$B$9,IF(AND(AH$4=核心参数输入!$B$9,核心参数输入!$B$9>核心参数输入!$B$16),核心参数输入!$B$28,0),0) -> 0
A113: 项目口径年度投资支出 | B113: 万元 | D113: =IF(D$4<=核心参数输入!$B$9,D110+D111,0) -> 8000 | E113: =IF(E$4<=核心参数输入!$B$9,E110+E111,0) -> 17463.6 | F113: =IF(F$4<=核心参数输入!$B$9,F110+F111,0) -> 23284.8 | G113: =IF(G$4<=核心参数输入!$B$9,G110+G111,0) -> 17463.6 | H113: =IF(H$4<=核心参数输入!$B$9,H110+H111,0) -> 500 | I113: =IF(I$4<=核心参数输入!$B$9,I110+I111,0) -> 0 | J113: =IF(J$4<=核心参数输入!$B$9,J110+J111,0) -> 0 | K113: =IF(K$4<=核心参数输入!$B$9,K110+K111,0) -> 0 | ... AH113: =IF(AH$4<=核心参数输入!$B$9,AH110+AH111,0) -> 0
A114: 建设期利息现金支付 | B114: 万元 | D114: =IF(D$4<=核心参数输入!$B$9,融资与还本付息!D96,0) -> 0 | E114: =IF(E$4<=核心参数输入!$B$9,融资与还本付息!E96,0) -> 189 | F114: =IF(F$4<=核心参数输入!$B$9,融资与还本付息!F96,0) -> 630 | G114: =IF(G$4<=核心参数输入!$B$9,融资与还本付息!G96,0) -> 1071 | H114: =IF(H$4<=核心参数输入!$B$9,融资与还本付息!H96,0) -> 0 | I114: =IF(I$4<=核心参数输入!$B$9,融资与还本付息!I96,0) -> 0 | J114: =IF(J$4<=核心参数输入!$B$9,融资与还本付息!J96,0) -> 0 | K114: =IF(K$4<=核心参数输入!$B$9,融资与还本付息!K96,0) -> 0 | ... AH114: =IF(AH$4<=核心参数输入!$B$9,融资与还本付息!AH96,0) -> 0
A115: 含融资费用年度投资支出 | B115: 万元 | D115: =IF(D$4<=核心参数输入!$B$9,D113+D114,0) -> 8000 | E115: =IF(E$4<=核心参数输入!$B$9,E113+E114,0) -> 17652.6 | F115: =IF(F$4<=核心参数输入!$B$9,F113+F114,0) -> 23914.8 | G115: =IF(G$4<=核心参数输入!$B$9,G113+G114,0) -> 18534.6 | H115: =IF(H$4<=核心参数输入!$B$9,H113+H114,0) -> 500 | I115: =IF(I$4<=核心参数输入!$B$9,I113+I114,0) -> 0 | J115: =IF(J$4<=核心参数输入!$B$9,J113+J114,0) -> 0 | K115: =IF(K$4<=核心参数输入!$B$9,K113+K114,0) -> 0 | ... AH115: =IF(AH$4<=核心参数输入!$B$9,AH113+AH114,0) -> 0

Sheet 销售与出租收入
A2: 销售与出租收入 · 模拟数据
A4: 项目年度 / 日历年份 | D4: =核心参数输入!D87 -> 0 | E4: =核心参数输入!E87 -> 1 | F4: =核心参数输入!F87 -> 2 | G4: =核心参数输入!G87 -> 3 | H4: =核心参数输入!H87 -> 4 | I4: =核心参数输入!I87 -> 5 | J4: =核心参数输入!J87 -> 6 | K4: =核心参数输入!K87 -> 7 | ... AH4: =核心参数输入!AH87 -> 30
D5: =核心参数输入!$B$8+D4 -> 2026 | E5: =核心参数输入!$B$8+E4 -> 2027 | F5: =核心参数输入!$B$8+F4 -> 2028 | G5: =核心参数输入!$B$8+G4 -> 2029 | H5: =核心参数输入!$B$8+H4 -> 2030 | I5: =核心参数输入!$B$8+I4 -> 2031 | J5: =核心参数输入!$B$8+J4 -> 2032 | K5: =核心参数输入!$B$8+K4 -> 2033 | ... AH5: =核心参数输入!$B$8+AH4 -> 2056
A7: 基准情景 · 销售与持有分别核算
A10: 年度销售比例 | B10: % | D10: =IF(D$4<=核心参数输入!$B$9,建筑面积与开发计划!D21,0) -> 0 | E10: =IF(E$4<=核心参数输入!$B$9,建筑面积与开发计划!E21,0) -> 0 | F10: =IF(F$4<=核心参数输入!$B$9,建筑面积与开发计划!F21,0) -> 0 | G10: =IF(G$4<=核心参数输入!$B$9,建筑面积与开发计划!G21,0) -> 0 | H10: =IF(H$4<=核心参数输入!$B$9,建筑面积与开发计划!H21,0) -> 0.3 | I10: =IF(I$4<=核心参数输入!$B$9,建筑面积与开发计划!I21,0) -> 0.4 | J10: =IF(J$4<=核心参数输入!$B$9,建筑面积与开发计划!J21,0) -> 0.3 | K10: =IF(K$4<=核心参数输入!$B$9,建筑面积与开发计划!K21,0) -> 0 | ... AH10: =IF(AH$4<=核心参数输入!$B$9,建筑面积与开发计划!AH21,0) -> 0
A11: 当年销售面积 | B11: 平方米 | D11: =IF(D$4<=核心参数输入!$B$9,建筑面积与开发计划!D23,0) -> 0 | E11: =IF(E$4<=核心参数输入!$B$9,建筑面积与开发计划!E23,0) -> 0 | F11: =IF(F$4<=核心参数输入!$B$9,建筑面积与开发计划!F23,0) -> 0 | G11: =IF(G$4<=核心参数输入!$B$9,建筑面积与开发计划!G23,0) -> 0 | H11: =IF(H$4<=核心参数输入!$B$9,建筑面积与开发计划!H23,0) -> 22275 | I11: =IF(I$4<=核心参数输入!$B$9,建筑面积与开发计划!I23,0) -> 29700 | J11: =IF(J$4<=核心参数输入!$B$9,建筑面积与开发计划!J23,0) -> 22275 | K11: =IF(K$4<=核心参数输入!$B$9,建筑面积与开发计划!K23,0) -> 0 | ... AH11: =IF(AH$4<=核心参数输入!$B$9,建筑面积与开发计划!AH23,0) -> 0
A12: 销售价格 | B12: 元/平方米 | D12: =IF(D$4<=核心参数输入!$B$9,核心参数输入!$B$31,0) -> 6500 | E12: =IF(E$4<=核心参数输入!$B$9,核心参数输入!$B$31,0) -> 6500 | F12: =IF(F$4<=核心参数输入!$B$9,核心参数输入!$B$31,0) -> 6500 | G12: =IF(G$4<=核心参数输入!$B$9,核心参数输入!$B$31,0) -> 6500 | H12: =IF(H$4<=核心参数输入!$B$9,核心参数输入!$B$31,0) -> 6500 | I12: =IF(I$4<=核心参数输入!$B$9,核心参数输入!$B$31,0) -> 6500 | J12: =IF(J$4<=核心参数输入!$B$9,核心参数输入!$B$31,0) -> 6500 | K12: =IF(K$4<=核心参数输入!$B$9,核心参数输入!$B$31,0) -> 6500 | ... AH12: =IF(AH$4<=核心参数输入!$B$9,核心参数输入!$B$31,0) -> 0
A13: 销售回款 | B13: 万元 | D13: =IF(D$4<=核心参数输入!$B$9,D11*D12/10000,0) -> 0 | E13: =IF(E$4<=核心参数输入!$B$9,E11*E12/10000,0) -> 0 | F13: =IF(F$4<=核心参数输入!$B$9,F11*F12/10000,0) -> 0 | G13: =IF(G$4<=核心参数输入!$B$9,G11*G12/10000,0) -> 0 | H13: =IF(H$4<=核心参数输入!$B$9,H11*H12/10000,0) -> 14478.75 | I13: =IF(I$4<=核心参数输入!$B$9,I11*I12/10000,0) -> 19305 | J13: =IF(J$4<=核心参数输入!$B$9,J11*J12/10000,0) -> 14478.75 | K13: =IF(K$4<=核心参数输入!$B$9,K11*K12/10000,0) -> 0 | ... AH13: =IF(AH$4<=核心参数输入!$B$9,AH11*AH12/10000,0) -> 0
A14: 实际出租率 | B14: % | D14: =IF(D$4<=核心参数输入!$B$9,建筑面积与开发计划!D26,0) -> 0 | E14: =IF(E$4<=核心参数输入!$B$9,建筑面积与开发计划!E26,0) -> 0 | F14: =IF(F$4<=核心参数输入!$B$9,建筑面积与开发计划!F26,0) -> 0 | G14: =IF(G$4<=核心参数输入!$B$9,建筑面积与开发计划!G26,0) -> 0 | H14: =IF(H$4<=核心参数输入!$B$9,建筑面积与开发计划!H26,0) -> 0.5 | I14: =IF(I$4<=核心参数输入!$B$9,建筑面积与开发计划!I26,0) -> 0.7 | J14: =IF(J$4<=核心参数输入!$B$9,建筑面积与开发计划!J26,0) -> 0.85 | K14: =IF(K$4<=核心参数输入!$B$9,建筑面积与开发计划!K26,0) -> 0.9 | ... AH14: =IF(AH$4<=核心参数输入!$B$9,建筑面积与开发计划!AH26,0) -> 0
A15: 已出租面积 | B15: 平方米 | D15: =IF(D$4<=核心参数输入!$B$9,建筑面积与开发计划!D27,0) -> 0 | E15: =IF(E$4<=核心参数输入!$B$9,建筑面积与开发计划!E27,0) -> 0 | F15: =IF(F$4<=核心参数输入!$B$9,建筑面积与开发计划!F27,0) -> 0 | G15: =IF(G$4<=核心参数输入!$B$9,建筑面积与开发计划!G27,0) -> 0 | H15: =IF(H$4<=核心参数输入!$B$9,建筑面积与开发计划!H27,0) -> 30375 | I15: =IF(I$4<=核心参数输入!$B$9,建筑面积与开发计划!I27,0) -> 42525 | J15: =IF(J$4<=核心参数输入!$B$9,建筑面积与开发计划!J27,0) -> 51637.5 | K15: =IF(K$4<=核心参数输入!$B$9,建筑面积与开发计划!K27,0) -> 54675 | ... AH15: =IF(AH$4<=核心参数输入!$B$9,建筑面积与开发计划!AH27,0) -> 0
A16: 新增出租面积 | B16: 平方米 | D16: =IF(D$4<=核心参数输入!$B$9,建筑面积与开发计划!D28,0) -> 0 | E16: =IF(E$4<=核心参数输入!$B$9,建筑面积与开发计划!E28,0) -> 0 | F16: =IF(F$4<=核心参数输入!$B$9,建筑面积与开发计划!F28,0) -> 0 | G16: =IF(G$4<=核心参数输入!$B$9,建筑面积与开发计划!G28,0) -> 0 | H16: =IF(H$4<=核心参数输入!$B$9,建筑面积与开发计划!H28,0) -> 30375 | I16: =IF(I$4<=核心参数输入!$B$9,建筑面积与开发计划!I28,0) -> 12150 | J16: =IF(J$4<=核心参数输入!$B$9,建筑面积与开发计划!J28,0) -> 9112.5 | K16: =IF(K$4<=核心参数输入!$B$9,建筑面积与开发计划!K28,0) -> 3037.5 | ... AH16: =IF(AH$4<=核心参数输入!$B$9,建筑面积与开发计划!AH28,0) -> 0
A17: 出租第几个年度 | B17: 年 | D17: =IF(D$4<=核心参数输入!$B$9,建筑面积与开发计划!D25,0) -> 0 | E17: =IF(E$4<=核心参数输入!$B$9,建筑面积与开发计划!E25,0) -> 0 | F17: =IF(F$4<=核心参数输入!$B$9,建筑面积与开发计划!F25,0) -> 0 | G17: =IF(G$4<=核心参数输入!$B$9,建筑面积与开发计划!G25,0) -> 0 | H17: =IF(H$4<=核心参数输入!$B$9,建筑面积与开发计划!H25,0) -> 1 | I17: =IF(I$4<=核心参数输入!$B$9,建筑面积与开发计划!I25,0) -> 2 | J17: =IF(J$4<=核心参数输入!$B$9,建筑面积与开发计划!J25,0) -> 3 | K17: =IF(K$4<=核心参数输入!$B$9,建筑面积与开发计划!K25,0) -> 4 | ... AH17: =IF(AH$4<=核心参数输入!$B$9,建筑面积与开发计划!AH25,0) -> 0
A18: 月租金 | B18: 元/平方米/月 | D18: =IF(D$4<=核心参数输入!$B$9,IF(D17>0,核心参数输入!$B$36*(1+核心参数输入!$B$37)^MAX(0,D17-1),0),0) -> 0 | E18: =IF(E$4<=核心参数输入!$B$9,IF(E17>0,核心参数输入!$B$36*(1+核心参数输入!$B$37)^MAX(0,E17-1),0),0) -> 0 | F18: =IF(F$4<=核心参数输入!$B$9,IF(F17>0,核心参数输入!$B$36*(1+核心参数输入!$B$37)^MAX(0,F17-1),0),0) -> 0 | G18: =IF(G$4<=核心参数输入!$B$9,IF(G17>0,核心参数输入!$B$36*(1+核心参数输入!$B$37)^MAX(0,G17-1),0),0) -> 0 | H18: =IF(H$4<=核心参数输入!$B$9,IF(H17>0,核心参数输入!$B$36*(1+核心参数输入!$B$37)^MAX(0,H17-1),0),0) -> 26 | I18: =IF(I$4<=核心参数输入!$B$9,IF(I17>0,核心参数输入!$B$36*(1+核心参数输入!$B$37)^MAX(0,I17-1),0),0) -> 26.39 | J18: =IF(J$4<=核心参数输入!$B$9,IF(J17>0,核心参数输入!$B$36*(1+核心参数输入!$B$37)^MAX(0,J17-1),0),0) -> 26.78585 | K18: =IF(K$4<=核心参数输入!$B$9,IF(K17>0,核心参数输入!$B$36*(1+核心参数输入!$B$37)^MAX(0,K17-1),0),0) -> 27.187638 | ... AH18: =IF(AH$4<=核心参数输入!$B$9,IF(AH17>0,核心参数输入!$B$36*(1+核心参数输入!$B$37)^MAX(0,AH17-1),0),0) -> 0
A19: 新增面积一次免租损失 | B19: 万元 | D19: =IF(D$4<=核心参数输入!$B$9,D16*D18*核心参数输入!$B$42/10000,0) -> 0 | E19: =IF(E$4<=核心参数输入!$B$9,E16*E18*核心参数输入!$B$42/10000,0) -> 0 | F19: =IF(F$4<=核心参数输入!$B$9,F16*F18*核心参数输入!$B$42/10000,0) -> 0 | G19: =IF(G$4<=核心参数输入!$B$9,G16*G18*核心参数输入!$B$42/10000,0) -> 0 | H19: =IF(H$4<=核心参数输入!$B$9,H16*H18*核心参数输入!$B$42/10000,0) -> 236.925 | I19: =IF(I$4<=核心参数输入!$B$9,I16*I18*核心参数输入!$B$42/10000,0) -> 96.19155 | J19: =IF(J$4<=核心参数输入!$B$9,J16*J18*核心参数输入!$B$42/10000,0) -> 73.225817 | K19: =IF(K$4<=核心参数输入!$B$9,K16*K18*核心参数输入!$B$42/10000,0) -> 24.774735 | ... AH19: =IF(AH$4<=核心参数输入!$B$9,AH16*AH18*核心参数输入!$B$42/10000,0) -> 0
A20: 实收租金 | B20: 万元 | D20: =IF(D$4<=核心参数输入!$B$9,(D15*D18*12/10000-D19)*核心参数输入!$B$43,0) -> 0 | E20: =IF(E$4<=核心参数输入!$B$9,(E15*E18*12/10000-E19)*核心参数输入!$B$43,0) -> 0 | F20: =IF(F$4<=核心参数输入!$B$9,(F15*F18*12/10000-F19)*核心参数输入!$B$43,0) -> 0 | G20: =IF(G$4<=核心参数输入!$B$9,(G15*G18*12/10000-G19)*核心参数输入!$B$43,0) -> 0 | H20: =IF(H$4<=核心参数输入!$B$9,(H15*H18*12/10000-H19)*核心参数输入!$B$43,0) -> 696.5595 | I20: =IF(I$4<=核心参数输入!$B$9,(I15*I18*12/10000-I19)*核心参数输入!$B$43,0) -> 1225.4803 | J20: =IF(J$4<=核心参数输入!$B$9,(J15*J18*12/10000-J19)*核心参数输入!$B$43,0) -> 1554.8282 | K20: =IF(K$4<=核心参数输入!$B$9,(K15*K18*12/10000-K19)*核心参数输入!$B$43,0) -> 1723.8261 | ... AH20: =IF(AH$4<=核心参数输入!$B$9,(AH15*AH18*12/10000-AH19)*核心参数输入!$B$43,0) -> 0
A21: 其他经营收入 | B21: 万元 | D21: =IF(D$4<=核心参数输入!$B$9,D20*核心参数输入!$B$44,0) -> 0 | E21: =IF(E$4<=核心参数输入!$B$9,E20*核心参数输入!$B$44,0) -> 0 | F21: =IF(F$4<=核心参数输入!$B$9,F20*核心参数输入!$B$44,0) -> 0 | G21: =IF(G$4<=核心参数输入!$B$9,G20*核心参数输入!$B$44,0) -> 0 | H21: =IF(H$4<=核心参数输入!$B$9,H20*核心参数输入!$B$44,0) -> 34.827975 | I21: =IF(I$4<=核心参数输入!$B$9,I20*核心参数输入!$B$44,0) -> 61.274017 | J21: =IF(J$4<=核心参数输入!$B$9,J20*核心参数输入!$B$44,0) -> 77.74141 | K21: =IF(K$4<=核心参数输入!$B$9,K20*核心参数输入!$B$44,0) -> 86.191303 | ... AH21: =IF(AH$4<=核心参数输入!$B$9,AH20*核心参数输入!$B$44,0) -> 0
A22: 持有经营收入合计 | B22: 万元 | D22: =IF(D$4<=核心参数输入!$B$9,SUM(D20:D21),0) -> 0 | E22: =IF(E$4<=核心参数输入!$B$9,SUM(E20:E21),0) -> 0 | F22: =IF(F$4<=核心参数输入!$B$9,SUM(F20:F21),0) -> 0 | G22: =IF(G$4<=核心参数输入!$B$9,SUM(G20:G21),0) -> 0 | H22: =IF(H$4<=核心参数输入!$B$9,SUM(H20:H21),0) -> 731.38747 | I22: =IF(I$4<=核心参数输入!$B$9,SUM(I20:I21),0) -> 1286.7544 | J22: =IF(J$4<=核心参数输入!$B$9,SUM(J20:J21),0) -> 1632.5696 | K22: =IF(K$4<=核心参数输入!$B$9,SUM(K20:K21),0) -> 1810.0174 | ... AH22: =IF(AH$4<=核心参数输入!$B$9,SUM(AH20:AH21),0) -> 0
A23: 营业收入合计 | B23: 万元 | D23: =IF(D$4<=核心参数输入!$B$9,D13+D22,0) -> 0 | E23: =IF(E$4<=核心参数输入!$B$9,E13+E22,0) -> 0 | F23: =IF(F$4<=核心参数输入!$B$9,F13+F22,0) -> 0 | G23: =IF(G$4<=核心参数输入!$B$9,G13+G22,0) -> 0 | H23: =IF(H$4<=核心参数输入!$B$9,H13+H22,0) -> 15210.137 | I23: =IF(I$4<=核心参数输入!$B$9,I13+I22,0) -> 20591.754 | J23: =IF(J$4<=核心参数输入!$B$9,J13+J22,0) -> 16111.32 | K23: =IF(K$4<=核心参数输入!$B$9,K13+K22,0) -> 1810.0174 | ... AH23: =IF(AH$4<=核心参数输入!$B$9,AH13+AH22,0) -> 0
A24: 期末持有物业处置价 | B24: 万元 | D24: =IF(D$4<=核心参数输入!$B$9,IF(AND(核心参数输入!$B$64=1,D$4=核心参数输入!$B$9),核心参数输入!$B$65,0),0) -> 0 | E24: =IF(E$4<=核心参数输入!$B$9,IF(AND(核心参数输入!$B$64=1,E$4=核心参数输入!$B$9),核心参数输入!$B$65,0),0) -> 0 | F24: =IF(F$4<=核心参数输入!$B$9,IF(AND(核心参数输入!$B$64=1,F$4=核心参数输入!$B$9),核心参数输入!$B$65,0),0) -> 0 | G24: =IF(G$4<=核心参数输入!$B$9,IF(AND(核心参数输入!$B$64=1,G$4=核心参数输入!$B$9),核心参数输入!$B$65,0),0) -> 0 | H24: =IF(H$4<=核心参数输入!$B$9,IF(AND(核心参数输入!$B$64=1,H$4=核心参数输入!$B$9),核心参数输入!$B$65,0),0) -> 0 | I24: =IF(I$4<=核心参数输入!$B$9,IF(AND(核心参数输入!$B$64=1,I$4=核心参数输入!$B$9),核心参数输入!$B$65,0),0) -> 0 | J24: =IF(J$4<=核心参数输入!$B$9,IF(AND(核心参数输入!$B$64=1,J$4=核心参数输入!$B$9),核心参数输入!$B$65,0),0) -> 0 | K24: =IF(K$4<=核心参数输入!$B$9,IF(AND(核心参数输入!$B$64=1,K$4=核心参数输入!$B$9),核心参数输入!$B$65,0),0) -> 0 | ... AH24: =IF(AH$4<=核心参数输入!$B$9,IF(AND(核心参数输入!$B$64=1,AH$4=核心参数输入!$B$9),核心参数输入!$B$65,0),0) -> 0
A25: 处置交易费用含简税 | B25: 万元 | D25: =IF(D$4<=核心参数输入!$B$9,D24*核心参数输入!$B$66,0) -> 0 | E25: =IF(E$4<=核心参数输入!$B$9,E24*核心参数输入!$B$66,0) -> 0 | F25: =IF(F$4<=核心参数输入!$B$9,F24*核心参数输入!$B$66,0) -> 0 | G25: =IF(G$4<=核心参数输入!$B$9,G24*核心参数输入!$B$66,0) -> 0 | H25: =IF(H$4<=核心参数输入!$B$9,H24*核心参数输入!$B$66,0) -> 0 | I25: =IF(I$4<=核心参数输入!$B$9,I24*核心参数输入!$B$66,0) -> 0 | J25: =IF(J$4<=核心参数输入!$B$9,J24*核心参数输入!$B$66,0) -> 0 | K25: =IF(K$4<=核心参数输入!$B$9,K24*核心参数输入!$B$66,0) -> 0 | ... AH25: =IF(AH$4<=核心参数输入!$B$9,AH24*核心参数输入!$B$66,0) -> 0
A26: 期末处置净收入（所得税前） | B26: 万元 | D26: =IF(D$4<=核心参数输入!$B$9,D24-D25,0) -> 0 | E26: =IF(E$4<=核心参数输入!$B$9,E24-E25,0) -> 0 | F26: =IF(F$4<=核心参数输入!$B$9,F24-F25,0) -> 0 | G26: =IF(G$4<=核心参数输入!$B$9,G24-G25,0) -> 0 | H26: =IF(H$4<=核心参数输入!$B$9,H24-H25,0) -> 0 | I26: =IF(I$4<=核心参数输入!$B$9,I24-I25,0) -> 0 | J26: =IF(J$4<=核心参数输入!$B$9,J24-J25,0) -> 0 | K26: =IF(K$4<=核心参数输入!$B$9,K24-K25,0) -> 0 | ... AH26: =IF(AH$4<=核心参数输入!$B$9,AH24-AH25,0) -> 0
A87: 组合压力情景 · 同时降低售价、租金和出租率
A90: 年度销售比例 | B90: % | D90: =IF(D$4<=核心参数输入!$B$9,建筑面积与开发计划!D101,0) -> 0 | E90: =IF(E$4<=核心参数输入!$B$9,建筑面积与开发计划!E101,0) -> 0 | F90: =IF(F$4<=核心参数输入!$B$9,建筑面积与开发计划!F101,0) -> 0 | G90: =IF(G$4<=核心参数输入!$B$9,建筑面积与开发计划!G101,0) -> 0 | H90: =IF(H$4<=核心参数输入!$B$9,建筑面积与开发计划!H101,0) -> 0.3 | I90: =IF(I$4<=核心参数输入!$B$9,建筑面积与开发计划!I101,0) -> 0.4 | J90: =IF(J$4<=核心参数输入!$B$9,建筑面积与开发计划!J101,0) -> 0.3 | K90: =IF(K$4<=核心参数输入!$B$9,建筑面积与开发计划!K101,0) -> 0 | ... AH90: =IF(AH$4<=核心参数输入!$B$9,建筑面积与开发计划!AH101,0) -> 0
A91: 当年销售面积 | B91: 平方米 | D91: =IF(D$4<=核心参数输入!$B$9,建筑面积与开发计划!D103,0) -> 0 | E91: =IF(E$4<=核心参数输入!$B$9,建筑面积与开发计划!E103,0) -> 0 | F91: =IF(F$4<=核心参数输入!$B$9,建筑面积与开发计划!F103,0) -> 0 | G91: =IF(G$4<=核心参数输入!$B$9,建筑面积与开发计划!G103,0) -> 0 | H91: =IF(H$4<=核心参数输入!$B$9,建筑面积与开发计划!H103,0) -> 22275 | I91: =IF(I$4<=核心参数输入!$B$9,建筑面积与开发计划!I103,0) -> 29700 | J91: =IF(J$4<=核心参数输入!$B$9,建筑面积与开发计划!J103,0) -> 22275 | K91: =IF(K$4<=核心参数输入!$B$9,建筑面积与开发计划!K103,0) -> 0 | ... AH91: =IF(AH$4<=核心参数输入!$B$9,建筑面积与开发计划!AH103,0) -> 0
A92: 销售价格 | B92: 元/平方米 | D92: =IF(D$4<=核心参数输入!$B$9,核心参数输入!$B$31*(1-核心参数输入!$B$78),0) -> 5850 | E92: =IF(E$4<=核心参数输入!$B$9,核心参数输入!$B$31*(1-核心参数输入!$B$78),0) -> 5850 | F92: =IF(F$4<=核心参数输入!$B$9,核心参数输入!$B$31*(1-核心参数输入!$B$78),0) -> 5850 | G92: =IF(G$4<=核心参数输入!$B$9,核心参数输入!$B$31*(1-核心参数输入!$B$78),0) -> 5850 | H92: =IF(H$4<=核心参数输入!$B$9,核心参数输入!$B$31*(1-核心参数输入!$B$78),0) -> 5850 | I92: =IF(I$4<=核心参数输入!$B$9,核心参数输入!$B$31*(1-核心参数输入!$B$78),0) -> 5850 | J92: =IF(J$4<=核心参数输入!$B$9,核心参数输入!$B$31*(1-核心参数输入!$B$78),0) -> 5850 | K92: =IF(K$4<=核心参数输入!$B$9,核心参数输入!$B$31*(1-核心参数输入!$B$78),0) -> 5850 | ... AH92: =IF(AH$4<=核心参数输入!$B$9,核心参数输入!$B$31*(1-核心参数输入!$B$78),0) -> 0
A93: 销售回款 | B93: 万元 | D93: =IF(D$4<=核心参数输入!$B$9,D91*D92/10000,0) -> 0 | E93: =IF(E$4<=核心参数输入!$B$9,E91*E92/10000,0) -> 0 | F93: =IF(F$4<=核心参数输入!$B$9,F91*F92/10000,0) -> 0 | G93: =IF(G$4<=核心参数输入!$B$9,G91*G92/10000,0) -> 0 | H93: =IF(H$4<=核心参数输入!$B$9,H91*H92/10000,0) -> 13030.875 | I93: =IF(I$4<=核心参数输入!$B$9,I91*I92/10000,0) -> 17374.5 | J93: =IF(J$4<=核心参数输入!$B$9,J91*J92/10000,0) -> 13030.875 | K93: =IF(K$4<=核心参数输入!$B$9,K91*K92/10000,0) -> 0 | ... AH93: =IF(AH$4<=核心参数输入!$B$9,AH91*AH92/10000,0) -> 0
A94: 实际出租率 | B94: % | D94: =IF(D$4<=核心参数输入!$B$9,建筑面积与开发计划!D106,0) -> 0 | E94: =IF(E$4<=核心参数输入!$B$9,建筑面积与开发计划!E106,0) -> 0 | F94: =IF(F$4<=核心参数输入!$B$9,建筑面积与开发计划!F106,0) -> 0 | G94: =IF(G$4<=核心参数输入!$B$9,建筑面积与开发计划!G106,0) -> 0 | H94: =IF(H$4<=核心参数输入!$B$9,建筑面积与开发计划!H106,0) -> 0.4 | I94: =IF(I$4<=核心参数输入!$B$9,建筑面积与开发计划!I106,0) -> 0.6 | J94: =IF(J$4<=核心参数输入!$B$9,建筑面积与开发计划!J106,0) -> 0.75 | K94: =IF(K$4<=核心参数输入!$B$9,建筑面积与开发计划!K106,0) -> 0.8 | ... AH94: =IF(AH$4<=核心参数输入!$B$9,建筑面积与开发计划!AH106,0) -> 0
A95: 已出租面积 | B95: 平方米 | D95: =IF(D$4<=核心参数输入!$B$9,建筑面积与开发计划!D107,0) -> 0 | E95: =IF(E$4<=核心参数输入!$B$9,建筑面积与开发计划!E107,0) -> 0 | F95: =IF(F$4<=核心参数输入!$B$9,建筑面积与开发计划!F107,0) -> 0 | G95: =IF(G$4<=核心参数输入!$B$9,建筑面积与开发计划!G107,0) -> 0 | H95: =IF(H$4<=核心参数输入!$B$9,建筑面积与开发计划!H107,0) -> 24300 | I95: =IF(I$4<=核心参数输入!$B$9,建筑面积与开发计划!I107,0) -> 36450 | J95: =IF(J$4<=核心参数输入!$B$9,建筑面积与开发计划!J107,0) -> 45562.5 | K95: =IF(K$4<=核心参数输入!$B$9,建筑面积与开发计划!K107,0) -> 48600 | ... AH95: =IF(AH$4<=核心参数输入!$B$9,建筑面积与开发计划!AH107,0) -> 0
A96: 新增出租面积 | B96: 平方米 | D96: =IF(D$4<=核心参数输入!$B$9,建筑面积与开发计划!D108,0) -> 0 | E96: =IF(E$4<=核心参数输入!$B$9,建筑面积与开发计划!E108,0) -> 0 | F96: =IF(F$4<=核心参数输入!$B$9,建筑面积与开发计划!F108,0) -> 0 | G96: =IF(G$4<=核心参数输入!$B$9,建筑面积与开发计划!G108,0) -> 0 | H96: =IF(H$4<=核心参数输入!$B$9,建筑面积与开发计划!H108,0) -> 24300 | I96: =IF(I$4<=核心参数输入!$B$9,建筑面积与开发计划!I108,0) -> 12150 | J96: =IF(J$4<=核心参数输入!$B$9,建筑面积与开发计划!J108,0) -> 9112.5 | K96: =IF(K$4<=核心参数输入!$B$9,建筑面积与开发计划!K108,0) -> 3037.5 | ... AH96: =IF(AH$4<=核心参数输入!$B$9,建筑面积与开发计划!AH108,0) -> 0
A97: 出租第几个年度 | B97: 年 | D97: =IF(D$4<=核心参数输入!$B$9,建筑面积与开发计划!D105,0) -> 0 | E97: =IF(E$4<=核心参数输入!$B$9,建筑面积与开发计划!E105,0) -> 0 | F97: =IF(F$4<=核心参数输入!$B$9,建筑面积与开发计划!F105,0) -> 0 | G97: =IF(G$4<=核心参数输入!$B$9,建筑面积与开发计划!G105,0) -> 0 | H97: =IF(H$4<=核心参数输入!$B$9,建筑面积与开发计划!H105,0) -> 1 | I97: =IF(I$4<=核心参数输入!$B$9,建筑面积与开发计划!I105,0) -> 2 | J97: =IF(J$4<=核心参数输入!$B$9,建筑面积与开发计划!J105,0) -> 3 | K97: =IF(K$4<=核心参数输入!$B$9,建筑面积与开发计划!K105,0) -> 4 | ... AH97: =IF(AH$4<=核心参数输入!$B$9,建筑面积与开发计划!AH105,0) -> 0
A98: 月租金 | B98: 元/平方米/月 | D98: =IF(D$4<=核心参数输入!$B$9,IF(D97>0,核心参数输入!$B$36*(1+核心参数输入!$B$37)^MAX(0,D97-1)*(1-核心参数输入!$B$79),0),0) -> 0 | E98: =IF(E$4<=核心参数输入!$B$9,IF(E97>0,核心参数输入!$B$36*(1+核心参数输入!$B$37)^MAX(0,E97-1)*(1-核心参数输入!$B$79),0),0) -> 0 | F98: =IF(F$4<=核心参数输入!$B$9,IF(F97>0,核心参数输入!$B$36*(1+核心参数输入!$B$37)^MAX(0,F97-1)*(1-核心参数输入!$B$79),0),0) -> 0 | G98: =IF(G$4<=核心参数输入!$B$9,IF(G97>0,核心参数输入!$B$36*(1+核心参数输入!$B$37)^MAX(0,G97-1)*(1-核心参数输入!$B$79),0),0) -> 0 | H98: =IF(H$4<=核心参数输入!$B$9,IF(H97>0,核心参数输入!$B$36*(1+核心参数输入!$B$37)^MAX(0,H97-1)*(1-核心参数输入!$B$79),0),0) -> 23.4 | I98: =IF(I$4<=核心参数输入!$B$9,IF(I97>0,核心参数输入!$B$36*(1+核心参数输入!$B$37)^MAX(0,I97-1)*(1-核心参数输入!$B$79),0),0) -> 23.751 | J98: =IF(J$4<=核心参数输入!$B$9,IF(J97>0,核心参数输入!$B$36*(1+核心参数输入!$B$37)^MAX(0,J97-1)*(1-核心参数输入!$B$79),0),0) -> 24.107265 | K98: =IF(K$4<=核心参数输入!$B$9,IF(K97>0,核心参数输入!$B$36*(1+核心参数输入!$B$37)^MAX(0,K97-1)*(1-核心参数输入!$B$79),0),0) -> 24.468874 | ... AH98: =IF(AH$4<=核心参数输入!$B$9,IF(AH97>0,核心参数输入!$B$36*(1+核心参数输入!$B$37)^MAX(0,AH97-1)*(1-核心参数输入!$B$79),0),0) -> 0
A99: 新增面积一次免租损失 | B99: 万元 | D99: =IF(D$4<=核心参数输入!$B$9,D96*D98*核心参数输入!$B$42/10000,0) -> 0 | E99: =IF(E$4<=核心参数输入!$B$9,E96*E98*核心参数输入!$B$42/10000,0) -> 0 | F99: =IF(F$4<=核心参数输入!$B$9,F96*F98*核心参数输入!$B$42/10000,0) -> 0 | G99: =IF(G$4<=核心参数输入!$B$9,G96*G98*核心参数输入!$B$42/10000,0) -> 0 | H99: =IF(H$4<=核心参数输入!$B$9,H96*H98*核心参数输入!$B$42/10000,0) -> 170.586 | I99: =IF(I$4<=核心参数输入!$B$9,I96*I98*核心参数输入!$B$42/10000,0) -> 86.572395 | J99: =IF(J$4<=核心参数输入!$B$9,J96*J98*核心参数输入!$B$42/10000,0) -> 65.903236 | K99: =IF(K$4<=核心参数输入!$B$9,K96*K98*核心参数输入!$B$42/10000,0) -> 22.297261 | ... AH99: =IF(AH$4<=核心参数输入!$B$9,AH96*AH98*核心参数输入!$B$42/10000,0) -> 0
A100: 实收租金 | B100: 万元 | D100: =IF(D$4<=核心参数输入!$B$9,(D95*D98*12/10000-D99)*核心参数输入!$B$43,0) -> 0 | E100: =IF(E$4<=核心参数输入!$B$9,(E95*E98*12/10000-E99)*核心参数输入!$B$43,0) -> 0 | F100: =IF(F$4<=核心参数输入!$B$9,(F95*F98*12/10000-F99)*核心参数输入!$B$43,0) -> 0 | G100: =IF(G$4<=核心参数输入!$B$9,(G95*G98*12/10000-G99)*核心参数输入!$B$43,0) -> 0 | H100: =IF(H$4<=核心参数输入!$B$9,(H95*H98*12/10000-H99)*核心参数输入!$B$43,0) -> 501.52284 | I100: =IF(I$4<=核心参数输入!$B$9,(I95*I98*12/10000-I99)*核心参数输入!$B$43,0) -> 933.25042 | J100: =IF(J$4<=核心参数输入!$B$9,(J95*J98*12/10000-J99)*核心参数输入!$B$43,0) -> 1227.1182 | K100: =IF(K$4<=核心参数输入!$B$9,(K95*K98*12/10000-K99)*核心参数输入!$B$43,0) -> 1376.6329 | ... AH100: =IF(AH$4<=核心参数输入!$B$9,(AH95*AH98*12/10000-AH99)*核心参数输入!$B$43,0) -> 0
A101: 其他经营收入 | B101: 万元 | D101: =IF(D$4<=核心参数输入!$B$9,D100*核心参数输入!$B$44,0) -> 0 | E101: =IF(E$4<=核心参数输入!$B$9,E100*核心参数输入!$B$44,0) -> 0 | F101: =IF(F$4<=核心参数输入!$B$9,F100*核心参数输入!$B$44,0) -> 0 | G101: =IF(G$4<=核心参数输入!$B$9,G100*核心参数输入!$B$44,0) -> 0 | H101: =IF(H$4<=核心参数输入!$B$9,H100*核心参数输入!$B$44,0) -> 25.076142 | I101: =IF(I$4<=核心参数输入!$B$9,I100*核心参数输入!$B$44,0) -> 46.662521 | J101: =IF(J$4<=核心参数输入!$B$9,J100*核心参数输入!$B$44,0) -> 61.355912 | K101: =IF(K$4<=核心参数输入!$B$9,K100*核心参数输入!$B$44,0) -> 68.831646 | ... AH101: =IF(AH$4<=核心参数输入!$B$9,AH100*核心参数输入!$B$44,0) -> 0
A102: 持有经营收入合计 | B102: 万元 | D102: =IF(D$4<=核心参数输入!$B$9,SUM(D100:D101),0) -> 0 | E102: =IF(E$4<=核心参数输入!$B$9,SUM(E100:E101),0) -> 0 | F102: =IF(F$4<=核心参数输入!$B$9,SUM(F100:F101),0) -> 0 | G102: =IF(G$4<=核心参数输入!$B$9,SUM(G100:G101),0) -> 0 | H102: =IF(H$4<=核心参数输入!$B$9,SUM(H100:H101),0) -> 526.59898 | I102: =IF(I$4<=核心参数输入!$B$9,SUM(I100:I101),0) -> 979.91294 | J102: =IF(J$4<=核心参数输入!$B$9,SUM(J100:J101),0) -> 1288.4742 | K102: =IF(K$4<=核心参数输入!$B$9,SUM(K100:K101),0) -> 1445.4646 | ... AH102: =IF(AH$4<=核心参数输入!$B$9,SUM(AH100:AH101),0) -> 0
A103: 营业收入合计 | B103: 万元 | D103: =IF(D$4<=核心参数输入!$B$9,D93+D102,0) -> 0 | E103: =IF(E$4<=核心参数输入!$B$9,E93+E102,0) -> 0 | F103: =IF(F$4<=核心参数输入!$B$9,F93+F102,0) -> 0 | G103: =IF(G$4<=核心参数输入!$B$9,G93+G102,0) -> 0 | H103: =IF(H$4<=核心参数输入!$B$9,H93+H102,0) -> 13557.474 | I103: =IF(I$4<=核心参数输入!$B$9,I93+I102,0) -> 18354.413 | J103: =IF(J$4<=核心参数输入!$B$9,J93+J102,0) -> 14319.349 | K103: =IF(K$4<=核心参数输入!$B$9,K93+K102,0) -> 1445.4646 | ... AH103: =IF(AH$4<=核心参数输入!$B$9,AH93+AH102,0) -> 0
A104: 期末持有物业处置价 | B104: 万元 | D104: =IF(D$4<=核心参数输入!$B$9,IF(AND(核心参数输入!$B$64=1,D$4=核心参数输入!$B$9),核心参数输入!$B$65,0),0) -> 0 | E104: =IF(E$4<=核心参数输入!$B$9,IF(AND(核心参数输入!$B$64=1,E$4=核心参数输入!$B$9),核心参数输入!$B$65,0),0) -> 0 | F104: =IF(F$4<=核心参数输入!$B$9,IF(AND(核心参数输入!$B$64=1,F$4=核心参数输入!$B$9),核心参数输入!$B$65,0),0) -> 0 | G104: =IF(G$4<=核心参数输入!$B$9,IF(AND(核心参数输入!$B$64=1,G$4=核心参数输入!$B$9),核心参数输入!$B$65,0),0) -> 0 | H104: =IF(H$4<=核心参数输入!$B$9,IF(AND(核心参数输入!$B$64=1,H$4=核心参数输入!$B$9),核心参数输入!$B$65,0),0) -> 0 | I104: =IF(I$4<=核心参数输入!$B$9,IF(AND(核心参数输入!$B$64=1,I$4=核心参数输入!$B$9),核心参数输入!$B$65,0),0) -> 0 | J104: =IF(J$4<=核心参数输入!$B$9,IF(AND(核心参数输入!$B$64=1,J$4=核心参数输入!$B$9),核心参数输入!$B$65,0),0) -> 0 | K104: =IF(K$4<=核心参数输入!$B$9,IF(AND(核心参数输入!$B$64=1,K$4=核心参数输入!$B$9),核心参数输入!$B$65,0),0) -> 0 | ... AH104: =IF(AH$4<=核心参数输入!$B$9,IF(AND(核心参数输入!$B$64=1,AH$4=核心参数输入!$B$9),核心参数输入!$B$65,0),0) -> 0
A105: 处置交易费用含简税 | B105: 万元 | D105: =IF(D$4<=核心参数输入!$B$9,D104*核心参数输入!$B$66,0) -> 0 | E105: =IF(E$4<=核心参数输入!$B$9,E104*核心参数输入!$B$66,0) -> 0 | F105: =IF(F$4<=核心参数输入!$B$9,F104*核心参数输入!$B$66,0) -> 0 | G105: =IF(G$4<=核心参数输入!$B$9,G104*核心参数输入!$B$66,0) -> 0 | H105: =IF(H$4<=核心参数输入!$B$9,H104*核心参数输入!$B$66,0) -> 0 | I105: =IF(I$4<=核心参数输入!$B$9,I104*核心参数输入!$B$66,0) -> 0 | J105: =IF(J$4<=核心参数输入!$B$9,J104*核心参数输入!$B$66,0) -> 0 | K105: =IF(K$4<=核心参数输入!$B$9,K104*核心参数输入!$B$66,0) -> 0 | ... AH105: =IF(AH$4<=核心参数输入!$B$9,AH104*核心参数输入!$B$66,0) -> 0
A106: 期末处置净收入（所得税前） | B106: 万元 | D106: =IF(D$4<=核心参数输入!$B$9,D104-D105,0) -> 0 | E106: =IF(E$4<=核心参数输入!$B$9,E104-E105,0) -> 0 | F106: =IF(F$4<=核心参数输入!$B$9,F104-F105,0) -> 0 | G106: =IF(G$4<=核心参数输入!$B$9,G104-G105,0) -> 0 | H106: =IF(H$4<=核心参数输入!$B$9,H104-H105,0) -> 0 | I106: =IF(I$4<=核心参数输入!$B$9,I104-I105,0) -> 0 | J106: =IF(J$4<=核心参数输入!$B$9,J104-J105,0) -> 0 | K106: =IF(K$4<=核心参数输入!$B$9,K104-K105,0) -> 0 | ... AH106: =IF(AH$4<=核心参数输入!$B$9,AH104-AH105,0) -> 0

Sheet 运营成本与税费
A2: 运营成本与税费 · 模拟数据
A4: 项目年度 / 日历年份 | D4: =核心参数输入!D87 -> 0 | E4: =核心参数输入!E87 -> 1 | F4: =核心参数输入!F87 -> 2 | G4: =核心参数输入!G87 -> 3 | H4: =核心参数输入!H87 -> 4 | I4: =核心参数输入!I87 -> 5 | J4: =核心参数输入!J87 -> 6 | K4: =核心参数输入!K87 -> 7 | ... AH4: =核心参数输入!AH87 -> 30
D5: =核心参数输入!$B$8+D4 -> 2026 | E5: =核心参数输入!$B$8+E4 -> 2027 | F5: =核心参数输入!$B$8+F4 -> 2028 | G5: =核心参数输入!$B$8+G4 -> 2029 | H5: =核心参数输入!$B$8+H4 -> 2030 | I5: =核心参数输入!$B$8+I4 -> 2031 | J5: =核心参数输入!$B$8+J4 -> 2032 | K5: =核心参数输入!$B$8+K4 -> 2033 | ... AH5: =核心参数输入!$B$8+AH4 -> 2056
A7: 基准情景 · 现金成本与非现金成本分开
A10: 销售费用现金支出 | B10: 万元 | D10: =IF(D$4<=核心参数输入!$B$9,销售与出租收入!D13*核心参数输入!$B$32,0) -> 0 | E10: =IF(E$4<=核心参数输入!$B$9,销售与出租收入!E13*核心参数输入!$B$32,0) -> 0 | F10: =IF(F$4<=核心参数输入!$B$9,销售与出租收入!F13*核心参数输入!$B$32,0) -> 0 | G10: =IF(G$4<=核心参数输入!$B$9,销售与出租收入!G13*核心参数输入!$B$32,0) -> 0 | H10: =IF(H$4<=核心参数输入!$B$9,销售与出租收入!H13*核心参数输入!$B$32,0) -> 361.96875 | I10: =IF(I$4<=核心参数输入!$B$9,销售与出租收入!I13*核心参数输入!$B$32,0) -> 482.625 | J10: =IF(J$4<=核心参数输入!$B$9,销售与出租收入!J13*核心参数输入!$B$32,0) -> 361.96875 | K10: =IF(K$4<=核心参数输入!$B$9,销售与出租收入!K13*核心参数输入!$B$32,0) -> 0 | ... AH10: =IF(AH$4<=核心参数输入!$B$9,销售与出租收入!AH13*核心参数输入!$B$32,0) -> 0
A11: 销售相关税费现金支出 | B11: 万元 | D11: =IF(D$4<=核心参数输入!$B$9,销售与出租收入!D13*核心参数输入!$B$33,0) -> 0 | E11: =IF(E$4<=核心参数输入!$B$9,销售与出租收入!E13*核心参数输入!$B$33,0) -> 0 | F11: =IF(F$4<=核心参数输入!$B$9,销售与出租收入!F13*核心参数输入!$B$33,0) -> 0 | G11: =IF(G$4<=核心参数输入!$B$9,销售与出租收入!G13*核心参数输入!$B$33,0) -> 0 | H11: =IF(H$4<=核心参数输入!$B$9,销售与出租收入!H13*核心参数输入!$B$33,0) -> 1158.3 | I11: =IF(I$4<=核心参数输入!$B$9,销售与出租收入!I13*核心参数输入!$B$33,0) -> 1544.4 | J11: =IF(J$4<=核心参数输入!$B$9,销售与出租收入!J13*核心参数输入!$B$33,0) -> 1158.3 | K11: =IF(K$4<=核心参数输入!$B$9,销售与出租收入!K13*核心参数输入!$B$33,0) -> 0 | ... AH11: =IF(AH$4<=核心参数输入!$B$9,销售与出租收入!AH13*核心参数输入!$B$33,0) -> 0
A12: 持有固定运营成本 | B12: 万元 | D12: =IF(D$4<=核心参数输入!$B$9,IF(D$4-核心参数输入!$B$16>0,核心参数输入!$B$47*(1+核心参数输入!$B$48)^MAX(0,D$4-核心参数输入!$B$16-1),0),0) -> 0 | E12: =IF(E$4<=核心参数输入!$B$9,IF(E$4-核心参数输入!$B$16>0,核心参数输入!$B$47*(1+核心参数输入!$B$48)^MAX(0,E$4-核心参数输入!$B$16-1),0),0) -> 0 | F12: =IF(F$4<=核心参数输入!$B$9,IF(F$4-核心参数输入!$B$16>0,核心参数输入!$B$47*(1+核心参数输入!$B$48)^MAX(0,F$4-核心参数输入!$B$16-1),0),0) -> 0 | G12: =IF(G$4<=核心参数输入!$B$9,IF(G$4-核心参数输入!$B$16>0,核心参数输入!$B$47*(1+核心参数输入!$B$48)^MAX(0,G$4-核心参数输入!$B$16-1),0),0) -> 0 | H12: =IF(H$4<=核心参数输入!$B$9,IF(H$4-核心参数输入!$B$16>0,核心参数输入!$B$47*(1+核心参数输入!$B$48)^MAX(0,H$4-核心参数输入!$B$16-1),0),0) -> 300 | I12: =IF(I$4<=核心参数输入!$B$9,IF(I$4-核心参数输入!$B$16>0,核心参数输入!$B$47*(1+核心参数输入!$B$48)^MAX(0,I$4-核心参数输入!$B$16-1),0),0) -> 306 | J12: =IF(J$4<=核心参数输入!$B$9,IF(J$4-核心参数输入!$B$16>0,核心参数输入!$B$47*(1+核心参数输入!$B$48)^MAX(0,J$4-核心参数输入!$B$16-1),0),0) -> 312.12 | K12: =IF(K$4<=核心参数输入!$B$9,IF(K$4-核心参数输入!$B$16>0,核心参数输入!$B$47*(1+核心参数输入!$B$48)^MAX(0,K$4-核心参数输入!$B$16-1),0),0) -> 318.3624 | ... AH12: =IF(AH$4<=核心参数输入!$B$9,IF(AH$4-核心参数输入!$B$16>0,核心参数输入!$B$47*(1+核心参数输入!$B$48)^MAX(0,AH$4-核心参数输入!$B$16-1),0),0) -> 0
A13: 持有变动运营成本 | B13: 万元 | D13: =IF(D$4<=核心参数输入!$B$9,销售与出租收入!D22*核心参数输入!$B$49,0) -> 0 | E13: =IF(E$4<=核心参数输入!$B$9,销售与出租收入!E22*核心参数输入!$B$49,0) -> 0 | F13: =IF(F$4<=核心参数输入!$B$9,销售与出租收入!F22*核心参数输入!$B$49,0) -> 0 | G13: =IF(G$4<=核心参数输入!$B$9,销售与出租收入!G22*核心参数输入!$B$49,0) -> 0 | H13: =IF(H$4<=核心参数输入!$B$9,销售与出租收入!H22*核心参数输入!$B$49,0) -> 87.766497 | I13: =IF(I$4<=核心参数输入!$B$9,销售与出租收入!I22*核心参数输入!$B$49,0) -> 154.41052 | J13: =IF(J$4<=核心参数输入!$B$9,销售与出租收入!J22*核心参数输入!$B$49,0) -> 195.90835 | K13: =IF(K$4<=核心参数输入!$B$9,销售与出租收入!K22*核心参数输入!$B$49,0) -> 217.20208 | ... AH13: =IF(AH$4<=核心参数输入!$B$9,销售与出租收入!AH22*核心参数输入!$B$49,0) -> 0
A14: 维护更新支出（当期费用化） | B14: 万元 | D14: =IF(D$4<=核心参数输入!$B$9,IF(D$4-核心参数输入!$B$16>0,核心参数输入!$B$50,0),0) -> 0 | E14: =IF(E$4<=核心参数输入!$B$9,IF(E$4-核心参数输入!$B$16>0,核心参数输入!$B$50,0),0) -> 0 | F14: =IF(F$4<=核心参数输入!$B$9,IF(F$4-核心参数输入!$B$16>0,核心参数输入!$B$50,0),0) -> 0 | G14: =IF(G$4<=核心参数输入!$B$9,IF(G$4-核心参数输入!$B$16>0,核心参数输入!$B$50,0),0) -> 0 | H14: =IF(H$4<=核心参数输入!$B$9,IF(H$4-核心参数输入!$B$16>0,核心参数输入!$B$50,0),0) -> 180 | I14: =IF(I$4<=核心参数输入!$B$9,IF(I$4-核心参数输入!$B$16>0,核心参数输入!$B$50,0),0) -> 180 | J14: =IF(J$4<=核心参数输入!$B$9,IF(J$4-核心参数输入!$B$16>0,核心参数输入!$B$50,0),0) -> 180 | K14: =IF(K$4<=核心参数输入!$B$9,IF(K$4-核心参数输入!$B$16>0,核心参数输入!$B$50,0),0) -> 180 | ... AH14: =IF(AH$4<=核心参数输入!$B$9,IF(AH$4-核心参数输入!$B$16>0,核心参数输入!$B$50,0),0) -> 0
A15: 运营相关税费 | B15: 万元 | D15: =IF(D$4<=核心参数输入!$B$9,销售与出租收入!D22*核心参数输入!$B$51,0) -> 0 | E15: =IF(E$4<=核心参数输入!$B$9,销售与出租收入!E22*核心参数输入!$B$51,0) -> 0 | F15: =IF(F$4<=核心参数输入!$B$9,销售与出租收入!F22*核心参数输入!$B$51,0) -> 0 | G15: =IF(G$4<=核心参数输入!$B$9,销售与出租收入!G22*核心参数输入!$B$51,0) -> 0 | H15: =IF(H$4<=核心参数输入!$B$9,销售与出租收入!H22*核心参数输入!$B$51,0) -> 43.883248 | I15: =IF(I$4<=核心参数输入!$B$9,销售与出租收入!I22*核心参数输入!$B$51,0) -> 77.205262 | J15: =IF(J$4<=核心参数输入!$B$9,销售与出租收入!J22*核心参数输入!$B$51,0) -> 97.954176 | K15: =IF(K$4<=核心参数输入!$B$9,销售与出租收入!K22*核心参数输入!$B$51,0) -> 108.60104 | ... AH15: =IF(AH$4<=核心参数输入!$B$9,销售与出租收入!AH22*核心参数输入!$B$51,0) -> 0
A16: 现金成本及经营税费合计 | B16: 万元 | D16: =IF(D$4<=核心参数输入!$B$9,SUM(D10:D15),0) -> 0 | E16: =IF(E$4<=核心参数输入!$B$9,SUM(E10:E15),0) -> 0 | F16: =IF(F$4<=核心参数输入!$B$9,SUM(F10:F15),0) -> 0 | G16: =IF(G$4<=核心参数输入!$B$9,SUM(G10:G15),0) -> 0 | H16: =IF(H$4<=核心参数输入!$B$9,SUM(H10:H15),0) -> 2131.9185 | I16: =IF(I$4<=核心参数输入!$B$9,SUM(I10:I15),0) -> 2744.6408 | J16: =IF(J$4<=核心参数输入!$B$9,SUM(J10:J15),0) -> 2306.2513 | K16: =IF(K$4<=核心参数输入!$B$9,SUM(K10:K15),0) -> 824.16552 | ... AH16: =IF(AH$4<=核心参数输入!$B$9,SUM(AH10:AH15),0) -> 0
A17: 销售成本结转（项目口径） | B17: 万元 | D17: =IF(D$4<=核心参数输入!$B$9,投资与资金安排!$B$19*建筑面积与开发计划!D21,0) -> 0 | E17: =IF(E$4<=核心参数输入!$B$9,投资与资金安排!$B$19*建筑面积与开发计划!E21,0) -> 0 | F17: =IF(F$4<=核心参数输入!$B$9,投资与资金安排!$B$19*建筑面积与开发计划!F21,0) -> 0 | G17: =IF(G$4<=核心参数输入!$B$9,投资与资金安排!$B$19*建筑面积与开发计划!G21,0) -> 0 | H17: =IF(H$4<=核心参数输入!$B$9,投资与资金安排!$B$19*建筑面积与开发计划!H21,0) -> 10051.8 | I17: =IF(I$4<=核心参数输入!$B$9,投资与资金安排!$B$19*建筑面积与开发计划!I21,0) -> 13402.4 | J17: =IF(J$4<=核心参数输入!$B$9,投资与资金安排!$B$19*建筑面积与开发计划!J21,0) -> 10051.8 | K17: =IF(K$4<=核心参数输入!$B$9,投资与资金安排!$B$19*建筑面积与开发计划!K21,0) -> 0 | ... AH17: =IF(AH$4<=核心参数输入!$B$9,投资与资金安排!$B$19*建筑面积与开发计划!AH21,0) -> 0
A18: 销售成本结转（融资口径） | B18: 万元 | D18: =IF(D$4<=核心参数输入!$B$9,投资与资金安排!$B$22*建筑面积与开发计划!D21,0) -> 0 | E18: =IF(E$4<=核心参数输入!$B$9,投资与资金安排!$B$22*建筑面积与开发计划!E21,0) -> 0 | F18: =IF(F$4<=核心参数输入!$B$9,投资与资金安排!$B$22*建筑面积与开发计划!F21,0) -> 0 | G18: =IF(G$4<=核心参数输入!$B$9,投资与资金安排!$B$22*建筑面积与开发计划!G21,0) -> 0 | H18: =IF(H$4<=核心参数输入!$B$9,投资与资金安排!$B$22*建筑面积与开发计划!H21,0) -> 10363.65 | I18: =IF(I$4<=核心参数输入!$B$9,投资与资金安排!$B$22*建筑面积与开发计划!I21,0) -> 13818.2 | J18: =IF(J$4<=核心参数输入!$B$9,投资与资金安排!$B$22*建筑面积与开发计划!J21,0) -> 10363.65 | K18: =IF(K$4<=核心参数输入!$B$9,投资与资金安排!$B$22*建筑面积与开发计划!K21,0) -> 0 | ... AH18: =IF(AH$4<=核心参数输入!$B$9,投资与资金安排!$B$22*建筑面积与开发计划!AH21,0) -> 0
A19: 持有建筑折旧（项目口径） | B19: 万元 | D19: =IF(D$4<=核心参数输入!$B$9,IF(AND(D$4-核心参数输入!$B$16>0,D$4-核心参数输入!$B$16<=核心参数输入!$B$53),投资与资金安排!$B$20*(1-核心参数输入!$B$54)/MAX(1,核心参数输入!$B$53),0),0) -> 0 | E19: =IF(E$4<=核心参数输入!$B$9,IF(AND(E$4-核心参数输入!$B$16>0,E$4-核心参数输入!$B$16<=核心参数输入!$B$53),投资与资金安排!$B$20*(1-核心参数输入!$B$54)/MAX(1,核心参数输入!$B$53),0),0) -> 0 | F19: =IF(F$4<=核心参数输入!$B$9,IF(AND(F$4-核心参数输入!$B$16>0,F$4-核心参数输入!$B$16<=核心参数输入!$B$53),投资与资金安排!$B$20*(1-核心参数输入!$B$54)/MAX(1,核心参数输入!$B$53),0),0) -> 0 | G19: =IF(G$4<=核心参数输入!$B$9,IF(AND(G$4-核心参数输入!$B$16>0,G$4-核心参数输入!$B$16<=核心参数输入!$B$53),投资与资金安排!$B$20*(1-核心参数输入!$B$54)/MAX(1,核心参数输入!$B$53),0),0) -> 0 | H19: =IF(H$4<=核心参数输入!$B$9,IF(AND(H$4-核心参数输入!$B$16>0,H$4-核心参数输入!$B$16<=核心参数输入!$B$53),投资与资金安排!$B$20*(1-核心参数输入!$B$54)/MAX(1,核心参数输入!$B$53),0),0) -> 754.11 | I19: =IF(I$4<=核心参数输入!$B$9,IF(AND(I$4-核心参数输入!$B$16>0,I$4-核心参数输入!$B$16<=核心参数输入!$B$53),投资与资金安排!$B$20*(1-核心参数输入!$B$54)/MAX(1,核心参数输入!$B$53),0),0) -> 754.11 | J19: =IF(J$4<=核心参数输入!$B$9,IF(AND(J$4-核心参数输入!$B$16>0,J$4-核心参数输入!$B$16<=核心参数输入!$B$53),投资与资金安排!$B$20*(1-核心参数输入!$B$54)/MAX(1,核心参数输入!$B$53),0),0) -> 754.11 | K19: =IF(K$4<=核心参数输入!$B$9,IF(AND(K$4-核心参数输入!$B$16>0,K$4-核心参数输入!$B$16<=核心参数输入!$B$53),投资与资金安排!$B$20*(1-核心参数输入!$B$54)/MAX(1,核心参数输入!$B$53),0),0) -> 754.11 | ... AH19: =IF(AH$4<=核心参数输入!$B$9,IF(AND(AH$4-核心参数输入!$B$16>0,AH$4-核心参数输入!$B$16<=核心参数输入!$B$53),投资与资金安排!$B$20*(1-核心参数输入!$B$54)/MAX(1,核心参数输入!$B$53),0),0) -> 0
A20: 持有建筑折旧（融资口径） | B20: 万元 | D20: =IF(D$4<=核心参数输入!$B$9,IF(AND(D$4-核心参数输入!$B$16>0,D$4-核心参数输入!$B$16<=核心参数输入!$B$53),投资与资金安排!$B$23*(1-核心参数输入!$B$54)/MAX(1,核心参数输入!$B$53),0),0) -> 0 | E20: =IF(E$4<=核心参数输入!$B$9,IF(AND(E$4-核心参数输入!$B$16>0,E$4-核心参数输入!$B$16<=核心参数输入!$B$53),投资与资金安排!$B$23*(1-核心参数输入!$B$54)/MAX(1,核心参数输入!$B$53),0),0) -> 0 | F20: =IF(F$4<=核心参数输入!$B$9,IF(AND(F$4-核心参数输入!$B$16>0,F$4-核心参数输入!$B$16<=核心参数输入!$B$53),投资与资金安排!$B$23*(1-核心参数输入!$B$54)/MAX(1,核心参数输入!$B$53),0),0) -> 0 | G20: =IF(G$4<=核心参数输入!$B$9,IF(AND(G$4-核心参数输入!$B$16>0,G$4-核心参数输入!$B$16<=核心参数输入!$B$53),投资与资金安排!$B$23*(1-核心参数输入!$B$54)/MAX(1,核心参数输入!$B$53),0),0) -> 0 | H20: =IF(H$4<=核心参数输入!$B$9,IF(AND(H$4-核心参数输入!$B$16>0,H$4-核心参数输入!$B$16<=核心参数输入!$B$53),投资与资金安排!$B$23*(1-核心参数输入!$B$54)/MAX(1,核心参数输入!$B$53),0),0) -> 781.0425 | I20: =IF(I$4<=核心参数输入!$B$9,IF(AND(I$4-核心参数输入!$B$16>0,I$4-核心参数输入!$B$16<=核心参数输入!$B$53),投资与资金安排!$B$23*(1-核心参数输入!$B$54)/MAX(1,核心参数输入!$B$53),0),0) -> 781.0425 | J20: =IF(J$4<=核心参数输入!$B$9,IF(AND(J$4-核心参数输入!$B$16>0,J$4-核心参数输入!$B$16<=核心参数输入!$B$53),投资与资金安排!$B$23*(1-核心参数输入!$B$54)/MAX(1,核心参数输入!$B$53),0),0) -> 781.0425 | K20: =IF(K$4<=核心参数输入!$B$9,IF(AND(K$4-核心参数输入!$B$16>0,K$4-核心参数输入!$B$16<=核心参数输入!$B$53),投资与资金安排!$B$23*(1-核心参数输入!$B$54)/MAX(1,核心参数输入!$B$53),0),0) -> 781.0425 | ... AH20: =IF(AH$4<=核心参数输入!$B$9,IF(AND(AH$4-核心参数输入!$B$16>0,AH$4-核心参数输入!$B$16<=核心参数输入!$B$53),投资与资金安排!$B$23*(1-核心参数输入!$B$54)/MAX(1,核心参数输入!$B$53),0),0) -> 0
A21: 持有处置前账面净值（项目） | B21: 万元 | D21: =IF(D$4<=核心参数输入!$B$9,(SUM(投资与资金安排!$D$28:D28)+SUM(投资与资金安排!$D$29:D29))*核心参数输入!$B$15-SUM($D19:D19),0) -> 3600 | E21: =IF(E$4<=核心参数输入!$B$9,(SUM(投资与资金安排!$D$28:E28)+SUM(投资与资金安排!$D$29:E29))*核心参数输入!$B$15-SUM($D19:E19),0) -> 10744.2 | F21: =IF(F$4<=核心参数输入!$B$9,(SUM(投资与资金安排!$D$28:F28)+SUM(投资与资金安排!$D$29:F29))*核心参数输入!$B$15-SUM($D19:F19),0) -> 20269.8 | G21: =IF(G$4<=核心参数输入!$B$9,(SUM(投资与资金安排!$D$28:G28)+SUM(投资与资金安排!$D$29:G29))*核心参数输入!$B$15-SUM($D19:G19),0) -> 27414 | H21: =IF(H$4<=核心参数输入!$B$9,(SUM(投资与资金安排!$D$28:H28)+SUM(投资与资金安排!$D$29:H29))*核心参数输入!$B$15-SUM($D19:H19),0) -> 26659.89 | I21: =IF(I$4<=核心参数输入!$B$9,(SUM(投资与资金安排!$D$28:I28)+SUM(投资与资金安排!$D$29:I29))*核心参数输入!$B$15-SUM($D19:I19),0) -> 25905.78 | J21: =IF(J$4<=核心参数输入!$B$9,(SUM(投资与资金安排!$D$28:J28)+SUM(投资与资金安排!$D$29:J29))*核心参数输入!$B$15-SUM($D19:J19),0) -> 25151.67 | K21: =IF(K$4<=核心参数输入!$B$9,(SUM(投资与资金安排!$D$28:K28)+SUM(投资与资金安排!$D$29:K29))*核心参数输入!$B$15-SUM($D19:K19),0) -> 24397.56 | ... AH21: =IF(AH$4<=核心参数输入!$B$9,(SUM(投资与资金安排!$D$28:AH28)+SUM(投资与资金安排!$D$29:AH29))*核心参数输入!$B$15-SUM($D19:AH19),0) -> 0
A22: 持有处置前账面净值（融资） | B22: 万元 | D22: =IF(D$4<=核心参数输入!$B$9,(SUM(投资与资金安排!$D$28:D28)+SUM(投资与资金安排!$D$29:D29)+SUM(融资与还本付息!$D$16:D16))*核心参数输入!$B$15-SUM($D20:D20),0) -> 3600 | E22: =IF(E$4<=核心参数输入!$B$9,(SUM(投资与资金安排!$D$28:E28)+SUM(投资与资金安排!$D$29:E29)+SUM(融资与还本付息!$D$16:E16))*核心参数输入!$B$15-SUM($D20:E20),0) -> 10829.25 | F22: =IF(F$4<=核心参数输入!$B$9,(SUM(投资与资金安排!$D$28:F28)+SUM(投资与资金安排!$D$29:F29)+SUM(融资与还本付息!$D$16:F16))*核心参数输入!$B$15-SUM($D20:F20),0) -> 20638.35 | G22: =IF(G$4<=核心参数输入!$B$9,(SUM(投资与资金安排!$D$28:G28)+SUM(投资与资金安排!$D$29:G29)+SUM(融资与还本付息!$D$16:G16))*核心参数输入!$B$15-SUM($D20:G20),0) -> 28264.5 | H22: =IF(H$4<=核心参数输入!$B$9,(SUM(投资与资金安排!$D$28:H28)+SUM(投资与资金安排!$D$29:H29)+SUM(融资与还本付息!$D$16:H16))*核心参数输入!$B$15-SUM($D20:H20),0) -> 27483.457 | I22: =IF(I$4<=核心参数输入!$B$9,(SUM(投资与资金安排!$D$28:I28)+SUM(投资与资金安排!$D$29:I29)+SUM(融资与还本付息!$D$16:I16))*核心参数输入!$B$15-SUM($D20:I20),0) -> 26702.415 | J22: =IF(J$4<=核心参数输入!$B$9,(SUM(投资与资金安排!$D$28:J28)+SUM(投资与资金安排!$D$29:J29)+SUM(融资与还本付息!$D$16:J16))*核心参数输入!$B$15-SUM($D20:J20),0) -> 25921.372 | K22: =IF(K$4<=核心参数输入!$B$9,(SUM(投资与资金安排!$D$28:K28)+SUM(投资与资金安排!$D$29:K29)+SUM(融资与还本付息!$D$16:K16))*核心参数输入!$B$15-SUM($D20:K20),0) -> 25140.33 | ... AH22: =IF(AH$4<=核心参数输入!$B$9,(SUM(投资与资金安排!$D$28:AH28)+SUM(投资与资金安排!$D$29:AH29)+SUM(融资与还本付息!$D$16:AH16))*核心参数输入!$B$15-SUM($D20:AH20),0) -> 0
A23: 期末未售开发存货（融资） | B23: 万元 | D23: =IF(D$4<=核心参数输入!$B$9,(SUM(投资与资金安排!$D$28:D28)+SUM(投资与资金安排!$D$29:D29)+SUM(融资与还本付息!$D$16:D16))*核心参数输入!$B$14-SUM($D18:D18),0) -> 4400 | E23: =IF(E$4<=核心参数输入!$B$9,(SUM(投资与资金安排!$D$28:E28)+SUM(投资与资金安排!$D$29:E29)+SUM(融资与还本付息!$D$16:E16))*核心参数输入!$B$14-SUM($D18:E18),0) -> 13235.75 | F23: =IF(F$4<=核心参数输入!$B$9,(SUM(投资与资金安排!$D$28:F28)+SUM(投资与资金安排!$D$29:F29)+SUM(融资与还本付息!$D$16:F16))*核心参数输入!$B$14-SUM($D18:F18),0) -> 25224.65 | G23: =IF(G$4<=核心参数输入!$B$9,(SUM(投资与资金安排!$D$28:G28)+SUM(投资与资金安排!$D$29:G29)+SUM(融资与还本付息!$D$16:G16))*核心参数输入!$B$14-SUM($D18:G18),0) -> 34545.5 | H23: =IF(H$4<=核心参数输入!$B$9,(SUM(投资与资金安排!$D$28:H28)+SUM(投资与资金安排!$D$29:H29)+SUM(融资与还本付息!$D$16:H16))*核心参数输入!$B$14-SUM($D18:H18),0) -> 24181.85 | I23: =IF(I$4<=核心参数输入!$B$9,(SUM(投资与资金安排!$D$28:I28)+SUM(投资与资金安排!$D$29:I29)+SUM(融资与还本付息!$D$16:I16))*核心参数输入!$B$14-SUM($D18:I18),0) -> 10363.65 | J23: =IF(J$4<=核心参数输入!$B$9,(SUM(投资与资金安排!$D$28:J28)+SUM(投资与资金安排!$D$29:J29)+SUM(融资与还本付息!$D$16:J16))*核心参数输入!$B$14-SUM($D18:J18),0) -> 0 | K23: =IF(K$4<=核心参数输入!$B$9,(SUM(投资与资金安排!$D$28:K28)+SUM(投资与资金安排!$D$29:K29)+SUM(融资与还本付息!$D$16:K16))*核心参数输入!$B$14-SUM($D18:K18),0) -> 0 | ... AH23: =IF(AH$4<=核心参数输入!$B$9,(SUM(投资与资金安排!$D$28:AH28)+SUM(投资与资金安排!$D$29:AH29)+SUM(融资与还本付息!$D$16:AH16))*核心参数输入!$B$14-SUM($D18:AH18),0) -> 0
A24: 期末处置损益（项目口径） | B24: 万元 | D24: =IF(D$4<=核心参数输入!$B$9,IF(AND(核心参数输入!$B$64=1,D$4=核心参数输入!$B$9),销售与出租收入!D26-D21,0),0) -> 0 | E24: =IF(E$4<=核心参数输入!$B$9,IF(AND(核心参数输入!$B$64=1,E$4=核心参数输入!$B$9),销售与出租收入!E26-E21,0),0) -> 0 | F24: =IF(F$4<=核心参数输入!$B$9,IF(AND(核心参数输入!$B$64=1,F$4=核心参数输入!$B$9),销售与出租收入!F26-F21,0),0) -> 0 | G24: =IF(G$4<=核心参数输入!$B$9,IF(AND(核心参数输入!$B$64=1,G$4=核心参数输入!$B$9),销售与出租收入!G26-G21,0),0) -> 0 | H24: =IF(H$4<=核心参数输入!$B$9,IF(AND(核心参数输入!$B$64=1,H$4=核心参数输入!$B$9),销售与出租收入!H26-H21,0),0) -> 0 | I24: =IF(I$4<=核心参数输入!$B$9,IF(AND(核心参数输入!$B$64=1,I$4=核心参数输入!$B$9),销售与出租收入!I26-I21,0),0) -> 0 | J24: =IF(J$4<=核心参数输入!$B$9,IF(AND(核心参数输入!$B$64=1,J$4=核心参数输入!$B$9),销售与出租收入!J26-J21,0),0) -> 0 | K24: =IF(K$4<=核心参数输入!$B$9,IF(AND(核心参数输入!$B$64=1,K$4=核心参数输入!$B$9),销售与出租收入!K26-K21,0),0) -> 0 | ... AH24: =IF(AH$4<=核心参数输入!$B$9,IF(AND(核心参数输入!$B$64=1,AH$4=核心参数输入!$B$9),销售与出租收入!AH26-AH21,0),0) -> 0
A25: 期末处置损益（融资口径） | B25: 万元 | D25: =IF(D$4<=核心参数输入!$B$9,IF(AND(核心参数输入!$B$64=1,D$4=核心参数输入!$B$9),销售与出租收入!D26-D22,0),0) -> 0 | E25: =IF(E$4<=核心参数输入!$B$9,IF(AND(核心参数输入!$B$64=1,E$4=核心参数输入!$B$9),销售与出租收入!E26-E22,0),0) -> 0 | F25: =IF(F$4<=核心参数输入!$B$9,IF(AND(核心参数输入!$B$64=1,F$4=核心参数输入!$B$9),销售与出租收入!F26-F22,0),0) -> 0 | G25: =IF(G$4<=核心参数输入!$B$9,IF(AND(核心参数输入!$B$64=1,G$4=核心参数输入!$B$9),销售与出租收入!G26-G22,0),0) -> 0 | H25: =IF(H$4<=核心参数输入!$B$9,IF(AND(核心参数输入!$B$64=1,H$4=核心参数输入!$B$9),销售与出租收入!H26-H22,0),0) -> 0 | I25: =IF(I$4<=核心参数输入!$B$9,IF(AND(核心参数输入!$B$64=1,I$4=核心参数输入!$B$9),销售与出租收入!I26-I22,0),0) -> 0 | J25: =IF(J$4<=核心参数输入!$B$9,IF(AND(核心参数输入!$B$64=1,J$4=核心参数输入!$B$9),销售与出租收入!J26-J22,0),0) -> 0 | K25: =IF(K$4<=核心参数输入!$B$9,IF(AND(核心参数输入!$B$64=1,K$4=核心参数输入!$B$9),销售与出租收入!K26-K22,0),0) -> 0 | ... AH25: =IF(AH$4<=核心参数输入!$B$9,IF(AND(核心参数输入!$B$64=1,AH$4=核心参数输入!$B$9),销售与出租收入!AH26-AH22,0),0) -> 0
A87: 组合压力情景 · 建设成本上升并重算结转及折旧
A90: 销售费用现金支出 | B90: 万元 | D90: =IF(D$4<=核心参数输入!$B$9,销售与出租收入!D93*核心参数输入!$B$32,0) -> 0 | E90: =IF(E$4<=核心参数输入!$B$9,销售与出租收入!E93*核心参数输入!$B$32,0) -> 0 | F90: =IF(F$4<=核心参数输入!$B$9,销售与出租收入!F93*核心参数输入!$B$32,0) -> 0 | G90: =IF(G$4<=核心参数输入!$B$9,销售与出租收入!G93*核心参数输入!$B$32,0) -> 0 | H90: =IF(H$4<=核心参数输入!$B$9,销售与出租收入!H93*核心参数输入!$B$32,0) -> 325.77188 | I90: =IF(I$4<=核心参数输入!$B$9,销售与出租收入!I93*核心参数输入!$B$32,0) -> 434.3625 | J90: =IF(J$4<=核心参数输入!$B$9,销售与出租收入!J93*核心参数输入!$B$32,0) -> 325.77188 | K90: =IF(K$4<=核心参数输入!$B$9,销售与出租收入!K93*核心参数输入!$B$32,0) -> 0 | ... AH90: =IF(AH$4<=核心参数输入!$B$9,销售与出租收入!AH93*核心参数输入!$B$32,0) -> 0
A91: 销售相关税费现金支出 | B91: 万元 | D91: =IF(D$4<=核心参数输入!$B$9,销售与出租收入!D93*核心参数输入!$B$33,0) -> 0 | E91: =IF(E$4<=核心参数输入!$B$9,销售与出租收入!E93*核心参数输入!$B$33,0) -> 0 | F91: =IF(F$4<=核心参数输入!$B$9,销售与出租收入!F93*核心参数输入!$B$33,0) -> 0 | G91: =IF(G$4<=核心参数输入!$B$9,销售与出租收入!G93*核心参数输入!$B$33,0) -> 0 | H91: =IF(H$4<=核心参数输入!$B$9,销售与出租收入!H93*核心参数输入!$B$33,0) -> 1042.47 | I91: =IF(I$4<=核心参数输入!$B$9,销售与出租收入!I93*核心参数输入!$B$33,0) -> 1389.96 | J91: =IF(J$4<=核心参数输入!$B$9,销售与出租收入!J93*核心参数输入!$B$33,0) -> 1042.47 | K91: =IF(K$4<=核心参数输入!$B$9,销售与出租收入!K93*核心参数输入!$B$33,0) -> 0 | ... AH91: =IF(AH$4<=核心参数输入!$B$9,销售与出租收入!AH93*核心参数输入!$B$33,0) -> 0
A92: 持有固定运营成本 | B92: 万元 | D92: =IF(D$4<=核心参数输入!$B$9,IF(D$4-核心参数输入!$B$16>0,核心参数输入!$B$47*(1+核心参数输入!$B$48)^MAX(0,D$4-核心参数输入!$B$16-1),0),0) -> 0 | E92: =IF(E$4<=核心参数输入!$B$9,IF(E$4-核心参数输入!$B$16>0,核心参数输入!$B$47*(1+核心参数输入!$B$48)^MAX(0,E$4-核心参数输入!$B$16-1),0),0) -> 0 | F92: =IF(F$4<=核心参数输入!$B$9,IF(F$4-核心参数输入!$B$16>0,核心参数输入!$B$47*(1+核心参数输入!$B$48)^MAX(0,F$4-核心参数输入!$B$16-1),0),0) -> 0 | G92: =IF(G$4<=核心参数输入!$B$9,IF(G$4-核心参数输入!$B$16>0,核心参数输入!$B$47*(1+核心参数输入!$B$48)^MAX(0,G$4-核心参数输入!$B$16-1),0),0) -> 0 | H92: =IF(H$4<=核心参数输入!$B$9,IF(H$4-核心参数输入!$B$16>0,核心参数输入!$B$47*(1+核心参数输入!$B$48)^MAX(0,H$4-核心参数输入!$B$16-1),0),0) -> 300 | I92: =IF(I$4<=核心参数输入!$B$9,IF(I$4-核心参数输入!$B$16>0,核心参数输入!$B$47*(1+核心参数输入!$B$48)^MAX(0,I$4-核心参数输入!$B$16-1),0),0) -> 306 | J92: =IF(J$4<=核心参数输入!$B$9,IF(J$4-核心参数输入!$B$16>0,核心参数输入!$B$47*(1+核心参数输入!$B$48)^MAX(0,J$4-核心参数输入!$B$16-1),0),0) -> 312.12 | K92: =IF(K$4<=核心参数输入!$B$9,IF(K$4-核心参数输入!$B$16>0,核心参数输入!$B$47*(1+核心参数输入!$B$48)^MAX(0,K$4-核心参数输入!$B$16-1),0),0) -> 318.3624 | ... AH92: =IF(AH$4<=核心参数输入!$B$9,IF(AH$4-核心参数输入!$B$16>0,核心参数输入!$B$47*(1+核心参数输入!$B$48)^MAX(0,AH$4-核心参数输入!$B$16-1),0),0) -> 0
A93: 持有变动运营成本 | B93: 万元 | D93: =IF(D$4<=核心参数输入!$B$9,销售与出租收入!D102*核心参数输入!$B$49,0) -> 0 | E93: =IF(E$4<=核心参数输入!$B$9,销售与出租收入!E102*核心参数输入!$B$49,0) -> 0 | F93: =IF(F$4<=核心参数输入!$B$9,销售与出租收入!F102*核心参数输入!$B$49,0) -> 0 | G93: =IF(G$4<=核心参数输入!$B$9,销售与出租收入!G102*核心参数输入!$B$49,0) -> 0 | H93: =IF(H$4<=核心参数输入!$B$9,销售与出租收入!H102*核心参数输入!$B$49,0) -> 63.191878 | I93: =IF(I$4<=核心参数输入!$B$9,销售与出租收入!I102*核心参数输入!$B$49,0) -> 117.58955 | J93: =IF(J$4<=核心参数输入!$B$9,销售与出租收入!J102*核心参数输入!$B$49,0) -> 154.6169 | K93: =IF(K$4<=核心参数输入!$B$9,销售与出租收入!K102*核心参数输入!$B$49,0) -> 173.45575 | ... AH93: =IF(AH$4<=核心参数输入!$B$9,销售与出租收入!AH102*核心参数输入!$B$49,0) -> 0
A94: 维护更新支出（当期费用化） | B94: 万元 | D94: =IF(D$4<=核心参数输入!$B$9,IF(D$4-核心参数输入!$B$16>0,核心参数输入!$B$50,0),0) -> 0 | E94: =IF(E$4<=核心参数输入!$B$9,IF(E$4-核心参数输入!$B$16>0,核心参数输入!$B$50,0),0) -> 0 | F94: =IF(F$4<=核心参数输入!$B$9,IF(F$4-核心参数输入!$B$16>0,核心参数输入!$B$50,0),0) -> 0 | G94: =IF(G$4<=核心参数输入!$B$9,IF(G$4-核心参数输入!$B$16>0,核心参数输入!$B$50,0),0) -> 0 | H94: =IF(H$4<=核心参数输入!$B$9,IF(H$4-核心参数输入!$B$16>0,核心参数输入!$B$50,0),0) -> 180 | I94: =IF(I$4<=核心参数输入!$B$9,IF(I$4-核心参数输入!$B$16>0,核心参数输入!$B$50,0),0) -> 180 | J94: =IF(J$4<=核心参数输入!$B$9,IF(J$4-核心参数输入!$B$16>0,核心参数输入!$B$50,0),0) -> 180 | K94: =IF(K$4<=核心参数输入!$B$9,IF(K$4-核心参数输入!$B$16>0,核心参数输入!$B$50,0),0) -> 180 | ... AH94: =IF(AH$4<=核心参数输入!$B$9,IF(AH$4-核心参数输入!$B$16>0,核心参数输入!$B$50,0),0) -> 0
A95: 运营相关税费 | B95: 万元 | D95: =IF(D$4<=核心参数输入!$B$9,销售与出租收入!D102*核心参数输入!$B$51,0) -> 0 | E95: =IF(E$4<=核心参数输入!$B$9,销售与出租收入!E102*核心参数输入!$B$51,0) -> 0 | F95: =IF(F$4<=核心参数输入!$B$9,销售与出租收入!F102*核心参数输入!$B$51,0) -> 0 | G95: =IF(G$4<=核心参数输入!$B$9,销售与出租收入!G102*核心参数输入!$B$51,0) -> 0 | H95: =IF(H$4<=核心参数输入!$B$9,销售与出租收入!H102*核心参数输入!$B$51,0) -> 31.595939 | I95: =IF(I$4<=核心参数输入!$B$9,销售与出租收入!I102*核心参数输入!$B$51,0) -> 58.794776 | J95: =IF(J$4<=核心参数输入!$B$9,销售与出租收入!J102*核心参数输入!$B$51,0) -> 77.30845 | K95: =IF(K$4<=核心参数输入!$B$9,销售与出租收入!K102*核心参数输入!$B$51,0) -> 86.727874 | ... AH95: =IF(AH$4<=核心参数输入!$B$9,销售与出租收入!AH102*核心参数输入!$B$51,0) -> 0
A96: 现金成本及经营税费合计 | B96: 万元 | D96: =IF(D$4<=核心参数输入!$B$9,SUM(D90:D95),0) -> 0 | E96: =IF(E$4<=核心参数输入!$B$9,SUM(E90:E95),0) -> 0 | F96: =IF(F$4<=核心参数输入!$B$9,SUM(F90:F95),0) -> 0 | G96: =IF(G$4<=核心参数输入!$B$9,SUM(G90:G95),0) -> 0 | H96: =IF(H$4<=核心参数输入!$B$9,SUM(H90:H95),0) -> 1943.0297 | I96: =IF(I$4<=核心参数输入!$B$9,SUM(I90:I95),0) -> 2486.7068 | J96: =IF(J$4<=核心参数输入!$B$9,SUM(J90:J95),0) -> 2092.2872 | K96: =IF(K$4<=核心参数输入!$B$9,SUM(K90:K95),0) -> 758.54602 | ... AH96: =IF(AH$4<=核心参数输入!$B$9,SUM(AH90:AH95),0) -> 0
A97: 销售成本结转（项目口径） | B97: 万元 | D97: =IF(D$4<=核心参数输入!$B$9,投资与资金安排!$B$99*建筑面积与开发计划!D101,0) -> 0 | E97: =IF(E$4<=核心参数输入!$B$9,投资与资金安排!$B$99*建筑面积与开发计划!E101,0) -> 0 | F97: =IF(F$4<=核心参数输入!$B$9,投资与资金安排!$B$99*建筑面积与开发计划!F101,0) -> 0 | G97: =IF(G$4<=核心参数输入!$B$9,投资与资金安排!$B$99*建筑面积与开发计划!G101,0) -> 0 | H97: =IF(H$4<=核心参数输入!$B$9,投资与资金安排!$B$99*建筑面积与开发计划!H101,0) -> 10924.98 | I97: =IF(I$4<=核心参数输入!$B$9,投资与资金安排!$B$99*建筑面积与开发计划!I101,0) -> 14566.64 | J97: =IF(J$4<=核心参数输入!$B$9,投资与资金安排!$B$99*建筑面积与开发计划!J101,0) -> 10924.98 | K97: =IF(K$4<=核心参数输入!$B$9,投资与资金安排!$B$99*建筑面积与开发计划!K101,0) -> 0 | ... AH97: =IF(AH$4<=核心参数输入!$B$9,投资与资金安排!$B$99*建筑面积与开发计划!AH101,0) -> 0
A98: 销售成本结转（融资口径） | B98: 万元 | D98: =IF(D$4<=核心参数输入!$B$9,投资与资金安排!$B$102*建筑面积与开发计划!D101,0) -> 0 | E98: =IF(E$4<=核心参数输入!$B$9,投资与资金安排!$B$102*建筑面积与开发计划!E101,0) -> 0 | F98: =IF(F$4<=核心参数输入!$B$9,投资与资金安排!$B$102*建筑面积与开发计划!F101,0) -> 0 | G98: =IF(G$4<=核心参数输入!$B$9,投资与资金安排!$B$102*建筑面积与开发计划!G101,0) -> 0 | H98: =IF(H$4<=核心参数输入!$B$9,投资与资金安排!$B$102*建筑面积与开发计划!H101,0) -> 11236.83 | I98: =IF(I$4<=核心参数输入!$B$9,投资与资金安排!$B$102*建筑面积与开发计划!I101,0) -> 14982.44 | J98: =IF(J$4<=核心参数输入!$B$9,投资与资金安排!$B$102*建筑面积与开发计划!J101,0) -> 11236.83 | K98: =IF(K$4<=核心参数输入!$B$9,投资与资金安排!$B$102*建筑面积与开发计划!K101,0) -> 0 | ... AH98: =IF(AH$4<=核心参数输入!$B$9,投资与资金安排!$B$102*建筑面积与开发计划!AH101,0) -> 0
A99: 持有建筑折旧（项目口径） | B99: 万元 | D99: =IF(D$4<=核心参数输入!$B$9,IF(AND(D$4-核心参数输入!$B$16>0,D$4-核心参数输入!$B$16<=核心参数输入!$B$53),投资与资金安排!$B$100*(1-核心参数输入!$B$54)/MAX(1,核心参数输入!$B$53),0),0) -> 0 | E99: =IF(E$4<=核心参数输入!$B$9,IF(AND(E$4-核心参数输入!$B$16>0,E$4-核心参数输入!$B$16<=核心参数输入!$B$53),投资与资金安排!$B$100*(1-核心参数输入!$B$54)/MAX(1,核心参数输入!$B$53),0),0) -> 0 | F99: =IF(F$4<=核心参数输入!$B$9,IF(AND(F$4-核心参数输入!$B$16>0,F$4-核心参数输入!$B$16<=核心参数输入!$B$53),投资与资金安排!$B$100*(1-核心参数输入!$B$54)/MAX(1,核心参数输入!$B$53),0),0) -> 0 | G99: =IF(G$4<=核心参数输入!$B$9,IF(AND(G$4-核心参数输入!$B$16>0,G$4-核心参数输入!$B$16<=核心参数输入!$B$53),投资与资金安排!$B$100*(1-核心参数输入!$B$54)/MAX(1,核心参数输入!$B$53),0),0) -> 0 | H99: =IF(H$4<=核心参数输入!$B$9,IF(AND(H$4-核心参数输入!$B$16>0,H$4-核心参数输入!$B$16<=核心参数输入!$B$53),投资与资金安排!$B$100*(1-核心参数输入!$B$54)/MAX(1,核心参数输入!$B$53),0),0) -> 829.521 | I99: =IF(I$4<=核心参数输入!$B$9,IF(AND(I$4-核心参数输入!$B$16>0,I$4-核心参数输入!$B$16<=核心参数输入!$B$53),投资与资金安排!$B$100*(1-核心参数输入!$B$54)/MAX(1,核心参数输入!$B$53),0),0) -> 829.521 | J99: =IF(J$4<=核心参数输入!$B$9,IF(AND(J$4-核心参数输入!$B$16>0,J$4-核心参数输入!$B$16<=核心参数输入!$B$53),投资与资金安排!$B$100*(1-核心参数输入!$B$54)/MAX(1,核心参数输入!$B$53),0),0) -> 829.521 | K99: =IF(K$4<=核心参数输入!$B$9,IF(AND(K$4-核心参数输入!$B$16>0,K$4-核心参数输入!$B$16<=核心参数输入!$B$53),投资与资金安排!$B$100*(1-核心参数输入!$B$54)/MAX(1,核心参数输入!$B$53),0),0) -> 829.521 | ... AH99: =IF(AH$4<=核心参数输入!$B$9,IF(AND(AH$4-核心参数输入!$B$16>0,AH$4-核心参数输入!$B$16<=核心参数输入!$B$53),投资与资金安排!$B$100*(1-核心参数输入!$B$54)/MAX(1,核心参数输入!$B$53),0),0) -> 0
A100: 持有建筑折旧（融资口径） | B100: 万元 | D100: =IF(D$4<=核心参数输入!$B$9,IF(AND(D$4-核心参数输入!$B$16>0,D$4-核心参数输入!$B$16<=核心参数输入!$B$53),投资与资金安排!$B$103*(1-核心参数输入!$B$54)/MAX(1,核心参数输入!$B$53),0),0) -> 0 | E100: =IF(E$4<=核心参数输入!$B$9,IF(AND(E$4-核心参数输入!$B$16>0,E$4-核心参数输入!$B$16<=核心参数输入!$B$53),投资与资金安排!$B$103*(1-核心参数输入!$B$54)/MAX(1,核心参数输入!$B$53),0),0) -> 0 | F100: =IF(F$4<=核心参数输入!$B$9,IF(AND(F$4-核心参数输入!$B$16>0,F$4-核心参数输入!$B$16<=核心参数输入!$B$53),投资与资金安排!$B$103*(1-核心参数输入!$B$54)/MAX(1,核心参数输入!$B$53),0),0) -> 0 | G100: =IF(G$4<=核心参数输入!$B$9,IF(AND(G$4-核心参数输入!$B$16>0,G$4-核心参数输入!$B$16<=核心参数输入!$B$53),投资与资金安排!$B$103*(1-核心参数输入!$B$54)/MAX(1,核心参数输入!$B$53),0),0) -> 0 | H100: =IF(H$4<=核心参数输入!$B$9,IF(AND(H$4-核心参数输入!$B$16>0,H$4-核心参数输入!$B$16<=核心参数输入!$B$53),投资与资金安排!$B$103*(1-核心参数输入!$B$54)/MAX(1,核心参数输入!$B$53),0),0) -> 856.4535 | I100: =IF(I$4<=核心参数输入!$B$9,IF(AND(I$4-核心参数输入!$B$16>0,I$4-核心参数输入!$B$16<=核心参数输入!$B$53),投资与资金安排!$B$103*(1-核心参数输入!$B$54)/MAX(1,核心参数输入!$B$53),0),0) -> 856.4535 | J100: =IF(J$4<=核心参数输入!$B$9,IF(AND(J$4-核心参数输入!$B$16>0,J$4-核心参数输入!$B$16<=核心参数输入!$B$53),投资与资金安排!$B$103*(1-核心参数输入!$B$54)/MAX(1,核心参数输入!$B$53),0),0) -> 856.4535 | K100: =IF(K$4<=核心参数输入!$B$9,IF(AND(K$4-核心参数输入!$B$16>0,K$4-核心参数输入!$B$16<=核心参数输入!$B$53),投资与资金安排!$B$103*(1-核心参数输入!$B$54)/MAX(1,核心参数输入!$B$53),0),0) -> 856.4535 | ... AH100: =IF(AH$4<=核心参数输入!$B$9,IF(AND(AH$4-核心参数输入!$B$16>0,AH$4-核心参数输入!$B$16<=核心参数输入!$B$53),投资与资金安排!$B$103*(1-核心参数输入!$B$54)/MAX(1,核心参数输入!$B$53),0),0) -> 0
A101: 持有处置前账面净值（项目） | B101: 万元 | D101: =IF(D$4<=核心参数输入!$B$9,(SUM(投资与资金安排!$D$108:D108)+SUM(投资与资金安排!$D$109:D109))*核心参数输入!$B$15-SUM($D99:D99),0) -> 3600 | E101: =IF(E$4<=核心参数输入!$B$9,(SUM(投资与资金安排!$D$108:E108)+SUM(投资与资金安排!$D$109:E109))*核心参数输入!$B$15-SUM($D99:E99),0) -> 11458.62 | F101: =IF(F$4<=核心参数输入!$B$9,(SUM(投资与资金安排!$D$108:F108)+SUM(投资与资金安排!$D$109:F109))*核心参数输入!$B$15-SUM($D99:F99),0) -> 21936.78 | G101: =IF(G$4<=核心参数输入!$B$9,(SUM(投资与资金安排!$D$108:G108)+SUM(投资与资金安排!$D$109:G109))*核心参数输入!$B$15-SUM($D99:G99),0) -> 29795.4 | H101: =IF(H$4<=核心参数输入!$B$9,(SUM(投资与资金安排!$D$108:H108)+SUM(投资与资金安排!$D$109:H109))*核心参数输入!$B$15-SUM($D99:H99),0) -> 28965.879 | I101: =IF(I$4<=核心参数输入!$B$9,(SUM(投资与资金安排!$D$108:I108)+SUM(投资与资金安排!$D$109:I109))*核心参数输入!$B$15-SUM($D99:I99),0) -> 28136.358 | J101: =IF(J$4<=核心参数输入!$B$9,(SUM(投资与资金安排!$D$108:J108)+SUM(投资与资金安排!$D$109:J109))*核心参数输入!$B$15-SUM($D99:J99),0) -> 27306.837 | K101: =IF(K$4<=核心参数输入!$B$9,(SUM(投资与资金安排!$D$108:K108)+SUM(投资与资金安排!$D$109:K109))*核心参数输入!$B$15-SUM($D99:K99),0) -> 26477.316 | ... AH101: =IF(AH$4<=核心参数输入!$B$9,(SUM(投资与资金安排!$D$108:AH108)+SUM(投资与资金安排!$D$109:AH109))*核心参数输入!$B$15-SUM($D99:AH99),0) -> 0
A102: 持有处置前账面净值（融资） | B102: 万元 | D102: =IF(D$4<=核心参数输入!$B$9,(SUM(投资与资金安排!$D$108:D108)+SUM(投资与资金安排!$D$109:D109)+SUM(融资与还本付息!$D$96:D96))*核心参数输入!$B$15-SUM($D100:D100),0) -> 3600 | E102: =IF(E$4<=核心参数输入!$B$9,(SUM(投资与资金安排!$D$108:E108)+SUM(投资与资金安排!$D$109:E109)+SUM(融资与还本付息!$D$96:E96))*核心参数输入!$B$15-SUM($D100:E100),0) -> 11543.67 | F102: =IF(F$4<=核心参数输入!$B$9,(SUM(投资与资金安排!$D$108:F108)+SUM(投资与资金安排!$D$109:F109)+SUM(融资与还本付息!$D$96:F96))*核心参数输入!$B$15-SUM($D100:F100),0) -> 22305.33 | G102: =IF(G$4<=核心参数输入!$B$9,(SUM(投资与资金安排!$D$108:G108)+SUM(投资与资金安排!$D$109:G109)+SUM(融资与还本付息!$D$96:G96))*核心参数输入!$B$15-SUM($D100:G100),0) -> 30645.9 | H102: =IF(H$4<=核心参数输入!$B$9,(SUM(投资与资金安排!$D$108:H108)+SUM(投资与资金安排!$D$109:H109)+SUM(融资与还本付息!$D$96:H96))*核心参数输入!$B$15-SUM($D100:H100),0) -> 29789.446 | I102: =IF(I$4<=核心参数输入!$B$9,(SUM(投资与资金安排!$D$108:I108)+SUM(投资与资金安排!$D$109:I109)+SUM(融资与还本付息!$D$96:I96))*核心参数输入!$B$15-SUM($D100:I100),0) -> 28932.993 | J102: =IF(J$4<=核心参数输入!$B$9,(SUM(投资与资金安排!$D$108:J108)+SUM(投资与资金安排!$D$109:J109)+SUM(融资与还本付息!$D$96:J96))*核心参数输入!$B$15-SUM($D100:J100),0) -> 28076.539 | K102: =IF(K$4<=核心参数输入!$B$9,(SUM(投资与资金安排!$D$108:K108)+SUM(投资与资金安排!$D$109:K109)+SUM(融资与还本付息!$D$96:K96))*核心参数输入!$B$15-SUM($D100:K100),0) -> 27220.086 | ... AH102: =IF(AH$4<=核心参数输入!$B$9,(SUM(投资与资金安排!$D$108:AH108)+SUM(投资与资金安排!$D$109:AH109)+SUM(融资与还本付息!$D$96:AH96))*核心参数输入!$B$15-SUM($D100:AH100),0) -> 0
A103: 期末未售开发存货（融资） | B103: 万元 | D103: =IF(D$4<=核心参数输入!$B$9,(SUM(投资与资金安排!$D$108:D108)+SUM(投资与资金安排!$D$109:D109)+SUM(融资与还本付息!$D$96:D96))*核心参数输入!$B$14-SUM($D98:D98),0) -> 4400 | E103: =IF(E$4<=核心参数输入!$B$9,(SUM(投资与资金安排!$D$108:E108)+SUM(投资与资金安排!$D$109:E109)+SUM(融资与还本付息!$D$96:E96))*核心参数输入!$B$14-SUM($D98:E98),0) -> 14108.93 | F103: =IF(F$4<=核心参数输入!$B$9,(SUM(投资与资金安排!$D$108:F108)+SUM(投资与资金安排!$D$109:F109)+SUM(融资与还本付息!$D$96:F96))*核心参数输入!$B$14-SUM($D98:F98),0) -> 27262.07 | G103: =IF(G$4<=核心参数输入!$B$9,(SUM(投资与资金安排!$D$108:G108)+SUM(投资与资金安排!$D$109:G109)+SUM(融资与还本付息!$D$96:G96))*核心参数输入!$B$14-SUM($D98:G98),0) -> 37456.1 | H103: =IF(H$4<=核心参数输入!$B$9,(SUM(投资与资金安排!$D$108:H108)+SUM(投资与资金安排!$D$109:H109)+SUM(融资与还本付息!$D$96:H96))*核心参数输入!$B$14-SUM($D98:H98),0) -> 26219.27 | I103: =IF(I$4<=核心参数输入!$B$9,(SUM(投资与资金安排!$D$108:I108)+SUM(投资与资金安排!$D$109:I109)+SUM(融资与还本付息!$D$96:I96))*核心参数输入!$B$14-SUM($D98:I98),0) -> 11236.83 | J103: =IF(J$4<=核心参数输入!$B$9,(SUM(投资与资金安排!$D$108:J108)+SUM(投资与资金安排!$D$109:J109)+SUM(融资与还本付息!$D$96:J96))*核心参数输入!$B$14-SUM($D98:J98),0) -> 0 | K103: =IF(K$4<=核心参数输入!$B$9,(SUM(投资与资金安排!$D$108:K108)+SUM(投资与资金安排!$D$109:K109)+SUM(融资与还本付息!$D$96:K96))*核心参数输入!$B$14-SUM($D98:K98),0) -> 0 | ... AH103: =IF(AH$4<=核心参数输入!$B$9,(SUM(投资与资金安排!$D$108:AH108)+SUM(投资与资金安排!$D$109:AH109)+SUM(融资与还本付息!$D$96:AH96))*核心参数输入!$B$14-SUM($D98:AH98),0) -> 0
A104: 期末处置损益（项目口径） | B104: 万元 | D104: =IF(D$4<=核心参数输入!$B$9,IF(AND(核心参数输入!$B$64=1,D$4=核心参数输入!$B$9),销售与出租收入!D106-D101,0),0) -> 0 | E104: =IF(E$4<=核心参数输入!$B$9,IF(AND(核心参数输入!$B$64=1,E$4=核心参数输入!$B$9),销售与出租收入!E106-E101,0),0) -> 0 | F104: =IF(F$4<=核心参数输入!$B$9,IF(AND(核心参数输入!$B$64=1,F$4=核心参数输入!$B$9),销售与出租收入!F106-F101,0),0) -> 0 | G104: =IF(G$4<=核心参数输入!$B$9,IF(AND(核心参数输入!$B$64=1,G$4=核心参数输入!$B$9),销售与出租收入!G106-G101,0),0) -> 0 | H104: =IF(H$4<=核心参数输入!$B$9,IF(AND(核心参数输入!$B$64=1,H$4=核心参数输入!$B$9),销售与出租收入!H106-H101,0),0) -> 0 | I104: =IF(I$4<=核心参数输入!$B$9,IF(AND(核心参数输入!$B$64=1,I$4=核心参数输入!$B$9),销售与出租收入!I106-I101,0),0) -> 0 | J104: =IF(J$4<=核心参数输入!$B$9,IF(AND(核心参数输入!$B$64=1,J$4=核心参数输入!$B$9),销售与出租收入!J106-J101,0),0) -> 0 | K104: =IF(K$4<=核心参数输入!$B$9,IF(AND(核心参数输入!$B$64=1,K$4=核心参数输入!$B$9),销售与出租收入!K106-K101,0),0) -> 0 | ... AH104: =IF(AH$4<=核心参数输入!$B$9,IF(AND(核心参数输入!$B$64=1,AH$4=核心参数输入!$B$9),销售与出租收入!AH106-AH101,0),0) -> 0
A105: 期末处置损益（融资口径） | B105: 万元 | D105: =IF(D$4<=核心参数输入!$B$9,IF(AND(核心参数输入!$B$64=1,D$4=核心参数输入!$B$9),销售与出租收入!D106-D102,0),0) -> 0 | E105: =IF(E$4<=核心参数输入!$B$9,IF(AND(核心参数输入!$B$64=1,E$4=核心参数输入!$B$9),销售与出租收入!E106-E102,0),0) -> 0 | F105: =IF(F$4<=核心参数输入!$B$9,IF(AND(核心参数输入!$B$64=1,F$4=核心参数输入!$B$9),销售与出租收入!F106-F102,0),0) -> 0 | G105: =IF(G$4<=核心参数输入!$B$9,IF(AND(核心参数输入!$B$64=1,G$4=核心参数输入!$B$9),销售与出租收入!G106-G102,0),0) -> 0 | H105: =IF(H$4<=核心参数输入!$B$9,IF(AND(核心参数输入!$B$64=1,H$4=核心参数输入!$B$9),销售与出租收入!H106-H102,0),0) -> 0 | I105: =IF(I$4<=核心参数输入!$B$9,IF(AND(核心参数输入!$B$64=1,I$4=核心参数输入!$B$9),销售与出租收入!I106-I102,0),0) -> 0 | J105: =IF(J$4<=核心参数输入!$B$9,IF(AND(核心参数输入!$B$64=1,J$4=核心参数输入!$B$9),销售与出租收入!J106-J102,0),0) -> 0 | K105: =IF(K$4<=核心参数输入!$B$9,IF(AND(核心参数输入!$B$64=1,K$4=核心参数输入!$B$9),销售与出租收入!K106-K102,0),0) -> 0 | ... AH105: =IF(AH$4<=核心参数输入!$B$9,IF(AND(核心参数输入!$B$64=1,AH$4=核心参数输入!$B$9),销售与出租收入!AH106-AH102,0),0) -> 0

Sheet 融资与还本付息
A2: 融资与还本付息 · 模拟数据
A3: 基准情景 · 单笔贷款
A4: 项目年度 / 日历年份 | D4: =核心参数输入!D87 -> 0 | E4: =核心参数输入!E87 -> 1 | F4: =核心参数输入!F87 -> 2 | G4: =核心参数输入!G87 -> 3 | H4: =核心参数输入!H87 -> 4 | I4: =核心参数输入!I87 -> 5 | J4: =核心参数输入!J87 -> 6 | K4: =核心参数输入!K87 -> 7 | ... AH4: =核心参数输入!AH87 -> 30
D5: =核心参数输入!$B$8+D4 -> 2026 | E5: =核心参数输入!$B$8+E4 -> 2027 | F5: =核心参数输入!$B$8+F4 -> 2028 | G5: =核心参数输入!$B$8+G4 -> 2029 | H5: =核心参数输入!$B$8+H4 -> 2030 | I5: =核心参数输入!$B$8+I4 -> 2031 | J5: =核心参数输入!$B$8+J4 -> 2032 | K5: =核心参数输入!$B$8+K4 -> 2033 | ... AH5: =核心参数输入!$B$8+AH4 -> 2056
A6: 首次提款年 | B6: =IF(核心参数输入!$B$57=0,0,IFERROR(MATCH(1,融资与还本付息!$D$12:$AH$12,0)-1,0)) -> 1
A7: 贷款到期年 | B7: =IF(核心参数输入!$B$57=0,0,B6+核心参数输入!$B$59-1) -> 10
A8: 等额本金还款年度数 | B8: =IF(核心参数输入!$B$57=0,0,MAX(1,B7-核心参数输入!$B$60+1)) -> 7
A10: 期初贷款本金 | B10: 万元 | D10: =IF(D$4<=核心参数输入!$B$9,0,0) -> 0 | E10: =IF(E$4<=核心参数输入!$B$9,D15,0) -> 0 | F10: =IF(F$4<=核心参数输入!$B$9,E15,0) -> 9000 | G10: =IF(G$4<=核心参数输入!$B$9,F15,0) -> 21000 | H10: =IF(H$4<=核心参数输入!$B$9,G15,0) -> 30000 | I10: =IF(I$4<=核心参数输入!$B$9,H15,0) -> 25714.286 | J10: =IF(J$4<=核心参数输入!$B$9,I15,0) -> 21428.571 | K10: =IF(K$4<=核心参数输入!$B$9,J15,0) -> 17142.857 | L10: =IF(L$4<=核心参数输入!$B$9,K15,0) -> 12857.143 | ... AH10: =IF(AH$4<=核心参数输入!$B$9,AG15,0) -> 0
A11: 当年贷款提款 | B11: 万元 | D11: =IF(D$4<=核心参数输入!$B$9,核心参数输入!$B$57*建筑面积与开发计划!D20,0) -> 0 | E11: =IF(E$4<=核心参数输入!$B$9,核心参数输入!$B$57*建筑面积与开发计划!E20,0) -> 9000 | F11: =IF(F$4<=核心参数输入!$B$9,核心参数输入!$B$57*建筑面积与开发计划!F20,0) -> 12000 | G11: =IF(G$4<=核心参数输入!$B$9,核心参数输入!$B$57*建筑面积与开发计划!G20,0) -> 9000 | H11: =IF(H$4<=核心参数输入!$B$9,核心参数输入!$B$57*建筑面积与开发计划!H20,0) -> 0 | I11: =IF(I$4<=核心参数输入!$B$9,核心参数输入!$B$57*建筑面积与开发计划!I20,0) -> 0 | J11: =IF(J$4<=核心参数输入!$B$9,核心参数输入!$B$57*建筑面积与开发计划!J20,0) -> 0 | K11: =IF(K$4<=核心参数输入!$B$9,核心参数输入!$B$57*建筑面积与开发计划!K20,0) -> 0 | ... AH11: =IF(AH$4<=核心参数输入!$B$9,核心参数输入!$B$57*建筑面积与开发计划!AH20,0) -> 0
A12: 提款年度标记 | B12: 0/1 | D12: =IF(D$4<=核心参数输入!$B$9,IF(D11>0.000001,1,0),0) -> 0 | E12: =IF(E$4<=核心参数输入!$B$9,IF(E11>0.000001,1,0),0) -> 1 | F12: =IF(F$4<=核心参数输入!$B$9,IF(F11>0.000001,1,0),0) -> 1 | G12: =IF(G$4<=核心参数输入!$B$9,IF(G11>0.000001,1,0),0) -> 1 | H12: =IF(H$4<=核心参数输入!$B$9,IF(H11>0.000001,1,0),0) -> 0 | I12: =IF(I$4<=核心参数输入!$B$9,IF(I11>0.000001,1,0),0) -> 0 | J12: =IF(J$4<=核心参数输入!$B$9,IF(J11>0.000001,1,0),0) -> 0 | K12: =IF(K$4<=核心参数输入!$B$9,IF(K11>0.000001,1,0),0) -> 0 | ... AH12: =IF(AH$4<=核心参数输入!$B$9,IF(AH11>0.000001,1,0),0) -> 0
A13: 当年还本 | B13: 万元 | D13: =IF(D$4<=核心参数输入!$B$9,IF(AND(核心参数输入!$B$57>0,D$4>=核心参数输入!$B$60,D$4<=$B$7),MIN(D10+D11,核心参数输入!$B$57/MAX(1,$B$8)),0),0) -> 0 | E13: =IF(E$4<=核心参数输入!$B$9,IF(AND(核心参数输入!$B$57>0,E$4>=核心参数输入!$B$60,E$4<=$B$7),MIN(E10+E11,核心参数输入!$B$57/MAX(1,$B$8)),0),0) -> 0 | F13: =IF(F$4<=核心参数输入!$B$9,IF(AND(核心参数输入!$B$57>0,F$4>=核心参数输入!$B$60,F$4<=$B$7),MIN(F10+F11,核心参数输入!$B$57/MAX(1,$B$8)),0),0) -> 0 | G13: =IF(G$4<=核心参数输入!$B$9,IF(AND(核心参数输入!$B$57>0,G$4>=核心参数输入!$B$60,G$4<=$B$7),MIN(G10+G11,核心参数输入!$B$57/MAX(1,$B$8)),0),0) -> 0 | H13: =IF(H$4<=核心参数输入!$B$9,IF(AND(核心参数输入!$B$57>0,H$4>=核心参数输入!$B$60,H$4<=$B$7),MIN(H10+H11,核心参数输入!$B$57/MAX(1,$B$8)),0),0) -> 4285.7143 | I13: =IF(I$4<=核心参数输入!$B$9,IF(AND(核心参数输入!$B$57>0,I$4>=核心参数输入!$B$60,I$4<=$B$7),MIN(I10+I11,核心参数输入!$B$57/MAX(1,$B$8)),0),0) -> 4285.7143 | J13: =IF(J$4<=核心参数输入!$B$9,IF(AND(核心参数输入!$B$57>0,J$4>=核心参数输入!$B$60,J$4<=$B$7),MIN(J10+J11,核心参数输入!$B$57/MAX(1,$B$8)),0),0) -> 4285.7143 | K13: =IF(K$4<=核心参数输入!$B$9,IF(AND(核心参数输入!$B$57>0,K$4>=核心参数输入!$B$60,K$4<=$B$7),MIN(K10+K11,核心参数输入!$B$57/MAX(1,$B$8)),0),0) -> 4285.7143 | ... AH13: =IF(AH$4<=核心参数输入!$B$9,IF(AND(核心参数输入!$B$57>0,AH$4>=核心参数输入!$B$60,AH$4<=$B$7),MIN(AH10+AH11,核心参数输入!$B$57/MAX(1,$B$8)),0),0) -> 0
A14: 当年利息 | B14: 万元 | D14: =IF(D$4<=核心参数输入!$B$9,MAX(0,D10+D11/2-D13/2)*核心参数输入!$B$58,0) -> 0 | E14: =IF(E$4<=核心参数输入!$B$9,MAX(0,E10+E11/2-E13/2)*核心参数输入!$B$58,0) -> 189 | F14: =IF(F$4<=核心参数输入!$B$9,MAX(0,F10+F11/2-F13/2)*核心参数输入!$B$58,0) -> 630 | G14: =IF(G$4<=核心参数输入!$B$9,MAX(0,G10+G11/2-G13/2)*核心参数输入!$B$58,0) -> 1071 | H14: =IF(H$4<=核心参数输入!$B$9,MAX(0,H10+H11/2-H13/2)*核心参数输入!$B$58,0) -> 1170 | I14: =IF(I$4<=核心参数输入!$B$9,MAX(0,I10+I11/2-I13/2)*核心参数输入!$B$58,0) -> 990 | J14: =IF(J$4<=核心参数输入!$B$9,MAX(0,J10+J11/2-J13/2)*核心参数输入!$B$58,0) -> 810 | K14: =IF(K$4<=核心参数输入!$B$9,MAX(0,K10+K11/2-K13/2)*核心参数输入!$B$58,0) -> 630 | ... AH14: =IF(AH$4<=核心参数输入!$B$9,MAX(0,AH10+AH11/2-AH13/2)*核心参数输入!$B$58,0) -> 0
A15: 期末贷款本金 | B15: 万元 | D15: =IF(D$4<=核心参数输入!$B$9,MAX(0,D10+D11-D13),0) -> 0 | E15: =IF(E$4<=核心参数输入!$B$9,MAX(0,E10+E11-E13),0) -> 9000 | F15: =IF(F$4<=核心参数输入!$B$9,MAX(0,F10+F11-F13),0) -> 21000 | G15: =IF(G$4<=核心参数输入!$B$9,MAX(0,G10+G11-G13),0) -> 30000 | H15: =IF(H$4<=核心参数输入!$B$9,MAX(0,H10+H11-H13),0) -> 25714.286 | I15: =IF(I$4<=核心参数输入!$B$9,MAX(0,I10+I11-I13),0) -> 21428.571 | J15: =IF(J$4<=核心参数输入!$B$9,MAX(0,J10+J11-J13),0) -> 17142.857 | K15: =IF(K$4<=核心参数输入!$B$9,MAX(0,K10+K11-K13),0) -> 12857.143 | ... AH15: =IF(AH$4<=核心参数输入!$B$9,MAX(0,AH10+AH11-AH13),0) -> 0
A16: 其中：建设期利息 | B16: 万元 | D16: =IF(D$4<=核心参数输入!$B$9,IF(D$4<=核心参数输入!$B$16,D14,0),0) -> 0 | E16: =IF(E$4<=核心参数输入!$B$9,IF(E$4<=核心参数输入!$B$16,E14,0),0) -> 189 | F16: =IF(F$4<=核心参数输入!$B$9,IF(F$4<=核心参数输入!$B$16,F14,0),0) -> 630 | G16: =IF(G$4<=核心参数输入!$B$9,IF(G$4<=核心参数输入!$B$16,G14,0),0) -> 1071 | H16: =IF(H$4<=核心参数输入!$B$9,IF(H$4<=核心参数输入!$B$16,H14,0),0) -> 0 | I16: =IF(I$4<=核心参数输入!$B$9,IF(I$4<=核心参数输入!$B$16,I14,0),0) -> 0 | J16: =IF(J$4<=核心参数输入!$B$9,IF(J$4<=核心参数输入!$B$16,J14,0),0) -> 0 | K16: =IF(K$4<=核心参数输入!$B$9,IF(K$4<=核心参数输入!$B$16,K14,0),0) -> 0 | ... AH16: =IF(AH$4<=核心参数输入!$B$9,IF(AH$4<=核心参数输入!$B$16,AH14,0),0) -> 0
A17: 其中：建成后费用化利息 | B17: 万元 | D17: =IF(D$4<=核心参数输入!$B$9,D14-D16,0) -> 0 | E17: =IF(E$4<=核心参数输入!$B$9,E14-E16,0) -> 0 | F17: =IF(F$4<=核心参数输入!$B$9,F14-F16,0) -> 0 | G17: =IF(G$4<=核心参数输入!$B$9,G14-G16,0) -> 0 | H17: =IF(H$4<=核心参数输入!$B$9,H14-H16,0) -> 1170 | I17: =IF(I$4<=核心参数输入!$B$9,I14-I16,0) -> 990 | J17: =IF(J$4<=核心参数输入!$B$9,J14-J16,0) -> 810 | K17: =IF(K$4<=核心参数输入!$B$9,K14-K16,0) -> 630 | ... AH17: =IF(AH$4<=核心参数输入!$B$9,AH14-AH16,0) -> 0
A18: 当年本息合计 | B18: 万元 | D18: =IF(D$4<=核心参数输入!$B$9,D13+D14,0) -> 0 | E18: =IF(E$4<=核心参数输入!$B$9,E13+E14,0) -> 189 | F18: =IF(F$4<=核心参数输入!$B$9,F13+F14,0) -> 630 | G18: =IF(G$4<=核心参数输入!$B$9,G13+G14,0) -> 1071 | H18: =IF(H$4<=核心参数输入!$B$9,H13+H14,0) -> 5455.7143 | I18: =IF(I$4<=核心参数输入!$B$9,I13+I14,0) -> 5275.7143 | J18: =IF(J$4<=核心参数输入!$B$9,J13+J14,0) -> 5095.7143 | K18: =IF(K$4<=核心参数输入!$B$9,K13+K14,0) -> 4915.7143 | ... AH18: =IF(AH$4<=核心参数输入!$B$9,AH13+AH14,0) -> 0
A19: 到期未还本金（到期年标记） | B19: 万元 | D19: =IF(D$4<=核心参数输入!$B$9,IF(D$4=$B$7,D15,0),0) -> 0 | E19: =IF(E$4<=核心参数输入!$B$9,IF(E$4=$B$7,E15,0),0) -> 0 | F19: =IF(F$4<=核心参数输入!$B$9,IF(F$4=$B$7,F15,0),0) -> 0 | G19: =IF(G$4<=核心参数输入!$B$9,IF(G$4=$B$7,G15,0),0) -> 0 | H19: =IF(H$4<=核心参数输入!$B$9,IF(H$4=$B$7,H15,0),0) -> 0 | I19: =IF(I$4<=核心参数输入!$B$9,IF(I$4=$B$7,I15,0),0) -> 0 | J19: =IF(J$4<=核心参数输入!$B$9,IF(J$4=$B$7,J15,0),0) -> 0 | K19: =IF(K$4<=核心参数输入!$B$9,IF(K$4=$B$7,K15,0),0) -> 0 | ... AH19: =IF(AH$4<=核心参数输入!$B$9,IF(AH$4=$B$7,AH15,0),0) -> 0
A83: 组合压力情景 · 贷款额度不增加
A86: 首次提款年 | B86: =IF(核心参数输入!$B$57=0,0,IFERROR(MATCH(1,融资与还本付息!$D$92:$AH$92,0)-1,0)) -> 1
A87: 贷款到期年 | B87: =IF(核心参数输入!$B$57=0,0,B86+核心参数输入!$B$59-1) -> 10
A88: 等额本金还款年度数 | B88: =IF(核心参数输入!$B$57=0,0,MAX(1,B87-核心参数输入!$B$60+1)) -> 7
A90: 期初贷款本金 | B90: 万元 | D90: =IF(D$4<=核心参数输入!$B$9,0,0) -> 0 | E90: =IF(E$4<=核心参数输入!$B$9,D95,0) -> 0 | F90: =IF(F$4<=核心参数输入!$B$9,E95,0) -> 9000 | G90: =IF(G$4<=核心参数输入!$B$9,F95,0) -> 21000 | H90: =IF(H$4<=核心参数输入!$B$9,G95,0) -> 30000 | I90: =IF(I$4<=核心参数输入!$B$9,H95,0) -> 25714.286 | J90: =IF(J$4<=核心参数输入!$B$9,I95,0) -> 21428.571 | K90: =IF(K$4<=核心参数输入!$B$9,J95,0) -> 17142.857 | L90: =IF(L$4<=核心参数输入!$B$9,K95,0) -> 12857.143 | ... AH90: =IF(AH$4<=核心参数输入!$B$9,AG95,0) -> 0
A91: 当年贷款提款 | B91: 万元 | D91: =IF(D$4<=核心参数输入!$B$9,核心参数输入!$B$57*建筑面积与开发计划!D100,0) -> 0 | E91: =IF(E$4<=核心参数输入!$B$9,核心参数输入!$B$57*建筑面积与开发计划!E100,0) -> 9000 | F91: =IF(F$4<=核心参数输入!$B$9,核心参数输入!$B$57*建筑面积与开发计划!F100,0) -> 12000 | G91: =IF(G$4<=核心参数输入!$B$9,核心参数输入!$B$57*建筑面积与开发计划!G100,0) -> 9000 | H91: =IF(H$4<=核心参数输入!$B$9,核心参数输入!$B$57*建筑面积与开发计划!H100,0) -> 0 | I91: =IF(I$4<=核心参数输入!$B$9,核心参数输入!$B$57*建筑面积与开发计划!I100,0) -> 0 | J91: =IF(J$4<=核心参数输入!$B$9,核心参数输入!$B$57*建筑面积与开发计划!J100,0) -> 0 | K91: =IF(K$4<=核心参数输入!$B$9,核心参数输入!$B$57*建筑面积与开发计划!K100,0) -> 0 | ... AH91: =IF(AH$4<=核心参数输入!$B$9,核心参数输入!$B$57*建筑面积与开发计划!AH100,0) -> 0
A92: 提款年度标记 | B92: 0/1 | D92: =IF(D$4<=核心参数输入!$B$9,IF(D91>0.000001,1,0),0) -> 0 | E92: =IF(E$4<=核心参数输入!$B$9,IF(E91>0.000001,1,0),0) -> 1 | F92: =IF(F$4<=核心参数输入!$B$9,IF(F91>0.000001,1,0),0) -> 1 | G92: =IF(G$4<=核心参数输入!$B$9,IF(G91>0.000001,1,0),0) -> 1 | H92: =IF(H$4<=核心参数输入!$B$9,IF(H91>0.000001,1,0),0) -> 0 | I92: =IF(I$4<=核心参数输入!$B$9,IF(I91>0.000001,1,0),0) -> 0 | J92: =IF(J$4<=核心参数输入!$B$9,IF(J91>0.000001,1,0),0) -> 0 | K92: =IF(K$4<=核心参数输入!$B$9,IF(K91>0.000001,1,0),0) -> 0 | ... AH92: =IF(AH$4<=核心参数输入!$B$9,IF(AH91>0.000001,1,0),0) -> 0
A93: 当年还本 | B93: 万元 | D93: =IF(D$4<=核心参数输入!$B$9,IF(AND(核心参数输入!$B$57>0,D$4>=核心参数输入!$B$60,D$4<=$B$87),MIN(D90+D91,核心参数输入!$B$57/MAX(1,$B$88)),0),0) -> 0 | E93: =IF(E$4<=核心参数输入!$B$9,IF(AND(核心参数输入!$B$57>0,E$4>=核心参数输入!$B$60,E$4<=$B$87),MIN(E90+E91,核心参数输入!$B$57/MAX(1,$B$88)),0),0) -> 0 | F93: =IF(F$4<=核心参数输入!$B$9,IF(AND(核心参数输入!$B$57>0,F$4>=核心参数输入!$B$60,F$4<=$B$87),MIN(F90+F91,核心参数输入!$B$57/MAX(1,$B$88)),0),0) -> 0 | G93: =IF(G$4<=核心参数输入!$B$9,IF(AND(核心参数输入!$B$57>0,G$4>=核心参数输入!$B$60,G$4<=$B$87),MIN(G90+G91,核心参数输入!$B$57/MAX(1,$B$88)),0),0) -> 0 | H93: =IF(H$4<=核心参数输入!$B$9,IF(AND(核心参数输入!$B$57>0,H$4>=核心参数输入!$B$60,H$4<=$B$87),MIN(H90+H91,核心参数输入!$B$57/MAX(1,$B$88)),0),0) -> 4285.7143 | I93: =IF(I$4<=核心参数输入!$B$9,IF(AND(核心参数输入!$B$57>0,I$4>=核心参数输入!$B$60,I$4<=$B$87),MIN(I90+I91,核心参数输入!$B$57/MAX(1,$B$88)),0),0) -> 4285.7143 | J93: =IF(J$4<=核心参数输入!$B$9,IF(AND(核心参数输入!$B$57>0,J$4>=核心参数输入!$B$60,J$4<=$B$87),MIN(J90+J91,核心参数输入!$B$57/MAX(1,$B$88)),0),0) -> 4285.7143 | K93: =IF(K$4<=核心参数输入!$B$9,IF(AND(核心参数输入!$B$57>0,K$4>=核心参数输入!$B$60,K$4<=$B$87),MIN(K90+K91,核心参数输入!$B$57/MAX(1,$B$88)),0),0) -> 4285.7143 | ... AH93: =IF(AH$4<=核心参数输入!$B$9,IF(AND(核心参数输入!$B$57>0,AH$4>=核心参数输入!$B$60,AH$4<=$B$87),MIN(AH90+AH91,核心参数输入!$B$57/MAX(1,$B$88)),0),0) -> 0
A94: 当年利息 | B94: 万元 | D94: =IF(D$4<=核心参数输入!$B$9,MAX(0,D90+D91/2-D93/2)*核心参数输入!$B$58,0) -> 0 | E94: =IF(E$4<=核心参数输入!$B$9,MAX(0,E90+E91/2-E93/2)*核心参数输入!$B$58,0) -> 189 | F94: =IF(F$4<=核心参数输入!$B$9,MAX(0,F90+F91/2-F93/2)*核心参数输入!$B$58,0) -> 630 | G94: =IF(G$4<=核心参数输入!$B$9,MAX(0,G90+G91/2-G93/2)*核心参数输入!$B$58,0) -> 1071 | H94: =IF(H$4<=核心参数输入!$B$9,MAX(0,H90+H91/2-H93/2)*核心参数输入!$B$58,0) -> 1170 | I94: =IF(I$4<=核心参数输入!$B$9,MAX(0,I90+I91/2-I93/2)*核心参数输入!$B$58,0) -> 990 | J94: =IF(J$4<=核心参数输入!$B$9,MAX(0,J90+J91/2-J93/2)*核心参数输入!$B$58,0) -> 810 | K94: =IF(K$4<=核心参数输入!$B$9,MAX(0,K90+K91/2-K93/2)*核心参数输入!$B$58,0) -> 630 | ... AH94: =IF(AH$4<=核心参数输入!$B$9,MAX(0,AH90+AH91/2-AH93/2)*核心参数输入!$B$58,0) -> 0
A95: 期末贷款本金 | B95: 万元 | D95: =IF(D$4<=核心参数输入!$B$9,MAX(0,D90+D91-D93),0) -> 0 | E95: =IF(E$4<=核心参数输入!$B$9,MAX(0,E90+E91-E93),0) -> 9000 | F95: =IF(F$4<=核心参数输入!$B$9,MAX(0,F90+F91-F93),0) -> 21000 | G95: =IF(G$4<=核心参数输入!$B$9,MAX(0,G90+G91-G93),0) -> 30000 | H95: =IF(H$4<=核心参数输入!$B$9,MAX(0,H90+H91-H93),0) -> 25714.286 | I95: =IF(I$4<=核心参数输入!$B$9,MAX(0,I90+I91-I93),0) -> 21428.571 | J95: =IF(J$4<=核心参数输入!$B$9,MAX(0,J90+J91-J93),0) -> 17142.857 | K95: =IF(K$4<=核心参数输入!$B$9,MAX(0,K90+K91-K93),0) -> 12857.143 | ... AH95: =IF(AH$4<=核心参数输入!$B$9,MAX(0,AH90+AH91-AH93),0) -> 0
A96: 其中：建设期利息 | B96: 万元 | D96: =IF(D$4<=核心参数输入!$B$9,IF(D$4<=核心参数输入!$B$16,D94,0),0) -> 0 | E96: =IF(E$4<=核心参数输入!$B$9,IF(E$4<=核心参数输入!$B$16,E94,0),0) -> 189 | F96: =IF(F$4<=核心参数输入!$B$9,IF(F$4<=核心参数输入!$B$16,F94,0),0) -> 630 | G96: =IF(G$4<=核心参数输入!$B$9,IF(G$4<=核心参数输入!$B$16,G94,0),0) -> 1071 | H96: =IF(H$4<=核心参数输入!$B$9,IF(H$4<=核心参数输入!$B$16,H94,0),0) -> 0 | I96: =IF(I$4<=核心参数输入!$B$9,IF(I$4<=核心参数输入!$B$16,I94,0),0) -> 0 | J96: =IF(J$4<=核心参数输入!$B$9,IF(J$4<=核心参数输入!$B$16,J94,0),0) -> 0 | K96: =IF(K$4<=核心参数输入!$B$9,IF(K$4<=核心参数输入!$B$16,K94,0),0) -> 0 | ... AH96: =IF(AH$4<=核心参数输入!$B$9,IF(AH$4<=核心参数输入!$B$16,AH94,0),0) -> 0
A97: 其中：建成后费用化利息 | B97: 万元 | D97: =IF(D$4<=核心参数输入!$B$9,D94-D96,0) -> 0 | E97: =IF(E$4<=核心参数输入!$B$9,E94-E96,0) -> 0 | F97: =IF(F$4<=核心参数输入!$B$9,F94-F96,0) -> 0 | G97: =IF(G$4<=核心参数输入!$B$9,G94-G96,0) -> 0 | H97: =IF(H$4<=核心参数输入!$B$9,H94-H96,0) -> 1170 | I97: =IF(I$4<=核心参数输入!$B$9,I94-I96,0) -> 990 | J97: =IF(J$4<=核心参数输入!$B$9,J94-J96,0) -> 810 | K97: =IF(K$4<=核心参数输入!$B$9,K94-K96,0) -> 630 | ... AH97: =IF(AH$4<=核心参数输入!$B$9,AH94-AH96,0) -> 0
A98: 当年本息合计 | B98: 万元 | D98: =IF(D$4<=核心参数输入!$B$9,D93+D94,0) -> 0 | E98: =IF(E$4<=核心参数输入!$B$9,E93+E94,0) -> 189 | F98: =IF(F$4<=核心参数输入!$B$9,F93+F94,0) -> 630 | G98: =IF(G$4<=核心参数输入!$B$9,G93+G94,0) -> 1071 | H98: =IF(H$4<=核心参数输入!$B$9,H93+H94,0) -> 5455.7143 | I98: =IF(I$4<=核心参数输入!$B$9,I93+I94,0) -> 5275.7143 | J98: =IF(J$4<=核心参数输入!$B$9,J93+J94,0) -> 5095.7143 | K98: =IF(K$4<=核心参数输入!$B$9,K93+K94,0) -> 4915.7143 | ... AH98: =IF(AH$4<=核心参数输入!$B$9,AH93+AH94,0) -> 0
A99: 到期未还本金（到期年标记） | B99: 万元 | D99: =IF(D$4<=核心参数输入!$B$9,IF(D$4=$B$87,D95,0),0) -> 0 | E99: =IF(E$4<=核心参数输入!$B$9,IF(E$4=$B$87,E95,0),0) -> 0 | F99: =IF(F$4<=核心参数输入!$B$9,IF(F$4=$B$87,F95,0),0) -> 0 | G99: =IF(G$4<=核心参数输入!$B$9,IF(G$4=$B$87,G95,0),0) -> 0 | H99: =IF(H$4<=核心参数输入!$B$9,IF(H$4=$B$87,H95,0),0) -> 0 | I99: =IF(I$4<=核心参数输入!$B$9,IF(I$4=$B$87,I95,0),0) -> 0 | J99: =IF(J$4<=核心参数输入!$B$9,IF(J$4=$B$87,J95,0),0) -> 0 | K99: =IF(K$4<=核心参数输入!$B$9,IF(K$4=$B$87,K95,0),0) -> 0 | ... AH99: =IF(AH$4<=核心参数输入!$B$9,IF(AH$4=$B$87,AH95,0),0) -> 0

Sheet 利润与现金流
A2: 利润与现金流 · 模拟数据
A4: 项目年度 / 日历年份 | D4: =核心参数输入!D87 -> 0 | E4: =核心参数输入!E87 -> 1 | F4: =核心参数输入!F87 -> 2 | G4: =核心参数输入!G87 -> 3 | H4: =核心参数输入!H87 -> 4 | I4: =核心参数输入!I87 -> 5 | J4: =核心参数输入!J87 -> 6 | K4: =核心参数输入!K87 -> 7 | ... AH4: =核心参数输入!AH87 -> 30
D5: =核心参数输入!$B$8+D4 -> 2026 | E5: =核心参数输入!$B$8+E4 -> 2027 | F5: =核心参数输入!$B$8+F4 -> 2028 | G5: =核心参数输入!$B$8+G4 -> 2029 | H5: =核心参数输入!$B$8+H4 -> 2030 | I5: =核心参数输入!$B$8+I4 -> 2031 | J5: =核心参数输入!$B$8+J4 -> 2032 | K5: =核心参数输入!$B$8+K4 -> 2033 | ... AH5: =核心参数输入!$B$8+AH4 -> 2056
A7: 基准情景 · 利润、现金流与资金约束
A10: 营业收入（销售＋持有） | B10: 万元 | D10: =IF(D$4<=核心参数输入!$B$9,销售与出租收入!D23,0) -> 0 | E10: =IF(E$4<=核心参数输入!$B$9,销售与出租收入!E23,0) -> 0 | F10: =IF(F$4<=核心参数输入!$B$9,销售与出租收入!F23,0) -> 0 | G10: =IF(G$4<=核心参数输入!$B$9,销售与出租收入!G23,0) -> 0 | H10: =IF(H$4<=核心参数输入!$B$9,销售与出租收入!H23,0) -> 15210.137 | I10: =IF(I$4<=核心参数输入!$B$9,销售与出租收入!I23,0) -> 20591.754 | J10: =IF(J$4<=核心参数输入!$B$9,销售与出租收入!J23,0) -> 16111.32 | K10: =IF(K$4<=核心参数输入!$B$9,销售与出租收入!K23,0) -> 1810.0174 | ... AH10: =IF(AH$4<=核心参数输入!$B$9,销售与出租收入!AH23,0) -> 0
A11: 现金成本及经营税费 | B11: 万元 | D11: =IF(D$4<=核心参数输入!$B$9,运营成本与税费!D16,0) -> 0 | E11: =IF(E$4<=核心参数输入!$B$9,运营成本与税费!E16,0) -> 0 | F11: =IF(F$4<=核心参数输入!$B$9,运营成本与税费!F16,0) -> 0 | G11: =IF(G$4<=核心参数输入!$B$9,运营成本与税费!G16,0) -> 0 | H11: =IF(H$4<=核心参数输入!$B$9,运营成本与税费!H16,0) -> 2131.9185 | I11: =IF(I$4<=核心参数输入!$B$9,运营成本与税费!I16,0) -> 2744.6408 | J11: =IF(J$4<=核心参数输入!$B$9,运营成本与税费!J16,0) -> 2306.2513 | K11: =IF(K$4<=核心参数输入!$B$9,运营成本与税费!K16,0) -> 824.16552 | ... AH11: =IF(AH$4<=核心参数输入!$B$9,运营成本与税费!AH16,0) -> 0
A12: 无融资经营利润EBIT | B12: 万元 | D12: =IF(D$4<=核心参数输入!$B$9,D10-D11-运营成本与税费!D17-运营成本与税费!D19,0) -> 0 | E12: =IF(E$4<=核心参数输入!$B$9,E10-E11-运营成本与税费!E17-运营成本与税费!E19,0) -> 0 | F12: =IF(F$4<=核心参数输入!$B$9,F10-F11-运营成本与税费!F17-运营成本与税费!F19,0) -> 0 | G12: =IF(G$4<=核心参数输入!$B$9,G10-G11-运营成本与税费!G17-运营成本与税费!G19,0) -> 0 | H12: =IF(H$4<=核心参数输入!$B$9,H10-H11-运营成本与税费!H17-运营成本与税费!H19,0) -> 2272.309 | I12: =IF(I$4<=核心参数输入!$B$9,I10-I11-运营成本与税费!I17-运营成本与税费!I19,0) -> 3690.6036 | J12: =IF(J$4<=核心参数输入!$B$9,J10-J11-运营成本与税费!J17-运营成本与税费!J19,0) -> 2999.1583 | K12: =IF(K$4<=核心参数输入!$B$9,K10-K11-运营成本与税费!K17-运营成本与税费!K19,0) -> 231.74183 | ... AH12: =IF(AH$4<=核心参数输入!$B$9,AH10-AH11-运营成本与税费!AH17-运营成本与税费!AH19,0) -> 0
A13: 融资口径经营利润EBIT | B13: 万元 | D13: =IF(D$4<=核心参数输入!$B$9,D10-D11-运营成本与税费!D18-运营成本与税费!D20,0) -> 0 | E13: =IF(E$4<=核心参数输入!$B$9,E10-E11-运营成本与税费!E18-运营成本与税费!E20,0) -> 0 | F13: =IF(F$4<=核心参数输入!$B$9,F10-F11-运营成本与税费!F18-运营成本与税费!F20,0) -> 0 | G13: =IF(G$4<=核心参数输入!$B$9,G10-G11-运营成本与税费!G18-运营成本与税费!G20,0) -> 0 | H13: =IF(H$4<=核心参数输入!$B$9,H10-H11-运营成本与税费!H18-运营成本与税费!H20,0) -> 1933.5265 | I13: =IF(I$4<=核心参数输入!$B$9,I10-I11-运营成本与税费!I18-运营成本与税费!I20,0) -> 3247.8711 | J13: =IF(J$4<=核心参数输入!$B$9,J10-J11-运营成本与税费!J18-运营成本与税费!J20,0) -> 2660.3758 | K13: =IF(K$4<=核心参数输入!$B$9,K10-K11-运营成本与税费!K18-运营成本与税费!K20,0) -> 204.80933 | ... AH13: =IF(AH$4<=核心参数输入!$B$9,AH10-AH11-运营成本与税费!AH18-运营成本与税费!AH20,0) -> 0
A14: 建成后利息费用 | B14: 万元 | D14: =IF(D$4<=核心参数输入!$B$9,融资与还本付息!D17,0) -> 0 | E14: =IF(E$4<=核心参数输入!$B$9,融资与还本付息!E17,0) -> 0 | F14: =IF(F$4<=核心参数输入!$B$9,融资与还本付息!F17,0) -> 0 | G14: =IF(G$4<=核心参数输入!$B$9,融资与还本付息!G17,0) -> 0 | H14: =IF(H$4<=核心参数输入!$B$9,融资与还本付息!H17,0) -> 1170 | I14: =IF(I$4<=核心参数输入!$B$9,融资与还本付息!I17,0) -> 990 | J14: =IF(J$4<=核心参数输入!$B$9,融资与还本付息!J17,0) -> 810 | K14: =IF(K$4<=核心参数输入!$B$9,融资与还本付息!K17,0) -> 630 | ... AH14: =IF(AH$4<=核心参数输入!$B$9,融资与还本付息!AH17,0) -> 0
A15: 融资口径处置前税前利润 | B15: 万元 | D15: =IF(D$4<=核心参数输入!$B$9,D13-D14,0) -> 0 | E15: =IF(E$4<=核心参数输入!$B$9,E13-E14,0) -> 0 | F15: =IF(F$4<=核心参数输入!$B$9,F13-F14,0) -> 0 | G15: =IF(G$4<=核心参数输入!$B$9,G13-G14,0) -> 0 | H15: =IF(H$4<=核心参数输入!$B$9,H13-H14,0) -> 763.52648 | I15: =IF(I$4<=核心参数输入!$B$9,I13-I14,0) -> 2257.8711 | J15: =IF(J$4<=核心参数输入!$B$9,J13-J14,0) -> 1850.3758 | K15: =IF(K$4<=核心参数输入!$B$9,K13-K14,0) -> -425.19067 | ... AH15: =IF(AH$4<=核心参数输入!$B$9,AH13-AH14,0) -> 0
A16: 项目口径所得税含处置损益 | B16: 万元 | D16: =IF(D$4<=核心参数输入!$B$9,MAX(0,D12+运营成本与税费!D24)*核心参数输入!$B$52,0) -> 0 | E16: =IF(E$4<=核心参数输入!$B$9,MAX(0,E12+运营成本与税费!E24)*核心参数输入!$B$52,0) -> 0 | F16: =IF(F$4<=核心参数输入!$B$9,MAX(0,F12+运营成本与税费!F24)*核心参数输入!$B$52,0) -> 0 | G16: =IF(G$4<=核心参数输入!$B$9,MAX(0,G12+运营成本与税费!G24)*核心参数输入!$B$52,0) -> 0 | H16: =IF(H$4<=核心参数输入!$B$9,MAX(0,H12+运营成本与税费!H24)*核心参数输入!$B$52,0) -> 568.07724 | I16: =IF(I$4<=核心参数输入!$B$9,MAX(0,I12+运营成本与税费!I24)*核心参数输入!$B$52,0) -> 922.65089 | J16: =IF(J$4<=核心参数输入!$B$9,MAX(0,J12+运营成本与税费!J24)*核心参数输入!$B$52,0) -> 749.78958 | K16: =IF(K$4<=核心参数输入!$B$9,MAX(0,K12+运营成本与税费!K24)*核心参数输入!$B$52,0) -> 57.935458 | ... AH16: =IF(AH$4<=核心参数输入!$B$9,MAX(0,AH12+运营成本与税费!AH24)*核心参数输入!$B$52,0) -> 0
A17: 融资口径所得税含处置损益 | B17: 万元 | D17: =IF(D$4<=核心参数输入!$B$9,MAX(0,D15+运营成本与税费!D25)*核心参数输入!$B$52,0) -> 0 | E17: =IF(E$4<=核心参数输入!$B$9,MAX(0,E15+运营成本与税费!E25)*核心参数输入!$B$52,0) -> 0 | F17: =IF(F$4<=核心参数输入!$B$9,MAX(0,F15+运营成本与税费!F25)*核心参数输入!$B$52,0) -> 0 | G17: =IF(G$4<=核心参数输入!$B$9,MAX(0,G15+运营成本与税费!G25)*核心参数输入!$B$52,0) -> 0 | H17: =IF(H$4<=核心参数输入!$B$9,MAX(0,H15+运营成本与税费!H25)*核心参数输入!$B$52,0) -> 190.88162 | I17: =IF(I$4<=核心参数输入!$B$9,MAX(0,I15+运营成本与税费!I25)*核心参数输入!$B$52,0) -> 564.46777 | J17: =IF(J$4<=核心参数输入!$B$9,MAX(0,J15+运营成本与税费!J25)*核心参数输入!$B$52,0) -> 462.59396 | K17: =IF(K$4<=核心参数输入!$B$9,MAX(0,K15+运营成本与税费!K25)*核心参数输入!$B$52,0) -> 0 | ... AH17: =IF(AH$4<=核心参数输入!$B$9,MAX(0,AH15+运营成本与税费!AH25)*核心参数输入!$B$52,0) -> 0
A18: 融资口径净利润含处置损益 | B18: 万元 | D18: =IF(D$4<=核心参数输入!$B$9,D15+运营成本与税费!D25-D17,0) -> 0 | E18: =IF(E$4<=核心参数输入!$B$9,E15+运营成本与税费!E25-E17,0) -> 0 | F18: =IF(F$4<=核心参数输入!$B$9,F15+运营成本与税费!F25-F17,0) -> 0 | G18: =IF(G$4<=核心参数输入!$B$9,G15+运营成本与税费!G25-G17,0) -> 0 | H18: =IF(H$4<=核心参数输入!$B$9,H15+运营成本与税费!H25-H17,0) -> 572.64486 | I18: =IF(I$4<=核心参数输入!$B$9,I15+运营成本与税费!I25-I17,0) -> 1693.4033 | J18: =IF(J$4<=核心参数输入!$B$9,J15+运营成本与税费!J25-J17,0) -> 1387.7819 | K18: =IF(K$4<=核心参数输入!$B$9,K15+运营成本与税费!K25-K17,0) -> -425.19067 | ... AH18: =IF(AH$4<=核心参数输入!$B$9,AH15+运营成本与税费!AH25-AH17,0) -> 0
A19: 可用于偿债现金CFADS（不含处置） | B19: 万元 | D19: =IF(D$4<=核心参数输入!$B$9,D10-D11-MAX(0,D15)*核心参数输入!$B$52,0) -> 0 | E19: =IF(E$4<=核心参数输入!$B$9,E10-E11-MAX(0,E15)*核心参数输入!$B$52,0) -> 0 | F19: =IF(F$4<=核心参数输入!$B$9,F10-F11-MAX(0,F15)*核心参数输入!$B$52,0) -> 0 | G19: =IF(G$4<=核心参数输入!$B$9,G10-G11-MAX(0,G15)*核心参数输入!$B$52,0) -> 0 | H19: =IF(H$4<=核心参数输入!$B$9,H10-H11-MAX(0,H15)*核心参数输入!$B$52,0) -> 12887.337 | I19: =IF(I$4<=核心参数输入!$B$9,I10-I11-MAX(0,I15)*核心参数输入!$B$52,0) -> 17282.646 | J19: =IF(J$4<=核心参数输入!$B$9,J10-J11-MAX(0,J15)*核心参数输入!$B$52,0) -> 13342.474 | K19: =IF(K$4<=核心参数输入!$B$9,K10-K11-MAX(0,K15)*核心参数输入!$B$52,0) -> 985.85183 | ... AH19: =IF(AH$4<=核心参数输入!$B$9,AH10-AH11-MAX(0,AH15)*核心参数输入!$B$52,0) -> 0
A20: 项目经营现金流（不含处置） | B20: 万元 | D20: =IF(D$4<=核心参数输入!$B$9,D10-D11-MAX(0,D12)*核心参数输入!$B$52,0) -> 0 | E20: =IF(E$4<=核心参数输入!$B$9,E10-E11-MAX(0,E12)*核心参数输入!$B$52,0) -> 0 | F20: =IF(F$4<=核心参数输入!$B$9,F10-F11-MAX(0,F12)*核心参数输入!$B$52,0) -> 0 | G20: =IF(G$4<=核心参数输入!$B$9,G10-G11-MAX(0,G12)*核心参数输入!$B$52,0) -> 0 | H20: =IF(H$4<=核心参数输入!$B$9,H10-H11-MAX(0,H12)*核心参数输入!$B$52,0) -> 12510.142 | I20: =IF(I$4<=核心参数输入!$B$9,I10-I11-MAX(0,I12)*核心参数输入!$B$52,0) -> 16924.463 | J20: =IF(J$4<=核心参数输入!$B$9,J10-J11-MAX(0,J12)*核心参数输入!$B$52,0) -> 13055.279 | K20: =IF(K$4<=核心参数输入!$B$9,K10-K11-MAX(0,K12)*核心参数输入!$B$52,0) -> 927.91637 | ... AH20: =IF(AH$4<=核心参数输入!$B$9,AH10-AH11-MAX(0,AH12)*核心参数输入!$B$52,0) -> 0
A21: 土地现金支出 | B21: 万元 | D21: =IF(D$4<=核心参数输入!$B$9,投资与资金安排!D28,0) -> 8000 | E21: =IF(E$4<=核心参数输入!$B$9,投资与资金安排!E28,0) -> 0 | F21: =IF(F$4<=核心参数输入!$B$9,投资与资金安排!F28,0) -> 0 | G21: =IF(G$4<=核心参数输入!$B$9,投资与资金安排!G28,0) -> 0 | H21: =IF(H$4<=核心参数输入!$B$9,投资与资金安排!H28,0) -> 0 | I21: =IF(I$4<=核心参数输入!$B$9,投资与资金安排!I28,0) -> 0 | J21: =IF(J$4<=核心参数输入!$B$9,投资与资金安排!J28,0) -> 0 | K21: =IF(K$4<=核心参数输入!$B$9,投资与资金安排!K28,0) -> 0 | ... AH21: =IF(AH$4<=核心参数输入!$B$9,投资与资金安排!AH28,0) -> 0
A22: 非土地建设现金支出 | B22: 万元 | D22: =IF(D$4<=核心参数输入!$B$9,投资与资金安排!D29,0) -> 0 | E22: =IF(E$4<=核心参数输入!$B$9,投资与资金安排!E29,0) -> 15876 | F22: =IF(F$4<=核心参数输入!$B$9,投资与资金安排!F29,0) -> 21168 | G22: =IF(G$4<=核心参数输入!$B$9,投资与资金安排!G29,0) -> 15876 | H22: =IF(H$4<=核心参数输入!$B$9,投资与资金安排!H29,0) -> 0 | I22: =IF(I$4<=核心参数输入!$B$9,投资与资金安排!I29,0) -> 0 | J22: =IF(J$4<=核心参数输入!$B$9,投资与资金安排!J29,0) -> 0 | K22: =IF(K$4<=核心参数输入!$B$9,投资与资金安排!K29,0) -> 0 | ... AH22: =IF(AH$4<=核心参数输入!$B$9,投资与资金安排!AH29,0) -> 0
A23: 周转资金投入 | B23: 万元 | D23: =IF(D$4<=核心参数输入!$B$9,投资与资金安排!D31,0) -> 0 | E23: =IF(E$4<=核心参数输入!$B$9,投资与资金安排!E31,0) -> 0 | F23: =IF(F$4<=核心参数输入!$B$9,投资与资金安排!F31,0) -> 0 | G23: =IF(G$4<=核心参数输入!$B$9,投资与资金安排!G31,0) -> 0 | H23: =IF(H$4<=核心参数输入!$B$9,投资与资金安排!H31,0) -> 500 | I23: =IF(I$4<=核心参数输入!$B$9,投资与资金安排!I31,0) -> 0 | J23: =IF(J$4<=核心参数输入!$B$9,投资与资金安排!J31,0) -> 0 | K23: =IF(K$4<=核心参数输入!$B$9,投资与资金安排!K31,0) -> 0 | ... AH23: =IF(AH$4<=核心参数输入!$B$9,投资与资金安排!AH31,0) -> 0
A24: 周转资金收回 | B24: 万元 | D24: =IF(D$4<=核心参数输入!$B$9,投资与资金安排!D32,0) -> 0 | E24: =IF(E$4<=核心参数输入!$B$9,投资与资金安排!E32,0) -> 0 | F24: =IF(F$4<=核心参数输入!$B$9,投资与资金安排!F32,0) -> 0 | G24: =IF(G$4<=核心参数输入!$B$9,投资与资金安排!G32,0) -> 0 | H24: =IF(H$4<=核心参数输入!$B$9,投资与资金安排!H32,0) -> 0 | I24: =IF(I$4<=核心参数输入!$B$9,投资与资金安排!I32,0) -> 0 | J24: =IF(J$4<=核心参数输入!$B$9,投资与资金安排!J32,0) -> 0 | K24: =IF(K$4<=核心参数输入!$B$9,投资与资金安排!K32,0) -> 0 | ... AH24: =IF(AH$4<=核心参数输入!$B$9,投资与资金安排!AH32,0) -> 0
A25: 持有处置净现金（所得税前） | B25: 万元 | D25: =IF(D$4<=核心参数输入!$B$9,销售与出租收入!D26,0) -> 0 | E25: =IF(E$4<=核心参数输入!$B$9,销售与出租收入!E26,0) -> 0 | F25: =IF(F$4<=核心参数输入!$B$9,销售与出租收入!F26,0) -> 0 | G25: =IF(G$4<=核心参数输入!$B$9,销售与出租收入!G26,0) -> 0 | H25: =IF(H$4<=核心参数输入!$B$9,销售与出租收入!H26,0) -> 0 | I25: =IF(I$4<=核心参数输入!$B$9,销售与出租收入!I26,0) -> 0 | J25: =IF(J$4<=核心参数输入!$B$9,销售与出租收入!J26,0) -> 0 | K25: =IF(K$4<=核心参数输入!$B$9,销售与出租收入!K26,0) -> 0 | ... AH25: =IF(AH$4<=核心参数输入!$B$9,销售与出租收入!AH26,0) -> 0
A26: 项目投资税后现金流 | B26: 万元 | D26: =IF(D$4<=核心参数输入!$B$9,D10-D11-D16-D21-D22-D23+D24+D25,0) -> -8000 | E26: =IF(E$4<=核心参数输入!$B$9,E10-E11-E16-E21-E22-E23+E24+E25,0) -> -15876 | F26: =IF(F$4<=核心参数输入!$B$9,F10-F11-F16-F21-F22-F23+F24+F25,0) -> -21168 | G26: =IF(G$4<=核心参数输入!$B$9,G10-G11-G16-G21-G22-G23+G24+G25,0) -> -15876 | H26: =IF(H$4<=核心参数输入!$B$9,H10-H11-H16-H21-H22-H23+H24+H25,0) -> 12010.142 | I26: =IF(I$4<=核心参数输入!$B$9,I10-I11-I16-I21-I22-I23+I24+I25,0) -> 16924.463 | J26: =IF(J$4<=核心参数输入!$B$9,J10-J11-J16-J21-J22-J23+J24+J25,0) -> 13055.279 | K26: =IF(K$4<=核心参数输入!$B$9,K10-K11-K16-K21-K22-K23+K24+K25,0) -> 927.91637 | ... AH26: =IF(AH$4<=核心参数输入!$B$9,AH10-AH11-AH16-AH21-AH22-AH23+AH24+AH25,0) -> 0
A27: 贷款提款（非营业收入） | B27: 万元 | D27: =IF(D$4<=核心参数输入!$B$9,融资与还本付息!D11,0) -> 0 | E27: =IF(E$4<=核心参数输入!$B$9,融资与还本付息!E11,0) -> 9000 | F27: =IF(F$4<=核心参数输入!$B$9,融资与还本付息!F11,0) -> 12000 | G27: =IF(G$4<=核心参数输入!$B$9,融资与还本付息!G11,0) -> 9000 | H27: =IF(H$4<=核心参数输入!$B$9,融资与还本付息!H11,0) -> 0 | I27: =IF(I$4<=核心参数输入!$B$9,融资与还本付息!I11,0) -> 0 | J27: =IF(J$4<=核心参数输入!$B$9,融资与还本付息!J11,0) -> 0 | K27: =IF(K$4<=核心参数输入!$B$9,融资与还本付息!K11,0) -> 0 | ... AH27: =IF(AH$4<=核心参数输入!$B$9,融资与还本付息!AH11,0) -> 0
A28: 全部现金利息支付 | B28: 万元 | D28: =IF(D$4<=核心参数输入!$B$9,融资与还本付息!D14,0) -> 0 | E28: =IF(E$4<=核心参数输入!$B$9,融资与还本付息!E14,0) -> 189 | F28: =IF(F$4<=核心参数输入!$B$9,融资与还本付息!F14,0) -> 630 | G28: =IF(G$4<=核心参数输入!$B$9,融资与还本付息!G14,0) -> 1071 | H28: =IF(H$4<=核心参数输入!$B$9,融资与还本付息!H14,0) -> 1170 | I28: =IF(I$4<=核心参数输入!$B$9,融资与还本付息!I14,0) -> 990 | J28: =IF(J$4<=核心参数输入!$B$9,融资与还本付息!J14,0) -> 810 | K28: =IF(K$4<=核心参数输入!$B$9,融资与还本付息!K14,0) -> 630 | ... AH28: =IF(AH$4<=核心参数输入!$B$9,融资与还本付息!AH14,0) -> 0
A29: 本金偿还 | B29: 万元 | D29: =IF(D$4<=核心参数输入!$B$9,融资与还本付息!D13,0) -> 0 | E29: =IF(E$4<=核心参数输入!$B$9,融资与还本付息!E13,0) -> 0 | F29: =IF(F$4<=核心参数输入!$B$9,融资与还本付息!F13,0) -> 0 | G29: =IF(G$4<=核心参数输入!$B$9,融资与还本付息!G13,0) -> 0 | H29: =IF(H$4<=核心参数输入!$B$9,融资与还本付息!H13,0) -> 4285.7143 | I29: =IF(I$4<=核心参数输入!$B$9,融资与还本付息!I13,0) -> 4285.7143 | J29: =IF(J$4<=核心参数输入!$B$9,融资与还本付息!J13,0) -> 4285.7143 | K29: =IF(K$4<=核心参数输入!$B$9,融资与还本付息!K13,0) -> 4285.7143 | ... AH29: =IF(AH$4<=核心参数输入!$B$9,融资与还本付息!AH13,0) -> 0
A30: 所得税口径调整（项目税－融资税） | B30: 万元 | D30: =IF(D$4<=核心参数输入!$B$9,D16-D17,0) -> 0 | E30: =IF(E$4<=核心参数输入!$B$9,E16-E17,0) -> 0 | F30: =IF(F$4<=核心参数输入!$B$9,F16-F17,0) -> 0 | G30: =IF(G$4<=核心参数输入!$B$9,G16-G17,0) -> 0 | H30: =IF(H$4<=核心参数输入!$B$9,H16-H17,0) -> 377.19563 | I30: =IF(I$4<=核心参数输入!$B$9,I16-I17,0) -> 358.18312 | J30: =IF(J$4<=核心参数输入!$B$9,J16-J17,0) -> 287.19563 | K30: =IF(K$4<=核心参数输入!$B$9,K16-K17,0) -> 57.935458 | ... AH30: =IF(AH$4<=核心参数输入!$B$9,AH16-AH17,0) -> 0
A31: 资本金投入前资金净流量 | B31: 万元 | D31: =IF(D$4<=核心参数输入!$B$9,D26+D30+D27-D28-D29,0) -> -8000 | E31: =IF(E$4<=核心参数输入!$B$9,E26+E30+E27-E28-E29,0) -> -7065 | F31: =IF(F$4<=核心参数输入!$B$9,F26+F30+F27-F28-F29,0) -> -9798 | G31: =IF(G$4<=核心参数输入!$B$9,G26+G30+G27-G28-G29,0) -> -7947 | H31: =IF(H$4<=核心参数输入!$B$9,H26+H30+H27-H28-H29,0) -> 6931.6231 | I31: =IF(I$4<=核心参数输入!$B$9,I26+I30+I27-I28-I29,0) -> 12006.932 | J31: =IF(J$4<=核心参数输入!$B$9,J26+J30+J27-J28-J29,0) -> 8246.7601 | K31: =IF(K$4<=核心参数输入!$B$9,K26+K30+K27-K28-K29,0) -> -3929.8625 | ... AH31: =IF(AH$4<=核心参数输入!$B$9,AH26+AH30+AH27-AH28-AH29,0) -> 0
A32: 期末后续支出及偿债留存需求 | B32: 万元 | D32: =IF(D$4<=核心参数输入!$B$9,MAX(0,E32-E31),0) -> 24810 | E32: =IF(E$4<=核心参数输入!$B$9,MAX(0,F32-F31),0) -> 17745 | F32: =IF(F$4<=核心参数输入!$B$9,MAX(0,G32-G31),0) -> 7947 | G32: =IF(G$4<=核心参数输入!$B$9,MAX(0,H32-H31),0) -> 0 | H32: =IF(H$4<=核心参数输入!$B$9,MAX(0,I32-I31),0) -> 0 | I32: =IF(I$4<=核心参数输入!$B$9,MAX(0,J32-J31),0) -> 6278.1162 | J32: =IF(J$4<=核心参数输入!$B$9,MAX(0,K32-K31),0) -> 14524.876 | K32: =IF(K$4<=核心参数输入!$B$9,MAX(0,L32-L31),0) -> 10595.014 | ... AG32: =IF(AG$4<=核心参数输入!$B$9,MAX(0,AH32-AH31),0) -> 0 | AH32: =IF(AH$4<=核心参数输入!$B$9,0,0) -> 0
A33: 理论期初资金余额 | B33: 万元 | D33: =IF(D$4<=核心参数输入!$B$9,0,0) -> 0 | E33: =IF(E$4<=核心参数输入!$B$9,D36,0) -> 0 | F33: =IF(F$4<=核心参数输入!$B$9,E36,0) -> 0 | G33: =IF(G$4<=核心参数输入!$B$9,F36,0) -> 0 | H33: =IF(H$4<=核心参数输入!$B$9,G36,0) -> 0 | I33: =IF(I$4<=核心参数输入!$B$9,H36,0) -> 0 | J33: =IF(J$4<=核心参数输入!$B$9,I36,0) -> 6278.1162 | K33: =IF(K$4<=核心参数输入!$B$9,J36,0) -> 14524.876 | L33: =IF(L$4<=核心参数输入!$B$9,K36,0) -> 10595.014 | ... AH33: =IF(AH$4<=核心参数输入!$B$9,AG36,0) -> 0
A34: 完成计划当年所需资本金 | B34: 万元 | D34: =IF(D$4<=核心参数输入!$B$9,MAX(0,-(D33+D31)),0) -> 8000 | E34: =IF(E$4<=核心参数输入!$B$9,MAX(0,-(E33+E31)),0) -> 7065 | F34: =IF(F$4<=核心参数输入!$B$9,MAX(0,-(F33+F31)),0) -> 9798 | G34: =IF(G$4<=核心参数输入!$B$9,MAX(0,-(G33+G31)),0) -> 7947 | H34: =IF(H$4<=核心参数输入!$B$9,MAX(0,-(H33+H31)),0) -> 0 | I34: =IF(I$4<=核心参数输入!$B$9,MAX(0,-(I33+I31)),0) -> 0 | J34: =IF(J$4<=核心参数输入!$B$9,MAX(0,-(J33+J31)),0) -> 0 | K34: =IF(K$4<=核心参数输入!$B$9,MAX(0,-(K33+K31)),0) -> 0 | ... AH34: =IF(AH$4<=核心参数输入!$B$9,MAX(0,-(AH33+AH31)),0) -> 0
A35: 完整出资可分配现金 | B35: 万元 | D35: =IF(D$4<=核心参数输入!$B$9,MAX(0,D33+D31+D34-D32),0) -> 0 | E35: =IF(E$4<=核心参数输入!$B$9,MAX(0,E33+E31+E34-E32),0) -> 0 | F35: =IF(F$4<=核心参数输入!$B$9,MAX(0,F33+F31+F34-F32),0) -> 0 | G35: =IF(G$4<=核心参数输入!$B$9,MAX(0,G33+G31+G34-G32),0) -> 0 | H35: =IF(H$4<=核心参数输入!$B$9,MAX(0,H33+H31+H34-H32),0) -> 6931.6231 | I35: =IF(I$4<=核心参数输入!$B$9,MAX(0,I33+I31+I34-I32),0) -> 5728.8153 | J35: =IF(J$4<=核心参数输入!$B$9,MAX(0,J33+J31+J34-J32),0) -> 0 | K35: =IF(K$4<=核心参数输入!$B$9,MAX(0,K33+K31+K34-K32),0) -> 0 | ... AH35: =IF(AH$4<=核心参数输入!$B$9,MAX(0,AH33+AH31+AH34-AH32),0) -> 0
A36: 理论期末资金余额 | B36: 万元 | D36: =IF(D$4<=核心参数输入!$B$9,D33+D31+D34-D35,0) -> 0 | E36: =IF(E$4<=核心参数输入!$B$9,E33+E31+E34-E35,0) -> 0 | F36: =IF(F$4<=核心参数输入!$B$9,F33+F31+F34-F35,0) -> 0 | G36: =IF(G$4<=核心参数输入!$B$9,G33+G31+G34-G35,0) -> 0 | H36: =IF(H$4<=核心参数输入!$B$9,H33+H31+H34-H35,0) -> 0 | I36: =IF(I$4<=核心参数输入!$B$9,I33+I31+I34-I35,0) -> 6278.1162 | J36: =IF(J$4<=核心参数输入!$B$9,J33+J31+J34-J35,0) -> 14524.876 | K36: =IF(K$4<=核心参数输入!$B$9,K33+K31+K34-K35,0) -> 10595.014 | ... AH36: =IF(AH$4<=核心参数输入!$B$9,AH33+AH31+AH34-AH35,0) -> 0
A37: 累计所需资本金 | B37: 万元 | D37: =IF(D$4<=核心参数输入!$B$9,0+D34,0) -> 8000 | E37: =IF(E$4<=核心参数输入!$B$9,D37+E34,0) -> 15065 | F37: =IF(F$4<=核心参数输入!$B$9,E37+F34,0) -> 24863 | G37: =IF(G$4<=核心参数输入!$B$9,F37+G34,0) -> 32810 | H37: =IF(H$4<=核心参数输入!$B$9,G37+H34,0) -> 32810 | I37: =IF(I$4<=核心参数输入!$B$9,H37+I34,0) -> 32810 | J37: =IF(J$4<=核心参数输入!$B$9,I37+J34,0) -> 32810 | K37: =IF(K$4<=核心参数输入!$B$9,J37+K34,0) -> 32810 | L37: =IF(L$4<=核心参数输入!$B$9,K37+L34,0) -> 32810 | ... AH37: =IF(AH$4<=核心参数输入!$B$9,AG37+AH34,0) -> 0
A38: 资本金现金流（完整出资理论） | B38: 万元 | D38: =IF(D$4<=核心参数输入!$B$9,D35-D34,0) -> -8000 | E38: =IF(E$4<=核心参数输入!$B$9,E35-E34,0) -> -7065 | F38: =IF(F$4<=核心参数输入!$B$9,F35-F34,0) -> -9798 | G38: =IF(G$4<=核心参数输入!$B$9,G35-G34,0) -> -7947 | H38: =IF(H$4<=核心参数输入!$B$9,H35-H34,0) -> 6931.6231 | I38: =IF(I$4<=核心参数输入!$B$9,I35-I34,0) -> 5728.8153 | J38: =IF(J$4<=核心参数输入!$B$9,J35-J34,0) -> 0 | K38: =IF(K$4<=核心参数输入!$B$9,K35-K34,0) -> 0 | ... AH38: =IF(AH$4<=核心参数输入!$B$9,AH35-AH34,0) -> 0
A39: 额度内期初现金余额 | B39: 万元 | D39: =IF(D$4<=核心参数输入!$B$9,0,0) -> 0 | E39: =IF(E$4<=核心参数输入!$B$9,D44,0) -> 0 | F39: =IF(F$4<=核心参数输入!$B$9,E44,0) -> 0 | G39: =IF(G$4<=核心参数输入!$B$9,F44,0) -> 0 | H39: =IF(H$4<=核心参数输入!$B$9,G44,0) -> 0 | I39: =IF(I$4<=核心参数输入!$B$9,H44,0) -> 0 | J39: =IF(J$4<=核心参数输入!$B$9,I44,0) -> 6278.1162 | K39: =IF(K$4<=核心参数输入!$B$9,J44,0) -> 14524.876 | L39: =IF(L$4<=核心参数输入!$B$9,K44,0) -> 10595.014 | ... AH39: =IF(AH$4<=核心参数输入!$B$9,AG44,0) -> 0
A40: 期初未落实资金缺口 | B40: 万元 | D40: =IF(D$4<=核心参数输入!$B$9,0,0) -> 0 | E40: =IF(E$4<=核心参数输入!$B$9,D45,0) -> 0 | F40: =IF(F$4<=核心参数输入!$B$9,E45,0) -> 0 | G40: =IF(G$4<=核心参数输入!$B$9,F45,0) -> 0 | H40: =IF(H$4<=核心参数输入!$B$9,G45,0) -> 0 | I40: =IF(I$4<=核心参数输入!$B$9,H45,0) -> 0 | J40: =IF(J$4<=核心参数输入!$B$9,I45,0) -> 0 | K40: =IF(K$4<=核心参数输入!$B$9,J45,0) -> 0 | L40: =IF(L$4<=核心参数输入!$B$9,K45,0) -> 0 | ... AH40: =IF(AH$4<=核心参数输入!$B$9,AG45,0) -> 0
A41: 额度内当年资金需要 | B41: 万元 | D41: =IF(D$4<=核心参数输入!$B$9,MAX(0,-(D39+D31-D40)),0) -> 8000 | E41: =IF(E$4<=核心参数输入!$B$9,MAX(0,-(E39+E31-E40)),0) -> 7065 | F41: =IF(F$4<=核心参数输入!$B$9,MAX(0,-(F39+F31-F40)),0) -> 9798 | G41: =IF(G$4<=核心参数输入!$B$9,MAX(0,-(G39+G31-G40)),0) -> 7947 | H41: =IF(H$4<=核心参数输入!$B$9,MAX(0,-(H39+H31-H40)),0) -> 0 | I41: =IF(I$4<=核心参数输入!$B$9,MAX(0,-(I39+I31-I40)),0) -> 0 | J41: =IF(J$4<=核心参数输入!$B$9,MAX(0,-(J39+J31-J40)),0) -> 0 | K41: =IF(K$4<=核心参数输入!$B$9,MAX(0,-(K39+K31-K40)),0) -> 0 | ... AH41: =IF(AH$4<=核心参数输入!$B$9,MAX(0,-(AH39+AH31-AH40)),0) -> 0
A42: 额度内当年实际可投资本金 | B42: 万元 | D42: =IF(D$4<=核心参数输入!$B$9,MIN(D41,MAX(0,核心参数输入!$B$61-0)),0) -> 8000 | E42: =IF(E$4<=核心参数输入!$B$9,MIN(E41,MAX(0,核心参数输入!$B$61-D47)),0) -> 7065 | F42: =IF(F$4<=核心参数输入!$B$9,MIN(F41,MAX(0,核心参数输入!$B$61-E47)),0) -> 9798 | G42: =IF(G$4<=核心参数输入!$B$9,MIN(G41,MAX(0,核心参数输入!$B$61-F47)),0) -> 7947 | H42: =IF(H$4<=核心参数输入!$B$9,MIN(H41,MAX(0,核心参数输入!$B$61-G47)),0) -> 0 | I42: =IF(I$4<=核心参数输入!$B$9,MIN(I41,MAX(0,核心参数输入!$B$61-H47)),0) -> 0 | J42: =IF(J$4<=核心参数输入!$B$9,MIN(J41,MAX(0,核心参数输入!$B$61-I47)),0) -> 0 | K42: =IF(K$4<=核心参数输入!$B$9,MIN(K41,MAX(0,核心参数输入!$B$61-J47)),0) -> 0 | L42: =IF(L$4<=核心参数输入!$B$9,MIN(L41,MAX(0,核心参数输入!$B$61-K47)),0) -> 0 | ... AH42: =IF(AH$4<=核心参数输入!$B$9,MIN(AH41,MAX(0,核心参数输入!$B$61-AG47)),0) -> 0
A43: 额度约束下可分配现金 | B43: 万元 | D43: =IF(D$4<=核心参数输入!$B$9,IF(D46>0.01,0,MAX(0,D39+D31-D40+D42-D32)),0) -> 0 | E43: =IF(E$4<=核心参数输入!$B$9,IF(E46>0.01,0,MAX(0,E39+E31-E40+E42-E32)),0) -> 0 | F43: =IF(F$4<=核心参数输入!$B$9,IF(F46>0.01,0,MAX(0,F39+F31-F40+F42-F32)),0) -> 0 | G43: =IF(G$4<=核心参数输入!$B$9,IF(G46>0.01,0,MAX(0,G39+G31-G40+G42-G32)),0) -> 0 | H43: =IF(H$4<=核心参数输入!$B$9,IF(H46>0.01,0,MAX(0,H39+H31-H40+H42-H32)),0) -> 6931.6231 | I43: =IF(I$4<=核心参数输入!$B$9,IF(I46>0.01,0,MAX(0,I39+I31-I40+I42-I32)),0) -> 5728.8153 | J43: =IF(J$4<=核心参数输入!$B$9,IF(J46>0.01,0,MAX(0,J39+J31-J40+J42-J32)),0) -> 0 | K43: =IF(K$4<=核心参数输入!$B$9,IF(K46>0.01,0,MAX(0,K39+K31-K40+K42-K32)),0) -> 0 | ... AH43: =IF(AH$4<=核心参数输入!$B$9,IF(AH46>0.01,0,MAX(0,AH39+AH31-AH40+AH42-AH32)),0) -> 0
A44: 额度内期末可用现金余额 | B44: 万元 | D44: =IF(D$4<=核心参数输入!$B$9,MAX(0,D39+D31-D40+D42)-D43,0) -> 0 | E44: =IF(E$4<=核心参数输入!$B$9,MAX(0,E39+E31-E40+E42)-E43,0) -> 0 | F44: =IF(F$4<=核心参数输入!$B$9,MAX(0,F39+F31-F40+F42)-F43,0) -> 0 | G44: =IF(G$4<=核心参数输入!$B$9,MAX(0,G39+G31-G40+G42)-G43,0) -> 0 | H44: =IF(H$4<=核心参数输入!$B$9,MAX(0,H39+H31-H40+H42)-H43,0) -> 0 | I44: =IF(I$4<=核心参数输入!$B$9,MAX(0,I39+I31-I40+I42)-I43,0) -> 6278.1162 | J44: =IF(J$4<=核心参数输入!$B$9,MAX(0,J39+J31-J40+J42)-J43,0) -> 14524.876 | K44: =IF(K$4<=核心参数输入!$B$9,MAX(0,K39+K31-K40+K42)-K43,0) -> 10595.014 | ... AH44: =IF(AH$4<=核心参数输入!$B$9,MAX(0,AH39+AH31-AH40+AH42)-AH43,0) -> 0
A45: 期末未落实资金缺口 | B45: 万元 | D45: =IF(D$4<=核心参数输入!$B$9,MAX(0,-(D39+D31-D40+D42)),0) -> 0 | E45: =IF(E$4<=核心参数输入!$B$9,MAX(0,-(E39+E31-E40+E42)),0) -> 0 | F45: =IF(F$4<=核心参数输入!$B$9,MAX(0,-(F39+F31-F40+F42)),0) -> 0 | G45: =IF(G$4<=核心参数输入!$B$9,MAX(0,-(G39+G31-G40+G42)),0) -> 0 | H45: =IF(H$4<=核心参数输入!$B$9,MAX(0,-(H39+H31-H40+H42)),0) -> 0 | I45: =IF(I$4<=核心参数输入!$B$9,MAX(0,-(I39+I31-I40+I42)),0) -> 0 | J45: =IF(J$4<=核心参数输入!$B$9,MAX(0,-(J39+J31-J40+J42)),0) -> 0 | K45: =IF(K$4<=核心参数输入!$B$9,MAX(0,-(K39+K31-K40+K42)),0) -> 0 | ... AH45: =IF(AH$4<=核心参数输入!$B$9,MAX(0,-(AH39+AH31-AH40+AH42)),0) -> 0
A46: 至当年最大未落实缺口 | B46: 万元 | D46: =IF(D$4<=核心参数输入!$B$9,MAX(0,D45),0) -> 0 | E46: =IF(E$4<=核心参数输入!$B$9,MAX(D46,E45),0) -> 0 | F46: =IF(F$4<=核心参数输入!$B$9,MAX(E46,F45),0) -> 0 | G46: =IF(G$4<=核心参数输入!$B$9,MAX(F46,G45),0) -> 0 | H46: =IF(H$4<=核心参数输入!$B$9,MAX(G46,H45),0) -> 0 | I46: =IF(I$4<=核心参数输入!$B$9,MAX(H46,I45),0) -> 0 | J46: =IF(J$4<=核心参数输入!$B$9,MAX(I46,J45),0) -> 0 | K46: =IF(K$4<=核心参数输入!$B$9,MAX(J46,K45),0) -> 0 | L46: =IF(L$4<=核心参数输入!$B$9,MAX(K46,L45),0) -> 0 | ... AH46: =IF(AH$4<=核心参数输入!$B$9,MAX(AG46,AH45),0) -> 0
A47: 累计额度内可投资本金 | B47: 万元 | D47: =IF(D$4<=核心参数输入!$B$9,0+D42,0) -> 8000 | E47: =IF(E$4<=核心参数输入!$B$9,D47+E42,0) -> 15065 | F47: =IF(F$4<=核心参数输入!$B$9,E47+F42,0) -> 24863 | G47: =IF(G$4<=核心参数输入!$B$9,F47+G42,0) -> 32810 | H47: =IF(H$4<=核心参数输入!$B$9,G47+H42,0) -> 32810 | I47: =IF(I$4<=核心参数输入!$B$9,H47+I42,0) -> 32810 | J47: =IF(J$4<=核心参数输入!$B$9,I47+J42,0) -> 32810 | K47: =IF(K$4<=核心参数输入!$B$9,J47+K42,0) -> 32810 | L47: =IF(L$4<=核心参数输入!$B$9,K47+L42,0) -> 32810 | ... AH47: =IF(AH$4<=核心参数输入!$B$9,AG47+AH42,0) -> 0
A48: 额度内资本金现金流 | B48: 万元 | D48: =IF(D$4<=核心参数输入!$B$9,D43-D42,0) -> -8000 | E48: =IF(E$4<=核心参数输入!$B$9,E43-E42,0) -> -7065 | F48: =IF(F$4<=核心参数输入!$B$9,F43-F42,0) -> -9798 | G48: =IF(G$4<=核心参数输入!$B$9,G43-G42,0) -> -7947 | H48: =IF(H$4<=核心参数输入!$B$9,H43-H42,0) -> 6931.6231 | I48: =IF(I$4<=核心参数输入!$B$9,I43-I42,0) -> 5728.8153 | J48: =IF(J$4<=核心参数输入!$B$9,J43-J42,0) -> 0 | K48: =IF(K$4<=核心参数输入!$B$9,K43-K42,0) -> 0 | ... AH48: =IF(AH$4<=核心参数输入!$B$9,AH43-AH42,0) -> 0
A49: 累计项目现金流 | B49: 万元 | D49: =IF(D$4<=核心参数输入!$B$9,0+D26,0) -> -8000 | E49: =IF(E$4<=核心参数输入!$B$9,D49+E26,0) -> -23876 | F49: =IF(F$4<=核心参数输入!$B$9,E49+F26,0) -> -45044 | G49: =IF(G$4<=核心参数输入!$B$9,F49+G26,0) -> -60920 | H49: =IF(H$4<=核心参数输入!$B$9,G49+H26,0) -> -48909.858 | I49: =IF(I$4<=核心参数输入!$B$9,H49+I26,0) -> -31985.396 | J49: =IF(J$4<=核心参数输入!$B$9,I49+J26,0) -> -18930.117 | K49: =IF(K$4<=核心参数输入!$B$9,J49+K26,0) -> -18002.2 | L49: =IF(L$4<=核心参数输入!$B$9,K49+L26,0) -> -17046.449 | ... AH49: =IF(AH$4<=核心参数输入!$B$9,AG49+AH26,0) -> 0
A50: 当年项目折现现金流 | B50: 万元 | D50: =IF(D$4<=核心参数输入!$B$9,D26/(1+核心参数输入!$B$71)^D$4,0) -> -8000 | E50: =IF(E$4<=核心参数输入!$B$9,E26/(1+核心参数输入!$B$71)^E$4,0) -> -14700 | F50: =IF(F$4<=核心参数输入!$B$9,F26/(1+核心参数输入!$B$71)^F$4,0) -> -18148.148 | G50: =IF(G$4<=核心参数输入!$B$9,G26/(1+核心参数输入!$B$71)^G$4,0) -> -12602.881 | H50: =IF(H$4<=核心参数输入!$B$9,H26/(1+核心参数输入!$B$71)^H$4,0) -> 8827.8127 | I50: =IF(I$4<=核心参数输入!$B$9,I26/(1+核心参数输入!$B$71)^I$4,0) -> 11518.505 | J50: =IF(J$4<=核心参数输入!$B$9,J26/(1+核心参数输入!$B$71)^J$4,0) -> 8227.0401 | K50: =IF(K$4<=核心参数输入!$B$9,K26/(1+核心参数输入!$B$71)^K$4,0) -> 541.43029 | ... AH50: =IF(AH$4<=核心参数输入!$B$9,AH26/(1+核心参数输入!$B$71)^AH$4,0) -> 0
A51: 累计项目折现现金流 | B51: 万元 | D51: =IF(D$4<=核心参数输入!$B$9,0+D50,0) -> -8000 | E51: =IF(E$4<=核心参数输入!$B$9,D51+E50,0) -> -22700 | F51: =IF(F$4<=核心参数输入!$B$9,E51+F50,0) -> -40848.148 | G51: =IF(G$4<=核心参数输入!$B$9,F51+G50,0) -> -53451.029 | H51: =IF(H$4<=核心参数输入!$B$9,G51+H50,0) -> -44623.216 | I51: =IF(I$4<=核心参数输入!$B$9,H51+I50,0) -> -33104.711 | J51: =IF(J$4<=核心参数输入!$B$9,I51+J50,0) -> -24877.671 | K51: =IF(K$4<=核心参数输入!$B$9,J51+K50,0) -> -24336.241 | L51: =IF(L$4<=核心参数输入!$B$9,K51+L50,0) -> -23819.878 | ... AH51: =IF(AH$4<=核心参数输入!$B$9,AG51+AH50,0) -> 0
A52: 当年运营偿债覆盖倍数 | B52: 倍 | D52: =IF(D$4<=核心参数输入!$B$9,IF(AND(D$4>核心参数输入!$B$16,融资与还本付息!D18>0.000001),D19/融资与还本付息!D18,""),"") | E52: =IF(E$4<=核心参数输入!$B$9,IF(AND(E$4>核心参数输入!$B$16,融资与还本付息!E18>0.000001),E19/融资与还本付息!E18,""),"") | F52: =IF(F$4<=核心参数输入!$B$9,IF(AND(F$4>核心参数输入!$B$16,融资与还本付息!F18>0.000001),F19/融资与还本付息!F18,""),"") | G52: =IF(G$4<=核心参数输入!$B$9,IF(AND(G$4>核心参数输入!$B$16,融资与还本付息!G18>0.000001),G19/融资与还本付息!G18,""),"") | H52: =IF(H$4<=核心参数输入!$B$9,IF(AND(H$4>核心参数输入!$B$16,融资与还本付息!H18>0.000001),H19/融资与还本付息!H18,""),"") -> 2.3621723 | I52: =IF(I$4<=核心参数输入!$B$9,IF(AND(I$4>核心参数输入!$B$16,融资与还本付息!I18>0.000001),I19/融资与还本付息!I18,""),"") -> 3.2758874 | J52: =IF(J$4<=核心参数输入!$B$9,IF(AND(J$4>核心参数输入!$B$16,融资与还本付息!J18>0.000001),J19/融资与还本付息!J18,""),"") -> 2.6183718 | K52: =IF(K$4<=核心参数输入!$B$9,IF(AND(K$4>核心参数输入!$B$16,融资与还本付息!K18>0.000001),K19/融资与还本付息!K18,""),"") -> 0.20055108 | ... AH52: =IF(AH$4<=核心参数输入!$B$9,IF(AND(AH$4>核心参数输入!$B$16,融资与还本付息!AH18>0.000001),AH19/融资与还本付息!AH18,""),"")
A53: 最低DSCR筛选值（非偿债年忽略） | B53: 倍 | D53: =IF(D$4<=核心参数输入!$B$9,IF(ISNUMBER(D52),D52,1E+99),1E+99) -> 1e+99 | E53: =IF(E$4<=核心参数输入!$B$9,IF(ISNUMBER(E52),E52,1E+99),1E+99) -> 1e+99 | F53: =IF(F$4<=核心参数输入!$B$9,IF(ISNUMBER(F52),F52,1E+99),1E+99) -> 1e+99 | G53: =IF(G$4<=核心参数输入!$B$9,IF(ISNUMBER(G52),G52,1E+99),1E+99) -> 1e+99 | H53: =IF(H$4<=核心参数输入!$B$9,IF(ISNUMBER(H52),H52,1E+99),1E+99) -> 2.3621723 | I53: =IF(I$4<=核心参数输入!$B$9,IF(ISNUMBER(I52),I52,1E+99),1E+99) -> 3.2758874 | J53: =IF(J$4<=核心参数输入!$B$9,IF(ISNUMBER(J52),J52,1E+99),1E+99) -> 2.6183718 | K53: =IF(K$4<=核心参数输入!$B$9,IF(ISNUMBER(K52),K52,1E+99),1E+99) -> 0.20055108 | ... AH53: =IF(AH$4<=核心参数输入!$B$9,IF(ISNUMBER(AH52),AH52,1E+99),1E+99) -> 1e+99
A54: 静态回收首次跨零标记 | B54: 标记 | D54: =IF(D$4<=核心参数输入!$B$9,IF(AND(D$4>0,0<0,D49>=0),1,0),0) -> 0 | E54: =IF(E$4<=核心参数输入!$B$9,IF(AND(E$4>0,D49<0,E49>=0),1,0),0) -> 0 | F54: =IF(F$4<=核心参数输入!$B$9,IF(AND(F$4>0,E49<0,F49>=0),1,0),0) -> 0 | G54: =IF(G$4<=核心参数输入!$B$9,IF(AND(G$4>0,F49<0,G49>=0),1,0),0) -> 0 | H54: =IF(H$4<=核心参数输入!$B$9,IF(AND(H$4>0,G49<0,H49>=0),1,0),0) -> 0 | I54: =IF(I$4<=核心参数输入!$B$9,IF(AND(I$4>0,H49<0,I49>=0),1,0),0) -> 0 | J54: =IF(J$4<=核心参数输入!$B$9,IF(AND(J$4>0,I49<0,J49>=0),1,0),0) -> 0 | K54: =IF(K$4<=核心参数输入!$B$9,IF(AND(K$4>0,J49<0,K49>=0),1,0),0) -> 0 | L54: =IF(L$4<=核心参数输入!$B$9,IF(AND(L$4>0,K49<0,L49>=0),1,0),0) -> 0 | ... AH54: =IF(AH$4<=核心参数输入!$B$9,IF(AND(AH$4>0,AG49<0,AH49>=0),1,0),0) -> 0
A55: 动态回收首次跨零标记 | B55: 标记 | D55: =IF(D$4<=核心参数输入!$B$9,IF(AND(D$4>0,0<0,D51>=0),1,0),0) -> 0 | E55: =IF(E$4<=核心参数输入!$B$9,IF(AND(E$4>0,D51<0,E51>=0),1,0),0) -> 0 | F55: =IF(F$4<=核心参数输入!$B$9,IF(AND(F$4>0,E51<0,F51>=0),1,0),0) -> 0 | G55: =IF(G$4<=核心参数输入!$B$9,IF(AND(G$4>0,F51<0,G51>=0),1,0),0) -> 0 | H55: =IF(H$4<=核心参数输入!$B$9,IF(AND(H$4>0,G51<0,H51>=0),1,0),0) -> 0 | I55: =IF(I$4<=核心参数输入!$B$9,IF(AND(I$4>0,H51<0,I51>=0),1,0),0) -> 0 | J55: =IF(J$4<=核心参数输入!$B$9,IF(AND(J$4>0,I51<0,J51>=0),1,0),0) -> 0 | K55: =IF(K$4<=核心参数输入!$B$9,IF(AND(K$4>0,J51<0,K51>=0),1,0),0) -> 0 | L55: =IF(L$4<=核心参数输入!$B$9,IF(AND(L$4>0,K51<0,L51>=0),1,0),0) -> 0 | ... AH55: =IF(AH$4<=核心参数输入!$B$9,IF(AND(AH$4>0,AG51<0,AH51>=0),1,0),0) -> 0
A56: 项目现金流符号 | B56: 标记 | D56: =IF(D$4<=核心参数输入!$B$9,IF(ABS(D26)<=0.000001,0,SIGN(D26)),0) -> -1 | E56: =IF(E$4<=核心参数输入!$B$9,IF(ABS(E26)<=0.000001,0,SIGN(E26)),0) -> -1 | F56: =IF(F$4<=核心参数输入!$B$9,IF(ABS(F26)<=0.000001,0,SIGN(F26)),0) -> -1 | G56: =IF(G$4<=核心参数输入!$B$9,IF(ABS(G26)<=0.000001,0,SIGN(G26)),0) -> -1 | H56: =IF(H$4<=核心参数输入!$B$9,IF(ABS(H26)<=0.000001,0,SIGN(H26)),0) -> 1 | I56: =IF(I$4<=核心参数输入!$B$9,IF(ABS(I26)<=0.000001,0,SIGN(I26)),0) -> 1 | J56: =IF(J$4<=核心参数输入!$B$9,IF(ABS(J26)<=0.000001,0,SIGN(J26)),0) -> 1 | K56: =IF(K$4<=核心参数输入!$B$9,IF(ABS(K26)<=0.000001,0,SIGN(K26)),0) -> 1 | ... AH56: =IF(AH$4<=核心参数输入!$B$9,IF(ABS(AH26)<=0.000001,0,SIGN(AH26)),0) -> 0
A57: 项目最近非零符号 | B57: 标记 | D57: =IF(D$4<=核心参数输入!$B$9,IF(D56=0,0,D56),0) -> -1 | E57: =IF(E$4<=核心参数输入!$B$9,IF(E56=0,D57,E56),0) -> -1 | F57: =IF(F$4<=核心参数输入!$B$9,IF(F56=0,E57,F56),0) -> -1 | G57: =IF(G$4<=核心参数输入!$B$9,IF(G56=0,F57,G56),0) -> -1 | H57: =IF(H$4<=核心参数输入!$B$9,IF(H56=0,G57,H56),0) -> 1 | I57: =IF(I$4<=核心参数输入!$B$9,IF(I56=0,H57,I56),0) -> 1 | J57: =IF(J$4<=核心参数输入!$B$9,IF(J56=0,I57,J56),0) -> 1 | K57: =IF(K$4<=核心参数输入!$B$9,IF(K56=0,J57,K56),0) -> 1 | L57: =IF(L$4<=核心参数输入!$B$9,IF(L56=0,K57,L56),0) -> 1 | ... AH57: =IF(AH$4<=核心参数输入!$B$9,IF(AH56=0,AG57,AH56),0) -> 0
A58: 项目现金流变号标记 | B58: 标记 | D58: =IF(D$4<=核心参数输入!$B$9,IF(AND(D56<>0,0<>0,D56<>0),1,0),0) -> 0 | E58: =IF(E$4<=核心参数输入!$B$9,IF(AND(E56<>0,D57<>0,E56<>D57),1,0),0) -> 0 | F58: =IF(F$4<=核心参数输入!$B$9,IF(AND(F56<>0,E57<>0,F56<>E57),1,0),0) -> 0 | G58: =IF(G$4<=核心参数输入!$B$9,IF(AND(G56<>0,F57<>0,G56<>F57),1,0),0) -> 0 | H58: =IF(H$4<=核心参数输入!$B$9,IF(AND(H56<>0,G57<>0,H56<>G57),1,0),0) -> 1 | I58: =IF(I$4<=核心参数输入!$B$9,IF(AND(I56<>0,H57<>0,I56<>H57),1,0),0) -> 0 | J58: =IF(J$4<=核心参数输入!$B$9,IF(AND(J56<>0,I57<>0,J56<>I57),1,0),0) -> 0 | K58: =IF(K$4<=核心参数输入!$B$9,IF(AND(K56<>0,J57<>0,K56<>J57),1,0),0) -> 0 | L58: =IF(L$4<=核心参数输入!$B$9,IF(AND(L56<>0,K57<>0,L56<>K57),1,0),0) -> 0 | ... AH58: =IF(AH$4<=核心参数输入!$B$9,IF(AND(AH56<>0,AG57<>0,AH56<>AG57),1,0),0) -> 0
A59: 理论资金平衡差额 | B59: 万元 | D59: =IF(D$4<=核心参数输入!$B$9,D33+D31+D34-D35-D36,0) -> 0 | E59: =IF(E$4<=核心参数输入!$B$9,E33+E31+E34-E35-E36,0) -> 0 | F59: =IF(F$4<=核心参数输入!$B$9,F33+F31+F34-F35-F36,0) -> 0 | G59: =IF(G$4<=核心参数输入!$B$9,G33+G31+G34-G35-G36,0) -> 0 | H59: =IF(H$4<=核心参数输入!$B$9,H33+H31+H34-H35-H36,0) -> 0 | I59: =IF(I$4<=核心参数输入!$B$9,I33+I31+I34-I35-I36,0) -> 0 | J59: =IF(J$4<=核心参数输入!$B$9,J33+J31+J34-J35-J36,0) -> 0 | K59: =IF(K$4<=核心参数输入!$B$9,K33+K31+K34-K35-K36,0) -> 0 | ... AH59: =IF(AH$4<=核心参数输入!$B$9,AH33+AH31+AH34-AH35-AH36,0) -> 0
A60: 额度内资金平衡差额 | B60: 万元 | D60: =IF(D$4<=核心参数输入!$B$9,D39-D40+D31+D42-D43-D44+D45,0) -> 0 | E60: =IF(E$4<=核心参数输入!$B$9,E39-E40+E31+E42-E43-E44+E45,0) -> 0 | F60: =IF(F$4<=核心参数输入!$B$9,F39-F40+F31+F42-F43-F44+F45,0) -> 0 | G60: =IF(G$4<=核心参数输入!$B$9,G39-G40+G31+G42-G43-G44+G45,0) -> 0 | H60: =IF(H$4<=核心参数输入!$B$9,H39-H40+H31+H42-H43-H44+H45,0) -> 0 | I60: =IF(I$4<=核心参数输入!$B$9,I39-I40+I31+I42-I43-I44+I45,0) -> 0 | J60: =IF(J$4<=核心参数输入!$B$9,J39-J40+J31+J42-J43-J44+J45,0) -> 0 | K60: =IF(K$4<=核心参数输入!$B$9,K39-K40+K31+K42-K43-K44+K45,0) -> 0 | ... AH60: =IF(AH$4<=核心参数输入!$B$9,AH39-AH40+AH31+AH42-AH43-AH44+AH45,0) -> 0
A61: 分配后未来追加资本金校验 | B61: 万元 | D61: =IF(D$4<=核心参数输入!$B$9,IF(D35>0.01,SUM(E34:$AH34),0),0) -> 0 | E61: =IF(E$4<=核心参数输入!$B$9,IF(E35>0.01,SUM(F34:$AH34),0),0) -> 0 | F61: =IF(F$4<=核心参数输入!$B$9,IF(F35>0.01,SUM(G34:$AH34),0),0) -> 0 | G61: =IF(G$4<=核心参数输入!$B$9,IF(G35>0.01,SUM(H34:$AH34),0),0) -> 0 | H61: =IF(H$4<=核心参数输入!$B$9,IF(H35>0.01,SUM(I34:$AH34),0),0) -> 9.094947e-13 | I61: =IF(I$4<=核心参数输入!$B$9,IF(I35>0.01,SUM(J34:$AH34),0),0) -> 9.094947e-13 | J61: =IF(J$4<=核心参数输入!$B$9,IF(J35>0.01,SUM(K34:$AH34),0),0) -> 0 | K61: =IF(K$4<=核心参数输入!$B$9,IF(K35>0.01,SUM(L34:$AH34),0),0) -> 0 | ... AG61: =IF(AG$4<=核心参数输入!$B$9,IF(AG35>0.01,SUM(AH34:$AH34),0),0) -> 0 | AH61: =IF(AH$4<=核心参数输入!$B$9,0,0) -> 0
A62: 资本金现金流符号 | B62: 标记 | D62: =IF(D$4<=核心参数输入!$B$9,IF(ABS(D38)<=0.000001,0,SIGN(D38)),0) -> -1 | E62: =IF(E$4<=核心参数输入!$B$9,IF(ABS(E38)<=0.000001,0,SIGN(E38)),0) -> -1 | F62: =IF(F$4<=核心参数输入!$B$9,IF(ABS(F38)<=0.000001,0,SIGN(F38)),0) -> -1 | G62: =IF(G$4<=核心参数输入!$B$9,IF(ABS(G38)<=0.000001,0,SIGN(G38)),0) -> -1 | H62: =IF(H$4<=核心参数输入!$B$9,IF(ABS(H38)<=0.000001,0,SIGN(H38)),0) -> 1 | I62: =IF(I$4<=核心参数输入!$B$9,IF(ABS(I38)<=0.000001,0,SIGN(I38)),0) -> 1 | J62: =IF(J$4<=核心参数输入!$B$9,IF(ABS(J38)<=0.000001,0,SIGN(J38)),0) -> 0 | K62: =IF(K$4<=核心参数输入!$B$9,IF(ABS(K38)<=0.000001,0,SIGN(K38)),0) -> 0 | ... AH62: =IF(AH$4<=核心参数输入!$B$9,IF(ABS(AH38)<=0.000001,0,SIGN(AH38)),0) -> 0
A63: 资本金最近非零符号 | B63: 标记 | D63: =IF(D$4<=核心参数输入!$B$9,IF(D62=0,0,D62),0) -> -1 | E63: =IF(E$4<=核心参数输入!$B$9,IF(E62=0,D63,E62),0) -> -1 | F63: =IF(F$4<=核心参数输入!$B$9,IF(F62=0,E63,F62),0) -> -1 | G63: =IF(G$4<=核心参数输入!$B$9,IF(G62=0,F63,G62),0) -> -1 | H63: =IF(H$4<=核心参数输入!$B$9,IF(H62=0,G63,H62),0) -> 1 | I63: =IF(I$4<=核心参数输入!$B$9,IF(I62=0,H63,I62),0) -> 1 | J63: =IF(J$4<=核心参数输入!$B$9,IF(J62=0,I63,J62),0) -> 1 | K63: =IF(K$4<=核心参数输入!$B$9,IF(K62=0,J63,K62),0) -> 1 | L63: =IF(L$4<=核心参数输入!$B$9,IF(L62=0,K63,L62),0) -> 1 | ... AH63: =IF(AH$4<=核心参数输入!$B$9,IF(AH62=0,AG63,AH62),0) -> 0
A64: 资本金现金流变号标记 | B64: 标记 | D64: =IF(D$4<=核心参数输入!$B$9,IF(AND(D62<>0,0<>0,D62<>0),1,0),0) -> 0 | E64: =IF(E$4<=核心参数输入!$B$9,IF(AND(E62<>0,D63<>0,E62<>D63),1,0),0) -> 0 | F64: =IF(F$4<=核心参数输入!$B$9,IF(AND(F62<>0,E63<>0,F62<>E63),1,0),0) -> 0 | G64: =IF(G$4<=核心参数输入!$B$9,IF(AND(G62<>0,F63<>0,G62<>F63),1,0),0) -> 0 | H64: =IF(H$4<=核心参数输入!$B$9,IF(AND(H62<>0,G63<>0,H62<>G63),1,0),0) -> 1 | I64: =IF(I$4<=核心参数输入!$B$9,IF(AND(I62<>0,H63<>0,I62<>H63),1,0),0) -> 0 | J64: =IF(J$4<=核心参数输入!$B$9,IF(AND(J62<>0,I63<>0,J62<>I63),1,0),0) -> 0 | K64: =IF(K$4<=核心参数输入!$B$9,IF(AND(K62<>0,J63<>0,K62<>J63),1,0),0) -> 0 | L64: =IF(L$4<=核心参数输入!$B$9,IF(AND(L62<>0,K63<>0,L62<>K63),1,0),0) -> 0 | ... AH64: =IF(AH$4<=核心参数输入!$B$9,IF(AND(AH62<>0,AG63<>0,AH62<>AG63),1,0),0) -> 0
A65: 销售净回款贡献（所得税前） | B65: 万元 | D65: =IF(D$4<=核心参数输入!$B$9,销售与出租收入!D13-运营成本与税费!D10-运营成本与税费!D11,0) -> 0 | E65: =IF(E$4<=核心参数输入!$B$9,销售与出租收入!E13-运营成本与税费!E10-运营成本与税费!E11,0) -> 0 | F65: =IF(F$4<=核心参数输入!$B$9,销售与出租收入!F13-运营成本与税费!F10-运营成本与税费!F11,0) -> 0 | G65: =IF(G$4<=核心参数输入!$B$9,销售与出租收入!G13-运营成本与税费!G10-运营成本与税费!G11,0) -> 0 | H65: =IF(H$4<=核心参数输入!$B$9,销售与出租收入!H13-运营成本与税费!H10-运营成本与税费!H11,0) -> 12958.481 | I65: =IF(I$4<=核心参数输入!$B$9,销售与出租收入!I13-运营成本与税费!I10-运营成本与税费!I11,0) -> 17277.975 | J65: =IF(J$4<=核心参数输入!$B$9,销售与出租收入!J13-运营成本与税费!J10-运营成本与税费!J11,0) -> 12958.481 | K65: =IF(K$4<=核心参数输入!$B$9,销售与出租收入!K13-运营成本与税费!K10-运营成本与税费!K11,0) -> 0 | ... AH65: =IF(AH$4<=核心参数输入!$B$9,销售与出租收入!AH13-运营成本与税费!AH10-运营成本与税费!AH11,0) -> 0
A66: 持有净经营现金贡献（所得税前） | B66: 万元 | D66: =IF(D$4<=核心参数输入!$B$9,销售与出租收入!D22-运营成本与税费!D12-运营成本与税费!D13-运营成本与税费!D14-运营成本与税费!D15,0) -> 0 | E66: =IF(E$4<=核心参数输入!$B$9,销售与出租收入!E22-运营成本与税费!E12-运营成本与税费!E13-运营成本与税费!E14-运营成本与税费!E15,0) -> 0 | F66: =IF(F$4<=核心参数输入!$B$9,销售与出租收入!F22-运营成本与税费!F12-运营成本与税费!F13-运营成本与税费!F14-运营成本与税费!F15,0) -> 0 | G66: =IF(G$4<=核心参数输入!$B$9,销售与出租收入!G22-运营成本与税费!G12-运营成本与税费!G13-运营成本与税费!G14-运营成本与税费!G15,0) -> 0 | H66: =IF(H$4<=核心参数输入!$B$9,销售与出租收入!H22-运营成本与税费!H12-运营成本与税费!H13-运营成本与税费!H14-运营成本与税费!H15,0) -> 119.73773 | I66: =IF(I$4<=核心参数输入!$B$9,销售与出租收入!I22-运营成本与税费!I12-运营成本与税费!I13-运营成本与税费!I14-运营成本与税费!I15,0) -> 569.13858 | J66: =IF(J$4<=核心参数输入!$B$9,销售与出租收入!J22-运营成本与税费!J12-运营成本与税费!J13-运营成本与税费!J14-运营成本与税费!J15,0) -> 846.58707 | K66: =IF(K$4<=核心参数输入!$B$9,销售与出租收入!K22-运营成本与税费!K12-运营成本与税费!K13-运营成本与税费!K14-运营成本与税费!K15,0) -> 985.85183 | ... AH66: =IF(AH$4<=核心参数输入!$B$9,销售与出租收入!AH22-运营成本与税费!AH12-运营成本与税费!AH13-运营成本与税费!AH14-运营成本与税费!AH15,0) -> 0
A87: 组合压力情景 · 全链条重算
A90: 营业收入（销售＋持有） | B90: 万元 | D90: =IF(D$4<=核心参数输入!$B$9,销售与出租收入!D103,0) -> 0 | E90: =IF(E$4<=核心参数输入!$B$9,销售与出租收入!E103,0) -> 0 | F90: =IF(F$4<=核心参数输入!$B$9,销售与出租收入!F103,0) -> 0 | G90: =IF(G$4<=核心参数输入!$B$9,销售与出租收入!G103,0) -> 0 | H90: =IF(H$4<=核心参数输入!$B$9,销售与出租收入!H103,0) -> 13557.474 | I90: =IF(I$4<=核心参数输入!$B$9,销售与出租收入!I103,0) -> 18354.413 | J90: =IF(J$4<=核心参数输入!$B$9,销售与出租收入!J103,0) -> 14319.349 | K90: =IF(K$4<=核心参数输入!$B$9,销售与出租收入!K103,0) -> 1445.4646 | ... AH90: =IF(AH$4<=核心参数输入!$B$9,销售与出租收入!AH103,0) -> 0
A91: 现金成本及经营税费 | B91: 万元 | D91: =IF(D$4<=核心参数输入!$B$9,运营成本与税费!D96,0) -> 0 | E91: =IF(E$4<=核心参数输入!$B$9,运营成本与税费!E96,0) -> 0 | F91: =IF(F$4<=核心参数输入!$B$9,运营成本与税费!F96,0) -> 0 | G91: =IF(G$4<=核心参数输入!$B$9,运营成本与税费!G96,0) -> 0 | H91: =IF(H$4<=核心参数输入!$B$9,运营成本与税费!H96,0) -> 1943.0297 | I91: =IF(I$4<=核心参数输入!$B$9,运营成本与税费!I96,0) -> 2486.7068 | J91: =IF(J$4<=核心参数输入!$B$9,运营成本与税费!J96,0) -> 2092.2872 | K91: =IF(K$4<=核心参数输入!$B$9,运营成本与税费!K96,0) -> 758.54602 | ... AH91: =IF(AH$4<=核心参数输入!$B$9,运营成本与税费!AH96,0) -> 0
A92: 无融资经营利润EBIT | B92: 万元 | D92: =IF(D$4<=核心参数输入!$B$9,D90-D91-运营成本与税费!D97-运营成本与税费!D99,0) -> 0 | E92: =IF(E$4<=核心参数输入!$B$9,E90-E91-运营成本与税费!E97-运营成本与税费!E99,0) -> 0 | F92: =IF(F$4<=核心参数输入!$B$9,F90-F91-运营成本与税费!F97-运营成本与税费!F99,0) -> 0 | G92: =IF(G$4<=核心参数输入!$B$9,G90-G91-运营成本与税费!G97-运营成本与税费!G99,0) -> 0 | H92: =IF(H$4<=核心参数输入!$B$9,H90-H91-运营成本与税费!H97-运营成本与税费!H99,0) -> -140.05671 | I92: =IF(I$4<=核心参数输入!$B$9,I90-I91-运营成本与税费!I97-运营成本与税费!I99,0) -> 471.54511 | J92: =IF(J$4<=核心参数输入!$B$9,J90-J91-运营成本与税费!J97-运营成本与税费!J99,0) -> 472.56094 | K92: =IF(K$4<=核心参数输入!$B$9,K90-K91-运营成本与税费!K97-运营成本与税费!K99,0) -> -142.60246 | ... AH92: =IF(AH$4<=核心参数输入!$B$9,AH90-AH91-运营成本与税费!AH97-运营成本与税费!AH99,0) -> 0
A93: 融资口径经营利润EBIT | B93: 万元 | D93: =IF(D$4<=核心参数输入!$B$9,D90-D91-运营成本与税费!D98-运营成本与税费!D100,0) -> 0 | E93: =IF(E$4<=核心参数输入!$B$9,E90-E91-运营成本与税费!E98-运营成本与税费!E100,0) -> 0 | F93: =IF(F$4<=核心参数输入!$B$9,F90-F91-运营成本与税费!F98-运营成本与税费!F100,0) -> 0 | G93: =IF(G$4<=核心参数输入!$B$9,G90-G91-运营成本与税费!G98-运营成本与税费!G100,0) -> 0 | H93: =IF(H$4<=核心参数输入!$B$9,H90-H91-运营成本与税费!H98-运营成本与税费!H100,0) -> -478.83921 | I93: =IF(I$4<=核心参数输入!$B$9,I90-I91-运营成本与税费!I98-运营成本与税费!I100,0) -> 28.81261 | J93: =IF(J$4<=核心参数输入!$B$9,J90-J91-运营成本与税费!J98-运营成本与税费!J100,0) -> 133.77844 | K93: =IF(K$4<=核心参数输入!$B$9,K90-K91-运营成本与税费!K98-运营成本与税费!K100,0) -> -169.53496 | ... AH93: =IF(AH$4<=核心参数输入!$B$9,AH90-AH91-运营成本与税费!AH98-运营成本与税费!AH100,0) -> 0
A94: 建成后利息费用 | B94: 万元 | D94: =IF(D$4<=核心参数输入!$B$9,融资与还本付息!D97,0) -> 0 | E94: =IF(E$4<=核心参数输入!$B$9,融资与还本付息!E97,0) -> 0 | F94: =IF(F$4<=核心参数输入!$B$9,融资与还本付息!F97,0) -> 0 | G94: =IF(G$4<=核心参数输入!$B$9,融资与还本付息!G97,0) -> 0 | H94: =IF(H$4<=核心参数输入!$B$9,融资与还本付息!H97,0) -> 1170 | I94: =IF(I$4<=核心参数输入!$B$9,融资与还本付息!I97,0) -> 990 | J94: =IF(J$4<=核心参数输入!$B$9,融资与还本付息!J97,0) -> 810 | K94: =IF(K$4<=核心参数输入!$B$9,融资与还本付息!K97,0) -> 630 | ... AH94: =IF(AH$4<=核心参数输入!$B$9,融资与还本付息!AH97,0) -> 0
A95: 融资口径处置前税前利润 | B95: 万元 | D95: =IF(D$4<=核心参数输入!$B$9,D93-D94,0) -> 0 | E95: =IF(E$4<=核心参数输入!$B$9,E93-E94,0) -> 0 | F95: =IF(F$4<=核心参数输入!$B$9,F93-F94,0) -> 0 | G95: =IF(G$4<=核心参数输入!$B$9,G93-G94,0) -> 0 | H95: =IF(H$4<=核心参数输入!$B$9,H93-H94,0) -> -1648.8392 | I95: =IF(I$4<=核心参数输入!$B$9,I93-I94,0) -> -961.18739 | J95: =IF(J$4<=核心参数输入!$B$9,J93-J94,0) -> -676.22156 | K95: =IF(K$4<=核心参数输入!$B$9,K93-K94,0) -> -799.53496 | ... AH95: =IF(AH$4<=核心参数输入!$B$9,AH93-AH94,0) -> 0
A96: 项目口径所得税含处置损益 | B96: 万元 | D96: =IF(D$4<=核心参数输入!$B$9,MAX(0,D92+运营成本与税费!D104)*核心参数输入!$B$52,0) -> 0 | E96: =IF(E$4<=核心参数输入!$B$9,MAX(0,E92+运营成本与税费!E104)*核心参数输入!$B$52,0) -> 0 | F96: =IF(F$4<=核心参数输入!$B$9,MAX(0,F92+运营成本与税费!F104)*核心参数输入!$B$52,0) -> 0 | G96: =IF(G$4<=核心参数输入!$B$9,MAX(0,G92+运营成本与税费!G104)*核心参数输入!$B$52,0) -> 0 | H96: =IF(H$4<=核心参数输入!$B$9,MAX(0,H92+运营成本与税费!H104)*核心参数输入!$B$52,0) -> 0 | I96: =IF(I$4<=核心参数输入!$B$9,MAX(0,I92+运营成本与税费!I104)*核心参数输入!$B$52,0) -> 117.88628 | J96: =IF(J$4<=核心参数输入!$B$9,MAX(0,J92+运营成本与税费!J104)*核心参数输入!$B$52,0) -> 118.14023 | K96: =IF(K$4<=核心参数输入!$B$9,MAX(0,K92+运营成本与税费!K104)*核心参数输入!$B$52,0) -> 0 | ... AH96: =IF(AH$4<=核心参数输入!$B$9,MAX(0,AH92+运营成本与税费!AH104)*核心参数输入!$B$52,0) -> 0
A97: 融资口径所得税含处置损益 | B97: 万元 | D97: =IF(D$4<=核心参数输入!$B$9,MAX(0,D95+运营成本与税费!D105)*核心参数输入!$B$52,0) -> 0 | E97: =IF(E$4<=核心参数输入!$B$9,MAX(0,E95+运营成本与税费!E105)*核心参数输入!$B$52,0) -> 0 | F97: =IF(F$4<=核心参数输入!$B$9,MAX(0,F95+运营成本与税费!F105)*核心参数输入!$B$52,0) -> 0 | G97: =IF(G$4<=核心参数输入!$B$9,MAX(0,G95+运营成本与税费!G105)*核心参数输入!$B$52,0) -> 0 | H97: =IF(H$4<=核心参数输入!$B$9,MAX(0,H95+运营成本与税费!H105)*核心参数输入!$B$52,0) -> 0 | I97: =IF(I$4<=核心参数输入!$B$9,MAX(0,I95+运营成本与税费!I105)*核心参数输入!$B$52,0) -> 0 | J97: =IF(J$4<=核心参数输入!$B$9,MAX(0,J95+运营成本与税费!J105)*核心参数输入!$B$52,0) -> 0 | K97: =IF(K$4<=核心参数输入!$B$9,MAX(0,K95+运营成本与税费!K105)*核心参数输入!$B$52,0) -> 0 | ... AH97: =IF(AH$4<=核心参数输入!$B$9,MAX(0,AH95+运营成本与税费!AH105)*核心参数输入!$B$52,0) -> 0
A98: 融资口径净利润含处置损益 | B98: 万元 | D98: =IF(D$4<=核心参数输入!$B$9,D95+运营成本与税费!D105-D97,0) -> 0 | E98: =IF(E$4<=核心参数输入!$B$9,E95+运营成本与税费!E105-E97,0) -> 0 | F98: =IF(F$4<=核心参数输入!$B$9,F95+运营成本与税费!F105-F97,0) -> 0 | G98: =IF(G$4<=核心参数输入!$B$9,G95+运营成本与税费!G105-G97,0) -> 0 | H98: =IF(H$4<=核心参数输入!$B$9,H95+运营成本与税费!H105-H97,0) -> -1648.8392 | I98: =IF(I$4<=核心参数输入!$B$9,I95+运营成本与税费!I105-I97,0) -> -961.18739 | J98: =IF(J$4<=核心参数输入!$B$9,J95+运营成本与税费!J105-J97,0) -> -676.22156 | K98: =IF(K$4<=核心参数输入!$B$9,K95+运营成本与税费!K105-K97,0) -> -799.53496 | ... AH98: =IF(AH$4<=核心参数输入!$B$9,AH95+运营成本与税费!AH105-AH97,0) -> 0
A99: 可用于偿债现金CFADS（不含处置） | B99: 万元 | D99: =IF(D$4<=核心参数输入!$B$9,D90-D91-MAX(0,D95)*核心参数输入!$B$52,0) -> 0 | E99: =IF(E$4<=核心参数输入!$B$9,E90-E91-MAX(0,E95)*核心参数输入!$B$52,0) -> 0 | F99: =IF(F$4<=核心参数输入!$B$9,F90-F91-MAX(0,F95)*核心参数输入!$B$52,0) -> 0 | G99: =IF(G$4<=核心参数输入!$B$9,G90-G91-MAX(0,G95)*核心参数输入!$B$52,0) -> 0 | H99: =IF(H$4<=核心参数输入!$B$9,H90-H91-MAX(0,H95)*核心参数输入!$B$52,0) -> 11614.444 | I99: =IF(I$4<=核心参数输入!$B$9,I90-I91-MAX(0,I95)*核心参数输入!$B$52,0) -> 15867.706 | J99: =IF(J$4<=核心参数输入!$B$9,J90-J91-MAX(0,J95)*核心参数输入!$B$52,0) -> 12227.062 | K99: =IF(K$4<=核心参数输入!$B$9,K90-K91-MAX(0,K95)*核心参数输入!$B$52,0) -> 686.91854 | ... AH99: =IF(AH$4<=核心参数输入!$B$9,AH90-AH91-MAX(0,AH95)*核心参数输入!$B$52,0) -> 0
A100: 项目经营现金流（不含处置） | B100: 万元 | D100: =IF(D$4<=核心参数输入!$B$9,D90-D91-MAX(0,D92)*核心参数输入!$B$52,0) -> 0 | E100: =IF(E$4<=核心参数输入!$B$9,E90-E91-MAX(0,E92)*核心参数输入!$B$52,0) -> 0 | F100: =IF(F$4<=核心参数输入!$B$9,F90-F91-MAX(0,F92)*核心参数输入!$B$52,0) -> 0 | G100: =IF(G$4<=核心参数输入!$B$9,G90-G91-MAX(0,G92)*核心参数输入!$B$52,0) -> 0 | H100: =IF(H$4<=核心参数输入!$B$9,H90-H91-MAX(0,H92)*核心参数输入!$B$52,0) -> 11614.444 | I100: =IF(I$4<=核心参数输入!$B$9,I90-I91-MAX(0,I92)*核心参数输入!$B$52,0) -> 15749.82 | J100: =IF(J$4<=核心参数输入!$B$9,J90-J91-MAX(0,J92)*核心参数输入!$B$52,0) -> 12108.922 | K100: =IF(K$4<=核心参数输入!$B$9,K90-K91-MAX(0,K92)*核心参数输入!$B$52,0) -> 686.91854 | ... AH100: =IF(AH$4<=核心参数输入!$B$9,AH90-AH91-MAX(0,AH92)*核心参数输入!$B$52,0) -> 0
A101: 土地现金支出 | B101: 万元 | D101: =IF(D$4<=核心参数输入!$B$9,投资与资金安排!D108,0) -> 8000 | E101: =IF(E$4<=核心参数输入!$B$9,投资与资金安排!E108,0) -> 0 | F101: =IF(F$4<=核心参数输入!$B$9,投资与资金安排!F108,0) -> 0 | G101: =IF(G$4<=核心参数输入!$B$9,投资与资金安排!G108,0) -> 0 | H101: =IF(H$4<=核心参数输入!$B$9,投资与资金安排!H108,0) -> 0 | I101: =IF(I$4<=核心参数输入!$B$9,投资与资金安排!I108,0) -> 0 | J101: =IF(J$4<=核心参数输入!$B$9,投资与资金安排!J108,0) -> 0 | K101: =IF(K$4<=核心参数输入!$B$9,投资与资金安排!K108,0) -> 0 | ... AH101: =IF(AH$4<=核心参数输入!$B$9,投资与资金安排!AH108,0) -> 0
A102: 非土地建设现金支出 | B102: 万元 | D102: =IF(D$4<=核心参数输入!$B$9,投资与资金安排!D109,0) -> 0 | E102: =IF(E$4<=核心参数输入!$B$9,投资与资金安排!E109,0) -> 17463.6 | F102: =IF(F$4<=核心参数输入!$B$9,投资与资金安排!F109,0) -> 23284.8 | G102: =IF(G$4<=核心参数输入!$B$9,投资与资金安排!G109,0) -> 17463.6 | H102: =IF(H$4<=核心参数输入!$B$9,投资与资金安排!H109,0) -> 0 | I102: =IF(I$4<=核心参数输入!$B$9,投资与资金安排!I109,0) -> 0 | J102: =IF(J$4<=核心参数输入!$B$9,投资与资金安排!J109,0) -> 0 | K102: =IF(K$4<=核心参数输入!$B$9,投资与资金安排!K109,0) -> 0 | ... AH102: =IF(AH$4<=核心参数输入!$B$9,投资与资金安排!AH109,0) -> 0
A103: 周转资金投入 | B103: 万元 | D103: =IF(D$4<=核心参数输入!$B$9,投资与资金安排!D111,0) -> 0 | E103: =IF(E$4<=核心参数输入!$B$9,投资与资金安排!E111,0) -> 0 | F103: =IF(F$4<=核心参数输入!$B$9,投资与资金安排!F111,0) -> 0 | G103: =IF(G$4<=核心参数输入!$B$9,投资与资金安排!G111,0) -> 0 | H103: =IF(H$4<=核心参数输入!$B$9,投资与资金安排!H111,0) -> 500 | I103: =IF(I$4<=核心参数输入!$B$9,投资与资金安排!I111,0) -> 0 | J103: =IF(J$4<=核心参数输入!$B$9,投资与资金安排!J111,0) -> 0 | K103: =IF(K$4<=核心参数输入!$B$9,投资与资金安排!K111,0) -> 0 | ... AH103: =IF(AH$4<=核心参数输入!$B$9,投资与资金安排!AH111,0) -> 0
A104: 周转资金收回 | B104: 万元 | D104: =IF(D$4<=核心参数输入!$B$9,投资与资金安排!D112,0) -> 0 | E104: =IF(E$4<=核心参数输入!$B$9,投资与资金安排!E112,0) -> 0 | F104: =IF(F$4<=核心参数输入!$B$9,投资与资金安排!F112,0) -> 0 | G104: =IF(G$4<=核心参数输入!$B$9,投资与资金安排!G112,0) -> 0 | H104: =IF(H$4<=核心参数输入!$B$9,投资与资金安排!H112,0) -> 0 | I104: =IF(I$4<=核心参数输入!$B$9,投资与资金安排!I112,0) -> 0 | J104: =IF(J$4<=核心参数输入!$B$9,投资与资金安排!J112,0) -> 0 | K104: =IF(K$4<=核心参数输入!$B$9,投资与资金安排!K112,0) -> 0 | ... AH104: =IF(AH$4<=核心参数输入!$B$9,投资与资金安排!AH112,0) -> 0
A105: 持有处置净现金（所得税前） | B105: 万元 | D105: =IF(D$4<=核心参数输入!$B$9,销售与出租收入!D106,0) -> 0 | E105: =IF(E$4<=核心参数输入!$B$9,销售与出租收入!E106,0) -> 0 | F105: =IF(F$4<=核心参数输入!$B$9,销售与出租收入!F106,0) -> 0 | G105: =IF(G$4<=核心参数输入!$B$9,销售与出租收入!G106,0) -> 0 | H105: =IF(H$4<=核心参数输入!$B$9,销售与出租收入!H106,0) -> 0 | I105: =IF(I$4<=核心参数输入!$B$9,销售与出租收入!I106,0) -> 0 | J105: =IF(J$4<=核心参数输入!$B$9,销售与出租收入!J106,0) -> 0 | K105: =IF(K$4<=核心参数输入!$B$9,销售与出租收入!K106,0) -> 0 | ... AH105: =IF(AH$4<=核心参数输入!$B$9,销售与出租收入!AH106,0) -> 0
A106: 项目投资税后现金流 | B106: 万元 | D106: =IF(D$4<=核心参数输入!$B$9,D90-D91-D96-D101-D102-D103+D104+D105,0) -> -8000 | E106: =IF(E$4<=核心参数输入!$B$9,E90-E91-E96-E101-E102-E103+E104+E105,0) -> -17463.6 | F106: =IF(F$4<=核心参数输入!$B$9,F90-F91-F96-F101-F102-F103+F104+F105,0) -> -23284.8 | G106: =IF(G$4<=核心参数输入!$B$9,G90-G91-G96-G101-G102-G103+G104+G105,0) -> -17463.6 | H106: =IF(H$4<=核心参数输入!$B$9,H90-H91-H96-H101-H102-H103+H104+H105,0) -> 11114.444 | I106: =IF(I$4<=核心参数输入!$B$9,I90-I91-I96-I101-I102-I103+I104+I105,0) -> 15749.82 | J106: =IF(J$4<=核心参数输入!$B$9,J90-J91-J96-J101-J102-J103+J104+J105,0) -> 12108.922 | K106: =IF(K$4<=核心参数输入!$B$9,K90-K91-K96-K101-K102-K103+K104+K105,0) -> 686.91854 | ... AH106: =IF(AH$4<=核心参数输入!$B$9,AH90-AH91-AH96-AH101-AH102-AH103+AH104+AH105,0) -> 0
A107: 贷款提款（非营业收入） | B107: 万元 | D107: =IF(D$4<=核心参数输入!$B$9,融资与还本付息!D91,0) -> 0 | E107: =IF(E$4<=核心参数输入!$B$9,融资与还本付息!E91,0) -> 9000 | F107: =IF(F$4<=核心参数输入!$B$9,融资与还本付息!F91,0) -> 12000 | G107: =IF(G$4<=核心参数输入!$B$9,融资与还本付息!G91,0) -> 9000 | H107: =IF(H$4<=核心参数输入!$B$9,融资与还本付息!H91,0) -> 0 | I107: =IF(I$4<=核心参数输入!$B$9,融资与还本付息!I91,0) -> 0 | J107: =IF(J$4<=核心参数输入!$B$9,融资与还本付息!J91,0) -> 0 | K107: =IF(K$4<=核心参数输入!$B$9,融资与还本付息!K91,0) -> 0 | ... AH107: =IF(AH$4<=核心参数输入!$B$9,融资与还本付息!AH91,0) -> 0
A108: 全部现金利息支付 | B108: 万元 | D108: =IF(D$4<=核心参数输入!$B$9,融资与还本付息!D94,0) -> 0 | E108: =IF(E$4<=核心参数输入!$B$9,融资与还本付息!E94,0) -> 189 | F108: =IF(F$4<=核心参数输入!$B$9,融资与还本付息!F94,0) -> 630 | G108: =IF(G$4<=核心参数输入!$B$9,融资与还本付息!G94,0) -> 1071 | H108: =IF(H$4<=核心参数输入!$B$9,融资与还本付息!H94,0) -> 1170 | I108: =IF(I$4<=核心参数输入!$B$9,融资与还本付息!I94,0) -> 990 | J108: =IF(J$4<=核心参数输入!$B$9,融资与还本付息!J94,0) -> 810 | K108: =IF(K$4<=核心参数输入!$B$9,融资与还本付息!K94,0) -> 630 | ... AH108: =IF(AH$4<=核心参数输入!$B$9,融资与还本付息!AH94,0) -> 0
A109: 本金偿还 | B109: 万元 | D109: =IF(D$4<=核心参数输入!$B$9,融资与还本付息!D93,0) -> 0 | E109: =IF(E$4<=核心参数输入!$B$9,融资与还本付息!E93,0) -> 0 | F109: =IF(F$4<=核心参数输入!$B$9,融资与还本付息!F93,0) -> 0 | G109: =IF(G$4<=核心参数输入!$B$9,融资与还本付息!G93,0) -> 0 | H109: =IF(H$4<=核心参数输入!$B$9,融资与还本付息!H93,0) -> 4285.7143 | I109: =IF(I$4<=核心参数输入!$B$9,融资与还本付息!I93,0) -> 4285.7143 | J109: =IF(J$4<=核心参数输入!$B$9,融资与还本付息!J93,0) -> 4285.7143 | K109: =IF(K$4<=核心参数输入!$B$9,融资与还本付息!K93,0) -> 4285.7143 | ... AH109: =IF(AH$4<=核心参数输入!$B$9,融资与还本付息!AH93,0) -> 0
A110: 所得税口径调整（项目税－融资税） | B110: 万元 | D110: =IF(D$4<=核心参数输入!$B$9,D96-D97,0) -> 0 | E110: =IF(E$4<=核心参数输入!$B$9,E96-E97,0) -> 0 | F110: =IF(F$4<=核心参数输入!$B$9,F96-F97,0) -> 0 | G110: =IF(G$4<=核心参数输入!$B$9,G96-G97,0) -> 0 | H110: =IF(H$4<=核心参数输入!$B$9,H96-H97,0) -> 0 | I110: =IF(I$4<=核心参数输入!$B$9,I96-I97,0) -> 117.88628 | J110: =IF(J$4<=核心参数输入!$B$9,J96-J97,0) -> 118.14023 | K110: =IF(K$4<=核心参数输入!$B$9,K96-K97,0) -> 0 | ... AH110: =IF(AH$4<=核心参数输入!$B$9,AH96-AH97,0) -> 0
A111: 资本金投入前资金净流量 | B111: 万元 | D111: =IF(D$4<=核心参数输入!$B$9,D106+D110+D107-D108-D109,0) -> -8000 | E111: =IF(E$4<=核心参数输入!$B$9,E106+E110+E107-E108-E109,0) -> -8652.6 | F111: =IF(F$4<=核心参数输入!$B$9,F106+F110+F107-F108-F109,0) -> -11914.8 | G111: =IF(G$4<=核心参数输入!$B$9,G106+G110+G107-G108-G109,0) -> -9534.6 | H111: =IF(H$4<=核心参数输入!$B$9,H106+H110+H107-H108-H109,0) -> 5658.73 | I111: =IF(I$4<=核心参数输入!$B$9,I106+I110+I107-I108-I109,0) -> 10591.992 | J111: =IF(J$4<=核心参数输入!$B$9,J106+J110+J107-J108-J109,0) -> 7131.3477 | K111: =IF(K$4<=核心参数输入!$B$9,K106+K110+K107-K108-K109,0) -> -4228.7957 | ... AH111: =IF(AH$4<=核心参数输入!$B$9,AH106+AH110+AH107-AH108-AH109,0) -> 0
A112: 期末后续支出及偿债留存需求 | B112: 万元 | D112: =IF(D$4<=核心参数输入!$B$9,MAX(0,E112-E111),0) -> 30102 | E112: =IF(E$4<=核心参数输入!$B$9,MAX(0,F112-F111),0) -> 21449.4 | F112: =IF(F$4<=核心参数输入!$B$9,MAX(0,G112-G111),0) -> 9534.6 | G112: =IF(G$4<=核心参数输入!$B$9,MAX(0,H112-H111),0) -> 0 | H112: =IF(H$4<=核心参数输入!$B$9,MAX(0,I112-I111),0) -> 0 | I112: =IF(I$4<=核心参数输入!$B$9,MAX(0,J112-J111),0) -> 8576.6525 | J112: =IF(J$4<=核心参数输入!$B$9,MAX(0,K112-K111),0) -> 15708 | K112: =IF(K$4<=核心参数输入!$B$9,MAX(0,L112-L111),0) -> 11479.204 | ... AG112: =IF(AG$4<=核心参数输入!$B$9,MAX(0,AH112-AH111),0) -> 0 | AH112: =IF(AH$4<=核心参数输入!$B$9,0,0) -> 0
A113: 理论期初资金余额 | B113: 万元 | D113: =IF(D$4<=核心参数输入!$B$9,0,0) -> 0 | E113: =IF(E$4<=核心参数输入!$B$9,D116,0) -> 0 | F113: =IF(F$4<=核心参数输入!$B$9,E116,0) -> 0 | G113: =IF(G$4<=核心参数输入!$B$9,F116,0) -> 0 | H113: =IF(H$4<=核心参数输入!$B$9,G116,0) -> 0 | I113: =IF(I$4<=核心参数输入!$B$9,H116,0) -> 0 | J113: =IF(J$4<=核心参数输入!$B$9,I116,0) -> 8576.6525 | K113: =IF(K$4<=核心参数输入!$B$9,J116,0) -> 15708 | L113: =IF(L$4<=核心参数输入!$B$9,K116,0) -> 11479.204 | ... AH113: =IF(AH$4<=核心参数输入!$B$9,AG116,0) -> 0
A114: 完成计划当年所需资本金 | B114: 万元 | D114: =IF(D$4<=核心参数输入!$B$9,MAX(0,-(D113+D111)),0) -> 8000 | E114: =IF(E$4<=核心参数输入!$B$9,MAX(0,-(E113+E111)),0) -> 8652.6 | F114: =IF(F$4<=核心参数输入!$B$9,MAX(0,-(F113+F111)),0) -> 11914.8 | G114: =IF(G$4<=核心参数输入!$B$9,MAX(0,-(G113+G111)),0) -> 9534.6 | H114: =IF(H$4<=核心参数输入!$B$9,MAX(0,-(H113+H111)),0) -> 0 | I114: =IF(I$4<=核心参数输入!$B$9,MAX(0,-(I113+I111)),0) -> 0 | J114: =IF(J$4<=核心参数输入!$B$9,MAX(0,-(J113+J111)),0) -> 0 | K114: =IF(K$4<=核心参数输入!$B$9,MAX(0,-(K113+K111)),0) -> 0 | ... AH114: =IF(AH$4<=核心参数输入!$B$9,MAX(0,-(AH113+AH111)),0) -> 0
A115: 完整出资可分配现金 | B115: 万元 | D115: =IF(D$4<=核心参数输入!$B$9,MAX(0,D113+D111+D114-D112),0) -> 0 | E115: =IF(E$4<=核心参数输入!$B$9,MAX(0,E113+E111+E114-E112),0) -> 0 | F115: =IF(F$4<=核心参数输入!$B$9,MAX(0,F113+F111+F114-F112),0) -> 0 | G115: =IF(G$4<=核心参数输入!$B$9,MAX(0,G113+G111+G114-G112),0) -> 0 | H115: =IF(H$4<=核心参数输入!$B$9,MAX(0,H113+H111+H114-H112),0) -> 5658.73 | I115: =IF(I$4<=核心参数输入!$B$9,MAX(0,I113+I111+I114-I112),0) -> 2015.3393 | J115: =IF(J$4<=核心参数输入!$B$9,MAX(0,J113+J111+J114-J112),0) -> 0 | K115: =IF(K$4<=核心参数输入!$B$9,MAX(0,K113+K111+K114-K112),0) -> 0 | ... AH115: =IF(AH$4<=核心参数输入!$B$9,MAX(0,AH113+AH111+AH114-AH112),0) -> 0
A116: 理论期末资金余额 | B116: 万元 | D116: =IF(D$4<=核心参数输入!$B$9,D113+D111+D114-D115,0) -> 0 | E116: =IF(E$4<=核心参数输入!$B$9,E113+E111+E114-E115,0) -> 0 | F116: =IF(F$4<=核心参数输入!$B$9,F113+F111+F114-F115,0) -> 0 | G116: =IF(G$4<=核心参数输入!$B$9,G113+G111+G114-G115,0) -> 0 | H116: =IF(H$4<=核心参数输入!$B$9,H113+H111+H114-H115,0) -> 0 | I116: =IF(I$4<=核心参数输入!$B$9,I113+I111+I114-I115,0) -> 8576.6525 | J116: =IF(J$4<=核心参数输入!$B$9,J113+J111+J114-J115,0) -> 15708 | K116: =IF(K$4<=核心参数输入!$B$9,K113+K111+K114-K115,0) -> 11479.204 | ... AH116: =IF(AH$4<=核心参数输入!$B$9,AH113+AH111+AH114-AH115,0) -> 0
A117: 累计所需资本金 | B117: 万元 | D117: =IF(D$4<=核心参数输入!$B$9,0+D114,0) -> 8000 | E117: =IF(E$4<=核心参数输入!$B$9,D117+E114,0) -> 16652.6 | F117: =IF(F$4<=核心参数输入!$B$9,E117+F114,0) -> 28567.4 | G117: =IF(G$4<=核心参数输入!$B$9,F117+G114,0) -> 38102 | H117: =IF(H$4<=核心参数输入!$B$9,G117+H114,0) -> 38102 | I117: =IF(I$4<=核心参数输入!$B$9,H117+I114,0) -> 38102 | J117: =IF(J$4<=核心参数输入!$B$9,I117+J114,0) -> 38102 | K117: =IF(K$4<=核心参数输入!$B$9,J117+K114,0) -> 38102 | L117: =IF(L$4<=核心参数输入!$B$9,K117+L114,0) -> 38102 | ... AH117: =IF(AH$4<=核心参数输入!$B$9,AG117+AH114,0) -> 0
A118: 资本金现金流（完整出资理论） | B118: 万元 | D118: =IF(D$4<=核心参数输入!$B$9,D115-D114,0) -> -8000 | E118: =IF(E$4<=核心参数输入!$B$9,E115-E114,0) -> -8652.6 | F118: =IF(F$4<=核心参数输入!$B$9,F115-F114,0) -> -11914.8 | G118: =IF(G$4<=核心参数输入!$B$9,G115-G114,0) -> -9534.6 | H118: =IF(H$4<=核心参数输入!$B$9,H115-H114,0) -> 5658.73 | I118: =IF(I$4<=核心参数输入!$B$9,I115-I114,0) -> 2015.3393 | J118: =IF(J$4<=核心参数输入!$B$9,J115-J114,0) -> 0 | K118: =IF(K$4<=核心参数输入!$B$9,K115-K114,0) -> 0 | ... AH118: =IF(AH$4<=核心参数输入!$B$9,AH115-AH114,0) -> 0
A119: 额度内期初现金余额 | B119: 万元 | D119: =IF(D$4<=核心参数输入!$B$9,0,0) -> 0 | E119: =IF(E$4<=核心参数输入!$B$9,D124,0) -> 0 | F119: =IF(F$4<=核心参数输入!$B$9,E124,0) -> 0 | G119: =IF(G$4<=核心参数输入!$B$9,F124,0) -> 0 | H119: =IF(H$4<=核心参数输入!$B$9,G124,0) -> 0 | I119: =IF(I$4<=核心参数输入!$B$9,H124,0) -> 556.73 | J119: =IF(J$4<=核心参数输入!$B$9,I124,0) -> 11148.722 | K119: =IF(K$4<=核心参数输入!$B$9,J124,0) -> 18280.069 | L119: =IF(L$4<=核心参数输入!$B$9,K124,0) -> 14051.274 | ... AH119: =IF(AH$4<=核心参数输入!$B$9,AG124,0) -> 0
A120: 期初未落实资金缺口 | B120: 万元 | D120: =IF(D$4<=核心参数输入!$B$9,0,0) -> 0 | E120: =IF(E$4<=核心参数输入!$B$9,D125,0) -> 0 | F120: =IF(F$4<=核心参数输入!$B$9,E125,0) -> 0 | G120: =IF(G$4<=核心参数输入!$B$9,F125,0) -> 0 | H120: =IF(H$4<=核心参数输入!$B$9,G125,0) -> 5102 | I120: =IF(I$4<=核心参数输入!$B$9,H125,0) -> 0 | J120: =IF(J$4<=核心参数输入!$B$9,I125,0) -> 0 | K120: =IF(K$4<=核心参数输入!$B$9,J125,0) -> 0 | L120: =IF(L$4<=核心参数输入!$B$9,K125,0) -> 0 | ... AH120: =IF(AH$4<=核心参数输入!$B$9,AG125,0) -> 0
A121: 额度内当年资金需要 | B121: 万元 | D121: =IF(D$4<=核心参数输入!$B$9,MAX(0,-(D119+D111-D120)),0) -> 8000 | E121: =IF(E$4<=核心参数输入!$B$9,MAX(0,-(E119+E111-E120)),0) -> 8652.6 | F121: =IF(F$4<=核心参数输入!$B$9,MAX(0,-(F119+F111-F120)),0) -> 11914.8 | G121: =IF(G$4<=核心参数输入!$B$9,MAX(0,-(G119+G111-G120)),0) -> 9534.6 | H121: =IF(H$4<=核心参数输入!$B$9,MAX(0,-(H119+H111-H120)),0) -> 0 | I121: =IF(I$4<=核心参数输入!$B$9,MAX(0,-(I119+I111-I120)),0) -> 0 | J121: =IF(J$4<=核心参数输入!$B$9,MAX(0,-(J119+J111-J120)),0) -> 0 | K121: =IF(K$4<=核心参数输入!$B$9,MAX(0,-(K119+K111-K120)),0) -> 0 | ... AH121: =IF(AH$4<=核心参数输入!$B$9,MAX(0,-(AH119+AH111-AH120)),0) -> 0
A122: 额度内当年实际可投资本金 | B122: 万元 | D122: =IF(D$4<=核心参数输入!$B$9,MIN(D121,MAX(0,核心参数输入!$B$61-0)),0) -> 8000 | E122: =IF(E$4<=核心参数输入!$B$9,MIN(E121,MAX(0,核心参数输入!$B$61-D127)),0) -> 8652.6 | F122: =IF(F$4<=核心参数输入!$B$9,MIN(F121,MAX(0,核心参数输入!$B$61-E127)),0) -> 11914.8 | G122: =IF(G$4<=核心参数输入!$B$9,MIN(G121,MAX(0,核心参数输入!$B$61-F127)),0) -> 4432.6 | H122: =IF(H$4<=核心参数输入!$B$9,MIN(H121,MAX(0,核心参数输入!$B$61-G127)),0) -> 0 | I122: =IF(I$4<=核心参数输入!$B$9,MIN(I121,MAX(0,核心参数输入!$B$61-H127)),0) -> 0 | J122: =IF(J$4<=核心参数输入!$B$9,MIN(J121,MAX(0,核心参数输入!$B$61-I127)),0) -> 0 | K122: =IF(K$4<=核心参数输入!$B$9,MIN(K121,MAX(0,核心参数输入!$B$61-J127)),0) -> 0 | L122: =IF(L$4<=核心参数输入!$B$9,MIN(L121,MAX(0,核心参数输入!$B$61-K127)),0) -> 0 | ... AH122: =IF(AH$4<=核心参数输入!$B$9,MIN(AH121,MAX(0,核心参数输入!$B$61-AG127)),0) -> 0
A123: 额度约束下可分配现金 | B123: 万元 | D123: =IF(D$4<=核心参数输入!$B$9,IF(D126>0.01,0,MAX(0,D119+D111-D120+D122-D112)),0) -> 0 | E123: =IF(E$4<=核心参数输入!$B$9,IF(E126>0.01,0,MAX(0,E119+E111-E120+E122-E112)),0) -> 0 | F123: =IF(F$4<=核心参数输入!$B$9,IF(F126>0.01,0,MAX(0,F119+F111-F120+F122-F112)),0) -> 0 | G123: =IF(G$4<=核心参数输入!$B$9,IF(G126>0.01,0,MAX(0,G119+G111-G120+G122-G112)),0) -> 0 | H123: =IF(H$4<=核心参数输入!$B$9,IF(H126>0.01,0,MAX(0,H119+H111-H120+H122-H112)),0) -> 0 | I123: =IF(I$4<=核心参数输入!$B$9,IF(I126>0.01,0,MAX(0,I119+I111-I120+I122-I112)),0) -> 0 | J123: =IF(J$4<=核心参数输入!$B$9,IF(J126>0.01,0,MAX(0,J119+J111-J120+J122-J112)),0) -> 0 | K123: =IF(K$4<=核心参数输入!$B$9,IF(K126>0.01,0,MAX(0,K119+K111-K120+K122-K112)),0) -> 0 | ... AH123: =IF(AH$4<=核心参数输入!$B$9,IF(AH126>0.01,0,MAX(0,AH119+AH111-AH120+AH122-AH112)),0) -> 0
A124: 额度内期末可用现金余额 | B124: 万元 | D124: =IF(D$4<=核心参数输入!$B$9,MAX(0,D119+D111-D120+D122)-D123,0) -> 0 | E124: =IF(E$4<=核心参数输入!$B$9,MAX(0,E119+E111-E120+E122)-E123,0) -> 0 | F124: =IF(F$4<=核心参数输入!$B$9,MAX(0,F119+F111-F120+F122)-F123,0) -> 0 | G124: =IF(G$4<=核心参数输入!$B$9,MAX(0,G119+G111-G120+G122)-G123,0) -> 0 | H124: =IF(H$4<=核心参数输入!$B$9,MAX(0,H119+H111-H120+H122)-H123,0) -> 556.73 | I124: =IF(I$4<=核心参数输入!$B$9,MAX(0,I119+I111-I120+I122)-I123,0) -> 11148.722 | J124: =IF(J$4<=核心参数输入!$B$9,MAX(0,J119+J111-J120+J122)-J123,0) -> 18280.069 | K124: =IF(K$4<=核心参数输入!$B$9,MAX(0,K119+K111-K120+K122)-K123,0) -> 14051.274 | ... AH124: =IF(AH$4<=核心参数输入!$B$9,MAX(0,AH119+AH111-AH120+AH122)-AH123,0) -> 0
A125: 期末未落实资金缺口 | B125: 万元 | D125: =IF(D$4<=核心参数输入!$B$9,MAX(0,-(D119+D111-D120+D122)),0) -> 0 | E125: =IF(E$4<=核心参数输入!$B$9,MAX(0,-(E119+E111-E120+E122)),0) -> 0 | F125: =IF(F$4<=核心参数输入!$B$9,MAX(0,-(F119+F111-F120+F122)),0) -> 0 | G125: =IF(G$4<=核心参数输入!$B$9,MAX(0,-(G119+G111-G120+G122)),0) -> 5102 | H125: =IF(H$4<=核心参数输入!$B$9,MAX(0,-(H119+H111-H120+H122)),0) -> 0 | I125: =IF(I$4<=核心参数输入!$B$9,MAX(0,-(I119+I111-I120+I122)),0) -> 0 | J125: =IF(J$4<=核心参数输入!$B$9,MAX(0,-(J119+J111-J120+J122)),0) -> 0 | K125: =IF(K$4<=核心参数输入!$B$9,MAX(0,-(K119+K111-K120+K122)),0) -> 0 | ... AH125: =IF(AH$4<=核心参数输入!$B$9,MAX(0,-(AH119+AH111-AH120+AH122)),0) -> 0
A126: 至当年最大未落实缺口 | B126: 万元 | D126: =IF(D$4<=核心参数输入!$B$9,MAX(0,D125),0) -> 0 | E126: =IF(E$4<=核心参数输入!$B$9,MAX(D126,E125),0) -> 0 | F126: =IF(F$4<=核心参数输入!$B$9,MAX(E126,F125),0) -> 0 | G126: =IF(G$4<=核心参数输入!$B$9,MAX(F126,G125),0) -> 5102 | H126: =IF(H$4<=核心参数输入!$B$9,MAX(G126,H125),0) -> 5102 | I126: =IF(I$4<=核心参数输入!$B$9,MAX(H126,I125),0) -> 5102 | J126: =IF(J$4<=核心参数输入!$B$9,MAX(I126,J125),0) -> 5102 | K126: =IF(K$4<=核心参数输入!$B$9,MAX(J126,K125),0) -> 5102 | L126: =IF(L$4<=核心参数输入!$B$9,MAX(K126,L125),0) -> 5102 | ... AH126: =IF(AH$4<=核心参数输入!$B$9,MAX(AG126,AH125),0) -> 0
A127: 累计额度内可投资本金 | B127: 万元 | D127: =IF(D$4<=核心参数输入!$B$9,0+D122,0) -> 8000 | E127: =IF(E$4<=核心参数输入!$B$9,D127+E122,0) -> 16652.6 | F127: =IF(F$4<=核心参数输入!$B$9,E127+F122,0) -> 28567.4 | G127: =IF(G$4<=核心参数输入!$B$9,F127+G122,0) -> 33000 | H127: =IF(H$4<=核心参数输入!$B$9,G127+H122,0) -> 33000 | I127: =IF(I$4<=核心参数输入!$B$9,H127+I122,0) -> 33000 | J127: =IF(J$4<=核心参数输入!$B$9,I127+J122,0) -> 33000 | K127: =IF(K$4<=核心参数输入!$B$9,J127+K122,0) -> 33000 | L127: =IF(L$4<=核心参数输入!$B$9,K127+L122,0) -> 33000 | ... AH127: =IF(AH$4<=核心参数输入!$B$9,AG127+AH122,0) -> 0
...

Sheet 指标与情景测算
A2: 指标与情景测算 · 模拟数据
A4: 指标 / 观察项 | B4: 基准情景 | C4: 单位 | D4: 组合压力情景 | G4: 口径 / 提示
A6: 项目税后IRR | B6: =IF(AND(COUNTIF(利润与现金流!$D$26:INDEX(利润与现金流!$D$26:$AH$26,核心参数输入!$B$9+1),"<0")>0,COUNTIF(利润与现金流!$D$26:INDEX(利润与现金流!$D$26:$AH$26,核心参数输入!$B$9+1),">0")>0),IFERROR(IRR(利润与现金流!$D$26:INDEX(利润与现金流!$D$26:$AH$26,核心参数输入!$B$9+1)),"无法计算"),"无法计算") -> -0.011985485 | C6: % | D6: =IF(AND(COUNTIF(利润与现金流!$D$106:INDEX(利润与现金流!$D$106:$AH$106,核心参数输入!$B$9+1),"<0")>0,COUNTIF(利润与现金流!$D$106:INDEX(利润与现金流!$D$106:$AH$106,核心参数输入!$B$9+1),">0")>0),IFERROR(IRR(利润与现金流!$D$106:INDEX(利润与现金流!$D$106:$AH$106,核心参数输入!$B$9+1)),"无法计算"),"无法计算") -> -0.045961145 | G6: 不含融资，所得税按无融资口径；IRR只取第0年至第N年
A7: 资本金IRR | B7: =IF(AND(COUNTIF(利润与现金流!$D$38:INDEX(利润与现金流!$D$38:$AH$38,核心参数输入!$B$9+1),"<0")>0,COUNTIF(利润与现金流!$D$38:INDEX(利润与现金流!$D$38:$AH$38,核心参数输入!$B$9+1),">0")>0),IFERROR(IRR(利润与现金流!$D$38:INDEX(利润与现金流!$D$38:$AH$38,核心参数输入!$B$9+1)),"无法计算"),"无法计算") -> -0.03575104 | C7: % | D7: =IF(AND(COUNTIF(利润与现金流!$D$118:INDEX(利润与现金流!$D$118:$AH$118,核心参数输入!$B$9+1),"<0")>0,COUNTIF(利润与现金流!$D$118:INDEX(利润与现金流!$D$118:$AH$118,核心参数输入!$B$9+1),">0")>0),IFERROR(IRR(利润与现金流!$D$118:INDEX(利润与现金流!$D$118:$AH$118,核心参数输入!$B$9+1)),"无法计算"),"无法计算") -> -0.079012248 | G7: 完整出资理论：实际所需股东投入与留存后分配现金
A8: 项目NPV | B8: =NPV(核心参数输入!$B$71,利润与现金流!$E$26:INDEX(利润与现金流!$D$26:$AH$26,核心参数输入!$B$9+1))+利润与现金流!D26 -> -19528.19 | C8: 万元 | D8: =NPV(核心参数输入!$B$71,利润与现金流!$E$106:INDEX(利润与现金流!$D$106:$AH$106,核心参数输入!$B$9+1))+利润与现金流!D106 -> -27383.782 | G8: NPV(第1年至第N年)＋第0年；按项目折现率
A9: 资本金NPV | B9: =NPV(核心参数输入!$B$72,利润与现金流!$E$38:INDEX(利润与现金流!$D$38:$AH$38,核心参数输入!$B$9+1))+利润与现金流!D38 -> -17639.683 | C9: 万元 | D9: =NPV(核心参数输入!$B$72,利润与现金流!$E$118:INDEX(利润与现金流!$D$118:$AH$118,核心参数输入!$B$9+1))+利润与现金流!D118 -> -25789.873 | G9: 按资本金折现率，完整出资理论
A10: 项目静态回收期 | B10: =IF(COUNTIF(利润与现金流!$D$26:INDEX(利润与现金流!$D$26:$AH$26,核心参数输入!$B$9+1),"<0")=0,"不适用",IF(COUNTIF(利润与现金流!$D$54:INDEX(利润与现金流!$D$54:$AH$54,核心参数输入!$B$9+1),1)=0,"测算期内未回收",MATCH(1,利润与现金流!$D$54:INDEX(利润与现金流!$D$54:$AH$54,核心参数输入!$B$9+1),0)-2-INDEX(利润与现金流!$D$49:$AH$49,MAX(1,MATCH(1,利润与现金流!$D$54:INDEX(利润与现金流!$D$54:$AH$54,核心参数输入!$B$9+1),0)-1))/INDEX(利润与现金流!$D$26:$AH$26,MATCH(1,利润与现金流!$D$54:INDEX(利润与现金流!$D$54:$AH$54,核心参数输入!$B$9+1),0)))) -> 测算期内未回收 | C10: 年 | D10: =IF(COUNTIF(利润与现金流!$D$106:INDEX(利润与现金流!$D$106:$AH$106,核心参数输入!$B$9+1),"<0")=0,"不适用",IF(COUNTIF(利润与现金流!$D$134:INDEX(利润与现金流!$D$134:$AH$134,核心参数输入!$B$9+1),1)=0,"测算期内未回收",MATCH(1,利润与现金流!$D$134:INDEX(利润与现金流!$D$134:$AH$134,核心参数输入!$B$9+1),0)-2-INDEX(利润与现金流!$D$129:$AH$129,MAX(1,MATCH(1,利润与现金流!$D$134:INDEX(利润与现金流!$D$134:$AH$134,核心参数输入!$B$9+1),0)-1))/INDEX(利润与现金流!$D$106:$AH$106,MATCH(1,利润与现金流!$D$134:INDEX(利润与现金流!$D$134:$AH$134,核心参数输入!$B$9+1),0)))) -> 测算期内未回收 | G10: 含建设期；跨年线性插值
A11: 项目动态回收期 | B11: =IF(COUNTIF(利润与现金流!$D$50:INDEX(利润与现金流!$D$50:$AH$50,核心参数输入!$B$9+1),"<0")=0,"不适用",IF(COUNTIF(利润与现金流!$D$55:INDEX(利润与现金流!$D$55:$AH$55,核心参数输入!$B$9+1),1)=0,"测算期内未回收",MATCH(1,利润与现金流!$D$55:INDEX(利润与现金流!$D$55:$AH$55,核心参数输入!$B$9+1),0)-2-INDEX(利润与现金流!$D$51:$AH$51,MAX(1,MATCH(1,利润与现金流!$D$55:INDEX(利润与现金流!$D$55:$AH$55,核心参数输入!$B$9+1),0)-1))/INDEX(利润与现金流!$D$50:$AH$50,MATCH(1,利润与现金流!$D$55:INDEX(利润与现金流!$D$55:$AH$55,核心参数输入!$B$9+1),0)))) -> 测算期内未回收 | C11: 年 | D11: =IF(COUNTIF(利润与现金流!$D$130:INDEX(利润与现金流!$D$130:$AH$130,核心参数输入!$B$9+1),"<0")=0,"不适用",IF(COUNTIF(利润与现金流!$D$135:INDEX(利润与现金流!$D$135:$AH$135,核心参数输入!$B$9+1),1)=0,"测算期内未回收",MATCH(1,利润与现金流!$D$135:INDEX(利润与现金流!$D$135:$AH$135,核心参数输入!$B$9+1),0)-2-INDEX(利润与现金流!$D$131:$AH$131,MAX(1,MATCH(1,利润与现金流!$D$135:INDEX(利润与现金流!$D$135:$AH$135,核心参数输入!$B$9+1),0)-1))/INDEX(利润与现金流!$D$130:$AH$130,MATCH(1,利润与现金流!$D$135:INDEX(利润与现金流!$D$135:$AH$135,核心参数输入!$B$9+1),0)))) -> 测算期内未回收 | G11: 使用折现项目现金流；跨年线性插值
A12: 运营期最低偿债覆盖倍数 | B12: =IF(核心参数输入!$B$57=0,"不适用",IF(COUNT(利润与现金流!$D$52:INDEX(利润与现金流!$D$52:$AH$52,核心参数输入!$B$9+1))=0,"无法计算",MIN(利润与现金流!$D$53:INDEX(利润与现金流!$D$53:$AH$53,核心参数输入!$B$9+1)))) -> 0.20055108 | C12: 倍 | D12: =IF(核心参数输入!$B$57=0,"不适用",IF(COUNT(利润与现金流!$D$132:INDEX(利润与现金流!$D$132:$AH$132,核心参数输入!$B$9+1))=0,"无法计算",MIN(利润与现金流!$D$133:INDEX(利润与现金流!$D$133:$AH$133,核心参数输入!$B$9+1)))) -> 0.13973931 | G12: CFADS/本息；无贷款为不适用；排除处置、周转回收及融资流入
A13: 所需累计资本金 | B13: =SUM(利润与现金流!$D$34:INDEX(利润与现金流!$D$34:$AH$34,核心参数输入!$B$9+1)) -> 32810 | C13: 万元 | D13: =SUM(利润与现金流!$D$114:INDEX(利润与现金流!$D$114:$AH$114,核心参数输入!$B$9+1)) -> 38102 | G13: 按完整计划及留存规则计算所需投入
A14: 未落实资金缺口最大值 | B14: =MAX(利润与现金流!$D$45:INDEX(利润与现金流!$D$45:$AH$45,核心参数输入!$B$9+1)) -> 0 | C14: 万元 | D14: =MAX(利润与现金流!$D$125:INDEX(利润与现金流!$D$125:$AH$125,核心参数输入!$B$9+1)) -> 5102 | G14: 额度内资金平衡的历史最大未落实缺口
A15: 贷款到期未偿本金 | B15: =IF(核心参数输入!$B$57=0,0,IF(OR(融资与还本付息!$B$7>30,融资与还本付息!$B$7>核心参数输入!$B$9),"无法计算",INDEX(融资与还本付息!$D$15:$AH$15,融资与还本付息!$B$7+1))) -> 0 | C15: 万元 | D15: =IF(核心参数输入!$B$57=0,0,IF(OR(融资与还本付息!$B$87>30,融资与还本付息!$B$87>核心参数输入!$B$9),"无法计算",INDEX(融资与还本付息!$D$95:$AH$95,融资与还本付息!$B$87+1))) -> 0 | G15: 只取到期年；期限未覆盖时参数校验失败
A16: 项目总投资 | B16: =投资与资金安排!$B$18 -> 63310 | C16: 万元 | D16: =投资与资金安排!$B$98 -> 68602 | G16: 土地＋非土地建设＋建设期利息＋周转资金
A17: 贷款金额 | B17: =核心参数输入!$B$57 -> 30000 | C17: 万元 | D17: =核心参数输入!$B$57 -> 30000 | G17: 压力情景保持额度不变
A18: 可投入资本金额度 | B18: =核心参数输入!$B$61 -> 33000 | C18: 万元 | D18: =核心参数输入!$B$61 -> 33000 | G18: 唯一额度输入，无额外资本金上限
A19: 测算期累计销售去化率 | B19: =SUM(建筑面积与开发计划!$D$21:INDEX(建筑面积与开发计划!$D$21:$AH$21,核心参数输入!$B$9+1)) -> 1 | C19: % | D19: =SUM(建筑面积与开发计划!$D$101:INDEX(建筑面积与开发计划!$D$101:$AH$101,核心参数输入!$B$9+1)) -> 1 | G19: 年度销售占总可售面积的比例累计
A20: 完成销售年份 | B20: =IF(B19<0.999999,"测算期内未完成",IFERROR(MATCH(1,建筑面积与开发计划!$D$29:$AH$29,0)-1,"测算期内未完成")) -> 6 | C20: 项目年 | D20: =IF(D19<0.999999,"测算期内未完成",IFERROR(MATCH(1,建筑面积与开发计划!$D$109:$AH$109,0)-1,"测算期内未完成")) -> 6 | G20: 首次达到100%；未完成销售不自动产生处置回款
A21: 稳定期实际出租率 | B21: =IF(ISNUMBER(B28),INDEX(建筑面积与开发计划!$D$26:$AH$26,B28+1),"不适用") -> 0.9 | C21: % | D21: =IF(ISNUMBER(D28),INDEX(建筑面积与开发计划!$D$106:$AH$106,D28+1),"不适用") -> 0.8 | G21: 取第4个出租年度；未覆盖显示不适用
A22: 持有经营保本出租率 | B22: =IF(ISNUMBER(B28),IF(建筑面积与开发计划!$B$10*INDEX(销售与出租收入!$D$18:$AH$18,B28+1)*12/10000*核心参数输入!$B$43*(1+核心参数输入!$B$44)*(1-核心参数输入!$B$49-核心参数输入!$B$51)<=0,"无法计算",(INDEX(运营成本与税费!$D$12:$AH$12,B28+1)+核心参数输入!$B$50)/(建筑面积与开发计划!$B$10*INDEX(销售与出租收入!$D$18:$AH$18,B28+1)*12/10000*核心参数输入!$B$43*(1+核心参数输入!$B$44)*(1-核心参数输入!$B$49-核心参数输入!$B$51))),"不适用") -> 0.29800053 | C22: % | D22: =IF(ISNUMBER(D28),IF(建筑面积与开发计划!$B$10*INDEX(销售与出租收入!$D$98:$AH$98,D28+1)*12/10000*核心参数输入!$B$43*(1+核心参数输入!$B$44)*(1-核心参数输入!$B$49-核心参数输入!$B$51)<=0,"无法计算",(INDEX(运营成本与税费!$D$92:$AH$92,D28+1)+核心参数输入!$B$50)/(建筑面积与开发计划!$B$10*INDEX(销售与出租收入!$D$98:$AH$98,D28+1)*12/10000*核心参数输入!$B$43*(1+核心参数输入!$B$44)*(1-核心参数输入!$B$49-核心参数输入!$B$51))),"不适用") -> 0.3311117 | G22: =IF(OR(AND(ISNUMBER(B22),B22>1),AND(ISNUMBER(D22),D22>1)),"保本出租率超过100%：满租也无法覆盖经营现金支出","保本率假设稳定全年租赁、无新增免租；不含折旧、本息及所得税") -> 保本率假设稳定全年租赁、无新增免租；不含折旧、本息及所得税
A23: 持有稳定期净经营收益率 | B23: =IF(ISNUMBER(B28),IF(投资与资金安排!$B$24>0,(INDEX(销售与出租收入!$D$22:$AH$22,B28+1)-INDEX(运营成本与税费!$D$12:$AH$12,B28+1)-INDEX(运营成本与税费!$D$13:$AH$13,B28+1)-INDEX(运营成本与税费!$D$14:$AH$14,B28+1)-INDEX(运营成本与税费!$D$15:$AH$15,B28+1))/投资与资金安排!$B$24,"无法计算"),"不适用") -> 0.034273213 | C23: % | D23: =IF(ISNUMBER(D28),IF(投资与资金安排!$B$104>0,(INDEX(销售与出租收入!$D$102:$AH$102,D28+1)-INDEX(运营成本与税费!$D$92:$AH$92,D28+1)-INDEX(运营成本与税费!$D$93:$AH$93,D28+1)-INDEX(运营成本与税费!$D$94:$AH$94,D28+1)-INDEX(运营成本与税费!$D$95:$AH$95,D28+1))/投资与资金安排!$B$104,"无法计算"),"不适用") -> 0.022054863 | G23: 第4个出租年度NOI/持有分摊总投资，含维护；不等于IRR
A24: 期末处置净收入占现金流入 | B24: =IF(SUM(销售与出租收入!$D$23:$AH$23)+SUM(销售与出租收入!$D$26:$AH$26)+SUM(投资与资金安排!$D$32:$AH$32)=0,"不适用",SUM(销售与出租收入!$D$26:$AH$26)/(SUM(销售与出租收入!$D$23:$AH$23)+SUM(销售与出租收入!$D$26:$AH$26)+SUM(投资与资金安排!$D$32:$AH$32))) -> 0 | C24: % | D24: =IF(SUM(销售与出租收入!$D$103:$AH$103)+SUM(销售与出租收入!$D$106:$AH$106)+SUM(投资与资金安排!$D$112:$AH$112)=0,"不适用",SUM(销售与出租收入!$D$106:$AH$106)/(SUM(销售与出租收入!$D$103:$AH$103)+SUM(销售与出租收入!$D$106:$AH$106)+SUM(投资与资金安排!$D$112:$AH$112))) -> 0 | G24: 所得税前处置净收入/销售＋租金＋其他＋处置净收入＋周转回收
A25: 项目IRR变号提示 | B25: =IF(SUM(利润与现金流!$D$58:INDEX(利润与现金流!$D$58:$AH$58,核心参数输入!$B$9+1))>1,"多次变号：IRR可能有歧义","单次变号或无变号") -> 单次变号或无变号 | C25: 文本 | D25: =IF(SUM(利润与现金流!$D$138:INDEX(利润与现金流!$D$138:$AH$138,核心参数输入!$B$9+1))>1,"多次变号：IRR可能有歧义","单次变号或无变号") -> 单次变号或无变号 | G25: 忽略中间零现金流；多次变号需谨慎理解IRR
A26: 资本金IRR变号提示 | B26: =IF(SUM(利润与现金流!$D$64:INDEX(利润与现金流!$D$64:$AH$64,核心参数输入!$B$9+1))>1,"多次变号：IRR可能有歧义","单次变号或无变号") -> 单次变号或无变号 | C26: 文本 | D26: =IF(SUM(利润与现金流!$D$144:INDEX(利润与现金流!$D$144:$AH$144,核心参数输入!$B$9+1))>1,"多次变号：IRR可能有歧义","单次变号或无变号") -> 单次变号或无变号 | G26: 同样检查完整出资资本金现金流
A27: 资本金收益结果标识 | B27: =IF(B14>0.01,"理论结果，资金尚未落实","按完整出资计划测算") -> 按完整出资计划测算 | C27: 文本 | D27: =IF(D14>0.01,"理论结果，资金尚未落实","按完整出资计划测算") -> 理论结果，资金尚未落实 | G27: 缺口大于0时最终决策仍未通过
A28: 稳定观察年份 | B28: =IF(核心参数输入!$B$9>=核心参数输入!$B$18+3,核心参数输入!$B$18+3,"不适用") -> 7 | C28: 项目年 | D28: =IF(核心参数输入!$B$9>=核心参数输入!$B$18+3,核心参数输入!$B$18+3,"不适用") -> 7 | G28: 出租开始年＋3，第4出租年度；仍有少量新增免租
A31: 逐项判断（金额容差0.01万元；回收期未回收即未通过；阈值均为模拟值）
A33: 指标 / 安全条件 | B33: 基准测算值 | C33: 标准 | D33: 基准状态 | E33: 压力测算值 | F33: 压力状态
A34: 项目税后IRR | B34: =B6 -> -0.011985485 | C34: =核心参数输入!$B$69 -> 0.08 | D34: =IF(B34="不适用","未通过",IF(NOT(ISNUMBER(B34)),IF(B34="无法计算","待判断","未通过"),IF(B34>=C34-0.00000001,"通过","未通过"))) -> 未通过 | E34: =D6 -> -0.045961145 | F34: =IF(E34="不适用","未通过",IF(NOT(ISNUMBER(E34)),IF(E34="无法计算","待判断","未通过"),IF(E34>=C34-0.00000001,"通过","未通过"))) -> 未通过
A35: 资本金IRR | B35: =B7 -> -0.03575104 | C35: =核心参数输入!$B$70 -> 0.1 | D35: =IF(B35="不适用","未通过",IF(NOT(ISNUMBER(B35)),IF(B35="无法计算","待判断","未通过"),IF(B35>=C35-0.00000001,"通过","未通过"))) -> 未通过 | E35: =D7 -> -0.079012248 | F35: =IF(E35="不适用","未通过",IF(NOT(ISNUMBER(E35)),IF(E35="无法计算","待判断","未通过"),IF(E35>=C35-0.00000001,"通过","未通过"))) -> 未通过
A36: 项目NPV | B36: =B8 -> -19528.19 | C36: =0 -> 0 | D36: =IF(B36="不适用","未通过",IF(NOT(ISNUMBER(B36)),IF(B36="无法计算","待判断","未通过"),IF(B36>=-0.01,"通过","未通过"))) -> 未通过 | E36: =D8 -> -27383.782 | F36: =IF(E36="不适用","未通过",IF(NOT(ISNUMBER(E36)),IF(E36="无法计算","待判断","未通过"),IF(E36>=-0.01,"通过","未通过"))) -> 未通过
A37: 资本金NPV | B37: =B9 -> -17639.683 | C37: =0 -> 0 | D37: =IF(B37="不适用","未通过",IF(NOT(ISNUMBER(B37)),IF(B37="无法计算","待判断","未通过"),IF(B37>=-0.01,"通过","未通过"))) -> 未通过 | E37: =D9 -> -25789.873 | F37: =IF(E37="不适用","未通过",IF(NOT(ISNUMBER(E37)),IF(E37="无法计算","待判断","未通过"),IF(E37>=-0.01,"通过","未通过"))) -> 未通过
A38: 静态回收期 | B38: =B10 -> 测算期内未回收 | C38: =核心参数输入!$B$73 -> 15 | D38: =IF(B38="不适用","未通过",IF(NOT(ISNUMBER(B38)),IF(B38="无法计算","待判断","未通过"),IF(B38<=C38+0.00000001,"通过","未通过"))) -> 未通过 | E38: =D10 -> 测算期内未回收 | F38: =IF(E38="不适用","未通过",IF(NOT(ISNUMBER(E38)),IF(E38="无法计算","待判断","未通过"),IF(E38<=C38+0.00000001,"通过","未通过"))) -> 未通过
A39: 动态回收期 | B39: =B11 -> 测算期内未回收 | C39: =核心参数输入!$B$74 -> 20 | D39: =IF(B39="不适用","未通过",IF(NOT(ISNUMBER(B39)),IF(B39="无法计算","待判断","未通过"),IF(B39<=C39+0.00000001,"通过","未通过"))) -> 未通过 | E39: =D11 -> 测算期内未回收 | F39: =IF(E39="不适用","未通过",IF(NOT(ISNUMBER(E39)),IF(E39="无法计算","待判断","未通过"),IF(E39<=C39+0.00000001,"通过","未通过"))) -> 未通过
A40: 最低偿债覆盖倍数 | B40: =B12 -> 0.20055108 | C40: =核心参数输入!$B$75 -> 1.2 | D40: =IF(B40="不适用","不适用",IF(NOT(ISNUMBER(B40)),IF(B40="无法计算","待判断","未通过"),IF(B40>=C40-0.00000001,"通过","未通过"))) -> 未通过 | E40: =D12 -> 0.13973931 | F40: =IF(E40="不适用","不适用",IF(NOT(ISNUMBER(E40)),IF(E40="无法计算","待判断","未通过"),IF(E40>=C40-0.00000001,"通过","未通过"))) -> 未通过
A41: 所需累计资本金 | B41: =B13 -> 32810 | C41: =核心参数输入!$B$61 -> 33000 | D41: =IF(B41="不适用","未通过",IF(NOT(ISNUMBER(B41)),IF(B41="无法计算","待判断","未通过"),IF(B41<=C41+0.01,"通过","未通过"))) -> 通过 | E41: =D13 -> 38102 | F41: =IF(E41="不适用","未通过",IF(NOT(ISNUMBER(E41)),IF(E41="无法计算","待判断","未通过"),IF(E41<=C41+0.01,"通过","未通过"))) -> 未通过
A42: 未落实资金缺口最大值 | B42: =B14 -> 0 | C42: =0 -> 0 | D42: =IF(B42="不适用","未通过",IF(NOT(ISNUMBER(B42)),IF(B42="无法计算","待判断","未通过"),IF(ABS(B42)<=0.01,"通过","未通过"))) -> 通过 | E42: =D14 -> 5102 | F42: =IF(E42="不适用","未通过",IF(NOT(ISNUMBER(E42)),IF(E42="无法计算","待判断","未通过"),IF(ABS(E42)<=0.01,"通过","未通过"))) -> 未通过
A43: 贷款到期未偿本金 | B43: =B15 -> 0 | C43: =0 -> 0 | D43: =IF(B43="不适用","未通过",IF(NOT(ISNUMBER(B43)),IF(B43="无法计算","待判断","未通过"),IF(ABS(B43)<=0.01,"通过","未通过"))) -> 通过 | E43: =D15 -> 0 | F43: =IF(E43="不适用","未通过",IF(NOT(ISNUMBER(E43)),IF(E43="无法计算","待判断","未通过"),IF(ABS(E43)<=0.01,"通过","未通过"))) -> 通过
A46: 情景总体状态 | B46: =IF(OR(COUNTIF(决策看板!$D$35:$D$64,"未通过")>0,COUNTIF(D34:D43,"待判断")>0),"待判断：请检查参数",IF(COUNTIF(D34:D43,"未通过")>0,"未通过","通过")) -> 未通过 | E46: =IF(OR(COUNTIF(决策看板!$D$35:$D$64,"未通过")>0,COUNTIF(F34:F43,"待判断")>0),"待判断：请检查参数",IF(COUNTIF(F34:F43,"未通过")>0,"未通过","通过")) -> 未通过
A48: 基准不通过原因 | B48: =IF(COUNTIF(决策看板!$D$35:$D$64,"未通过")>0,"参数校验未通过；","")&IF(D34="未通过","项目税后IRR未达标；",IF(D34="待判断","项目税后IRR无法计算；",""))&IF(D35="未通过","资本金IRR未达标；",IF(D35="待判断","资本金IRR无法计算；",""))&IF(D36="未通过","项目NPV未达标；",IF(D36="待判断","项目NPV无法计算；",""))&IF(D37="未通过","资本金NPV未达标；",IF(D37="待判断","资本金NPV无法计算；",""))&IF(D38="未通过","静态回收期未达标；",IF(D38="待判断","静态回收期无法计算；",""))&IF(D39="未通过","动态回收期未达标；",IF(D39="待判断","动态回收期无法计算；",""))&IF(D40="未通过","最低偿债覆盖倍数未达标；",IF(D40="待判断","最低偿债覆盖倍数无法计算；",""))&IF(D41="未通过","所需累计资本金未达标；",IF(D41="待判断","所需累计资本金无法计算；",""))&IF(D42="未通过","未落实资金缺口最大值未达标；",IF(D42="待判断","未落实资金缺口最大值无法计算；",""))&IF(D43="未通过","贷款到期未偿本金未达标；",IF(D43="待判断","贷款到期未偿本金无法计算；","")) -> 项目税后IRR未达标；资本金IRR未达标；项目NPV未达标；资本金NPV未达标；静态回收期未达标；动态回收期未达标；最低偿债覆盖倍数未达标；
A50: 压力不通过原因 | B50: =IF(COUNTIF(决策看板!$D$35:$D$64,"未通过")>0,"参数校验未通过；","")&IF(F34="未通过","项目税后IRR未达标；",IF(F34="待判断","项目税后IRR无法计算；",""))&IF(F35="未通过","资本金IRR未达标；",IF(F35="待判断","资本金IRR无法计算；",""))&IF(F36="未通过","项目NPV未达标；",IF(F36="待判断","项目NPV无法计算；",""))&IF(F37="未通过","资本金NPV未达标；",IF(F37="待判断","资本金NPV无法计算；",""))&IF(F38="未通过","静态回收期未达标；",IF(F38="待判断","静态回收期无法计算；",""))&IF(F39="未通过","动态回收期未达标；",IF(F39="待判断","动态回收期无法计算；",""))&IF(F40="未通过","最低偿债覆盖倍数未达标；",IF(F40="待判断","最低偿债覆盖倍数无法计算；",""))&IF(F41="未通过","所需累计资本金未达标；",IF(F41="待判断","所需累计资本金无法计算；",""))&IF(F42="未通过","未落实资金缺口最大值未达标；",IF(F42="待判断","未落实资金缺口最大值无法计算；",""))&IF(F43="未通过","贷款到期未偿本金未达标；",IF(F43="待判断","贷款到期未偿本金无法计算；","")) -> 项目税后IRR未达标；资本金IRR未达标；项目NPV未达标；资本金NPV未达标；静态回收期未达标；动态回收期未达标；最低偿债覆盖倍数未达标；所需累计资本金未达标；未落实资金缺口最大值未达标；

Sheet 决策看板
A2: 决策看板 · 模拟数据
A5: =IF(OR(LEFT(指标与情景测算!B46,3)="待判断",AND(核心参数输入!$B$82=1,LEFT(指标与情景测算!E46,3)="待判断")),"待判断：请检查参数",IF(AND(指标与情景测算!B46="通过",OR(核心参数输入!$B$82=0,指标与情景测算!E46="通过")),"通过：当前模拟参数下具备投资条件","未通过")) -> 未通过
A8: 项目名称 | B8: =核心参数输入!$B$7 -> 模拟产业园 · 租售结合 | E8: 可经营面积（平方米） | G8: =建筑面积与开发计划!$B$8 -> 135000
A9: 测算期限（年） | B9: =核心参数输入!$B$9 -> 20 | E9: 销售 / 出租比例 | G9: =TEXT(核心参数输入!$B$14,"0%")&" / "&TEXT(核心参数输入!$B$15,"0%") -> 55% / 45%
A10: 地上面积（平方米） | B10: =建筑面积与开发计划!$B$7 -> 150000 | E10: 持有面积（平方米） | G10: =建筑面积与开发计划!$B$10 -> 60750
A11: 项目总投资（万元） | B11: =指标与情景测算!B16 -> 63310 | E11: 贷款（万元） | G11: =核心参数输入!$B$57 -> 30000
A12: 所需资本金（万元） | B12: =指标与情景测算!B13 -> 32810 | E12: 资本金额度（万元） | G12: =核心参数输入!$B$61 -> 33000
A13: 最大未落实缺口（万元） | B13: =指标与情景测算!B14 -> 0 | E13: 压力情景是否须通过 | G13: =IF(核心参数输入!$B$82=1,"是","否，仅供观察") -> 否，仅供观察
A15: =指标与情景测算!B48&IF(核心参数输入!$B$82=1," 压力情景："&指标与情景测算!B50,"") -> 项目税后IRR未达标；资本金IRR未达标；项目NPV未达标；资本金NPV未达标；静态回收期未达标；动态回收期未达标；最低偿债覆盖倍数未达标；
A18: 指标 / 安全条件 | B18: 基准值 | C18: 通过标准 | D18: 状态 | E18: 压力值 | F18: 压力状态
A19: 项目税后IRR | B19: =指标与情景测算!B34 -> -0.011985485 | C19: =指标与情景测算!C34 -> 0.08 | D19: =指标与情景测算!D34 -> 未通过 | E19: =指标与情景测算!E34 -> -0.045961145 | F19: =指标与情景测算!F34 -> 未通过
A20: 资本金IRR | B20: =指标与情景测算!B35 -> -0.03575104 | C20: =指标与情景测算!C35 -> 0.1 | D20: =指标与情景测算!D35 -> 未通过 | E20: =指标与情景测算!E35 -> -0.079012248 | F20: =指标与情景测算!F35 -> 未通过
A21: 项目NPV | B21: =指标与情景测算!B36 -> -19528.19 | C21: =指标与情景测算!C36 -> 0 | D21: =指标与情景测算!D36 -> 未通过 | E21: =指标与情景测算!E36 -> -27383.782 | F21: =指标与情景测算!F36 -> 未通过
A22: 资本金NPV | B22: =指标与情景测算!B37 -> -17639.683 | C22: =指标与情景测算!C37 -> 0 | D22: =指标与情景测算!D37 -> 未通过 | E22: =指标与情景测算!E37 -> -25789.873 | F22: =指标与情景测算!F37 -> 未通过
A23: 静态回收期 | B23: =指标与情景测算!B38 -> 测算期内未回收 | C23: =指标与情景测算!C38 -> 15 | D23: =指标与情景测算!D38 -> 未通过 | E23: =指标与情景测算!E38 -> 测算期内未回收 | F23: =指标与情景测算!F38 -> 未通过
A24: 动态回收期 | B24: =指标与情景测算!B39 -> 测算期内未回收 | C24: =指标与情景测算!C39 -> 20 | D24: =指标与情景测算!D39 -> 未通过 | E24: =指标与情景测算!E39 -> 测算期内未回收 | F24: =指标与情景测算!F39 -> 未通过
A25: 最低偿债覆盖倍数 | B25: =指标与情景测算!B40 -> 0.20055108 | C25: =指标与情景测算!C40 -> 1.2 | D25: =指标与情景测算!D40 -> 未通过 | E25: =指标与情景测算!E40 -> 0.13973931 | F25: =指标与情景测算!F40 -> 未通过
A26: 所需累计资本金 | B26: =指标与情景测算!B41 -> 32810 | C26: =指标与情景测算!C41 -> 33000 | D26: =指标与情景测算!D41 -> 通过 | E26: =指标与情景测算!E41 -> 38102 | F26: =指标与情景测算!F41 -> 未通过
A27: 未落实资金缺口最大值 | B27: =指标与情景测算!B42 -> 0 | C27: =指标与情景测算!C42 -> 0 | D27: =指标与情景测算!D42 -> 通过 | E27: =指标与情景测算!E42 -> 5102 | F27: =指标与情景测算!F42 -> 未通过
A28: 贷款到期未偿本金 | B28: =指标与情景测算!B43 -> 0 | C28: =指标与情景测算!C43 -> 0 | D28: =指标与情景测算!D43 -> 通过 | E28: =指标与情景测算!E43 -> 0 | F28: =指标与情景测算!F43 -> 通过
A30: =指标与情景测算!B27&"；"&指标与情景测算!B25 -> 按完整出资计划测算；单次变号或无变号
A33: 参数与计算校验（两种情景均核对；全部通过才可作出投资判断）
A34: 校验项目 | B34: 说明 / 校验口径 | D34: 结果
A35: 必填输入完整 | B35: 数值必填，年度计划不得留空 | D35: =IF(AND(COUNT(核心参数输入!$B$8,核心参数输入!$B$9,核心参数输入!$B$10,核心参数输入!$B$11,核心参数输入!$B$12,核心参数输入!$B$13,核心参数输入!$B$14,核心参数输入!$B$16,核心参数输入!$B$17,核心参数输入!$B$18,核心参数输入!$B$21,核心参数输入!$B$22,核心参数输入!$B$23,核心参数输入!$B$24,核心参数输入!$B$25,核心参数输入!$B$26,核心参数输入!$B$27,核心参数输入!$B$28,核心参数输入!$B$31,核心参数输入!$B$32,核心参数输入!$B$33,核心参数输入!$B$36,核心参数输入!$B$37,核心参数输入!$B$38,核心参数输入!$B$39,核心参数输入!$B$40,核心参数输入!$B$41,核心参数输入!$B$42,核心参数输入!$B$43,核心参数输入!$B$44,核心参数输入!$B$47,核心参数输入!$B$48,核心参数输入!$B$49,核心参数输入!$B$50,核心参数输入!$B$51,核心参数输入!$B$52,核心参数输入!$B$53,核心参数输入!$B$54,核心参数输入!$B$57,核心参数输入!$B$58,核心参数输入!$B$59,核心参数输入!$B$60,核心参数输入!$B$61,核心参数输入!$B$64,核心参数输入!$B$65,核心参数输入!$B$66,核心参数输入!$B$69,核心参数输入!$B$70,核心参数输入!$B$71,核心参数输入!$B$72,核心参数输入!$B$73,核心参数输入!$B$74,核心参数输入!$B$75,核心参数输入!$B$78,核心参数输入!$B$79,核心参数输入!$B$80,核心参数输入!$B$81,核心参数输入!$B$82)=58,COUNT(核心参数输入!$D$88:$AH$88)=31,COUNT(核心参数输入!$D$89:$AH$89)=31,核心参数输入!$B$7<>""),"通过","未通过") -> 通过
A36: 测算期限与建设年限 | B36: 整数，1≤建设年限<期限≤30 | D36: =IF(AND(核心参数输入!$B$9=INT(核心参数输入!$B$9),核心参数输入!$B$9<=30,核心参数输入!$B$16=INT(核心参数输入!$B$16),核心参数输入!$B$16>=1,核心参数输入!$B$9>核心参数输入!$B$16),"通过","未通过") -> 通过
A37: 面积与租售比例 | B37: 面积>0，经营比例及销售出租比例有效 | D37: =IF(AND(核心参数输入!$B$10>0,核心参数输入!$B$11>0,核心参数输入!$B$13>=0,核心参数输入!$B$12>0,核心参数输入!$B$12<=1,核心参数输入!$B$14>0,核心参数输入!$B$14<1),"通过","未通过") -> 通过
A38: 面积分解平衡 | B38: 可售＋持有＝可经营 | D38: =IF(ABS(建筑面积与开发计划!$B$9+建筑面积与开发计划!$B$10-建筑面积与开发计划!$B$8)<=0.01,"通过","未通过") -> 通过
A39: 建设计划合计 | B39: 非土地建设比例累计100%，非负 | D39: =IF(AND(ABS(SUM(核心参数输入!$D$88:$AH$88)-1)<=0.000001,MIN(核心参数输入!$D$88:$AH$88)>=0,MAX(核心参数输入!$D$88:$AH$88)<=1),"通过","未通过") -> 通过
A40: 建设计划时点 | B40: 第0年及建设期外不得安排建设 | D40: =IF(SUMPRODUCT(核心参数输入!$D$88:$AH$88,--((核心参数输入!$D$87:$AH$87<1)+(核心参数输入!$D$87:$AH$87>核心参数输入!$B$16)))=0,"通过","未通过") -> 通过
A41: 销售计划合计 | B41: 累计不超过100%，允许未售存货 | D41: =IF(AND(SUM(核心参数输入!$D$89:$AH$89)<=1.000001,MIN(核心参数输入!$D$89:$AH$89)>=0,MAX(核心参数输入!$D$89:$AH$89)<=1),"通过","未通过") -> 通过
A42: 销售计划时点 | B42: 早于销售开始或超出期限不得销售 | D42: =IF(SUMPRODUCT(核心参数输入!$D$89:$AH$89,--((核心参数输入!$D$87:$AH$87<核心参数输入!$B$17)+(核心参数输入!$D$87:$AH$87>核心参数输入!$B$9)))=0,"通过","未通过") -> 通过
A43: 开发时点 | B43: 销售出租都在建成后且在期内开始 | D43: =IF(AND(核心参数输入!$B$17>核心参数输入!$B$16,核心参数输入!$B$18>核心参数输入!$B$16,核心参数输入!$B$17<=核心参数输入!$B$9,核心参数输入!$B$18<=核心参数输入!$B$9,核心参数输入!$B$17=INT(核心参数输入!$B$17),核心参数输入!$B$18=INT(核心参数输入!$B$18)),"通过","未通过") -> 通过
A44: 出租率与爬坡 | B44: 0≤首年≤次年≤第三年≤稳定率≤1 | D44: =IF(AND(核心参数输入!$B$38>=0,核心参数输入!$B$38<=核心参数输入!$B$39,核心参数输入!$B$39<=核心参数输入!$B$40,核心参数输入!$B$40<=核心参数输入!$B$41,核心参数输入!$B$41<=1),"通过","未通过") -> 通过
A45: 免租与收缴 | B45: 0—12月，收缴0—100% | D45: =IF(AND(核心参数输入!$B$42>=0,核心参数输入!$B$42<=12,核心参数输入!$B$43>0,核心参数输入!$B$43<=1),"通过","未通过") -> 通过
A46: 价格成本及额度非负 | B46: 全部金额/成本/贷款/额度非负 | D46: =IF(MIN(核心参数输入!$B$21,核心参数输入!$B$22,核心参数输入!$B$23,核心参数输入!$B$24,核心参数输入!$B$25,核心参数输入!$B$26,核心参数输入!$B$28,核心参数输入!$B$31,核心参数输入!$B$36,核心参数输入!$B$47,核心参数输入!$B$50,核心参数输入!$B$57,核心参数输入!$B$61,核心参数输入!$B$65)>=0,"通过","未通过") -> 通过
A47: 费用税率 | B47: 所有费用、税率、残值及预备费在0—1 | D47: =IF(AND(MIN(核心参数输入!$B$27,核心参数输入!$B$32,核心参数输入!$B$33,核心参数输入!$B$49,核心参数输入!$B$51,核心参数输入!$B$52,核心参数输入!$B$54,核心参数输入!$B$66,核心参数输入!$B$44)>=0,MAX(核心参数输入!$B$27,核心参数输入!$B$32,核心参数输入!$B$33,核心参数输入!$B$49,核心参数输入!$B$51,核心参数输入!$B$52,核心参数输入!$B$54,核心参数输入!$B$66,核心参数输入!$B$44)<=1),"通过","未通过") -> 通过
A48: 增长率折现率及利率 | B48: 增长>-100%；折现率非负，贷款利率0—100% | D48: =IF(AND(核心参数输入!$B$37>-1,核心参数输入!$B$48>-1,核心参数输入!$B$58>=0,核心参数输入!$B$58<=1,核心参数输入!$B$71>=0,核心参数输入!$B$72>=0),"通过","未通过") -> 通过
A49: 折旧年限 | B49: 折旧年限为1—100整数 | D49: =IF(AND(核心参数输入!$B$53>=1,核心参数输入!$B$53<=100,核心参数输入!$B$53=INT(核心参数输入!$B$53)),"通过","未通过") -> 通过
A50: 贷款金额与建设需求 | B50: 贷款不能超过基准非土地建设成本 | D50: =IF(核心参数输入!$B$57<=投资与资金安排!$B$14+0.01,"通过","未通过") -> 通过
A51: 贷款期限及偿还时点 | B51: 建设后开始还本，期限从首次提款年计 | D51: =IF(OR(核心参数输入!$B$57=0,AND(核心参数输入!$B$59>=1,核心参数输入!$B$59=INT(核心参数输入!$B$59),核心参数输入!$B$60=INT(核心参数输入!$B$60),核心参数输入!$B$60>核心参数输入!$B$16,核心参数输入!$B$60<=融资与还本付息!$B$7)),"通过","未通过") -> 通过
A52: 期限覆盖贷款到期 | B52: N≥首次提款年＋期限－1 | D52: =IF(OR(核心参数输入!$B$57=0,核心参数输入!$B$9>=融资与还本付息!$B$7),"通过","未通过") -> 通过
A53: 贷款提款总量 | B53: 两情景均按计划提款，不自动增贷 | D53: =IF(AND(ABS(SUM(融资与还本付息!$D$11:$AH$11)-核心参数输入!$B$57)<=0.01,ABS(SUM(融资与还本付息!$D$91:$AH$91)-核心参数输入!$B$57)<=0.01),"通过","未通过") -> 通过
A54: 贷款余额与还本平衡 | B54: 提款－还本＝期末本金，余额非负 | D54: =IF(AND(ABS(SUM(融资与还本付息!$D$11:$AH$11)-SUM(融资与还本付息!$D$13:$AH$13)-INDEX(融资与还本付息!$D$15:$AH$15,核心参数输入!$B$9+1))<=0.01,ABS(SUM(融资与还本付息!$D$91:$AH$91)-SUM(融资与还本付息!$D$93:$AH$93)-INDEX(融资与还本付息!$D$95:$AH$95,核心参数输入!$B$9+1))<=0.01),"通过","未通过") -> 通过
A55: 理论资金平衡 | B55: 期初＋净流＋出资－分配＝期末 | D55: =IF(AND(SUMPRODUCT(ABS(利润与现金流!$D$59:$AH$59))<=0.01,SUMPRODUCT(ABS(利润与现金流!$D$139:$AH$139))<=0.01),"通过","未通过") -> 通过
A56: 额度内资金平衡 | B56: 缺口作为待落实支出，不当成现金 | D56: =IF(AND(SUMPRODUCT(ABS(利润与现金流!$D$60:$AH$60))<=0.01,SUMPRODUCT(ABS(利润与现金流!$D$140:$AH$140))<=0.01),"通过","未通过") -> 通过
A57: 资本金不突破额度 | B57: 累计实际可投不超过输入额度 | D57: =IF(AND(SUM(利润与现金流!$D$42:$AH$42)<=核心参数输入!$B$61+0.01,SUM(利润与现金流!$D$122:$AH$122)<=核心参数输入!$B$61+0.01),"通过","未通过") -> 通过
A58: 留存后不立即补资 | B58: 分配后不再出现计划内追加资本金 | D58: =IF(AND(MAX(利润与现金流!$D$61:$AH$61)<=0.01,MAX(利润与现金流!$D$141:$AH$141)<=0.01),"通过","未通过") -> 通过
A59: 压力参数范围 | B59: 下降比例0—100%，出租率按百分点 | D59: =IF(AND(核心参数输入!$B$78>=0,核心参数输入!$B$78<=1,核心参数输入!$B$79>=0,核心参数输入!$B$79<=1,核心参数输入!$B$80>=0,核心参数输入!$B$80<=100,核心参数输入!$B$81>=0),"通过","未通过") -> 通过
A60: 开关参数 | B60: 两个开关均为0或1 | D60: =IF(AND(OR(核心参数输入!$B$64=0,核心参数输入!$B$64=1),OR(核心参数输入!$B$82=0,核心参数输入!$B$82=1)),"通过","未通过") -> 通过
A61: 总投资现金核对 | B61: 支付投资合计＝总投资（不扣周转回收） | D61: =IF(AND(ABS(SUM(投资与资金安排!$D$35:$AH$35)-投资与资金安排!$B$18)<=0.01,ABS(SUM(投资与资金安排!$D$115:$AH$115)-投资与资金安排!$B$98)<=0.01),"通过","未通过") -> 通过
A62: 第N年回收与处置时点 | B62: 周转仅期末回收，处置仅持有物业 | D62: =IF(AND(ABS(SUM(投资与资金安排!$D$32:$AH$32)-核心参数输入!$B$28)<=0.01,ABS(SUM(投资与资金安排!$D$112:$AH$112)-核心参数输入!$B$28)<=0.01),"通过","未通过") -> 通过
A63: 判断标准有效 | B63: IRR阈值非负、回收期上限及DSCR>0 | D63: =IF(AND(核心参数输入!$B$69>=0,核心参数输入!$B$70>=0,核心参数输入!$B$73>0,核心参数输入!$B$74>0,核心参数输入!$B$75>0),"通过","未通过") -> 通过
A64: 项目有投资且持有分摊合理 | B64: 总投资>0；销售＋持有分摊开发成本一致 | D64: =IF(AND(投资与资金安排!$B$18>0,ABS(投资与资金安排!$B$22+投资与资金安排!$B$23+投资与资金安排!$B$21-投资与资金安排!$B$16)<=0.01),"通过","未通过") -> 通过
A66: 基准情景图表 · 修改输入及期限后自动更新
A120: 项目年度 | B120: 销售收入 | C120: 实收租金 | D120: 其他收入 | E120: 可用于偿债现金 | F120: 应还本息 | G120: 累计项目现金流 | H120: 累计折现现金流
A121: =核心参数输入!D87 -> 0 | B121: =销售与出租收入!D13 -> 0 | C121: =销售与出租收入!D20 -> 0 | D121: =销售与出租收入!D21 -> 0 | E121: =利润与现金流!D19 -> 0 | F121: =融资与还本付息!D18 -> 0 | G121: =利润与现金流!D49 -> -8000 | H121: =利润与现金流!D51 -> -8000
A122: =核心参数输入!E87 -> 1 | B122: =销售与出租收入!E13 -> 0 | C122: =销售与出租收入!E20 -> 0 | D122: =销售与出租收入!E21 -> 0 | E122: =利润与现金流!E19 -> 0 | F122: =融资与还本付息!E18 -> 189 | G122: =利润与现金流!E49 -> -23876 | H122: =利润与现金流!E51 -> -22700
A123: =核心参数输入!F87 -> 2 | B123: =销售与出租收入!F13 -> 0 | C123: =销售与出租收入!F20 -> 0 | D123: =销售与出租收入!F21 -> 0 | E123: =利润与现金流!F19 -> 0 | F123: =融资与还本付息!F18 -> 630 | G123: =利润与现金流!F49 -> -45044 | H123: =利润与现金流!F51 -> -40848.148
A124: =核心参数输入!G87 -> 3 | B124: =销售与出租收入!G13 -> 0 | C124: =销售与出租收入!G20 -> 0 | D124: =销售与出租收入!G21 -> 0 | E124: =利润与现金流!G19 -> 0 | F124: =融资与还本付息!G18 -> 1071 | G124: =利润与现金流!G49 -> -60920 | H124: =利润与现金流!G51 -> -53451.029
A125: =核心参数输入!H87 -> 4 | B125: =销售与出租收入!H13 -> 14478.75 | C125: =销售与出租收入!H20 -> 696.5595 | D125: =销售与出租收入!H21 -> 34.827975 | E125: =利润与现金流!H19 -> 12887.337 | F125: =融资与还本付息!H18 -> 5455.7143 | G125: =利润与现金流!H49 -> -48909.858 | H125: =利润与现金流!H51 -> -44623.216
A126: =核心参数输入!I87 -> 5 | B126: =销售与出租收入!I13 -> 19305 | C126: =销售与出租收入!I20 -> 1225.4803 | D126: =销售与出租收入!I21 -> 61.274017 | E126: =利润与现金流!I19 -> 17282.646 | F126: =融资与还本付息!I18 -> 5275.7143 | G126: =利润与现金流!I49 -> -31985.396 | H126: =利润与现金流!I51 -> -33104.711
A127: =核心参数输入!J87 -> 6 | B127: =销售与出租收入!J13 -> 14478.75 | C127: =销售与出租收入!J20 -> 1554.8282 | D127: =销售与出租收入!J21 -> 77.74141 | E127: =利润与现金流!J19 -> 13342.474 | F127: =融资与还本付息!J18 -> 5095.7143 | G127: =利润与现金流!J49 -> -18930.117 | H127: =利润与现金流!J51 -> -24877.671
A128: =核心参数输入!K87 -> 7 | B128: =销售与出租收入!K13 -> 0 | C128: =销售与出租收入!K20 -> 1723.8261 | D128: =销售与出租收入!K21 -> 86.191303 | E128: =利润与现金流!K19 -> 985.85183 | F128: =融资与还本付息!K18 -> 4915.7143 | G128: =利润与现金流!K49 -> -18002.2 | H128: =利润与现金流!K51 -> -24336.241
A129: =核心参数输入!L87 -> 8 | B129: =销售与出租收入!L13 -> 0 | C129: =销售与出租收入!L20 -> 1774.3269 | D129: =销售与出租收入!L21 -> 88.716344 | E129: =利润与现金流!L19 -> 1022.9658 | F129: =融资与还本付息!L18 -> 4735.7143 | G129: =利润与现金流!L49 -> -17046.449 | H129: =利润与现金流!L51 -> -23819.878
A130: =核心参数输入!M87 -> 9 | B130: =销售与出租收入!M13 -> 0 | C130: =销售与出租收入!M20 -> 1800.9418 | D130: =销售与出租收入!M21 -> 90.047089 | E130: =利润与现金流!M19 -> 1039.3866 | F130: =融资与还本付息!M18 -> 4555.7143 | G130: =利润与现金流!M49 -> -16078.381 | H130: =利润与现金流!M51 -> -23335.603
A131: =核心参数输入!N87 -> 10 | B131: =销售与出租收入!N13 -> 0 | C131: =销售与出租收入!N20 -> 1827.9559 | D131: =销售与出租收入!N21 -> 91.397795 | E131: =利润与现金流!N19 -> 1009.7766 | F131: =融资与还本付息!N18 -> 4375.7143 | G131: =利润与现金流!N49 -> -15097.838 | H131: =利润与现金流!N51 -> -22881.422
A132: =核心参数输入!O87 -> 11 | B132: =销售与出租收入!O13 -> 0 | C132: =销售与出租收入!O20 -> 1855.3752 | D132: =销售与出租收入!O21 -> 92.768762 | E132: =利润与现金流!O19 -> 999.91491 | F132: =融资与还本付息!O18 -> 0 | G132: =利润与现金流!O49 -> -14104.656 | H132: =利润与现金流!O51 -> -22455.463
A133: =核心参数输入!P87 -> 12 | B133: =销售与出租收入!P13 -> 0 | C133: =销售与出租收入!P20 -> 1883.2059 | D133: =销售与出租收入!P21 -> 94.160294 | E133: =利润与现金流!P19 -> 1012.7175 | F133: =融资与还本付息!P18 -> 0 | G133: =利润与现金流!P49 -> -13098.672 | H133: =利润与现金流!P51 -> -22055.973
A134: =核心参数输入!Q87 -> 13 | B134: =销售与出租收入!Q13 -> 0 | C134: =销售与出租收入!Q20 -> 1911.454 | D134: =销售与出租收入!Q21 -> 95.572698 | E134: =利润与现金流!Q19 -> 1025.6862 | F134: =融资与还本付息!Q18 -> 0 | G134: =利润与现金流!Q49 -> -12079.718 | H134: =利润与现金流!Q51 -> -21681.306
A135: =核心参数输入!R87 -> 14 | B135: =销售与出租收入!R13 -> 0 | C135: =销售与出租收入!R20 -> 1940.1258 | D135: =销售与出租收入!R21 -> 97.006288 | E135: =利润与现金流!R19 -> 1038.8231 | F135: =融资与还本付息!R18 -> 0 | G135: =利润与现金流!R49 -> -11047.629 | H135: =利润与现金流!R51 -> -21329.919
A136: =核心参数输入!S87 -> 15 | B136: =销售与出租收入!S13 -> 0 | C136: =销售与出租收入!S20 -> 1969.2277 | D136: =销售与出租收入!S21 -> 98.461383 | E136: =利润与现金流!S19 -> 1052.1302 | F136: =融资与还本付息!S18 -> 0 | G136: =利润与现金流!S49 -> -10002.231 | H136: =利润与现金流!S51 -> -21000.367
A137: =核心参数输入!T87 -> 16 | B137: =销售与出租收入!T13 -> 0 | C137: =销售与出租收入!T20 -> 1998.7661 | D137: =销售与出租收入!T21 -> 99.938303 | E137: =利润与现金流!T19 -> 1065.6094 | F137: =融资与还本付息!T18 -> 0 | G137: =利润与现金流!T49 -> -8943.3552 | H137: =利润与现金流!T51 -> -20691.291
A138: =核心参数输入!U87 -> 17 | B138: =销售与出租收入!U13 -> 0 | C138: =销售与出租收入!U20 -> 2028.7476 | D138: =销售与出租收入!U21 -> 101.43738 | E138: =利润与现金流!U19 -> 1079.2629 | F138: =融资与还本付息!U18 -> 0 | G138: =利润与现金流!U49 -> -7870.8254 | H138: =利润与现金流!U51 -> -20401.419
A139: =核心参数输入!V87 -> 18 | B139: =销售与出租收入!V13 -> 0 | C139: =销售与出租收入!V20 -> 2059.1788 | D139: =销售与出租收入!V21 -> 102.95894 | E139: =利润与现金流!V19 -> 1093.0926 | F139: =融资与还本付息!V18 -> 0 | G139: =利润与现金流!V49 -> -6784.466 | H139: =利润与现金流!V51 -> -20129.559
A140: =核心参数输入!W87 -> 19 | B140: =销售与出租收入!W13 -> 0 | C140: =销售与出租收入!W20 -> 2090.0665 | D140: =销售与出租收入!W21 -> 104.50332 | E140: =利润与现金流!W19 -> 1107.1007 | F140: =融资与还本付息!W18 -> 0 | G140: =利润与现金流!W49 -> -5684.0984 | H140: =利润与现金流!W51 -> -19874.59
A141: =核心参数输入!X87 -> 20 | B141: =销售与出租收入!X13 -> 0 | C141: =销售与出租收入!X20 -> 2121.4175 | D141: =销售与出租收入!X21 -> 106.07087 | E141: =利润与现金流!X19 -> 1121.2892 | F141: =融资与还本付息!X18 -> 0 | G141: =利润与现金流!X49 -> -4069.5424 | H141: =利润与现金流!X51 -> -19528.19
A142: =核心参数输入!Y87 -> 21 | B142: =销售与出租收入!Y13 -> 0 | C142: =销售与出租收入!Y20 -> 0 | D142: =销售与出租收入!Y21 -> 0 | E142: =利润与现金流!Y19 -> 0 | F142: =融资与还本付息!Y18 -> 0 | G142: =利润与现金流!Y49 -> 0 | H142: =利润与现金流!Y51 -> 0
A143: =核心参数输入!Z87 -> 22 | B143: =销售与出租收入!Z13 -> 0 | C143: =销售与出租收入!Z20 -> 0 | D143: =销售与出租收入!Z21 -> 0 | E143: =利润与现金流!Z19 -> 0 | F143: =融资与还本付息!Z18 -> 0 | G143: =利润与现金流!Z49 -> 0 | H143: =利润与现金流!Z51 -> 0
A144: =核心参数输入!AA87 -> 23 | B144: =销售与出租收入!AA13 -> 0 | C144: =销售与出租收入!AA20 -> 0 | D144: =销售与出租收入!AA21 -> 0 | E144: =利润与现金流!AA19 -> 0 | F144: =融资与还本付息!AA18 -> 0 | G144: =利润与现金流!AA49 -> 0 | H144: =利润与现金流!AA51 -> 0
A145: =核心参数输入!AB87 -> 24 | B145: =销售与出租收入!AB13 -> 0 | C145: =销售与出租收入!AB20 -> 0 | D145: =销售与出租收入!AB21 -> 0 | E145: =利润与现金流!AB19 -> 0 | F145: =融资与还本付息!AB18 -> 0 | G145: =利润与现金流!AB49 -> 0 | H145: =利润与现金流!AB51 -> 0
A146: =核心参数输入!AC87 -> 25 | B146: =销售与出租收入!AC13 -> 0 | C146: =销售与出租收入!AC20 -> 0 | D146: =销售与出租收入!AC21 -> 0 | E146: =利润与现金流!AC19 -> 0 | F146: =融资与还本付息!AC18 -> 0 | G146: =利润与现金流!AC49 -> 0 | H146: =利润与现金流!AC51 -> 0
A147: =核心参数输入!AD87 -> 26 | B147: =销售与出租收入!AD13 -> 0 | C147: =销售与出租收入!AD20 -> 0 | D147: =销售与出租收入!AD21 -> 0 | E147: =利润与现金流!AD19 -> 0 | F147: =融资与还本付息!AD18 -> 0 | G147: =利润与现金流!AD49 -> 0 | H147: =利润与现金流!AD51 -> 0
A148: =核心参数输入!AE87 -> 27 | B148: =销售与出租收入!AE13 -> 0 | C148: =销售与出租收入!AE20 -> 0 | D148: =销售与出租收入!AE21 -> 0 | E148: =利润与现金流!AE19 -> 0 | F148: =融资与还本付息!AE18 -> 0 | G148: =利润与现金流!AE49 -> 0 | H148: =利润与现金流!AE51 -> 0
A149: =核心参数输入!AF87 -> 28 | B149: =销售与出租收入!AF13 -> 0 | C149: =销售与出租收入!AF20 -> 0 | D149: =销售与出租收入!AF21 -> 0 | E149: =利润与现金流!AF19 -> 0 | F149: =融资与还本付息!AF18 -> 0 | G149: =利润与现金流!AF49 -> 0 | H149: =利润与现金流!AF51 -> 0
A150: =核心参数输入!AG87 -> 29 | B150: =销售与出租收入!AG13 -> 0 | C150: =销售与出租收入!AG20 -> 0 | D150: =销售与出租收入!AG21 -> 0 | E150: =利润与现金流!AG19 -> 0 | F150: =融资与还本付息!AG18 -> 0 | G150: =利润与现金流!AG49 -> 0 | H150: =利润与现金流!AG51 -> 0
A151: =核心参数输入!AH87 -> 30 | B151: =销售与出租收入!AH13 -> 0 | C151: =销售与出租收入!AH20 -> 0 | D151: =销售与出租收入!AH21 -> 0 | E151: =利润与现金流!AH19 -> 0 | F151: =融资与还本付息!AH18 -> 0 | G151: =利润与现金流!AH49 -> 0 | H151: =利润与现金流!AH51 -> 0
