Workbook
Name V3ChartCash: 决策看板!$D$81:INDEX(决策看板!$D$81:$D$111,核心参数输入!$B$9+1)
Name V3ChartCFADS: 决策看板!$B$81:INDEX(决策看板!$B$81:$B$111,核心参数输入!$B$9+1)
Name V3ChartDistribution: 决策看板!$G$81:INDEX(决策看板!$G$81:$G$111,核心参数输入!$B$9+1)
Name V3ChartEquity: 决策看板!$F$81:INDEX(决策看板!$F$81:$F$111,核心参数输入!$B$9+1)
Name V3ChartGap: 决策看板!$E$81:INDEX(决策看板!$E$81:$E$111,核心参数输入!$B$9+1)
Name V3ChartService: 决策看板!$C$81:INDEX(决策看板!$C$81:$C$111,核心参数输入!$B$9+1)
Name V3ChartYear: 决策看板!$A$81:INDEX(决策看板!$A$81:$A$111,核心参数输入!$B$9+1)

Sheet 决策看板
A2: 决策看板 · V3模拟测算
A4: =IF(OR(指标与情景!B49=0,AND(核心参数输入!$B$82=1,指标与情景!E49=0)),"待判断：输入或计划条件无效",IF(AND(指标与情景!B50=1,OR(核心参数输入!$B$82=0,指标与情景!E50=1)),IF(核心参数输入!$B$97=1,"已纳入模型的财务条件达标","财务条件达标；新增假设待项目核对"),"已纳入模型的财务条件未全部达标")) -> 已纳入模型的财务条件未全部达标
A7: 项目名称 | B7: =核心参数输入!$B$7 -> 模拟产业园 · 租售结合 | E7: 经营模式 | F7: =核心参数输入!$B$149 -> 租售结合
A8: 当前期末口径 | B8: =IF(核心参数输入!$B$64=1,"期末出售持有物业","持续持有观察期") -> 持续持有观察期 | E8: 测算期限（年） | F8: =核心参数输入!$B$9 -> 20
A9: 总投资（万元） | B9: =指标与情景!B16 -> 63310 | E9: 既定贷款（万元） | F9: =核心参数输入!$B$57 -> 30000
A10: 所需累计资本金（万元） | B10: =指标与情景!B13 -> 32810 | E10: 资本金额度（万元） | F10: =核心参数输入!$B$61 -> 33000
A11: 最大未落实缺口（万元） | B11: =指标与情景!B14 -> 0 | E11: 缺口发生季度 | F11: =指标与情景!B31 -> 无未落实缺口
A12: 融资前峰值需要（万元） | B12: =指标与情景!B29 -> 62810 | E12: 峰值发生季度 | F12: =指标与情景!B30 -> 2029Q4
A13: 理论最大留存现金（万元） | B13: =指标与情景!B47 -> 15161.955 | E13: 收益口径 | F13: =指标与情景!B27 -> 完整出资、留存后分配口径
A15: =核心参数输入!$B$152&"；季度计算、年度汇总；"&指标与情景!B54 -> 综合税费率（沿用V2）；季度计算、年度汇总；新增假设待项目核对
A17: 指标／资金约束 | B17: 基准 | C17: 单位 | D17: 阈值 | E17: 压力 | F17: 基准状态 | G17: 压力状态
A18: 项目税后IRR（年化） | B18: =指标与情景!B6 -> -0.014445335 | C18: =指标与情景!C6 -> % | D18: =指标与情景!D6 -> 0.08 | E18: =指标与情景!E6 -> -0.049549603 | F18: =指标与情景!F6 -> 未通过 | G18: =指标与情景!G6 -> 未通过
A19: 资本金IRR（年化） | B19: =指标与情景!B7 -> -0.040676665 | C19: =指标与情景!C7 -> % | D19: =指标与情景!D7 -> 0.1 | E19: =指标与情景!E7 -> -0.087463531 | F19: =指标与情景!F7 -> 未通过 | G19: =指标与情景!G7 -> 未通过
A20: 项目NPV | B20: =指标与情景!B8 -> -20406.095 | C20: =指标与情景!C8 -> 万元 | D20: =指标与情景!D8 -> 0 | E20: =指标与情景!E8 -> -28525.14 | F20: =指标与情景!F8 -> 未通过 | G20: =指标与情景!G8 -> 未通过
A21: 资本金NPV | B21: =指标与情景!B9 -> -18467.837 | C21: =指标与情景!C9 -> 万元 | D21: =指标与情景!D9 -> 0 | E21: =指标与情景!E9 -> -27195.962 | F21: =指标与情景!F9 -> 未通过 | G21: =指标与情景!G9 -> 未通过
A22: 静态投资回收期 | B22: =指标与情景!B10 -> 测算期内未回收 | C22: =指标与情景!C10 -> 年 | D22: =指标与情景!D10 -> 15 | E22: =指标与情景!E10 -> 测算期内未回收 | F22: =指标与情景!F10 -> 未通过 | G22: =指标与情景!G10 -> 未通过
A23: 动态投资回收期 | B23: =指标与情景!B11 -> 测算期内未回收 | C23: =指标与情景!C11 -> 年 | D23: =指标与情景!D11 -> 20 | E23: =指标与情景!E11 -> 测算期内未回收 | F23: =指标与情景!F11 -> 未通过 | G23: =指标与情景!G11 -> 未通过
A24: 最低年度经营DSCR | B24: =指标与情景!B12 -> 0.21197153 | C24: =指标与情景!C12 -> 倍 | D24: =指标与情景!D12 -> 1.2 | E24: =指标与情景!E12 -> 0.14850575 | F24: =指标与情景!F12 -> 未通过 | G24: =指标与情景!G12 -> 未通过
A25: 所需累计资本金 | B25: =指标与情景!B13 -> 32810 | C25: =指标与情景!C13 -> 万元 | D25: =指标与情景!D13 -> 33000 | E25: =指标与情景!E13 -> 38102 | F25: =指标与情景!F13 -> 通过 | G25: =指标与情景!G13 -> 未通过
A26: 最大未落实资金缺口 | B26: =指标与情景!B14 -> 0 | C26: =指标与情景!C14 -> 万元 | D26: =指标与情景!D14 -> 0 | E26: =指标与情景!E14 -> 5102 | F26: =指标与情景!F14 -> 通过 | G26: =指标与情景!G14 -> 未通过
A27: 到期计划本金余额 | B27: =指标与情景!B15 -> 0 | C27: =指标与情景!C15 -> 万元 | D27: =指标与情景!D15 -> 0 | E27: =指标与情景!E15 -> 0 | F27: =指标与情景!F15 -> 通过 | G27: =指标与情景!G15 -> 通过
A29: 持续持有与期末出售（同一经营、融资假设）
A30: 指标 | B30: 持续持有 | D30: 期末出售 | F30: 说明
A31: 项目IRR | B31: =指标与情景!B38 -> -0.014445335 | D31: =指标与情景!B39 -> 0.033744637 | F31: %
A32: 项目NPV | B32: =指标与情景!B40 -> -20406.095 | D32: =指标与情景!B41 -> -14899.172 | F32: 万元
A33: 资本金IRR | B33: =指标与情景!B42 -> -0.040676665 | D33: =指标与情景!B43 -> 0.030390403 | F33: %
A35: 最低经营DSCR发生年度 | B35: =指标与情景!B48 -> 2034 | E35: 稳定经营现金保本出租率 | F35: =指标与情景!B22 -> 0.29842494
A36: 期末销售应收（万元） | B36: =指标与情景!B34 -> 0 | E36: 持续持有账面净值（万元） | F36: =指标与情景!B45 -> 13762.777
A37: 累计净利润（万元） | B37: =指标与情景!B35 -> 4193.6056 | E37: 精确边界刷新状态 | F37: =敏感性与边界!B66 -> 与当前参数一致
A39: ="经营DSCR衡量当年经营现金；前期销售留存另行支持偿债。"&IF(指标与情景!B14>0.01," 存在未落实缺口，当前计划不能视为已执行。","")&" "&指标与情景!B25 -> 经营DSCR衡量当年经营现金；前期销售留存另行支持偿债。 单次变号或无变号
A41: ="所选季度月内最大缺口（万元）："&TEXT(关键月份核对!B33,"#,##0.00")&IF(关键月份核对!B35=1,"；该季度月度安排通过","；月度安排需调整") -> 所选季度月内最大缺口（万元）：0.00；该季度月度安排通过
A80: 项目年 | B80: 经营CFADS | C80: 合同本息 | D80: 年末留存 | E80: 未落实缺口 | F80: 所需股东出资 | G80: 股东分配 | H80: 累计项目现金
A81: =IF(0<=核心参数输入!$B$9,0,"") -> 0 | B81: =IF(0<=核心参数输入!$B$9,年度汇总!D22,"") -> 0 | C81: =IF(0<=核心参数输入!$B$9,年度汇总!D23,"") -> 0 | D81: =IF(0<=核心参数输入!$B$9,年度汇总!D29,"") -> 0 | E81: =IF(0<=核心参数输入!$B$9,年度汇总!D30,"") -> 0 | F81: =IF(0<=核心参数输入!$B$9,年度汇总!D27,"") -> 8000 | G81: =IF(0<=核心参数输入!$B$9,年度汇总!D28,"") -> 0 | H81: =IF(0<=核心参数输入!$B$9,年度汇总!D33,"") -> -8000
A82: =IF(1<=核心参数输入!$B$9,1,"") -> 1 | B82: =IF(1<=核心参数输入!$B$9,年度汇总!E22,"") -> 0 | C82: =IF(1<=核心参数输入!$B$9,年度汇总!E23,"") -> 177.1875 | D82: =IF(1<=核心参数输入!$B$9,年度汇总!E29,"") -> 0 | E82: =IF(1<=核心参数输入!$B$9,年度汇总!E30,"") -> 0 | F82: =IF(1<=核心参数输入!$B$9,年度汇总!E27,"") -> 7065 | G82: =IF(1<=核心参数输入!$B$9,年度汇总!E28,"") -> 0 | H82: =IF(1<=核心参数输入!$B$9,年度汇总!E33,"") -> -23876
A83: =IF(2<=核心参数输入!$B$9,2,"") -> 2 | B83: =IF(2<=核心参数输入!$B$9,年度汇总!F22,"") -> 0 | C83: =IF(2<=核心参数输入!$B$9,年度汇总!F23,"") -> 630 | D83: =IF(2<=核心参数输入!$B$9,年度汇总!F29,"") -> 0 | E83: =IF(2<=核心参数输入!$B$9,年度汇总!F30,"") -> 0 | F83: =IF(2<=核心参数输入!$B$9,年度汇总!F27,"") -> 9798 | G83: =IF(2<=核心参数输入!$B$9,年度汇总!F28,"") -> 0 | H83: =IF(2<=核心参数输入!$B$9,年度汇总!F33,"") -> -45044
A84: =IF(3<=核心参数输入!$B$9,3,"") -> 3 | B84: =IF(3<=核心参数输入!$B$9,年度汇总!G22,"") -> 0 | C84: =IF(3<=核心参数输入!$B$9,年度汇总!G23,"") -> 1071 | D84: =IF(3<=核心参数输入!$B$9,年度汇总!G29,"") -> 0 | E84: =IF(3<=核心参数输入!$B$9,年度汇总!G30,"") -> 0 | F84: =IF(3<=核心参数输入!$B$9,年度汇总!G27,"") -> 7947 | G84: =IF(3<=核心参数输入!$B$9,年度汇总!G28,"") -> 0 | H84: =IF(3<=核心参数输入!$B$9,年度汇总!G33,"") -> -60920
A85: =IF(4<=核心参数输入!$B$9,4,"") -> 4 | B85: =IF(4<=核心参数输入!$B$9,年度汇总!H22,"") -> 11554.939 | C85: =IF(4<=核心参数输入!$B$9,年度汇总!H23,"") -> 5523.2143 | D85: =IF(4<=核心参数输入!$B$9,年度汇总!H29,"") -> 0 | E85: =IF(4<=核心参数输入!$B$9,年度汇总!H30,"") -> 0 | F85: =IF(4<=核心参数输入!$B$9,年度汇总!H27,"") -> 0 | G85: =IF(4<=核心参数输入!$B$9,年度汇总!H28,"") -> 5531.7249 | H85: =IF(4<=核心参数输入!$B$9,年度汇总!H33,"") -> -50259.131
A86: =IF(5<=核心参数输入!$B$9,5,"") -> 5 | B86: =IF(5<=核心参数输入!$B$9,年度汇总!I22,"") -> 16821.455 | C86: =IF(5<=核心参数输入!$B$9,年度汇总!I23,"") -> 5343.2143 | D86: =IF(5<=核心参数输入!$B$9,年度汇总!I29,"") -> 5240.8689 | E86: =IF(5<=核心参数输入!$B$9,年度汇总!I30,"") -> 0 | F86: =IF(5<=核心参数输入!$B$9,年度汇总!I27,"") -> 0 | G86: =IF(5<=核心参数输入!$B$9,年度汇总!I28,"") -> 6237.3722 | H86: =IF(5<=核心参数输入!$B$9,年度汇总!I33,"") -> -33812.734
A87: =IF(6<=核心参数输入!$B$9,6,"") -> 6 | B87: =IF(6<=核心参数输入!$B$9,年度汇总!J22,"") -> 13643.414 | C87: =IF(6<=核心参数输入!$B$9,年度汇总!J23,"") -> 5163.2143 | D87: =IF(6<=核心参数输入!$B$9,年度汇总!J29,"") -> 13721.069 | E87: =IF(6<=核心参数输入!$B$9,年度汇总!J30,"") -> 0 | F87: =IF(6<=核心参数输入!$B$9,年度汇总!J27,"") -> 0 | G87: =IF(6<=核心参数输入!$B$9,年度汇总!J28,"") -> 0 | H87: =IF(6<=核心参数输入!$B$9,年度汇总!J33,"") -> -20473.391
A88: =IF(7<=核心参数输入!$B$9,7,"") -> 7 | B88: =IF(7<=核心参数输入!$B$9,年度汇总!K22,"") -> 2022.6792 | C88: =IF(7<=核心参数输入!$B$9,年度汇总!K23,"") -> 4983.2143 | D88: =IF(7<=核心参数输入!$B$9,年度汇总!K29,"") -> 10760.534 | E88: =IF(7<=核心参数输入!$B$9,年度汇总!K30,"") -> 0 | F88: =IF(7<=核心参数输入!$B$9,年度汇总!K27,"") -> 0 | G88: =IF(7<=核心参数输入!$B$9,年度汇总!K28,"") -> 0 | H88: =IF(7<=核心参数输入!$B$9,年度汇总!K33,"") -> -18478.377
A89: =IF(8<=核心参数输入!$B$9,8,"") -> 8 | B89: =IF(8<=核心参数输入!$B$9,年度汇总!L22,"") -> 1018.1447 | C89: =IF(8<=核心参数输入!$B$9,年度汇总!L23,"") -> 4803.2143 | D89: =IF(8<=核心参数输入!$B$9,年度汇总!L29,"") -> 6975.4642 | E89: =IF(8<=核心参数输入!$B$9,年度汇总!L30,"") -> 0 | F89: =IF(8<=核心参数输入!$B$9,年度汇总!L27,"") -> 0 | G89: =IF(8<=核心参数输入!$B$9,年度汇总!L28,"") -> 0 | H89: =IF(8<=核心参数输入!$B$9,年度汇总!L33,"") -> -17508.241
A90: =IF(9<=核心参数输入!$B$9,9,"") -> 9 | B90: =IF(9<=核心参数输入!$B$9,年度汇总!M22,"") -> 1037.1814 | C90: =IF(9<=核心参数输入!$B$9,年度汇总!M23,"") -> 4623.2143 | D90: =IF(9<=核心参数输入!$B$9,年度汇总!M29,"") -> 3389.4313 | E90: =IF(9<=核心参数输入!$B$9,年度汇总!M30,"") -> 0 | F90: =IF(9<=核心参数输入!$B$9,年度汇总!M27,"") -> 0 | G90: =IF(9<=核心参数输入!$B$9,年度汇总!M28,"") -> 0 | H90: =IF(9<=核心参数输入!$B$9,年度汇总!M33,"") -> -16523.828
A91: =IF(10<=核心参数输入!$B$9,10,"") -> 10 | B91: =IF(10<=核心参数输入!$B$9,年度汇总!N22,"") -> 1053.783 | C91: =IF(10<=核心参数输入!$B$9,年度汇总!N23,"") -> 4443.2143 | D91: =IF(10<=核心参数输入!$B$9,年度汇总!N29,"") -> 0 | E91: =IF(10<=核心参数输入!$B$9,年度汇总!N30,"") -> 0 | F91: =IF(10<=核心参数输入!$B$9,年度汇总!N27,"") -> 0 | G91: =IF(10<=核心参数输入!$B$9,年度汇总!N28,"") -> 0 | H91: =IF(10<=核心参数输入!$B$9,年度汇总!N33,"") -> -15526.963
A92: =IF(11<=核心参数输入!$B$9,11,"") -> 11 | B92: =IF(11<=核心参数输入!$B$9,年度汇总!O22,"") -> 1070.6005 | C92: =IF(11<=核心参数输入!$B$9,年度汇总!O23,"") -> 0 | D92: =IF(11<=核心参数输入!$B$9,年度汇总!O29,"") -> 0 | E92: =IF(11<=核心参数输入!$B$9,年度汇总!O30,"") -> 0 | F92: =IF(11<=核心参数输入!$B$9,年度汇总!O27,"") -> 0 | G92: =IF(11<=核心参数输入!$B$9,年度汇总!O28,"") -> 1070.6005 | H92: =IF(11<=核心参数输入!$B$9,年度汇总!O33,"") -> -14517.485
A93: =IF(12<=核心参数输入!$B$9,12,"") -> 12 | B93: =IF(12<=核心参数输入!$B$9,年度汇总!P22,"") -> 1087.6365 | C93: =IF(12<=核心参数输入!$B$9,年度汇总!P23,"") -> 0 | D93: =IF(12<=核心参数输入!$B$9,年度汇总!P29,"") -> 0 | E93: =IF(12<=核心参数输入!$B$9,年度汇总!P30,"") -> 0 | F93: =IF(12<=核心参数输入!$B$9,年度汇总!P27,"") -> 0 | G93: =IF(12<=核心参数输入!$B$9,年度汇总!P28,"") -> 1087.6365 | H93: =IF(12<=核心参数输入!$B$9,年度汇总!P33,"") -> -13495.23
A94: =IF(13<=核心参数输入!$B$9,13,"") -> 13 | B94: =IF(13<=核心参数输入!$B$9,年度汇总!Q22,"") -> 1104.8935 | C94: =IF(13<=核心参数输入!$B$9,年度汇总!Q23,"") -> 0 | D94: =IF(13<=核心参数输入!$B$9,年度汇总!Q29,"") -> 0 | E94: =IF(13<=核心参数输入!$B$9,年度汇总!Q30,"") -> 0 | F94: =IF(13<=核心参数输入!$B$9,年度汇总!Q27,"") -> 0 | G94: =IF(13<=核心参数输入!$B$9,年度汇总!Q28,"") -> 1104.8935 | H94: =IF(13<=核心参数输入!$B$9,年度汇总!Q33,"") -> -12460.032
A95: =IF(14<=核心参数输入!$B$9,14,"") -> 14 | B95: =IF(14<=核心参数输入!$B$9,年度汇总!R22,"") -> 1093.3816 | C95: =IF(14<=核心参数输入!$B$9,年度汇总!R23,"") -> 0 | D95: =IF(14<=核心参数输入!$B$9,年度汇总!R29,"") -> 0 | E95: =IF(14<=核心参数输入!$B$9,年度汇总!R30,"") -> 0 | F95: =IF(14<=核心参数输入!$B$9,年度汇总!R27,"") -> 0 | G95: =IF(14<=核心参数输入!$B$9,年度汇总!R28,"") -> 1093.3816 | H95: =IF(14<=核心参数输入!$B$9,年度汇总!R33,"") -> -11411.724
A96: =IF(15<=核心参数输入!$B$9,15,"") -> 15 | B96: =IF(15<=核心参数输入!$B$9,年度汇总!S22,"") -> 1068.3217 | C96: =IF(15<=核心参数输入!$B$9,年度汇总!S23,"") -> 0 | D96: =IF(15<=核心参数输入!$B$9,年度汇总!S29,"") -> 0 | E96: =IF(15<=核心参数输入!$B$9,年度汇总!S30,"") -> 0 | F96: =IF(15<=核心参数输入!$B$9,年度汇总!S27,"") -> 0 | G96: =IF(15<=核心参数输入!$B$9,年度汇总!S28,"") -> 1068.3217 | H96: =IF(15<=核心参数输入!$B$9,年度汇总!S33,"") -> -10350.136
A97: =IF(16<=核心参数输入!$B$9,16,"") -> 16 | B97: =IF(16<=核心参数输入!$B$9,年度汇总!T22,"") -> 1081.7738 | C97: =IF(16<=核心参数输入!$B$9,年度汇总!T23,"") -> 0 | D97: =IF(16<=核心参数输入!$B$9,年度汇总!T29,"") -> 0 | E97: =IF(16<=核心参数输入!$B$9,年度汇总!T30,"") -> 0 | F97: =IF(16<=核心参数输入!$B$9,年度汇总!T27,"") -> 0 | G97: =IF(16<=核心参数输入!$B$9,年度汇总!T28,"") -> 1081.7738 | H97: =IF(16<=核心参数输入!$B$9,年度汇总!T33,"") -> -9275.0949
A98: =IF(17<=核心参数输入!$B$9,17,"") -> 17 | B98: =IF(17<=核心参数输入!$B$9,年度汇总!U22,"") -> 1095.3997 | C98: =IF(17<=核心参数输入!$B$9,年度汇总!U23,"") -> 0 | D98: =IF(17<=核心参数输入!$B$9,年度汇总!U29,"") -> 0 | E98: =IF(17<=核心参数输入!$B$9,年度汇总!U30,"") -> 0 | F98: =IF(17<=核心参数输入!$B$9,年度汇总!U27,"") -> 0 | G98: =IF(17<=核心参数输入!$B$9,年度汇总!U28,"") -> 1095.3997 | H98: =IF(17<=核心参数输入!$B$9,年度汇总!U33,"") -> -8186.4283
A99: =IF(18<=核心参数输入!$B$9,18,"") -> 18 | B99: =IF(18<=核心参数输入!$B$9,年度汇总!V22,"") -> 1109.2015 | C99: =IF(18<=核心参数输入!$B$9,年度汇总!V23,"") -> 0 | D99: =IF(18<=核心参数输入!$B$9,年度汇总!V29,"") -> 0 | E99: =IF(18<=核心参数输入!$B$9,年度汇总!V30,"") -> 0 | F99: =IF(18<=核心参数输入!$B$9,年度汇总!V27,"") -> 0 | G99: =IF(18<=核心参数输入!$B$9,年度汇总!V28,"") -> 1109.2015 | H99: =IF(18<=核心参数输入!$B$9,年度汇总!V33,"") -> -7083.9599
A100: =IF(19<=核心参数输入!$B$9,19,"") -> 19 | B100: =IF(19<=核心参数输入!$B$9,年度汇总!W22,"") -> 1123.1812 | C100: =IF(19<=核心参数输入!$B$9,年度汇总!W23,"") -> 0 | D100: =IF(19<=核心参数输入!$B$9,年度汇总!W29,"") -> 0 | E100: =IF(19<=核心参数输入!$B$9,年度汇总!W30,"") -> 0 | F100: =IF(19<=核心参数输入!$B$9,年度汇总!W27,"") -> 0 | G100: =IF(19<=核心参数输入!$B$9,年度汇总!W28,"") -> 1123.1812 | H100: =IF(19<=核心参数输入!$B$9,年度汇总!W33,"") -> -5967.5118
A101: =IF(20<=核心参数输入!$B$9,20,"") -> 20 | B101: =IF(20<=核心参数输入!$B$9,年度汇总!X22,"") -> 1137.3409 | C101: =IF(20<=核心参数输入!$B$9,年度汇总!X23,"") -> 0 | D101: =IF(20<=核心参数输入!$B$9,年度汇总!X29,"") -> 0 | E101: =IF(20<=核心参数输入!$B$9,年度汇总!X30,"") -> 0 | F101: =IF(20<=核心参数输入!$B$9,年度汇总!X27,"") -> 0 | G101: =IF(20<=核心参数输入!$B$9,年度汇总!X28,"") -> 1137.3409 | H101: =IF(20<=核心参数输入!$B$9,年度汇总!X33,"") -> -4836.904
A102: =IF(21<=核心参数输入!$B$9,21,"") | B102: =IF(21<=核心参数输入!$B$9,年度汇总!Y22,"") | C102: =IF(21<=核心参数输入!$B$9,年度汇总!Y23,"") | D102: =IF(21<=核心参数输入!$B$9,年度汇总!Y29,"") | E102: =IF(21<=核心参数输入!$B$9,年度汇总!Y30,"") | F102: =IF(21<=核心参数输入!$B$9,年度汇总!Y27,"") | G102: =IF(21<=核心参数输入!$B$9,年度汇总!Y28,"") | H102: =IF(21<=核心参数输入!$B$9,年度汇总!Y33,"")
A103: =IF(22<=核心参数输入!$B$9,22,"") | B103: =IF(22<=核心参数输入!$B$9,年度汇总!Z22,"") | C103: =IF(22<=核心参数输入!$B$9,年度汇总!Z23,"") | D103: =IF(22<=核心参数输入!$B$9,年度汇总!Z29,"") | E103: =IF(22<=核心参数输入!$B$9,年度汇总!Z30,"") | F103: =IF(22<=核心参数输入!$B$9,年度汇总!Z27,"") | G103: =IF(22<=核心参数输入!$B$9,年度汇总!Z28,"") | H103: =IF(22<=核心参数输入!$B$9,年度汇总!Z33,"")
A104: =IF(23<=核心参数输入!$B$9,23,"") | B104: =IF(23<=核心参数输入!$B$9,年度汇总!AA22,"") | C104: =IF(23<=核心参数输入!$B$9,年度汇总!AA23,"") | D104: =IF(23<=核心参数输入!$B$9,年度汇总!AA29,"") | E104: =IF(23<=核心参数输入!$B$9,年度汇总!AA30,"") | F104: =IF(23<=核心参数输入!$B$9,年度汇总!AA27,"") | G104: =IF(23<=核心参数输入!$B$9,年度汇总!AA28,"") | H104: =IF(23<=核心参数输入!$B$9,年度汇总!AA33,"")
A105: =IF(24<=核心参数输入!$B$9,24,"") | B105: =IF(24<=核心参数输入!$B$9,年度汇总!AB22,"") | C105: =IF(24<=核心参数输入!$B$9,年度汇总!AB23,"") | D105: =IF(24<=核心参数输入!$B$9,年度汇总!AB29,"") | E105: =IF(24<=核心参数输入!$B$9,年度汇总!AB30,"") | F105: =IF(24<=核心参数输入!$B$9,年度汇总!AB27,"") | G105: =IF(24<=核心参数输入!$B$9,年度汇总!AB28,"") | H105: =IF(24<=核心参数输入!$B$9,年度汇总!AB33,"")
A106: =IF(25<=核心参数输入!$B$9,25,"") | B106: =IF(25<=核心参数输入!$B$9,年度汇总!AC22,"") | C106: =IF(25<=核心参数输入!$B$9,年度汇总!AC23,"") | D106: =IF(25<=核心参数输入!$B$9,年度汇总!AC29,"") | E106: =IF(25<=核心参数输入!$B$9,年度汇总!AC30,"") | F106: =IF(25<=核心参数输入!$B$9,年度汇总!AC27,"") | G106: =IF(25<=核心参数输入!$B$9,年度汇总!AC28,"") | H106: =IF(25<=核心参数输入!$B$9,年度汇总!AC33,"")
A107: =IF(26<=核心参数输入!$B$9,26,"") | B107: =IF(26<=核心参数输入!$B$9,年度汇总!AD22,"") | C107: =IF(26<=核心参数输入!$B$9,年度汇总!AD23,"") | D107: =IF(26<=核心参数输入!$B$9,年度汇总!AD29,"") | E107: =IF(26<=核心参数输入!$B$9,年度汇总!AD30,"") | F107: =IF(26<=核心参数输入!$B$9,年度汇总!AD27,"") | G107: =IF(26<=核心参数输入!$B$9,年度汇总!AD28,"") | H107: =IF(26<=核心参数输入!$B$9,年度汇总!AD33,"")
A108: =IF(27<=核心参数输入!$B$9,27,"") | B108: =IF(27<=核心参数输入!$B$9,年度汇总!AE22,"") | C108: =IF(27<=核心参数输入!$B$9,年度汇总!AE23,"") | D108: =IF(27<=核心参数输入!$B$9,年度汇总!AE29,"") | E108: =IF(27<=核心参数输入!$B$9,年度汇总!AE30,"") | F108: =IF(27<=核心参数输入!$B$9,年度汇总!AE27,"") | G108: =IF(27<=核心参数输入!$B$9,年度汇总!AE28,"") | H108: =IF(27<=核心参数输入!$B$9,年度汇总!AE33,"")
A109: =IF(28<=核心参数输入!$B$9,28,"") | B109: =IF(28<=核心参数输入!$B$9,年度汇总!AF22,"") | C109: =IF(28<=核心参数输入!$B$9,年度汇总!AF23,"") | D109: =IF(28<=核心参数输入!$B$9,年度汇总!AF29,"") | E109: =IF(28<=核心参数输入!$B$9,年度汇总!AF30,"") | F109: =IF(28<=核心参数输入!$B$9,年度汇总!AF27,"") | G109: =IF(28<=核心参数输入!$B$9,年度汇总!AF28,"") | H109: =IF(28<=核心参数输入!$B$9,年度汇总!AF33,"")
A110: =IF(29<=核心参数输入!$B$9,29,"") | B110: =IF(29<=核心参数输入!$B$9,年度汇总!AG22,"") | C110: =IF(29<=核心参数输入!$B$9,年度汇总!AG23,"") | D110: =IF(29<=核心参数输入!$B$9,年度汇总!AG29,"") | E110: =IF(29<=核心参数输入!$B$9,年度汇总!AG30,"") | F110: =IF(29<=核心参数输入!$B$9,年度汇总!AG27,"") | G110: =IF(29<=核心参数输入!$B$9,年度汇总!AG28,"") | H110: =IF(29<=核心参数输入!$B$9,年度汇总!AG33,"")
A111: =IF(30<=核心参数输入!$B$9,30,"") | B111: =IF(30<=核心参数输入!$B$9,年度汇总!AH22,"") | C111: =IF(30<=核心参数输入!$B$9,年度汇总!AH23,"") | D111: =IF(30<=核心参数输入!$B$9,年度汇总!AH29,"") | E111: =IF(30<=核心参数输入!$B$9,年度汇总!AH30,"") | F111: =IF(30<=核心参数输入!$B$9,年度汇总!AH27,"") | G111: =IF(30<=核心参数输入!$B$9,年度汇总!AH28,"") | H111: =IF(30<=核心参数输入!$B$9,年度汇总!AH33,"")

Sheet 核心参数输入
A2: 核心参数输入 · V3模拟测算
A5: 参数 | B5: 输入值 | C5: 单位 | D5: 口径、来源与状态
A6: 基础与建筑参数
A7: 项目名称 | B7: 模拟产业园 · 租售结合 | C7: 文本 | D7: 全部数据为虚构模拟数据 | L7: V2保存参数
A8: 测算起始年份 | B8: 2026 | C8: 年 | D8: 第0年的日历年份；年度支出采用年末时点 | L8: V2保存参数
A9: 测算期限 | B9: 20 | C9: 年 | D9: 实际范围第0年至第N年，预留至30年；须覆盖贷款到期 | L9: V2保存参数
A10: 土地面积 | B10: 100000 | C10: 平方米 | D10: 地上面积＝土地面积×容积率 | L10: V2保存参数
A11: 容积率 | B11: 1.5 | C11: 倍 | D11: 地上总建筑面积口径 | L11: V2保存参数
A12: 地上可经营面积占比 | B12: 0.9 | C12: % | D12: 其余为公共及非经营空间；共同成本仍计入 | L12: V2保存参数
A13: 地下建筑面积 | B13: 15000 | C13: 平方米 | D13: 地下空间不独立产生收入 | L13: V2保存参数
A14: 可经营面积销售占比 | B14: 0.55 | C14: % | D14: 混合模式使用；纯出售／纯持有由B95切换，原55%示意值保留 | L14: V2保存参数
A15: 实际出租占比（模式后） | B15: =核心参数输入!$B$143 -> 0.45 | C15: % | D15: 自动＝1－销售占比 | L15: V2保存参数
A16: 建设年限 | B16: 3 | C16: 年 | D16: 第1年至第K年；土地在第0年支付 | L16: V2保存参数
A17: 销售开始年份 | B17: 4 | C17: 项目第几年 | D17: 必须晚于建设完成年；年度销售比例在下方输入 | L17: V2保存参数
A18: 出租开始年份 | B18: 4 | C18: 项目第几年 | D18: 必须晚于建设完成年；运营固定成本从K+1年开始 | L18: V2保存参数
A20: 投资参数
A21: 土地单价 | B21: 800 | C21: 元/平方米 | D21: 仅土地取得价款；不计入建筑折旧 | L21: V2保存参数
A22: 地上单方建安成本 | B22: 2400 | C22: 元/平方米 | D22: 不含下列配套、前期、管理费用 | L22: V2保存参数
A23: 地下单方建安成本 | B23: 3000 | C23: 元/平方米 | D23: 地下工程；不与地上重复 | L23: V2保存参数
A24: 园区配套工程费用 | B24: 4500 | C24: 万元 | D24: 园区道路、管网、公共配套；不含建安主体 | L24: V2保存参数
A25: 勘察设计咨询前期费用 | B25: 1800 | C25: 万元 | D25: 不含建安及管理费用 | L25: V2保存参数
A26: 管理及其他建设费用 | B26: 2200 | C26: 万元 | D26: 建设管理等；不含融资利息和运营成本 | L26: V2保存参数
A27: 预备费比例 | B27: 0.08 | C27: % | D27: 基数＝全部非土地建设费用（建安、配套、前期、管理） | L27: V2保存参数
A28: 初始运营周转资金 | B28: 500 | C28: 万元 | D28: K+1年投入，期末全额回收；不计入费用及折旧 | L28: V2保存参数
A30: 销售参数
A31: 销售均价 | B31: 6500 | C31: 元/平方米 | D31: 简化含税成交/实收口径；销售当年全额收款 | L31: V2保存参数
A32: 销售费用率 | B32: 0.025 | C32: % | D32: 销售回款×费用率 | L32: V2保存参数
A33: 简化销售相关税费率 | B33: 0.08 | C33: % | D33: 含税回款×综合率；不另行建立增值税抵扣 | L33: V2保存参数
A35: 出租参数
A36: 初始月租金 | B36: 26 | C36: 元/平方米/月 | D36: 出租首年价格；按12个月换算后除10000为万元 | L36: V2保存参数
A37: 年租金增长率 | B37: 0.015 | C37: % | D37: 从出租开始年递增 | L37: V2保存参数
A38: 出租第1年出租率 | B38: 0.5 | C38: % | D38: 第1个出租年度年末目标；V3按季内入驻位置形成平均面积 | L38: V2保存参数
A39: 出租第2年出租率 | B39: 0.7 | C39: % | D39: 第2个出租年度年末目标 | L39: V2保存参数
A40: 出租第3年出租率 | B40: 0.85 | C40: % | D40: 第3个出租年度年末目标 | L40: V2保存参数
A41: 第4年起稳定出租率 | B41: 0.9 | C41: % | D41: 第4出租年末及以后目标；不模拟租户更替 | L41: V2保存参数
A42: 新增出租面积平均免租月数 | B42: 3 | C42: 月 | D42: 0—12月；同一面积不重复免租 | L42: V2保存参数
A43: 租金收缴率 | B43: 0.98 | C43: % | D43: 实收租金，同时作为简化收入确认口径 | L43: V2保存参数
A44: 其他经营收入比例 | B44: 0.05 | C44: % | D44: 实收租金×比例；属于持有经营收入 | L44: V2保存参数
A46: 运营与税费
A47: 运营首年固定成本 | B47: 300 | C47: 万元/年 | D47: 仅持有部分：人员、管理、保险等；K+1年即承担 | L47: V2保存参数
A48: 固定成本年度增长率 | B48: 0.02 | C48: % | D48: 自K+1年起递增，与是否出租无关 | L48: V2保存参数
A49: 变动运营成本率 | B49: 0.12 | C49: % | D49: 实收租金及其他经营收入×比例；不含维护更新 | L49: V2保存参数
A50: 年度维护更新支出 | B50: 180 | C50: 万元/年 | D50: 常年维护按基准持有面积缩放；重大更新另列B117 | L50: V2保存参数
A51: 简化运营相关税费率 | B51: 0.06 | C51: % | D51: 租金及其他经营收入×综合率；不另计复杂税种 | L51: V2保存参数
A52: 企业所得税率 | B52: 0.25 | C52: % | D52: 年度计税，按B100:B101结转亏损；与现金支付时间分开 | L52: V2保存参数
A53: 持有建筑物折旧年限 | B53: 30 | C53: 年 | D53: K+1年起直线法；项目口径不含融资利息，资本金口径含资本化利息 | L53: V2保存参数
A54: 建筑物残值率 | B54: 0.05 | C54: % | D54: 仅影响账面价值，不能自动变成现金收入 | L54: V2保存参数
A56: 融资与资本金
A57: 贷款金额 | B57: 30000 | C57: 万元 | D57: 既定贷款额度；季度提款可覆盖，提款滞后不自动增贷 | L57: V2保存参数
A58: 贷款年利率 | B58: 0.042 | C58: % | D58: 利息＝（期初本金＋当年提款/2－当年还本/2）×利率 | L58: V2保存参数
A59: 贷款期限 | B59: 10 | C59: 年 | D59: 从首次提款年算起：到期年＝首次提款年＋期限－1 | L59: V2保存参数
A60: 开始偿还本金年份 | B60: 4 | C60: 项目第几年 | D60: 原开始年度年末首笔还本；整体延期时配套后移 | L60: V2保存参数
A61: 可投入资本金总额度 | B61: 33000 | C61: 万元 | D61: 按需投入且不突破额度；缺口单列，不作为真实资金 | L61: V2保存参数
A63: 期末处置
A64: 是否计入期末处置 | B64: 0 | C64: 0关闭/1开启 | D64: 当前展示口径开关；持有与出售结果始终并列计算 | L64: V2保存参数
A65: 持有物业期末处置价值 | B65: 30000 | C65: 万元 | D65: 仅持有物业的第N年含税售价；变更期限应重估 | L65: V2保存参数
A66: 期末处置费用率 | B66: 0.03 | C66: % | D66: 综合退出费用已包含交易税费，退出不再重复计销项增值税 | L66: V2保存参数
A68: 模拟判断标准
A69: 项目税后IRR最低值 | B69: 0.08 | C69: % | D69: 模拟阈值，非实际投资标准 | L69: V2保存参数
A70: 资本金IRR最低值 | B70: 0.1 | C70: % | D70: 资金不足时仅为完整出资的理论结果 | L70: V2保存参数
A71: 项目折现率 | B71: 0.08 | C71: % | D71: 项目NPV及动态回收期折现率 | L71: V2保存参数
A72: 资本金折现率 | B72: 0.1 | C72: % | D72: 资本金NPV折现率 | L72: V2保存参数
A73: 静态投资回收期上限 | B73: 15 | C73: 年 | D73: 含第0年及建设期；项目投资现金流口径 | L73: V2保存参数
A74: 动态投资回收期上限 | B74: 20 | C74: 年 | D74: 按项目折现率；测算期内未回收视为不达标 | L74: V2保存参数
A75: 最低偿债覆盖倍数 | B75: 1.2 | C75: 倍 | D75: 仅统计建成以后存在本息偿付的年度 | L75: V2保存参数
A77: 组合压力
A78: 销售价格下降比例 | B78: 0.1 | C78: % | D78: 基准售价×(1－下降比例) | L78: V2保存参数
A79: 租金下降比例 | B79: 0.1 | C79: % | D79: 基准各年租金×(1－下降比例) | L79: V2保存参数
A80: 出租率下降百分点 | B80: 10 | C80: 百分点 | D80: 10表示下降10个百分点，按10/100扣减，不是乘90% | L80: V2保存参数
A81: 非土地建设成本增加比例 | B81: 0.1 | C81: % | D81: 作用于建安、配套、前期、管理及对应预备费；土地不变 | L81: V2保存参数
A82: 是否要求压力情景也通过 | B82: 0 | C82: 0否/1是 | D82: 默认仅观察；开启后两种情景都必须通过 | L82: V2保存参数
D87: 0 | E87: 1 | F87: 2 | G87: 3 | H87: 4 | I87: 5 | J87: 6 | K87: 7 | L87: 8 | M87: 9 | N87: 10 | O87: 11 | P87: 12 | Q87: 13 | R87: 14 | S87: 15 | T87: 16 | U87: 17 | V87: 18 | W87: 19 | X87: 20 | Y87: 21 | Z87: 22 | AA87: 23 | AB87: 24 | AC87: 25 | AD87: 26 | AE87: 27 | AF87: 28 | AG87: 29 | AH87: 30
A88: 年度建设分配比例 | D88: 0 | E88: 0.3 | F88: 0.4 | G88: 0.3 | H88: 0 | I88: 0 | J88: 0 | K88: 0 | L88: 0 | M88: 0 | N88: 0 | O88: 0 | P88: 0 | Q88: 0 | R88: 0 | S88: 0 | T88: 0 | U88: 0 | V88: 0 | W88: 0 | X88: 0 | Y88: 0 | Z88: 0 | AA88: 0 | AB88: 0 | AC88: 0 | AD88: 0 | AE88: 0 | AF88: 0 | AG88: 0 | AH88: 0
A89: 年度签约销售比例 | D89: 0 | E89: 0 | F89: 0 | G89: 0 | H89: 0.3 | I89: 0.4 | J89: 0.3 | K89: 0 | L89: 0 | M89: 0 | N89: 0 | O89: 0 | P89: 0 | Q89: 0 | R89: 0 | S89: 0 | T89: 0 | U89: 0 | V89: 0 | W89: 0 | X89: 0 | Y89: 0 | Z89: 0 | AA89: 0 | AB89: 0 | AC89: 0 | AD89: 0 | AE89: 0 | AF89: 0 | AG89: 0 | AH89: 0
A93: V3补充假设（黄色输入；默认均为示意、待确认）
A95: 经营模式 | B95: 1 | C95: 编号 | D95: 1租售结合，2纯出售，3纯持有；混合模式读取原B14 | L95: V3示意新增，待核对
A96: 流转税计算口径 | B96: 1 | C96: 编号 | D96: 1沿用V2综合率；2分离增值税，必须填B118:B122财务参数 | L96: V3示意新增，待核对
A97: 新增假设已完成项目核对 | B97: 0 | C97: 0/1 | D97: 示意默认0；只有逐项核对后改1，仍不代表项目值得投资 | L97: V3示意新增，待核对
A98: 持有土地是否摊销 | B98: 1 | C98: 0/1 | D98: V3示意开启；仅财务假设，非税务适用结论 | L98: V3示意新增，待核对
A99: 持有土地摊销年限 | B99: 50 | C99: 年 | D99: 示意新增；从建成后开始，零残值；须核对剩余年限 | L99: V3示意新增，待核对
A100: 是否结转所得税亏损 | B100: 1 | C100: 0/1 | D100: 按年度、分年份、先发生先使用；不跨项目共享 | L100: V3示意新增，待核对
A101: 亏损可结转年限 | B101: 5 | C101: 年 | D101: 示意新增，非实际适用规则；0表示无到期，最大30年 | L101: V3示意新增，待核对
A102: 销售交付当季收款比例 | B102: 0.7 | C102: % | D102: 其余按B103延迟；收入按交付确认，未收保留应收 | L102: V3示意新增，待核对
A103: 销售尾款延迟季度数 | B103: 1 | C103: 季度 | D103: 示意新增；尾款超出测算期不自动收回，并提示应收余额 | L103: V3示意新增，待核对
A104: 租金收款延迟季度数 | B104: 0 | C104: 季度 | D104: 收缴率视为最终可收回比例，其余记坏账；收款另按此延迟 | L104: V3示意新增，待核对
A105: 建设付款相对工程形成滞后 | B105: 0 | C105: 季度 | D105: 可在季度计划逐季覆盖；形成成本与付款现金分开 | L105: V3示意新增，待核对
A106: 贷款提款相对建设付款滞后 | B106: 0 | C106: 季度 | D106: 既定额度；滞后会增加股东垫资，不自动新增贷款 | L106: V3示意新增，待核对
... A139: 压力情景期末售价系数 | B139: 1 | C139: 倍 | D139: 默认1沿用V2处置价；需要时单独压低退出价格 | L139: V3示意新增，待核对
A141: 当前生效口径（公式）
A142: 实际销售比例 | B142: =IF(核心参数输入!$B$95=2,1,IF(核心参数输入!$B$95=3,0,核心参数输入!$B$14)) -> 0.55
A143: 实际持有比例 | B143: =1-核心参数输入!$B$142 -> 0.45
A144: 生效土地单价 | B144: =IF(ISNUMBER(敏感性与边界!$B$6),敏感性与边界!$B$6,核心参数输入!$B$21) -> 800
A145: 生效销售均价 | B145: =IF(ISNUMBER(敏感性与边界!$B$7),敏感性与边界!$B$7,核心参数输入!$B$31) -> 6500
A146: 生效初始月租金 | B146: =IF(ISNUMBER(敏感性与边界!$B$8),敏感性与边界!$B$8,核心参数输入!$B$36) -> 26
A147: 生效非土地成本倍数 | B147: =IF(ISNUMBER(敏感性与边界!$B$9),敏感性与边界!$B$9,1) -> 1
A148: 生效整体延期季度 | B148: =IF(ISNUMBER(敏感性与边界!$B$10),敏感性与边界!$B$10,核心参数输入!$B$107) -> 0
A149: 经营模式名称 | B149: =CHOOSE(核心参数输入!$B$95,"租售结合","纯出售","纯持有") -> 租售结合
A150: 输入基础有效标志 | B150: =IF(AND(IF(AND(COUNT(B8,B9,B10,B11,B12,B13,B14,B16,B17,B18,B21,B22,B23,B24,B25,B26,B27,B28,B31,B32,B33,B36,B37,B38,B39,B40,B41,B42,B43,B44,B47,B48,B49,B50,B51,B52,B53,B54,B57,B58,B59,B60,B61,B64,B65,B66,B69,B70,B71,B72,B73,B74,B75,B78,B79,B80,B81,B82)=58,COUNT(B95,B96,B97,B98,B99,B100,B101,B102,B103,B104,B105,B106,B107,B108,B109,B110,B111,B112,B113,B114,B115,B116,B117,B118,B119,B120,B121,B122,B123,B124,B125,B126,B127,B128,B129,B130,B131,B132,B133,B134,B135,B136,B137,B139)=44,B7<>"",B9=INT(B9),B9>B16,B9<=30,B16>=1,B16=INT(B16),B10>0,B11>0,B12>0,B12<=1,B13>=0,B14>=0,B14<=1,B95>=1,B95<=3,B95=INT(B95),OR(B96=1,B96=2),MIN(B21:B26,B28,B31,B36,B47,B50,B57,B61,B65,B108,B114:B115,B117,B123)>=0,MIN(B38:B41)>=0,MAX(B38:B41)<=1,B38<=B39,B39<=B40,B40<=B41,B42>=0,B42<=12,B43>=0,B43<=1,B37>-1,B48>-1,B53>=1,B53=INT(B53),B99>=1,B99=INT(B99),B101>=0,B101=INT(B101),B69>=0,B70>=0,B71>=0,B72>=0,B73>0,B74>0,B75>0,SUM(B128:B131)>0,ABS(SUM(B128:B131)-1)<0.000001,MIN(B128:B131)>=0,MIN(D88:AH89)>=0,MAX(D88:AH89)<=1,COUNT(D88:AH88)=31,COUNT(D89:AH89)=31,ABS(SUM(D88:AH88)-1)<0.000001,SUM(D89:AH89)<=1.000001,OR(B142=0,AND(B17>B16,B17<=B9,B17=INT(B17))),OR(B143=0,AND(B18>B16,B18<=B9,B18=INT(B18),B108>0)),B102>=0,B102<=1,B105>=0,B105=INT(B105),B106>=0,B106=INT(B106),B148>=0,B148=INT(B148),B127>=1,B127=INT(B127),MIN(B118:B122)>=0,MAX(B118:B122)<=1,OR(B98=0,B98=1),OR(B100=0,B100=1),OR(B64=0,B64=1),OR(B82=0,B82=1)),1,0)=1,AND(B12>=0,B12<=1),AND(B14>=0,B14<=1),AND(B27>=0,B27<=1),AND(B32>=0,B32<=1),AND(B33>=0,B33<=1),AND(B38>=0,B38<=1),AND(B39>=0,B39<=1),AND(B40>=0,B40<=1),AND(B41>=0,B41<=1),AND(B43>=0,B43<=1),AND(B44>=0,B44<=1),AND(B49>=0,B49<=1),AND(B51>=0,B51<=1),AND(B52>=0,B52<=1),AND(B54>=0,B54<=1),AND(B58>=0,B58<=1),AND(B66>=0,B66<=1),AND(B69>=0,B69<=1),AND(B70>=0,B70<=1),AND(B71>=0,B71<=1),AND(B72>=0,B72<=1),AND(B78>=0,B78<=1),AND(B79>=0,B79<=1),AND(B102>=0,B102<=1),AND(B109>=0,B109<=1),AND(B110>=0,B110<=1),AND(B113>=0,B113<=1),AND(B118>=0,B118<=1),AND(B119>=0,B119<=1),AND(B120>=0,B120<=1),AND(B121>=0,B121<=1),AND(B122>=0,B122<=1),AND(B125>=0,B125<=1),AND(B128>=0,B128<=1),AND(B129>=0,B129<=1),AND(B130>=0,B130<=1),AND(B131>=0,B131<=1),AND(B137>=0,B137<=1),AND(B103>=0,B103=INT(B103)),AND(B104>=0,B104=INT(B104)),AND(B105>=0,B105=INT(B105)),AND(B106>=0,B106=INT(B106)),AND(B107>=0,B107=INT(B107)),AND(B111>=0,B111=INT(B111)),AND(B112>=0,B112=INT(B112)),AND(B124>=0,B124=INT(B124)),AND(B126>=0,B126=INT(B126)),AND(B148>=0,B148=INT(B148)),B8=INT(B8),B8>=1900,B8<=2200,B37>=-0.99,B37<=1,B48>=-0.99,B48<=1,B81>=0,B81<=10,B144>=0,B145>=0,B146>=0,B147>=0),1,0) -> 1
A152: 税费口径 | B152: =IF(核心参数输入!$B$96=1,"综合税费率（沿用V2）","分离增值税（财务参数）") -> 综合税费率（沿用V2）

Sheet 指标与情景
A2: 指标与情景 · V3模拟测算
A4: 指标 | B4: 基准 | C4: 单位 | D4: 阈值 | E4: 组合压力 | F4: 基准状态 | G4: 压力状态
A6: 项目税后IRR（年化） | B6: =IF(AND(COUNTIFS(季度现金流!$D$45:INDEX(季度现金流!$D$45:$DT$45,1,核心参数输入!$B$9*4+1),"<0")>0,COUNTIFS(季度现金流!$D$45:INDEX(季度现金流!$D$45:$DT$45,1,核心参数输入!$B$9*4+1),">0")>0),IFERROR((1+IRR(季度现金流!$D$45:INDEX(季度现金流!$D$45:$DT$45,1,核心参数输入!$B$9*4+1)))^4-1,"无法计算"),"无法计算") -> -0.014445335 | C6: % | D6: =核心参数输入!$B$69 -> 0.08 | E6: =IF(AND(COUNTIFS(季度现金流!$D$155:INDEX(季度现金流!$D$155:$DT$155,1,核心参数输入!$B$9*4+1),"<0")>0,COUNTIFS(季度现金流!$D$155:INDEX(季度现金流!$D$155:$DT$155,1,核心参数输入!$B$9*4+1),">0")>0),IFERROR((1+IRR(季度现金流!$D$155:INDEX(季度现金流!$D$155:$DT$155,1,核心参数输入!$B$9*4+1)))^4-1,"无法计算"),"无法计算") -> -0.049549603 | F6: =IF(B6="不适用","未通过",IF(NOT(ISNUMBER(B6)),IF(B6="无法计算","待判断","未通过"),IF(B6>=D6,"通过","未通过"))) -> 未通过 | G6: =IF(E6="不适用","未通过",IF(NOT(ISNUMBER(E6)),IF(E6="无法计算","待判断","未通过"),IF(E6>=D6,"通过","未通过"))) -> 未通过 | H6: 季度IRR按(1+r)^4－1年化；只取第0季至第N年末
A7: 资本金IRR（年化） | B7: =IF(AND(COUNTIFS(季度现金流!$D$47:INDEX(季度现金流!$D$47:$DT$47,1,核心参数输入!$B$9*4+1),"<0")>0,COUNTIFS(季度现金流!$D$47:INDEX(季度现金流!$D$47:$DT$47,1,核心参数输入!$B$9*4+1),">0")>0),IFERROR((1+IRR(季度现金流!$D$47:INDEX(季度现金流!$D$47:$DT$47,1,核心参数输入!$B$9*4+1)))^4-1,"无法计算"),"无法计算") -> -0.040676665 | C7: % | D7: =核心参数输入!$B$70 -> 0.1 | E7: =IF(AND(COUNTIFS(季度现金流!$D$157:INDEX(季度现金流!$D$157:$DT$157,1,核心参数输入!$B$9*4+1),"<0")>0,COUNTIFS(季度现金流!$D$157:INDEX(季度现金流!$D$157:$DT$157,1,核心参数输入!$B$9*4+1),">0")>0),IFERROR((1+IRR(季度现金流!$D$157:INDEX(季度现金流!$D$157:$DT$157,1,核心参数输入!$B$9*4+1)))^4-1,"无法计算"),"无法计算") -> -0.087463531 | F7: =IF(B7="不适用","未通过",IF(NOT(ISNUMBER(B7)),IF(B7="无法计算","待判断","未通过"),IF(B7>=D7,"通过","未通过"))) -> 未通过 | G7: =IF(E7="不适用","未通过",IF(NOT(ISNUMBER(E7)),IF(E7="无法计算","待判断","未通过"),IF(E7>=D7,"通过","未通过"))) -> 未通过 | H7: 完整出资并预留后续资金后的分配；不代表未落实资金已到位
A8: 项目NPV | B8: =NPV((1+核心参数输入!$B$71)^(1/4)-1,季度现金流!$E$45:INDEX(季度现金流!$D$45:$DT$45,1,核心参数输入!$B$9*4+1))+季度现金流!D45 -> -20406.095 | C8: 万元 | D8: =0 -> 0 | E8: =NPV((1+核心参数输入!$B$71)^(1/4)-1,季度现金流!$E$155:INDEX(季度现金流!$D$155:$DT$155,1,核心参数输入!$B$9*4+1))+季度现金流!D155 -> -28525.14 | F8: =IF(B8="不适用","未通过",IF(NOT(ISNUMBER(B8)),IF(B8="无法计算","待判断","未通过"),IF(B8>=D8,"通过","未通过"))) -> 未通过 | G8: =IF(E8="不适用","未通过",IF(NOT(ISNUMBER(E8)),IF(E8="无法计算","待判断","未通过"),IF(E8>=D8,"通过","未通过"))) -> 未通过 | H8: 按年折现率换算季度有效利率，第0季不折现
A9: 资本金NPV | B9: =NPV((1+核心参数输入!$B$72)^(1/4)-1,季度现金流!$E$47:INDEX(季度现金流!$D$47:$DT$47,1,核心参数输入!$B$9*4+1))+季度现金流!D47 -> -18467.837 | C9: 万元 | D9: =0 -> 0 | E9: =NPV((1+核心参数输入!$B$72)^(1/4)-1,季度现金流!$E$157:INDEX(季度现金流!$D$157:$DT$157,1,核心参数输入!$B$9*4+1))+季度现金流!D157 -> -27195.962 | F9: =IF(B9="不适用","未通过",IF(NOT(ISNUMBER(B9)),IF(B9="无法计算","待判断","未通过"),IF(B9>=D9,"通过","未通过"))) -> 未通过 | G9: =IF(E9="不适用","未通过",IF(NOT(ISNUMBER(E9)),IF(E9="无法计算","待判断","未通过"),IF(E9>=D9,"通过","未通过"))) -> 未通过
A10: 静态投资回收期 | B10: =IF(COUNTIFS(季度现金流!$D$45:INDEX(季度现金流!$D$45:$DT$45,1,核心参数输入!$B$9*4+1),"<0")=0,"不适用",IF(COUNTIFS(季度现金流!$D$71:INDEX(季度现金流!$D$71:$DT$71,1,核心参数输入!$B$9*4+1),1)=0,"测算期内未回收",(MATCH(1,季度现金流!$D$71:INDEX(季度现金流!$D$71:$DT$71,1,核心参数输入!$B$9*4+1),0)-2-INDEX(季度现金流!$D$68:$DT$68,1,MAX(1,MATCH(1,季度现金流!$D$71:INDEX(季度现金流!$D$71:$DT$71,1,核心参数输入!$B$9*4+1),0)-1))/INDEX(季度现金流!$D$45:$DT$45,1,MATCH(1,季度现金流!$D$71:INDEX(季度现金流!$D$71:$DT$71,1,核心参数输入!$B$9*4+1),0)))/4)) -> 测算期内未回收 | C10: 年 | D10: =核心参数输入!$B$73 -> 15 | E10: =IF(COUNTIFS(季度现金流!$D$155:INDEX(季度现金流!$D$155:$DT$155,1,核心参数输入!$B$9*4+1),"<0")=0,"不适用",IF(COUNTIFS(季度现金流!$D$181:INDEX(季度现金流!$D$181:$DT$181,1,核心参数输入!$B$9*4+1),1)=0,"测算期内未回收",(MATCH(1,季度现金流!$D$181:INDEX(季度现金流!$D$181:$DT$181,1,核心参数输入!$B$9*4+1),0)-2-INDEX(季度现金流!$D$178:$DT$178,1,MAX(1,MATCH(1,季度现金流!$D$181:INDEX(季度现金流!$D$181:$DT$181,1,核心参数输入!$B$9*4+1),0)-1))/INDEX(季度现金流!$D$155:$DT$155,1,MATCH(1,季度现金流!$D$181:INDEX(季度现金流!$D$181:$DT$181,1,核心参数输入!$B$9*4+1),0)))/4)) -> 测算期内未回收 | F10: =IF(B10="不适用","未通过",IF(NOT(ISNUMBER(B10)),IF(B10="无法计算","待判断","未通过"),IF(B10<=D10,"通过","未通过"))) -> 未通过 | G10: =IF(E10="不适用","未通过",IF(NOT(ISNUMBER(E10)),IF(E10="无法计算","待判断","未通过"),IF(E10<=D10,"通过","未通过"))) -> 未通过 | H10: 首次跨零、季内线性插值；若以后再次转负需另审视
A11: 动态投资回收期 | B11: =IF(COUNTIFS(季度现金流!$D$69:INDEX(季度现金流!$D$69:$DT$69,1,核心参数输入!$B$9*4+1),"<0")=0,"不适用",IF(COUNTIFS(季度现金流!$D$72:INDEX(季度现金流!$D$72:$DT$72,1,核心参数输入!$B$9*4+1),1)=0,"测算期内未回收",(MATCH(1,季度现金流!$D$72:INDEX(季度现金流!$D$72:$DT$72,1,核心参数输入!$B$9*4+1),0)-2-INDEX(季度现金流!$D$70:$DT$70,1,MAX(1,MATCH(1,季度现金流!$D$72:INDEX(季度现金流!$D$72:$DT$72,1,核心参数输入!$B$9*4+1),0)-1))/INDEX(季度现金流!$D$69:$DT$69,1,MATCH(1,季度现金流!$D$72:INDEX(季度现金流!$D$72:$DT$72,1,核心参数输入!$B$9*4+1),0)))/4)) -> 测算期内未回收 | C11: 年 | D11: =核心参数输入!$B$74 -> 20 | E11: =IF(COUNTIFS(季度现金流!$D$179:INDEX(季度现金流!$D$179:$DT$179,1,核心参数输入!$B$9*4+1),"<0")=0,"不适用",IF(COUNTIFS(季度现金流!$D$182:INDEX(季度现金流!$D$182:$DT$182,1,核心参数输入!$B$9*4+1),1)=0,"测算期内未回收",(MATCH(1,季度现金流!$D$182:INDEX(季度现金流!$D$182:$DT$182,1,核心参数输入!$B$9*4+1),0)-2-INDEX(季度现金流!$D$180:$DT$180,1,MAX(1,MATCH(1,季度现金流!$D$182:INDEX(季度现金流!$D$182:$DT$182,1,核心参数输入!$B$9*4+1),0)-1))/INDEX(季度现金流!$D$179:$DT$179,1,MATCH(1,季度现金流!$D$182:INDEX(季度现金流!$D$182:$DT$182,1,核心参数输入!$B$9*4+1),0)))/4)) -> 测算期内未回收 | F11: =IF(B11="不适用","未通过",IF(NOT(ISNUMBER(B11)),IF(B11="无法计算","待判断","未通过"),IF(B11<=D11,"通过","未通过"))) -> 未通过 | G11: =IF(E11="不适用","未通过",IF(NOT(ISNUMBER(E11)),IF(E11="无法计算","待判断","未通过"),IF(E11<=D11,"通过","未通过"))) -> 未通过
A12: 最低年度经营DSCR | B12: =IF(核心参数输入!$B$57=0,"不适用",IF(COUNT(年度汇总!$D$24:$AH$24)=0,"无法计算",MIN(年度汇总!$D$42:$AH$42))) -> 0.21197153 | C12: 倍 | D12: =核心参数输入!$B$75 -> 1.2 | E12: =IF(核心参数输入!$B$57=0,"不适用",IF(COUNT(年度汇总!$D$84:$AH$84)=0,"无法计算",MIN(年度汇总!$D$102:$AH$102))) -> 0.14850575 | F12: =IF(B12="不适用","通过",IF(NOT(ISNUMBER(B12)),IF(B12="无法计算","待判断","未通过"),IF(B12>=D12,"通过","未通过"))) -> 未通过 | G12: =IF(E12="不适用","通过",IF(NOT(ISNUMBER(E12)),IF(E12="无法计算","待判断","未通过"),IF(E12>=D12,"通过","未通过"))) -> 未通过 | H12: 按年度CFADS／年度合同本息；季度覆盖另见现金流表
A13: 所需累计资本金 | B13: =SUM(季度现金流!$D$49:INDEX(季度现金流!$D$49:$DT$49,1,核心参数输入!$B$9*4+1)) -> 32810 | C13: 万元 | D13: =核心参数输入!$B$61 -> 33000 | E13: =SUM(季度现金流!$D$159:INDEX(季度现金流!$D$159:$DT$159,1,核心参数输入!$B$9*4+1)) -> 38102 | F13: =IF(B13="不适用","未通过",IF(NOT(ISNUMBER(B13)),IF(B13="无法计算","待判断","未通过"),IF(B13<=D13+0.01,"通过","未通过"))) -> 通过 | G13: =IF(E13="不适用","未通过",IF(NOT(ISNUMBER(E13)),IF(E13="无法计算","待判断","未通过"),IF(E13<=D13+0.01,"通过","未通过"))) -> 未通过
A14: 最大未落实资金缺口 | B14: =MAX(季度现金流!$D$58:INDEX(季度现金流!$D$58:$DT$58,1,核心参数输入!$B$9*4+1)) -> 0 | C14: 万元 | D14: =0 -> 0 | E14: =MAX(季度现金流!$D$168:INDEX(季度现金流!$D$168:$DT$168,1,核心参数输入!$B$9*4+1)) -> 5102 | F14: =IF(B14="不适用","未通过",IF(NOT(ISNUMBER(B14)),IF(B14="无法计算","待判断","未通过"),IF(ABS(B14)<=0.01,"通过","未通过"))) -> 通过 | G14: =IF(E14="不适用","未通过",IF(NOT(ISNUMBER(E14)),IF(E14="无法计算","待判断","未通过"),IF(ABS(E14)<=0.01,"通过","未通过"))) -> 未通过
A15: 到期计划本金余额 | B15: =IF(核心参数输入!$B$57=0,0,IF(季度投融资!$B$29>核心参数输入!$B$9*4,"无法计算",INDEX(季度投融资!$D$43:$DT$43,1,MIN(121,季度投融资!$B$29+1)))) -> 0 | C15: 万元 | D15: =0 -> 0 | E15: =IF(核心参数输入!$B$57=0,0,IF(季度投融资!$E$29>核心参数输入!$B$9*4,"无法计算",INDEX(季度投融资!$D$153:$DT$153,1,MIN(121,季度投融资!$E$29+1)))) -> 0 | F15: =IF(B15="不适用","未通过",IF(NOT(ISNUMBER(B15)),IF(B15="无法计算","待判断","未通过"),IF(ABS(B15)<=0.01,"通过","未通过"))) -> 通过 | G15: =IF(E15="不适用","未通过",IF(NOT(ISNUMBER(E15)),IF(E15="无法计算","待判断","未通过"),IF(ABS(E15)<=0.01,"通过","未通过"))) -> 通过 | H15: 合同计划还款后的余额，不等于实际已经偿还
A16: 总投资含建设期融资费用 | B16: =季度投融资!$B$21 -> 63310 | C16: 万元 | E16: =季度投融资!$E$21 -> 68602
A17: 既定贷款额度 | B17: =核心参数输入!$B$57 -> 30000 | C17: 万元 | E17: =核心参数输入!$B$57 -> 30000
A18: 可投入资本金额度 | B18: =核心参数输入!$B$61 -> 33000 | C18: 万元 | E18: =核心参数输入!$B$61 -> 33000
A19: 测算期销售交付比例 | B19: =SUM(季度计划!$D$15:INDEX(季度计划!$D$15:$DT$15,1,核心参数输入!$B$9*4+1)) -> 1 | C19: % | E19: =SUM(季度计划!$D$125:INDEX(季度计划!$D$125:$DT$125,1,核心参数输入!$B$9*4+1)) -> 1
A20: 销售交付完成时间 | B20: =IF(核心参数输入!$B$142=0,"不适用",IF(B19<0.999999,"期内未完成",INDEX(季度计划!$D$5:$DT$5,1,MATCH(1,指标与情景!$D$90:$DT$90,0)))) -> 2032Q4 | C20: 说明 | E20: =IF(核心参数输入!$B$142=0,"不适用",IF(E19<0.999999,"期内未完成",INDEX(季度计划!$D$5:$DT$5,1,MATCH(1,指标与情景!$D$200:$DT$200,0)))) -> 2032Q4
A21: 持有出租面积 | B21: =(核心参数输入!$B$10*核心参数输入!$B$11*核心参数输入!$B$12*核心参数输入!$B$143) -> 60750 | C21: 平方米 | E21: =(核心参数输入!$B$10*核心参数输入!$B$11*核心参数输入!$B$12*核心参数输入!$B$143) -> 60750
A22: 稳定运营现金保本出租率 | B22: =IF(OR((核心参数输入!$B$10*核心参数输入!$B$11*核心参数输入!$B$12*核心参数输入!$B$143)=0,核心参数输入!$B$9<核心参数输入!$B$18+3+INT((核心参数输入!$B$148)/4)),"不适用",IF(((核心参数输入!$B$10*核心参数输入!$B$11*核心参数输入!$B$12*核心参数输入!$B$143)*INDEX(季度经营税费!$D$20:$DT$20,1,MIN(核心参数输入!$B$9*4,(核心参数输入!$B$18+3)*4+核心参数输入!$B$148)+1)*12/10000)*(核心参数输入!$B$43*(1+核心参数输入!$B$44)*(1-核心参数输入!$B$49)/(1+IF(核心参数输入!$B$96=2,核心参数输入!$B$119,0))-(1+核心参数输入!$B$43*核心参数输入!$B$44)*IF(核心参数输入!$B$96=1,核心参数输入!$B$51,核心参数输入!$B$122))<=0,"无法计算",(INDEX(季度经营税费!$D$37:$DT$37,1,MIN(核心参数输入!$B$9*4,(核心参数输入!$B$18+3)*4+核心参数输入!$B$148)+1)*4+核心参数输入!$B$50*(核心参数输入!$B$10*核心参数输入!$B$11*核心参数输入!$B$12*核心参数输入!$B$143)/MAX(1,核心参数输入!$B$108))/(((核心参数输入!$B$10*核心参数输入!$B$11*核心参数输入!$B$12*核心参数输入!$B$143)*INDEX(季度经营税费!$D$20:$DT$20,1,MIN(核心参数输入!$B$9*4,(核心参数输入!$B$18+3)*4+核心参数输入!$B$148)+1)*12/10000)*(核心参数输入!$B$43*(1+核心参数输入!$B$44)*(1-核心参数输入!$B$49)/(1+IF(核心参数输入!$B$96=2,核心参数输入!$B$119,0))-(1+核心参数输入!$B$43*核心参数输入!$B$44)*IF(核心参数输入!$B$96=1,核心参数输入!$B$51,核心参数输入!$B$122))))) -> 0.29842494 | C22: % | E22: =IF(OR((核心参数输入!$B$10*核心参数输入!$B$11*核心参数输入!$B$12*核心参数输入!$B$143)=0,核心参数输入!$B$9<核心参数输入!$B$18+3+INT((核心参数输入!$B$148+核心参数输入!$B$124)/4)),"不适用",IF(((核心参数输入!$B$10*核心参数输入!$B$11*核心参数输入!$B$12*核心参数输入!$B$143)*INDEX(季度经营税费!$D$130:$DT$130,1,MIN(核心参数输入!$B$9*4,(核心参数输入!$B$18+3)*4+核心参数输入!$B$148+核心参数输入!$B$124)+1)*12/10000)*(核心参数输入!$B$43*(1+核心参数输入!$B$44)*(1-核心参数输入!$B$49)/(1+IF(核心参数输入!$B$96=2,核心参数输入!$B$119,0))-(1+核心参数输入!$B$43*核心参数输入!$B$44)*IF(核心参数输入!$B$96=1,核心参数输入!$B$51,核心参数输入!$B$122))<=0,"无法计算",(INDEX(季度经营税费!$D$147:$DT$147,1,MIN(核心参数输入!$B$9*4,(核心参数输入!$B$18+3)*4+核心参数输入!$B$148+核心参数输入!$B$124)+1)*4+核心参数输入!$B$50*(核心参数输入!$B$10*核心参数输入!$B$11*核心参数输入!$B$12*核心参数输入!$B$143)/MAX(1,核心参数输入!$B$108))/(((核心参数输入!$B$10*核心参数输入!$B$11*核心参数输入!$B$12*核心参数输入!$B$143)*INDEX(季度经营税费!$D$130:$DT$130,1,MIN(核心参数输入!$B$9*4,(核心参数输入!$B$18+3)*4+核心参数输入!$B$148+核心参数输入!$B$124)+1)*12/10000)*(核心参数输入!$B$43*(1+核心参数输入!$B$44)*(1-核心参数输入!$B$49)/(1+IF(核心参数输入!$B$96=2,核心参数输入!$B$119,0))-(1+核心参数输入!$B$43*核心参数输入!$B$44)*IF(核心参数输入!$B$96=1,核心参数输入!$B$51,核心参数输入!$B$122))))) -> 0.33158327 | H22: 仅稳定运营现金保本，不含所得税、折旧、本息和投资回收；无新增免租
A23: 持有稳定NOI收益率 | B23: =IF(OR((核心参数输入!$B$10*核心参数输入!$B$11*核心参数输入!$B$12*核心参数输入!$B$143)=0,季度投融资!$B$27=0,核心参数输入!$B$9<核心参数输入!$B$18+3+INT((核心参数输入!$B$148)/4)),"不适用",INDEX(季度经营税费!$D$70:$DT$70,1,MIN(核心参数输入!$B$9*4,(核心参数输入!$B$18+3)*4+核心参数输入!$B$148)+1)*4/季度投融资!$B$27) -> 0.033836975 | C23: % | E23: =IF(OR((核心参数输入!$B$10*核心参数输入!$B$11*核心参数输入!$B$12*核心参数输入!$B$143)=0,季度投融资!$E$27=0,核心参数输入!$B$9<核心参数输入!$B$18+3+INT((核心参数输入!$B$148+核心参数输入!$B$124)/4)),"不适用",INDEX(季度经营税费!$D$180:$DT$180,1,MIN(核心参数输入!$B$9*4,(核心参数输入!$B$18+3)*4+核心参数输入!$B$148+核心参数输入!$B$124)+1)*4/季度投融资!$E$27) -> 0.02169914 | H23: 稳定观察季度NOI×4／持有分摊总投资；非IRR
A24: 期末净处置占现金流入 | B24: =IF(SUM(季度经营税费!$D$68:INDEX(季度经营税费!$D$68:$DT$68,1,核心参数输入!$B$9*4+1))+SUM(季度经营税费!$D$59:INDEX(季度经营税费!$D$59:$DT$59,1,核心参数输入!$B$9*4+1))=0,"不适用",IF(核心参数输入!$B$64=1,SUM(季度经营税费!$D$59:INDEX(季度经营税费!$D$59:$DT$59,1,核心参数输入!$B$9*4+1))/(SUM(季度经营税费!$D$68:INDEX(季度经营税费!$D$68:$DT$68,1,核心参数输入!$B$9*4+1))+SUM(季度经营税费!$D$59:INDEX(季度经营税费!$D$59:$DT$59,1,核心参数输入!$B$9*4+1))),0)) -> 0 | C24: % | E24: =IF(SUM(季度经营税费!$D$178:INDEX(季度经营税费!$D$178:$DT$178,1,核心参数输入!$B$9*4+1))+SUM(季度经营税费!$D$169:INDEX(季度经营税费!$D$169:$DT$169,1,核心参数输入!$B$9*4+1))=0,"不适用",IF(核心参数输入!$B$64=1,SUM(季度经营税费!$D$169:INDEX(季度经营税费!$D$169:$DT$169,1,核心参数输入!$B$9*4+1))/(SUM(季度经营税费!$D$178:INDEX(季度经营税费!$D$178:$DT$178,1,核心参数输入!$B$9*4+1))+SUM(季度经营税费!$D$169:INDEX(季度经营税费!$D$169:$DT$169,1,核心参数输入!$B$9*4+1))),0)) -> 0
A25: 项目IRR变号提示 | B25: =IF(SUM(季度现金流!$D$64:INDEX(季度现金流!$D$64:$DT$64,1,核心参数输入!$B$9*4+1))>1,"多次变号，IRR需结合NPV审视","单次变号或无变号") -> 单次变号或无变号 | C25: 说明 | E25: =IF(SUM(季度现金流!$D$174:INDEX(季度现金流!$D$174:$DT$174,1,核心参数输入!$B$9*4+1))>1,"多次变号，IRR需结合NPV审视","单次变号或无变号") -> 单次变号或无变号
A26: 资本金IRR变号提示 | B26: =IF(SUM(季度现金流!$D$75:INDEX(季度现金流!$D$75:$DT$75,1,核心参数输入!$B$9*4+1))>1,"多次变号，IRR需结合NPV审视","单次变号或无变号") -> 单次变号或无变号 | C26: 说明 | E26: =IF(SUM(季度现金流!$D$185:INDEX(季度现金流!$D$185:$DT$185,1,核心参数输入!$B$9*4+1))>1,"多次变号，IRR需结合NPV审视","单次变号或无变号") -> 单次变号或无变号
A27: 资本金收益可执行性 | B27: =IF(B14>0.01,"理论收益，资金尚未落实","完整出资、留存后分配口径") -> 完整出资、留存后分配口径 | C27: 说明 | E27: =IF(E14>0.01,"理论收益，资金尚未落实","完整出资、留存后分配口径") -> 理论收益，资金尚未落实
A28: 稳定观察项目年度 | B28: =IF(核心参数输入!$B$9>=核心参数输入!$B$18+3+INT((核心参数输入!$B$148)/4),核心参数输入!$B$18+3+INT((核心参数输入!$B$148)/4),"未覆盖稳定观察年") -> 7 | C28: 年 | E28: =IF(核心参数输入!$B$9>=核心参数输入!$B$18+3+INT((核心参数输入!$B$148+核心参数输入!$B$124)/4),核心参数输入!$B$18+3+INT((核心参数输入!$B$148+核心参数输入!$B$124)/4),"未覆盖稳定观察年") -> 7
A29: 融资前峰值资金需要 | B29: =MAX(季度现金流!$D$77:INDEX(季度现金流!$D$77:$DT$77,1,核心参数输入!$B$9*4+1)) -> 62810 | C29: 万元 | E29: =MAX(季度现金流!$D$187:INDEX(季度现金流!$D$187:$DT$187,1,核心参数输入!$B$9*4+1)) -> 68102 | H29: 排除贷款和股东流入及本金偿还，包含融资利息和手续费
A30: 融资前峰值发生季度 | B30: =INDEX(季度计划!$D$5:$DT$5,1,MATCH(MAX(季度现金流!$D$77:INDEX(季度现金流!$D$77:$DT$77,1,核心参数输入!$B$9*4+1)),季度现金流!$D$77:INDEX(季度现金流!$D$77:$DT$77,1,核心参数输入!$B$9*4+1),0)) -> 2029Q4 | C30: 说明 | E30: =INDEX(季度计划!$D$5:$DT$5,1,MATCH(MAX(季度现金流!$D$187:INDEX(季度现金流!$D$187:$DT$187,1,核心参数输入!$B$9*4+1)),季度现金流!$D$187:INDEX(季度现金流!$D$187:$DT$187,1,核心参数输入!$B$9*4+1),0)) -> 2029Q4
A31: 未落实缺口高峰季度 | B31: =IF(B14<=0.01,"无未落实缺口",INDEX(季度计划!$D$5:$DT$5,1,MATCH(MAX(季度现金流!$D$58:INDEX(季度现金流!$D$58:$DT$58,1,核心参数输入!$B$9*4+1)),季度现金流!$D$58:INDEX(季度现金流!$D$58:$DT$58,1,核心参数输入!$B$9*4+1),0))) -> 无未落实缺口 | C31: 说明 | E31: =IF(E14<=0.01,"无未落实缺口",INDEX(季度计划!$D$5:$DT$5,1,MATCH(MAX(季度现金流!$D$168:INDEX(季度现金流!$D$168:$DT$168,1,核心参数输入!$B$9*4+1)),季度现金流!$D$168:INDEX(季度现金流!$D$168:$DT$168,1,核心参数输入!$B$9*4+1),0))) -> 2029Q4
A32: 累计资本金投入高峰季度 | B32: =INDEX(季度计划!$D$5:$DT$5,1,MATCH(MAX(季度现金流!$D$79:INDEX(季度现金流!$D$79:$DT$79,1,核心参数输入!$B$9*4+1)),季度现金流!$D$79:INDEX(季度现金流!$D$79:$DT$79,1,核心参数输入!$B$9*4+1),0)) -> 2029Q4 | C32: 说明 | E32: =INDEX(季度计划!$D$5:$DT$5,1,MATCH(MAX(季度现金流!$D$189:INDEX(季度现金流!$D$189:$DT$189,1,核心参数输入!$B$9*4+1)),季度现金流!$D$189:INDEX(季度现金流!$D$189:$DT$189,1,核心参数输入!$B$9*4+1),0)) -> 2029Q4
A33: 最低额度内期末现金 | B33: =MIN(季度现金流!$D$57:INDEX(季度现金流!$D$57:$DT$57,1,核心参数输入!$B$9*4+1)) -> 0 | C33: 万元 | E33: =MIN(季度现金流!$D$167:INDEX(季度现金流!$D$167:$DT$167,1,核心参数输入!$B$9*4+1)) -> 0
A34: 期末销售应收余额 | B34: =INDEX(季度经营税费!$D$13:$DT$13,1,核心参数输入!$B$9*4+1) -> 0 | C34: 万元 | E34: =INDEX(季度经营税费!$D$123:$DT$123,1,核心参数输入!$B$9*4+1) -> 0
A35: 累计净利润 | B35: =SUM(年度汇总!$D$17:$AH$17) -> 4193.6056 | C35: 万元 | E35: =SUM(年度汇总!$D$77:$AH$77) -> -8045.9068
A36: 流转税口径 | B36: =核心参数输入!$B$152 -> 综合税费率（沿用V2） | C36: 说明 | E36: =核心参数输入!$B$152 -> 综合税费率（沿用V2）
A37: 贷款合同到期时间 | B37: =IF(核心参数输入!$B$57=0,"无贷款",INDEX(季度计划!$D$5:$DT$5,1,MAX(1,MIN(121,季度投融资!$B$29+1)))) -> 2036Q4 | C37: 说明 | E37: =IF(核心参数输入!$B$57=0,"无贷款",INDEX(季度计划!$D$5:$DT$5,1,MAX(1,MIN(121,季度投融资!$E$29+1)))) -> 2036Q4
A38: 持续持有项目IRR | B38: =IF(AND(COUNTIFS(季度现金流!$D$18:INDEX(季度现金流!$D$18:$DT$18,1,核心参数输入!$B$9*4+1),"<0")>0,COUNTIFS(季度现金流!$D$18:INDEX(季度现金流!$D$18:$DT$18,1,核心参数输入!$B$9*4+1),">0")>0),IFERROR((1+IRR(季度现金流!$D$18:INDEX(季度现金流!$D$18:$DT$18,1,核心参数输入!$B$9*4+1)))^4-1,"无法计算"),"无法计算") -> -0.014445335 | C38: % | E38: =IF(AND(COUNTIFS(季度现金流!$D$128:INDEX(季度现金流!$D$128:$DT$128,1,核心参数输入!$B$9*4+1),"<0")>0,COUNTIFS(季度现金流!$D$128:INDEX(季度现金流!$D$128:$DT$128,1,核心参数输入!$B$9*4+1),">0")>0),IFERROR((1+IRR(季度现金流!$D$128:INDEX(季度现金流!$D$128:$DT$128,1,核心参数输入!$B$9*4+1)))^4-1,"无法计算"),"无法计算") -> -0.049549603 | H38: 持续持有不将物业、存货或应收自动变现；周转按B109
A39: 期末出售项目IRR | B39: =IF(AND(COUNTIFS(季度现金流!$D$19:INDEX(季度现金流!$D$19:$DT$19,1,核心参数输入!$B$9*4+1),"<0")>0,COUNTIFS(季度现金流!$D$19:INDEX(季度现金流!$D$19:$DT$19,1,核心参数输入!$B$9*4+1),">0")>0),IFERROR((1+IRR(季度现金流!$D$19:INDEX(季度现金流!$D$19:$DT$19,1,核心参数输入!$B$9*4+1)))^4-1,"无法计算"),"无法计算") -> 0.033744637 | C39: % | E39: =IF(AND(COUNTIFS(季度现金流!$D$129:INDEX(季度现金流!$D$129:$DT$129,1,核心参数输入!$B$9*4+1),"<0")>0,COUNTIFS(季度现金流!$D$129:INDEX(季度现金流!$D$129:$DT$129,1,核心参数输入!$B$9*4+1),">0")>0),IFERROR((1+IRR(季度现金流!$D$129:INDEX(季度现金流!$D$129:$DT$129,1,核心参数输入!$B$9*4+1)))^4-1,"无法计算"),"无法计算") -> 0.014103066 | H39: 仅出售持有物业，扣费用与所得税，周转按B110
A40: 持续持有项目NPV | B40: =NPV((1+核心参数输入!$B$71)^(1/4)-1,季度现金流!$E$18:INDEX(季度现金流!$D$18:$DT$18,1,核心参数输入!$B$9*4+1))+季度现金流!D18 -> -20406.095 | C40: 万元 | E40: =NPV((1+核心参数输入!$B$71)^(1/4)-1,季度现金流!$E$128:INDEX(季度现金流!$D$128:$DT$128,1,核心参数输入!$B$9*4+1))+季度现金流!D128 -> -28525.14
A41: 期末出售项目NPV | B41: =NPV((1+核心参数输入!$B$71)^(1/4)-1,季度现金流!$E$19:INDEX(季度现金流!$D$19:$DT$19,1,核心参数输入!$B$9*4+1))+季度现金流!D19 -> -14899.172 | C41: 万元 | E41: =NPV((1+核心参数输入!$B$71)^(1/4)-1,季度现金流!$E$129:INDEX(季度现金流!$D$129:$DT$129,1,核心参数输入!$B$9*4+1))+季度现金流!D129 -> -22937.558
A42: 持续持有资本金IRR | B42: =IF(AND(COUNTIFS(季度现金流!$D$31:INDEX(季度现金流!$D$31:$DT$31,1,核心参数输入!$B$9*4+1),"<0")>0,COUNTIFS(季度现金流!$D$31:INDEX(季度现金流!$D$31:$DT$31,1,核心参数输入!$B$9*4+1),">0")>0),IFERROR((1+IRR(季度现金流!$D$31:INDEX(季度现金流!$D$31:$DT$31,1,核心参数输入!$B$9*4+1)))^4-1,"无法计算"),"无法计算") -> -0.040676665 | C42: % | E42: =IF(AND(COUNTIFS(季度现金流!$D$141:INDEX(季度现金流!$D$141:$DT$141,1,核心参数输入!$B$9*4+1),"<0")>0,COUNTIFS(季度现金流!$D$141:INDEX(季度现金流!$D$141:$DT$141,1,核心参数输入!$B$9*4+1),">0")>0),IFERROR((1+IRR(季度现金流!$D$141:INDEX(季度现金流!$D$141:$DT$141,1,核心参数输入!$B$9*4+1)))^4-1,"无法计算"),"无法计算") -> -0.087463531
A43: 期末出售资本金IRR | B43: =IF(AND(COUNTIFS(季度现金流!$D$41:INDEX(季度现金流!$D$41:$DT$41,1,核心参数输入!$B$9*4+1),"<0")>0,COUNTIFS(季度现金流!$D$41:INDEX(季度现金流!$D$41:$DT$41,1,核心参数输入!$B$9*4+1),">0")>0),IFERROR((1+IRR(季度现金流!$D$41:INDEX(季度现金流!$D$41:$DT$41,1,核心参数输入!$B$9*4+1)))^4-1,"无法计算"),"无法计算") -> 0.030390403 | C43: % | E43: =IF(AND(COUNTIFS(季度现金流!$D$151:INDEX(季度现金流!$D$151:$DT$151,1,核心参数输入!$B$9*4+1),"<0")>0,COUNTIFS(季度现金流!$D$151:INDEX(季度现金流!$D$151:$DT$151,1,核心参数输入!$B$9*4+1),">0")>0),IFERROR((1+IRR(季度现金流!$D$151:INDEX(季度现金流!$D$151:$DT$151,1,核心参数输入!$B$9*4+1)))^4-1,"无法计算"),"无法计算") -> 0.0046828705
A44: 当前口径周转回收 | B44: =SUM(季度现金流!$D$16:INDEX(季度现金流!$D$16:$DT$16,1,核心参数输入!$B$9*4+1))*(1-核心参数输入!$B$64)+SUM(季度现金流!$D$17:INDEX(季度现金流!$D$17:$DT$17,1,核心参数输入!$B$9*4+1))*核心参数输入!$B$64 -> 0 | C44: 万元 | E44: =SUM(季度现金流!$D$126:INDEX(季度现金流!$D$126:$DT$126,1,核心参数输入!$B$9*4+1))*(1-核心参数输入!$B$64)+SUM(季度现金流!$D$127:INDEX(季度现金流!$D$127:$DT$127,1,核心参数输入!$B$9*4+1))*核心参数输入!$B$64 -> 0
A45: 持有账面净值（出售前） | B45: =INDEX(季度经营税费!$D$56:$DT$56,1,核心参数输入!$B$9*4+1) -> 13762.777 | C45: 万元 | E45: =INDEX(季度经营税费!$D$166:$DT$166,1,核心参数输入!$B$9*4+1) -> 14862.19
A46: 期末未抵扣进项税 | B46: =INDEX(季度经营税费!$D$52:$DT$52,1,核心参数输入!$B$9*4+1) -> 0 | C46: 万元 | E46: =INDEX(季度经营税费!$D$162:$DT$162,1,核心参数输入!$B$9*4+1) -> 0
A47: 最大理论留存现金 | B47: =MAX(季度现金流!$D$51:INDEX(季度现金流!$D$51:$DT$51,1,核心参数输入!$B$9*4+1)) -> 15161.955 | C47: 万元 | E47: =MAX(季度现金流!$D$161:INDEX(季度现金流!$D$161:$DT$161,1,核心参数输入!$B$9*4+1)) -> 16491.084
A48: 最低DSCR发生年度 | B48: =IF(核心参数输入!$B$57=0,"不适用",IF(ISNUMBER(B12),INDEX(年度汇总!$D$5:$AH$5,1,MATCH(B12,年度汇总!$D$24:$AH$24,0)),"无法计算")) -> 2034 | C48: 说明 | E48: =IF(核心参数输入!$B$57=0,"不适用",IF(ISNUMBER(E12),INDEX(年度汇总!$D$5:$AH$5,1,MATCH(E12,年度汇总!$D$84:$AH$84,0)),"无法计算")) -> 2034
A49: 模型基础有效标志 | B49: =IF(AND(核心参数输入!$B$150=1,季度计划!$B$30=1,季度投融资!$B$33=1,季度投融资!$B$21>0),1,0) -> 1 | C49: 0/1 | E49: =IF(AND(核心参数输入!$B$150=1,季度计划!$B$30=1,季度投融资!$B$33=1,季度投融资!$E$21>0),1,0) -> 1 | H49: 输入、计划、融资的本地必要条件；独立校验在模型校验表
A50: 已建模全部财务条件达标标志 | B50: =IF(AND(B49=1,COUNTIFS(F6:F15,"未通过")=0,COUNTIFS(F6:F15,"待判断")=0),1,0) -> 0 | C50: 0/1 | E50: =IF(AND(E49=1,COUNTIFS(G6:G15,"未通过")=0,COUNTIFS(G6:G15,"待判断")=0),1,0) -> 0 | H50: 只代表当前已建模财务条件；不包含未确认假设和市场论证
A51: 资金约束达标标志 | B51: =IF(AND(ISNUMBER(B13),B13<=核心参数输入!$B$61+0.01,B14<=0.01,ISNUMBER(B15),ABS(B15)<=0.01),1,0) -> 1 | C51: 0/1 | E51: =IF(AND(ISNUMBER(E13),E13<=核心参数输入!$B$61+0.01,E14<=0.01,ISNUMBER(E15),ABS(E15)<=0.01),1,0) -> 0
A52: 项目NPV盈亏差额 | B52: =B8 -> -20406.095 | C52: 万元 | E52: =E8 -> -28525.14
A53: 稳定经营现金NOI | B53: =IF(OR((核心参数输入!$B$10*核心参数输入!$B$11*核心参数输入!$B$12*核心参数输入!$B$143)=0,核心参数输入!$B$9<核心参数输入!$B$18+3+INT((核心参数输入!$B$148)/4)),"不适用",INDEX(季度经营税费!$D$70:$DT$70,1,MIN(核心参数输入!$B$9*4,(核心参数输入!$B$18+3)*4+核心参数输入!$B$148)+1)*4) -> 973.30368 | C53: 万元 | E53: =IF(OR((核心参数输入!$B$10*核心参数输入!$B$11*核心参数输入!$B$12*核心参数输入!$B$143)=0,核心参数输入!$B$9<核心参数输入!$B$18+3+INT((核心参数输入!$B$148+核心参数输入!$B$124)/4)),"不适用",INDEX(季度经营税费!$D$180:$DT$180,1,MIN(核心参数输入!$B$9*4,(核心参数输入!$B$18+3)*4+核心参数输入!$B$148+核心参数输入!$B$124)+1)*4) -> 675.83926
A54: 已建模参数确认状态 | B54: =IF(核心参数输入!$B$97=1,"新增假设已核对","新增假设待项目核对") -> 新增假设待项目核对 | C54: 说明 | E54: =IF(核心参数输入!$B$97=1,"新增假设已核对","新增假设待项目核对") -> 新增假设待项目核对
D90: =IF(SUM(季度计划!$D$15:D15)>=0.999999,1,0) -> 0 | E90: =IF(SUM(季度计划!$D$15:E15)>=0.999999,1,0) -> 0 | F90: =IF(SUM(季度计划!$D$15:F15)>=0.999999,1,0) -> 0 | G90: =IF(SUM(季度计划!$D$15:G15)>=0.999999,1,0) -> 0 | H90: =IF(SUM(季度计划!$D$15:H15)>=0.999999,1,0) -> 0 | I90: =IF(SUM(季度计划!$D$15:I15)>=0.999999,1,0) -> 0 | J90: =IF(SUM(季度计划!$D$15:J15)>=0.999999,1,0) -> 0 | K90: =IF(SUM(季度计划!$D$15:K15)>=0.999999,1,0) -> 0 | ... DT90: =IF(SUM(季度计划!$D$15:DT15)>=0.999999,1,0) -> 1
D200: =IF(SUM(季度计划!$D$125:D125)>=0.999999,1,0) -> 0 | E200: =IF(SUM(季度计划!$D$125:E125)>=0.999999,1,0) -> 0 | F200: =IF(SUM(季度计划!$D$125:F125)>=0.999999,1,0) -> 0 | G200: =IF(SUM(季度计划!$D$125:G125)>=0.999999,1,0) -> 0 | H200: =IF(SUM(季度计划!$D$125:H125)>=0.999999,1,0) -> 0 | I200: =IF(SUM(季度计划!$D$125:I125)>=0.999999,1,0) -> 0 | J200: =IF(SUM(季度计划!$D$125:J125)>=0.999999,1,0) -> 0 | K200: =IF(SUM(季度计划!$D$125:K125)>=0.999999,1,0) -> 0 | ... DT200: =IF(SUM(季度计划!$D$125:DT125)>=0.999999,1,0) -> 1

Sheet 年度汇总
A2: 年度汇总 · V3模拟测算
A4: 项目年度 | D4: 0 | E4: 1 | F4: 2 | G4: 3 | H4: 4 | I4: 5 | J4: 6 | K4: 7 | L4: 8 | M4: 9 | N4: 10 | O4: 11 | P4: 12 | Q4: 13 | R4: 14 | S4: 15 | T4: 16 | U4: 17 | V4: 18 | W4: 19 | X4: 20 | Y4: 21 | Z4: 22 | AA4: 23 | AB4: 24 | AC4: 25 | AD4: 26 | AE4: 27 | AF4: 28 | AG4: 29 | AH4: 30
A5: 日历年份 | D5: =核心参数输入!$B$8+D$4 -> 2026 | E5: =核心参数输入!$B$8+E$4 -> 2027 | F5: =核心参数输入!$B$8+F$4 -> 2028 | G5: =核心参数输入!$B$8+G$4 -> 2029 | H5: =核心参数输入!$B$8+H$4 -> 2030 | I5: =核心参数输入!$B$8+I$4 -> 2031 | J5: =核心参数输入!$B$8+J$4 -> 2032 | K5: =核心参数输入!$B$8+K$4 -> 2033 | ... AH5: =核心参数输入!$B$8+AH$4 -> 2056
A8: 基准 · 年度汇总
A10: 销售收入（利润口径） | B10: 万元 | D10: =IF(0<=核心参数输入!$B$9,SUMIFS(季度经营税费!$D$32:$DT$32,季度经营税费!$D$6:$DT$6,0),0) -> 0 | E10: =IF(1<=核心参数输入!$B$9,SUMIFS(季度经营税费!$D$32:$DT$32,季度经营税费!$D$6:$DT$6,1),0) -> 0 | F10: =IF(2<=核心参数输入!$B$9,SUMIFS(季度经营税费!$D$32:$DT$32,季度经营税费!$D$6:$DT$6,2),0) -> 0 | G10: =IF(3<=核心参数输入!$B$9,SUMIFS(季度经营税费!$D$32:$DT$32,季度经营税费!$D$6:$DT$6,3),0) -> 0 | H10: =IF(4<=核心参数输入!$B$9,SUMIFS(季度经营税费!$D$32:$DT$32,季度经营税费!$D$6:$DT$6,4),0) -> 14478.75 | I10: =IF(5<=核心参数输入!$B$9,SUMIFS(季度经营税费!$D$32:$DT$32,季度经营税费!$D$6:$DT$6,5),0) -> 19305 | J10: =IF(6<=核心参数输入!$B$9,SUMIFS(季度经营税费!$D$32:$DT$32,季度经营税费!$D$6:$DT$6,6),0) -> 14478.75 | K10: =IF(7<=核心参数输入!$B$9,SUMIFS(季度经营税费!$D$32:$DT$32,季度经营税费!$D$6:$DT$6,7),0) -> 0 | L10: =IF(8<=核心参数输入!$B$9,SUMIFS(季度经营税费!$D$32:$DT$32,季度经营税费!$D$6:$DT$6,8),0) -> 0 | M10: =IF(9<=核心参数输入!$B$9,SUMIFS(季度经营税费!$D$32:$DT$32,季度经营税费!$D$6:$DT$6,9),0) -> 0 | N10: =IF(10<=核心参数输入!$B$9,SUMIFS(季度经营税费!$D$32:$DT$32,季度经营税费!$D$6:$DT$6,10),0) -> 0 | O10: =IF(11<=核心参数输入!$B$9,SUMIFS(季度经营税费!$D$32:$DT$32,季度经营税费!$D$6:$DT$6,11),0) -> 0 | P10: =IF(12<=核心参数输入!$B$9,SUMIFS(季度经营税费!$D$32:$DT$32,季度经营税费!$D$6:$DT$6,12),0) -> 0 | Q10: =IF(13<=核心参数输入!$B$9,SUMIFS(季度经营税费!$D$32:$DT$32,季度经营税费!$D$6:$DT$6,13),0) -> 0 | R10: =IF(14<=核心参数输入!$B$9,SUMIFS(季度经营税费!$D$32:$DT$32,季度经营税费!$D$6:$DT$6,14),0) -> 0 | S10: =IF(15<=核心参数输入!$B$9,SUMIFS(季度经营税费!$D$32:$DT$32,季度经营税费!$D$6:$DT$6,15),0) -> 0 | T10: =IF(16<=核心参数输入!$B$9,SUMIFS(季度经营税费!$D$32:$DT$32,季度经营税费!$D$6:$DT$6,16),0) -> 0 | U10: =IF(17<=核心参数输入!$B$9,SUMIFS(季度经营税费!$D$32:$DT$32,季度经营税费!$D$6:$DT$6,17),0) -> 0 | V10: =IF(18<=核心参数输入!$B$9,SUMIFS(季度经营税费!$D$32:$DT$32,季度经营税费!$D$6:$DT$6,18),0) -> 0 | W10: =IF(19<=核心参数输入!$B$9,SUMIFS(季度经营税费!$D$32:$DT$32,季度经营税费!$D$6:$DT$6,19),0) -> 0 | X10: =IF(20<=核心参数输入!$B$9,SUMIFS(季度经营税费!$D$32:$DT$32,季度经营税费!$D$6:$DT$6,20),0) -> 0 | Y10: =IF(21<=核心参数输入!$B$9,SUMIFS(季度经营税费!$D$32:$DT$32,季度经营税费!$D$6:$DT$6,21),0) -> 0 | Z10: =IF(22<=核心参数输入!$B$9,SUMIFS(季度经营税费!$D$32:$DT$32,季度经营税费!$D$6:$DT$6,22),0) -> 0 | AA10: =IF(23<=核心参数输入!$B$9,SUMIFS(季度经营税费!$D$32:$DT$32,季度经营税费!$D$6:$DT$6,23),0) -> 0 | AB10: =IF(24<=核心参数输入!$B$9,SUMIFS(季度经营税费!$D$32:$DT$32,季度经营税费!$D$6:$DT$6,24),0) -> 0 | AC10: =IF(25<=核心参数输入!$B$9,SUMIFS(季度经营税费!$D$32:$DT$32,季度经营税费!$D$6:$DT$6,25),0) -> 0 | AD10: =IF(26<=核心参数输入!$B$9,SUMIFS(季度经营税费!$D$32:$DT$32,季度经营税费!$D$6:$DT$6,26),0) -> 0 | AE10: =IF(27<=核心参数输入!$B$9,SUMIFS(季度经营税费!$D$32:$DT$32,季度经营税费!$D$6:$DT$6,27),0) -> 0 | AF10: =IF(28<=核心参数输入!$B$9,SUMIFS(季度经营税费!$D$32:$DT$32,季度经营税费!$D$6:$DT$6,28),0) -> 0 | AG10: =IF(29<=核心参数输入!$B$9,SUMIFS(季度经营税费!$D$32:$DT$32,季度经营税费!$D$6:$DT$6,29),0) -> 0 | AH10: =IF(30<=核心参数输入!$B$9,SUMIFS(季度经营税费!$D$32:$DT$32,季度经营税费!$D$6:$DT$6,30),0) -> 0
A11: 持有收入（利润口径） | B11: 万元 | D11: =IF(0<=核心参数输入!$B$9,SUMIFS(季度经营税费!$D$33:$DT$33,季度经营税费!$D$6:$DT$6,0),0) -> 0 | E11: =IF(1<=核心参数输入!$B$9,SUMIFS(季度经营税费!$D$33:$DT$33,季度经营税费!$D$6:$DT$6,1),0) -> 0 | F11: =IF(2<=核心参数输入!$B$9,SUMIFS(季度经营税费!$D$33:$DT$33,季度经营税费!$D$6:$DT$6,2),0) -> 0 | G11: =IF(3<=核心参数输入!$B$9,SUMIFS(季度经营税费!$D$33:$DT$33,季度经营税费!$D$6:$DT$6,3),0) -> 0 | H11: =IF(4<=核心参数输入!$B$9,SUMIFS(季度经营税费!$D$33:$DT$33,季度经营税费!$D$6:$DT$6,4),0) -> 279.60112 | I11: =IF(5<=核心参数输入!$B$9,SUMIFS(季度经营税费!$D$33:$DT$33,季度经营税费!$D$6:$DT$6,5),0) -> 1091.0346 | J11: =IF(6<=核心参数输入!$B$9,SUMIFS(季度经营税费!$D$33:$DT$33,季度经营税费!$D$6:$DT$6,6),0) -> 1507.4724 | K11: =IF(7<=核心参数输入!$B$9,SUMIFS(季度经营税费!$D$33:$DT$33,季度经营税费!$D$6:$DT$6,7),0) -> 1786.7229 | L11: =IF(8<=核心参数输入!$B$9,SUMIFS(季度经营税费!$D$33:$DT$33,季度经营税费!$D$6:$DT$6,8),0) -> 1895.9567 | M11: =IF(9<=核心参数输入!$B$9,SUMIFS(季度经营税费!$D$33:$DT$33,季度经营税费!$D$6:$DT$6,9),0) -> 1927.7428 | N11: =IF(10<=核心参数输入!$B$9,SUMIFS(季度经营税费!$D$33:$DT$33,季度经营税费!$D$6:$DT$6,10),0) -> 1956.6589 | O11: =IF(11<=核心参数输入!$B$9,SUMIFS(季度经营税费!$D$33:$DT$33,季度经营税费!$D$6:$DT$6,11),0) -> 1986.0088 | P11: =IF(12<=核心参数输入!$B$9,SUMIFS(季度经营税费!$D$33:$DT$33,季度经营税费!$D$6:$DT$6,12),0) -> 2015.7989 | Q11: =IF(13<=核心参数输入!$B$9,SUMIFS(季度经营税费!$D$33:$DT$33,季度经营税费!$D$6:$DT$6,13),0) -> 2046.0359 | R11: =IF(14<=核心参数输入!$B$9,SUMIFS(季度经营税费!$D$33:$DT$33,季度经营税费!$D$6:$DT$6,14),0) -> 2076.7265 | S11: =IF(15<=核心参数输入!$B$9,SUMIFS(季度经营税费!$D$33:$DT$33,季度经营税费!$D$6:$DT$6,15),0) -> 2107.8774 | T11: =IF(16<=核心参数输入!$B$9,SUMIFS(季度经营税费!$D$33:$DT$33,季度经营税费!$D$6:$DT$6,16),0) -> 2139.4955 | U11: =IF(17<=核心参数输入!$B$9,SUMIFS(季度经营税费!$D$33:$DT$33,季度经营税费!$D$6:$DT$6,17),0) -> 2171.588 | V11: =IF(18<=核心参数输入!$B$9,SUMIFS(季度经营税费!$D$33:$DT$33,季度经营税费!$D$6:$DT$6,18),0) -> 2204.1618 | W11: =IF(19<=核心参数输入!$B$9,SUMIFS(季度经营税费!$D$33:$DT$33,季度经营税费!$D$6:$DT$6,19),0) -> 2237.2242 | X11: =IF(20<=核心参数输入!$B$9,SUMIFS(季度经营税费!$D$33:$DT$33,季度经营税费!$D$6:$DT$6,20),0) -> 2270.7826 | Y11: =IF(21<=核心参数输入!$B$9,SUMIFS(季度经营税费!$D$33:$DT$33,季度经营税费!$D$6:$DT$6,21),0) -> 0 | Z11: =IF(22<=核心参数输入!$B$9,SUMIFS(季度经营税费!$D$33:$DT$33,季度经营税费!$D$6:$DT$6,22),0) -> 0 | AA11: =IF(23<=核心参数输入!$B$9,SUMIFS(季度经营税费!$D$33:$DT$33,季度经营税费!$D$6:$DT$6,23),0) -> 0 | AB11: =IF(24<=核心参数输入!$B$9,SUMIFS(季度经营税费!$D$33:$DT$33,季度经营税费!$D$6:$DT$6,24),0) -> 0 | AC11: =IF(25<=核心参数输入!$B$9,SUMIFS(季度经营税费!$D$33:$DT$33,季度经营税费!$D$6:$DT$6,25),0) -> 0 | AD11: =IF(26<=核心参数输入!$B$9,SUMIFS(季度经营税费!$D$33:$DT$33,季度经营税费!$D$6:$DT$6,26),0) -> 0 | AE11: =IF(27<=核心参数输入!$B$9,SUMIFS(季度经营税费!$D$33:$DT$33,季度经营税费!$D$6:$DT$6,27),0) -> 0 | AF11: =IF(28<=核心参数输入!$B$9,SUMIFS(季度经营税费!$D$33:$DT$33,季度经营税费!$D$6:$DT$6,28),0) -> 0 | AG11: =IF(29<=核心参数输入!$B$9,SUMIFS(季度经营税费!$D$33:$DT$33,季度经营税费!$D$6:$DT$6,29),0) -> 0 | AH11: =IF(30<=核心参数输入!$B$9,SUMIFS(季度经营税费!$D$33:$DT$33,季度经营税费!$D$6:$DT$6,30),0) -> 0
A12: 销售实收现金 | B12: 万元 | D12: =IF(0<=核心参数输入!$B$9,SUMIFS(季度经营税费!$D$12:$DT$12,季度经营税费!$D$6:$DT$6,0),0) -> 0 | E12: =IF(1<=核心参数输入!$B$9,SUMIFS(季度经营税费!$D$12:$DT$12,季度经营税费!$D$6:$DT$6,1),0) -> 0 | F12: =IF(2<=核心参数输入!$B$9,SUMIFS(季度经营税费!$D$12:$DT$12,季度经营税费!$D$6:$DT$6,2),0) -> 0 | G12: =IF(3<=核心参数输入!$B$9,SUMIFS(季度经营税费!$D$12:$DT$12,季度经营税费!$D$6:$DT$6,3),0) -> 0 | H12: =IF(4<=核心参数输入!$B$9,SUMIFS(季度经营税费!$D$12:$DT$12,季度经营税费!$D$6:$DT$6,4),0) -> 13392.844 | I12: =IF(5<=核心参数输入!$B$9,SUMIFS(季度经营税费!$D$12:$DT$12,季度经营税费!$D$6:$DT$6,5),0) -> 18943.031 | J12: =IF(6<=核心参数输入!$B$9,SUMIFS(季度经营税费!$D$12:$DT$12,季度经营税费!$D$6:$DT$6,6),0) -> 14840.719 | K12: =IF(7<=核心参数输入!$B$9,SUMIFS(季度经营税费!$D$12:$DT$12,季度经营税费!$D$6:$DT$6,7),0) -> 1085.9063 | L12: =IF(8<=核心参数输入!$B$9,SUMIFS(季度经营税费!$D$12:$DT$12,季度经营税费!$D$6:$DT$6,8),0) -> 0 | M12: =IF(9<=核心参数输入!$B$9,SUMIFS(季度经营税费!$D$12:$DT$12,季度经营税费!$D$6:$DT$6,9),0) -> 0 | N12: =IF(10<=核心参数输入!$B$9,SUMIFS(季度经营税费!$D$12:$DT$12,季度经营税费!$D$6:$DT$6,10),0) -> 0 | O12: =IF(11<=核心参数输入!$B$9,SUMIFS(季度经营税费!$D$12:$DT$12,季度经营税费!$D$6:$DT$6,11),0) -> 0 | P12: =IF(12<=核心参数输入!$B$9,SUMIFS(季度经营税费!$D$12:$DT$12,季度经营税费!$D$6:$DT$6,12),0) -> 0 | Q12: =IF(13<=核心参数输入!$B$9,SUMIFS(季度经营税费!$D$12:$DT$12,季度经营税费!$D$6:$DT$6,13),0) -> 0 | R12: =IF(14<=核心参数输入!$B$9,SUMIFS(季度经营税费!$D$12:$DT$12,季度经营税费!$D$6:$DT$6,14),0) -> 0 | S12: =IF(15<=核心参数输入!$B$9,SUMIFS(季度经营税费!$D$12:$DT$12,季度经营税费!$D$6:$DT$6,15),0) -> 0 | T12: =IF(16<=核心参数输入!$B$9,SUMIFS(季度经营税费!$D$12:$DT$12,季度经营税费!$D$6:$DT$6,16),0) -> 0 | U12: =IF(17<=核心参数输入!$B$9,SUMIFS(季度经营税费!$D$12:$DT$12,季度经营税费!$D$6:$DT$6,17),0) -> 0 | V12: =IF(18<=核心参数输入!$B$9,SUMIFS(季度经营税费!$D$12:$DT$12,季度经营税费!$D$6:$DT$6,18),0) -> 0 | W12: =IF(19<=核心参数输入!$B$9,SUMIFS(季度经营税费!$D$12:$DT$12,季度经营税费!$D$6:$DT$6,19),0) -> 0 | X12: =IF(20<=核心参数输入!$B$9,SUMIFS(季度经营税费!$D$12:$DT$12,季度经营税费!$D$6:$DT$6,20),0) -> 0 | Y12: =IF(21<=核心参数输入!$B$9,SUMIFS(季度经营税费!$D$12:$DT$12,季度经营税费!$D$6:$DT$6,21),0) -> 0 | Z12: =IF(22<=核心参数输入!$B$9,SUMIFS(季度经营税费!$D$12:$DT$12,季度经营税费!$D$6:$DT$6,22),0) -> 0 | AA12: =IF(23<=核心参数输入!$B$9,SUMIFS(季度经营税费!$D$12:$DT$12,季度经营税费!$D$6:$DT$6,23),0) -> 0 | AB12: =IF(24<=核心参数输入!$B$9,SUMIFS(季度经营税费!$D$12:$DT$12,季度经营税费!$D$6:$DT$6,24),0) -> 0 | AC12: =IF(25<=核心参数输入!$B$9,SUMIFS(季度经营税费!$D$12:$DT$12,季度经营税费!$D$6:$DT$6,25),0) -> 0 | AD12: =IF(26<=核心参数输入!$B$9,SUMIFS(季度经营税费!$D$12:$DT$12,季度经营税费!$D$6:$DT$6,26),0) -> 0 | AE12: =IF(27<=核心参数输入!$B$9,SUMIFS(季度经营税费!$D$12:$DT$12,季度经营税费!$D$6:$DT$6,27),0) -> 0 | AF12: =IF(28<=核心参数输入!$B$9,SUMIFS(季度经营税费!$D$12:$DT$12,季度经营税费!$D$6:$DT$6,28),0) -> 0 | AG12: =IF(29<=核心参数输入!$B$9,SUMIFS(季度经营税费!$D$12:$DT$12,季度经营税费!$D$6:$DT$6,29),0) -> 0 | AH12: =IF(30<=核心参数输入!$B$9,SUMIFS(季度经营税费!$D$12:$DT$12,季度经营税费!$D$6:$DT$6,30),0) -> 0
A13: 租金实收现金 | B13: 万元 | D13: =IF(0<=核心参数输入!$B$9,SUMIFS(季度经营税费!$D$26:$DT$26,季度经营税费!$D$6:$DT$6,0),0) -> 0 | E13: =IF(1<=核心参数输入!$B$9,SUMIFS(季度经营税费!$D$26:$DT$26,季度经营税费!$D$6:$DT$6,1),0) -> 0 | F13: =IF(2<=核心参数输入!$B$9,SUMIFS(季度经营税费!$D$26:$DT$26,季度经营税费!$D$6:$DT$6,2),0) -> 0 | G13: =IF(3<=核心参数输入!$B$9,SUMIFS(季度经营税费!$D$26:$DT$26,季度经营税费!$D$6:$DT$6,3),0) -> 0 | H13: =IF(4<=核心参数输入!$B$9,SUMIFS(季度经营税费!$D$26:$DT$26,季度经营税费!$D$6:$DT$6,4),0) -> 261.20981 | I13: =IF(5<=核心参数输入!$B$9,SUMIFS(季度经营税费!$D$26:$DT$26,季度经营税费!$D$6:$DT$6,5),0) -> 1019.2697 | J13: =IF(6<=核心参数输入!$B$9,SUMIFS(季度经营税费!$D$26:$DT$26,季度经营税费!$D$6:$DT$6,6),0) -> 1408.3155 | K13: =IF(7<=核心参数输入!$B$9,SUMIFS(季度经营税费!$D$26:$DT$26,季度经营税费!$D$6:$DT$6,7),0) -> 1669.1978 | L13: =IF(8<=核心参数输入!$B$9,SUMIFS(季度经营税费!$D$26:$DT$26,季度经营税费!$D$6:$DT$6,8),0) -> 1771.2464 | M13: =IF(9<=核心参数输入!$B$9,SUMIFS(季度经营税费!$D$26:$DT$26,季度经营税费!$D$6:$DT$6,9),0) -> 1800.9418 | N13: =IF(10<=核心参数输入!$B$9,SUMIFS(季度经营税费!$D$26:$DT$26,季度经营税费!$D$6:$DT$6,10),0) -> 1827.9559 | O13: =IF(11<=核心参数输入!$B$9,SUMIFS(季度经营税费!$D$26:$DT$26,季度经营税费!$D$6:$DT$6,11),0) -> 1855.3752 | P13: =IF(12<=核心参数输入!$B$9,SUMIFS(季度经营税费!$D$26:$DT$26,季度经营税费!$D$6:$DT$6,12),0) -> 1883.2059 | Q13: =IF(13<=核心参数输入!$B$9,SUMIFS(季度经营税费!$D$26:$DT$26,季度经营税费!$D$6:$DT$6,13),0) -> 1911.454 | R13: =IF(14<=核心参数输入!$B$9,SUMIFS(季度经营税费!$D$26:$DT$26,季度经营税费!$D$6:$DT$6,14),0) -> 1940.1258 | S13: =IF(15<=核心参数输入!$B$9,SUMIFS(季度经营税费!$D$26:$DT$26,季度经营税费!$D$6:$DT$6,15),0) -> 1969.2277 | T13: =IF(16<=核心参数输入!$B$9,SUMIFS(季度经营税费!$D$26:$DT$26,季度经营税费!$D$6:$DT$6,16),0) -> 1998.7661 | U13: =IF(17<=核心参数输入!$B$9,SUMIFS(季度经营税费!$D$26:$DT$26,季度经营税费!$D$6:$DT$6,17),0) -> 2028.7476 | V13: =IF(18<=核心参数输入!$B$9,SUMIFS(季度经营税费!$D$26:$DT$26,季度经营税费!$D$6:$DT$6,18),0) -> 2059.1788 | W13: =IF(19<=核心参数输入!$B$9,SUMIFS(季度经营税费!$D$26:$DT$26,季度经营税费!$D$6:$DT$6,19),0) -> 2090.0665 | X13: =IF(20<=核心参数输入!$B$9,SUMIFS(季度经营税费!$D$26:$DT$26,季度经营税费!$D$6:$DT$6,20),0) -> 2121.4175 | Y13: =IF(21<=核心参数输入!$B$9,SUMIFS(季度经营税费!$D$26:$DT$26,季度经营税费!$D$6:$DT$6,21),0) -> 0 | Z13: =IF(22<=核心参数输入!$B$9,SUMIFS(季度经营税费!$D$26:$DT$26,季度经营税费!$D$6:$DT$6,22),0) -> 0 | AA13: =IF(23<=核心参数输入!$B$9,SUMIFS(季度经营税费!$D$26:$DT$26,季度经营税费!$D$6:$DT$6,23),0) -> 0 | AB13: =IF(24<=核心参数输入!$B$9,SUMIFS(季度经营税费!$D$26:$DT$26,季度经营税费!$D$6:$DT$6,24),0) -> 0 | AC13: =IF(25<=核心参数输入!$B$9,SUMIFS(季度经营税费!$D$26:$DT$26,季度经营税费!$D$6:$DT$6,25),0) -> 0 | AD13: =IF(26<=核心参数输入!$B$9,SUMIFS(季度经营税费!$D$26:$DT$26,季度经营税费!$D$6:$DT$6,26),0) -> 0 | AE13: =IF(27<=核心参数输入!$B$9,SUMIFS(季度经营税费!$D$26:$DT$26,季度经营税费!$D$6:$DT$6,27),0) -> 0 | AF13: =IF(28<=核心参数输入!$B$9,SUMIFS(季度经营税费!$D$26:$DT$26,季度经营税费!$D$6:$DT$6,28),0) -> 0 | AG13: =IF(29<=核心参数输入!$B$9,SUMIFS(季度经营税费!$D$26:$DT$26,季度经营税费!$D$6:$DT$6,29),0) -> 0 | AH13: =IF(30<=核心参数输入!$B$9,SUMIFS(季度经营税费!$D$26:$DT$26,季度经营税费!$D$6:$DT$6,30),0) -> 0
A14: 其他经营实收现金 | B14: 万元 | D14: =IF(0<=核心参数输入!$B$9,SUMIFS(季度经营税费!$D$28:$DT$28,季度经营税费!$D$6:$DT$6,0),0) -> 0 | E14: =IF(1<=核心参数输入!$B$9,SUMIFS(季度经营税费!$D$28:$DT$28,季度经营税费!$D$6:$DT$6,1),0) -> 0 | F14: =IF(2<=核心参数输入!$B$9,SUMIFS(季度经营税费!$D$28:$DT$28,季度经营税费!$D$6:$DT$6,2),0) -> 0 | G14: =IF(3<=核心参数输入!$B$9,SUMIFS(季度经营税费!$D$28:$DT$28,季度经营税费!$D$6:$DT$6,3),0) -> 0 | H14: =IF(4<=核心参数输入!$B$9,SUMIFS(季度经营税费!$D$28:$DT$28,季度经营税费!$D$6:$DT$6,4),0) -> 13.060491 | I14: =IF(5<=核心参数输入!$B$9,SUMIFS(季度经营税费!$D$28:$DT$28,季度经营税费!$D$6:$DT$6,5),0) -> 50.963486 | J14: =IF(6<=核心参数输入!$B$9,SUMIFS(季度经营税费!$D$28:$DT$28,季度经营税费!$D$6:$DT$6,6),0) -> 70.415777 | K14: =IF(7<=核心参数输入!$B$9,SUMIFS(季度经营税费!$D$28:$DT$28,季度经营税费!$D$6:$DT$6,7),0) -> 83.459888 | L14: =IF(8<=核心参数输入!$B$9,SUMIFS(季度经营税费!$D$28:$DT$28,季度经营税费!$D$6:$DT$6,8),0) -> 88.562322 | M14: =IF(9<=核心参数输入!$B$9,SUMIFS(季度经营税费!$D$28:$DT$28,季度经营税费!$D$6:$DT$6,9),0) -> 90.047089 | N14: =IF(10<=核心参数输入!$B$9,SUMIFS(季度经营税费!$D$28:$DT$28,季度经营税费!$D$6:$DT$6,10),0) -> 91.397795 | O14: =IF(11<=核心参数输入!$B$9,SUMIFS(季度经营税费!$D$28:$DT$28,季度经营税费!$D$6:$DT$6,11),0) -> 92.768762 | P14: =IF(12<=核心参数输入!$B$9,SUMIFS(季度经营税费!$D$28:$DT$28,季度经营税费!$D$6:$DT$6,12),0) -> 94.160294 | Q14: =IF(13<=核心参数输入!$B$9,SUMIFS(季度经营税费!$D$28:$DT$28,季度经营税费!$D$6:$DT$6,13),0) -> 95.572698 | R14: =IF(14<=核心参数输入!$B$9,SUMIFS(季度经营税费!$D$28:$DT$28,季度经营税费!$D$6:$DT$6,14),0) -> 97.006288 | S14: =IF(15<=核心参数输入!$B$9,SUMIFS(季度经营税费!$D$28:$DT$28,季度经营税费!$D$6:$DT$6,15),0) -> 98.461383 | T14: =IF(16<=核心参数输入!$B$9,SUMIFS(季度经营税费!$D$28:$DT$28,季度经营税费!$D$6:$DT$6,16),0) -> 99.938303 | U14: =IF(17<=核心参数输入!$B$9,SUMIFS(季度经营税费!$D$28:$DT$28,季度经营税费!$D$6:$DT$6,17),0) -> 101.43738 | V14: =IF(18<=核心参数输入!$B$9,SUMIFS(季度经营税费!$D$28:$DT$28,季度经营税费!$D$6:$DT$6,18),0) -> 102.95894 | W14: =IF(19<=核心参数输入!$B$9,SUMIFS(季度经营税费!$D$28:$DT$28,季度经营税费!$D$6:$DT$6,19),0) -> 104.50332 | X14: =IF(20<=核心参数输入!$B$9,SUMIFS(季度经营税费!$D$28:$DT$28,季度经营税费!$D$6:$DT$6,20),0) -> 106.07087 | Y14: =IF(21<=核心参数输入!$B$9,SUMIFS(季度经营税费!$D$28:$DT$28,季度经营税费!$D$6:$DT$6,21),0) -> 0 | Z14: =IF(22<=核心参数输入!$B$9,SUMIFS(季度经营税费!$D$28:$DT$28,季度经营税费!$D$6:$DT$6,22),0) -> 0 | AA14: =IF(23<=核心参数输入!$B$9,SUMIFS(季度经营税费!$D$28:$DT$28,季度经营税费!$D$6:$DT$6,23),0) -> 0 | AB14: =IF(24<=核心参数输入!$B$9,SUMIFS(季度经营税费!$D$28:$DT$28,季度经营税费!$D$6:$DT$6,24),0) -> 0 | AC14: =IF(25<=核心参数输入!$B$9,SUMIFS(季度经营税费!$D$28:$DT$28,季度经营税费!$D$6:$DT$6,25),0) -> 0 | AD14: =IF(26<=核心参数输入!$B$9,SUMIFS(季度经营税费!$D$28:$DT$28,季度经营税费!$D$6:$DT$6,26),0) -> 0 | AE14: =IF(27<=核心参数输入!$B$9,SUMIFS(季度经营税费!$D$28:$DT$28,季度经营税费!$D$6:$DT$6,27),0) -> 0 | AF14: =IF(28<=核心参数输入!$B$9,SUMIFS(季度经营税费!$D$28:$DT$28,季度经营税费!$D$6:$DT$6,28),0) -> 0 | AG14: =IF(29<=核心参数输入!$B$9,SUMIFS(季度经营税费!$D$28:$DT$28,季度经营税费!$D$6:$DT$6,29),0) -> 0 | AH14: =IF(30<=核心参数输入!$B$9,SUMIFS(季度经营税费!$D$28:$DT$28,季度经营税费!$D$6:$DT$6,30),0) -> 0
A15: 现金成本及流转税 | B15: 万元 | D15: =IF(0<=核心参数输入!$B$9,SUMIFS(季度经营税费!$D$69:$DT$69,季度经营税费!$D$6:$DT$6,0),0) -> 0 | E15: =IF(1<=核心参数输入!$B$9,SUMIFS(季度经营税费!$D$69:$DT$69,季度经营税费!$D$6:$DT$6,1),0) -> 0 | F15: =IF(2<=核心参数输入!$B$9,SUMIFS(季度经营税费!$D$69:$DT$69,季度经营税费!$D$6:$DT$6,2),0) -> 0 | G15: =IF(3<=核心参数输入!$B$9,SUMIFS(季度经营税费!$D$69:$DT$69,季度经营税费!$D$6:$DT$6,3),0) -> 0 | H15: =IF(4<=核心参数输入!$B$9,SUMIFS(季度经营税费!$D$69:$DT$69,季度经营税费!$D$6:$DT$6,4),0) -> 2049.9573 | I15: =IF(5<=核心参数输入!$B$9,SUMIFS(季度经营税费!$D$69:$DT$69,季度经营税费!$D$6:$DT$6,5),0) -> 2706.9151 | J15: =IF(6<=核心参数输入!$B$9,SUMIFS(季度经营税费!$D$69:$DT$69,季度经营税费!$D$6:$DT$6,6),0) -> 2280.2849 | K15: =IF(7<=核心参数输入!$B$9,SUMIFS(季度经营税费!$D$69:$DT$69,季度经营税费!$D$6:$DT$6,7),0) -> 815.88469 | L15: =IF(8<=核心参数输入!$B$9,SUMIFS(季度经营税费!$D$69:$DT$69,季度经营税费!$D$6:$DT$6,8),0) -> 841.6641 | M15: =IF(9<=核心参数输入!$B$9,SUMIFS(季度经营税费!$D$69:$DT$69,季度经营税费!$D$6:$DT$6,9),0) -> 853.80747 | N15: =IF(10<=核心参数输入!$B$9,SUMIFS(季度经营税费!$D$69:$DT$69,季度经营税费!$D$6:$DT$6,10),0) -> 865.5707 | O15: =IF(11<=核心参数输入!$B$9,SUMIFS(季度经营税费!$D$69:$DT$69,季度经营税费!$D$6:$DT$6,11),0) -> 877.54351 | P15: =IF(12<=核心参数输入!$B$9,SUMIFS(季度经营税费!$D$69:$DT$69,季度经营税费!$D$6:$DT$6,12),0) -> 889.72969 | Q15: =IF(13<=核心参数输入!$B$9,SUMIFS(季度经营税费!$D$69:$DT$69,季度经营税费!$D$6:$DT$6,13),0) -> 902.13312 | R15: =IF(14<=核心参数输入!$B$9,SUMIFS(季度经营税费!$D$69:$DT$69,季度经营税费!$D$6:$DT$6,14),0) -> 914.75776 | S15: =IF(15<=核心参数输入!$B$9,SUMIFS(季度经营税费!$D$69:$DT$69,季度经营税费!$D$6:$DT$6,15),0) -> 927.60762 | T15: =IF(16<=核心参数输入!$B$9,SUMIFS(季度经营税费!$D$69:$DT$69,季度经营税费!$D$6:$DT$6,16),0) -> 940.68679 | U15: =IF(17<=核心参数输入!$B$9,SUMIFS(季度经营税费!$D$69:$DT$69,季度经营税费!$D$6:$DT$6,17),0) -> 953.99946 | V15: =IF(18<=核心参数输入!$B$9,SUMIFS(季度经营税费!$D$69:$DT$69,季度经营税费!$D$6:$DT$6,18),0) -> 967.54986 | W15: =IF(19<=核心参数输入!$B$9,SUMIFS(季度经营税费!$D$69:$DT$69,季度经营税费!$D$6:$DT$6,19),0) -> 981.34233 | X15: =IF(20<=核心参数输入!$B$9,SUMIFS(季度经营税费!$D$69:$DT$69,季度经营税费!$D$6:$DT$6,20),0) -> 995.38126 | Y15: =IF(21<=核心参数输入!$B$9,SUMIFS(季度经营税费!$D$69:$DT$69,季度经营税费!$D$6:$DT$6,21),0) -> 0 | Z15: =IF(22<=核心参数输入!$B$9,SUMIFS(季度经营税费!$D$69:$DT$69,季度经营税费!$D$6:$DT$6,22),0) -> 0 | AA15: =IF(23<=核心参数输入!$B$9,SUMIFS(季度经营税费!$D$69:$DT$69,季度经营税费!$D$6:$DT$6,23),0) -> 0 | AB15: =IF(24<=核心参数输入!$B$9,SUMIFS(季度经营税费!$D$69:$DT$69,季度经营税费!$D$6:$DT$6,24),0) -> 0 | AC15: =IF(25<=核心参数输入!$B$9,SUMIFS(季度经营税费!$D$69:$DT$69,季度经营税费!$D$6:$DT$6,25),0) -> 0 | AD15: =IF(26<=核心参数输入!$B$9,SUMIFS(季度经营税费!$D$69:$DT$69,季度经营税费!$D$6:$DT$6,26),0) -> 0 | AE15: =IF(27<=核心参数输入!$B$9,SUMIFS(季度经营税费!$D$69:$DT$69,季度经营税费!$D$6:$DT$6,27),0) -> 0 | AF15: =IF(28<=核心参数输入!$B$9,SUMIFS(季度经营税费!$D$69:$DT$69,季度经营税费!$D$6:$DT$6,28),0) -> 0 | AG15: =IF(29<=核心参数输入!$B$9,SUMIFS(季度经营税费!$D$69:$DT$69,季度经营税费!$D$6:$DT$6,29),0) -> 0 | AH15: =IF(30<=核心参数输入!$B$9,SUMIFS(季度经营税费!$D$69:$DT$69,季度经营税费!$D$6:$DT$6,30),0) -> 0
A16: 融资所得税现金 | B16: 万元 | D16: =IF(0<=核心参数输入!$B$9,IF(核心参数输入!$B$64=1,SUMIFS(季度经营税费!$D$65:$DT$65,季度经营税费!$D$6:$DT$6,0),SUMIFS(季度经营税费!$D$64:$DT$64,季度经营税费!$D$6:$DT$6,0)),0) -> 0 | E16: =IF(1<=核心参数输入!$B$9,IF(核心参数输入!$B$64=1,SUMIFS(季度经营税费!$D$65:$DT$65,季度经营税费!$D$6:$DT$6,1),SUMIFS(季度经营税费!$D$64:$DT$64,季度经营税费!$D$6:$DT$6,1)),0) -> 0 | F16: =IF(2<=核心参数输入!$B$9,IF(核心参数输入!$B$64=1,SUMIFS(季度经营税费!$D$65:$DT$65,季度经营税费!$D$6:$DT$6,2),SUMIFS(季度经营税费!$D$64:$DT$64,季度经营税费!$D$6:$DT$6,2)),0) -> 0 | G16: =IF(3<=核心参数输入!$B$9,IF(核心参数输入!$B$64=1,SUMIFS(季度经营税费!$D$65:$DT$65,季度经营税费!$D$6:$DT$6,3),SUMIFS(季度经营税费!$D$64:$DT$64,季度经营税费!$D$6:$DT$6,3)),0) -> 0 | H16: =IF(4<=核心参数输入!$B$9,IF(核心参数输入!$B$64=1,SUMIFS(季度经营税费!$D$65:$DT$65,季度经营税费!$D$6:$DT$6,4),SUMIFS(季度经营税费!$D$64:$DT$64,季度经营税费!$D$6:$DT$6,4)),0) -> 62.217637 | I16: =IF(5<=核心参数输入!$B$9,IF(核心参数输入!$B$64=1,SUMIFS(季度经营税费!$D$65:$DT$65,季度经营税费!$D$6:$DT$6,5),SUMIFS(季度经营税费!$D$64:$DT$64,季度经营税费!$D$6:$DT$6,5)),0) -> 484.89391 | J16: =IF(6<=核心参数输入!$B$9,IF(核心参数输入!$B$64=1,SUMIFS(季度经营税费!$D$65:$DT$65,季度经营税费!$D$6:$DT$6,6),SUMIFS(季度经营税费!$D$64:$DT$64,季度经营税费!$D$6:$DT$6,6)),0) -> 395.75099 | K16: =IF(7<=核心参数输入!$B$9,IF(核心参数输入!$B$64=1,SUMIFS(季度经营税费!$D$65:$DT$65,季度经营税费!$D$6:$DT$6,7),SUMIFS(季度经营税费!$D$64:$DT$64,季度经营税费!$D$6:$DT$6,7)),0) -> 0 | L16: =IF(8<=核心参数输入!$B$9,IF(核心参数输入!$B$64=1,SUMIFS(季度经营税费!$D$65:$DT$65,季度经营税费!$D$6:$DT$6,8),SUMIFS(季度经营税费!$D$64:$DT$64,季度经营税费!$D$6:$DT$6,8)),0) -> 0 | M16: =IF(9<=核心参数输入!$B$9,IF(核心参数输入!$B$64=1,SUMIFS(季度经营税费!$D$65:$DT$65,季度经营税费!$D$6:$DT$6,9),SUMIFS(季度经营税费!$D$64:$DT$64,季度经营税费!$D$6:$DT$6,9)),0) -> 0 | N16: =IF(10<=核心参数输入!$B$9,IF(核心参数输入!$B$64=1,SUMIFS(季度经营税费!$D$65:$DT$65,季度经营税费!$D$6:$DT$6,10),SUMIFS(季度经营税费!$D$64:$DT$64,季度经营税费!$D$6:$DT$6,10)),0) -> 0 | O16: =IF(11<=核心参数输入!$B$9,IF(核心参数输入!$B$64=1,SUMIFS(季度经营税费!$D$65:$DT$65,季度经营税费!$D$6:$DT$6,11),SUMIFS(季度经营税费!$D$64:$DT$64,季度经营税费!$D$6:$DT$6,11)),0) -> 0 | P16: =IF(12<=核心参数输入!$B$9,IF(核心参数输入!$B$64=1,SUMIFS(季度经营税费!$D$65:$DT$65,季度经营税费!$D$6:$DT$6,12),SUMIFS(季度经营税费!$D$64:$DT$64,季度经营税费!$D$6:$DT$6,12)),0) -> 0 | Q16: =IF(13<=核心参数输入!$B$9,IF(核心参数输入!$B$64=1,SUMIFS(季度经营税费!$D$65:$DT$65,季度经营税费!$D$6:$DT$6,13),SUMIFS(季度经营税费!$D$64:$DT$64,季度经营税费!$D$6:$DT$6,13)),0) -> 0 | R16: =IF(14<=核心参数输入!$B$9,IF(核心参数输入!$B$64=1,SUMIFS(季度经营税费!$D$65:$DT$65,季度经营税费!$D$6:$DT$6,14),SUMIFS(季度经营税费!$D$64:$DT$64,季度经营税费!$D$6:$DT$6,14)),0) -> 28.992673 | S16: =IF(15<=核心参数输入!$B$9,IF(核心参数输入!$B$64=1,SUMIFS(季度经营税费!$D$65:$DT$65,季度经营税费!$D$6:$DT$6,15),SUMIFS(季度经营税费!$D$64:$DT$64,季度经营税费!$D$6:$DT$6,15)),0) -> 71.75973 | T16: =IF(16<=核心参数输入!$B$9,IF(核心参数输入!$B$64=1,SUMIFS(季度经营税费!$D$65:$DT$65,季度经营税费!$D$6:$DT$6,16),SUMIFS(季度经营税费!$D$64:$DT$64,季度经营税费!$D$6:$DT$6,16)),0) -> 76.24377 | U16: =IF(17<=核心参数输入!$B$9,IF(核心参数输入!$B$64=1,SUMIFS(季度经营税费!$D$65:$DT$65,季度经营税费!$D$6:$DT$6,17),SUMIFS(季度经营税费!$D$64:$DT$64,季度经营税费!$D$6:$DT$6,17)),0) -> 80.785745 | V16: =IF(18<=核心参数输入!$B$9,IF(核心参数输入!$B$64=1,SUMIFS(季度经营税费!$D$65:$DT$65,季度经营税费!$D$6:$DT$6,18),SUMIFS(季度经营税费!$D$64:$DT$64,季度经营税费!$D$6:$DT$6,18)),0) -> 85.386338 | W16: =IF(19<=核心参数输入!$B$9,IF(核心参数输入!$B$64=1,SUMIFS(季度经营税费!$D$65:$DT$65,季度经营税费!$D$6:$DT$6,19),SUMIFS(季度经营税费!$D$64:$DT$64,季度经营税费!$D$6:$DT$6,19)),0) -> 90.046238 | X16: =IF(20<=核心参数输入!$B$9,IF(核心参数输入!$B$64=1,SUMIFS(季度经营税费!$D$65:$DT$65,季度经营税费!$D$6:$DT$6,20),SUMIFS(季度经营税费!$D$64:$DT$64,季度经营税费!$D$6:$DT$6,20)),0) -> 94.76614 | Y16: =IF(21<=核心参数输入!$B$9,IF(核心参数输入!$B$64=1,SUMIFS(季度经营税费!$D$65:$DT$65,季度经营税费!$D$6:$DT$6,21),SUMIFS(季度经营税费!$D$64:$DT$64,季度经营税费!$D$6:$DT$6,21)),0) -> 0 | Z16: =IF(22<=核心参数输入!$B$9,IF(核心参数输入!$B$64=1,SUMIFS(季度经营税费!$D$65:$DT$65,季度经营税费!$D$6:$DT$6,22),SUMIFS(季度经营税费!$D$64:$DT$64,季度经营税费!$D$6:$DT$6,22)),0) -> 0 | AA16: =IF(23<=核心参数输入!$B$9,IF(核心参数输入!$B$64=1,SUMIFS(季度经营税费!$D$65:$DT$65,季度经营税费!$D$6:$DT$6,23),SUMIFS(季度经营税费!$D$64:$DT$64,季度经营税费!$D$6:$DT$6,23)),0) -> 0 | AB16: =IF(24<=核心参数输入!$B$9,IF(核心参数输入!$B$64=1,SUMIFS(季度经营税费!$D$65:$DT$65,季度经营税费!$D$6:$DT$6,24),SUMIFS(季度经营税费!$D$64:$DT$64,季度经营税费!$D$6:$DT$6,24)),0) -> 0 | AC16: =IF(25<=核心参数输入!$B$9,IF(核心参数输入!$B$64=1,SUMIFS(季度经营税费!$D$65:$DT$65,季度经营税费!$D$6:$DT$6,25),SUMIFS(季度经营税费!$D$64:$DT$64,季度经营税费!$D$6:$DT$6,25)),0) -> 0 | AD16: =IF(26<=核心参数输入!$B$9,IF(核心参数输入!$B$64=1,SUMIFS(季度经营税费!$D$65:$DT$65,季度经营税费!$D$6:$DT$6,26),SUMIFS(季度经营税费!$D$64:$DT$64,季度经营税费!$D$6:$DT$6,26)),0) -> 0 | AE16: =IF(27<=核心参数输入!$B$9,IF(核心参数输入!$B$64=1,SUMIFS(季度经营税费!$D$65:$DT$65,季度经营税费!$D$6:$DT$6,27),SUMIFS(季度经营税费!$D$64:$DT$64,季度经营税费!$D$6:$DT$6,27)),0) -> 0 | AF16: =IF(28<=核心参数输入!$B$9,IF(核心参数输入!$B$64=1,SUMIFS(季度经营税费!$D$65:$DT$65,季度经营税费!$D$6:$DT$6,28),SUMIFS(季度经营税费!$D$64:$DT$64,季度经营税费!$D$6:$DT$6,28)),0) -> 0 | AG16: =IF(29<=核心参数输入!$B$9,IF(核心参数输入!$B$64=1,SUMIFS(季度经营税费!$D$65:$DT$65,季度经营税费!$D$6:$DT$6,29),SUMIFS(季度经营税费!$D$64:$DT$64,季度经营税费!$D$6:$DT$6,29)),0) -> 0 | AH16: =IF(30<=核心参数输入!$B$9,IF(核心参数输入!$B$64=1,SUMIFS(季度经营税费!$D$65:$DT$65,季度经营税费!$D$6:$DT$6,30),SUMIFS(季度经营税费!$D$64:$DT$64,季度经营税费!$D$6:$DT$6,30)),0) -> 0
A17: 净利润 | B17: 万元 | D17: =IF(0<=核心参数输入!$B$9,IF(核心参数输入!$B$64=1,SUMIFS(季度经营税费!$D$67:$DT$67,季度经营税费!$D$6:$DT$6,0),SUMIFS(季度经营税费!$D$66:$DT$66,季度经营税费!$D$6:$DT$6,0)),0) -> 0 | E17: =IF(1<=核心参数输入!$B$9,IF(核心参数输入!$B$64=1,SUMIFS(季度经营税费!$D$67:$DT$67,季度经营税费!$D$6:$DT$6,1),SUMIFS(季度经营税费!$D$66:$DT$66,季度经营税费!$D$6:$DT$6,1)),0) -> 0 | F17: =IF(2<=核心参数输入!$B$9,IF(核心参数输入!$B$64=1,SUMIFS(季度经营税费!$D$67:$DT$67,季度经营税费!$D$6:$DT$6,2),SUMIFS(季度经营税费!$D$66:$DT$66,季度经营税费!$D$6:$DT$6,2)),0) -> 0 | G17: =IF(3<=核心参数输入!$B$9,IF(核心参数输入!$B$64=1,SUMIFS(季度经营税费!$D$67:$DT$67,季度经营税费!$D$6:$DT$6,3),SUMIFS(季度经营税费!$D$66:$DT$66,季度经营税费!$D$6:$DT$6,3)),0) -> 0 | H17: =IF(4<=核心参数输入!$B$9,IF(核心参数输入!$B$64=1,SUMIFS(季度经营税费!$D$67:$DT$67,季度经营税费!$D$6:$DT$6,4),SUMIFS(季度经营税费!$D$66:$DT$66,季度经营税费!$D$6:$DT$6,4)),0) -> 186.65291 | I17: =IF(5<=核心参数输入!$B$9,IF(核心参数输入!$B$64=1,SUMIFS(季度经营税费!$D$67:$DT$67,季度经营税费!$D$6:$DT$6,5),SUMIFS(季度经营税费!$D$66:$DT$66,季度经营税费!$D$6:$DT$6,5)),0) -> 1454.6817 | J17: =IF(6<=核心参数输入!$B$9,IF(核心参数输入!$B$64=1,SUMIFS(季度经营税费!$D$67:$DT$67,季度经营税费!$D$6:$DT$6,6),SUMIFS(季度经营税费!$D$66:$DT$66,季度经营税费!$D$6:$DT$6,6)),0) -> 1187.253 | K17: =IF(7<=核心参数输入!$B$9,IF(核心参数输入!$B$64=1,SUMIFS(季度经营税费!$D$67:$DT$67,季度经营税费!$D$6:$DT$6,7),SUMIFS(季度经营税费!$D$66:$DT$66,季度经营税费!$D$6:$DT$6,7)),0) -> -613.76954 | L17: =IF(8<=核心参数输入!$B$9,IF(核心参数输入!$B$64=1,SUMIFS(季度经营税费!$D$67:$DT$67,季度经营税费!$D$6:$DT$6,8),SUMIFS(季度经营税费!$D$66:$DT$66,季度经营税费!$D$6:$DT$6,8)),0) -> -352.39783 | M17: =IF(9<=核心参数输入!$B$9,IF(核心参数输入!$B$64=1,SUMIFS(季度经营税费!$D$67:$DT$67,季度经营税费!$D$6:$DT$6,9),SUMIFS(季度经营税费!$D$66:$DT$66,季度经营税费!$D$6:$DT$6,9)),0) -> -153.36111 | N17: =IF(10<=核心参数输入!$B$9,IF(核心参数输入!$B$64=1,SUMIFS(季度经营税费!$D$67:$DT$67,季度经营税费!$D$6:$DT$6,10),SUMIFS(季度经营税费!$D$66:$DT$66,季度经营税费!$D$6:$DT$6,10)),0) -> 43.240494 | O17: =IF(11<=核心参数输入!$B$9,IF(核心参数输入!$B$64=1,SUMIFS(季度经营税费!$D$67:$DT$67,季度经营税费!$D$6:$DT$6,11),SUMIFS(季度经营税费!$D$66:$DT$66,季度经营税费!$D$6:$DT$6,11)),0) -> 217.558 | P17: =IF(12<=核心参数输入!$B$9,IF(核心参数输入!$B$64=1,SUMIFS(季度经营税费!$D$67:$DT$67,季度经营税费!$D$6:$DT$6,12),SUMIFS(季度经营税费!$D$66:$DT$66,季度经营税费!$D$6:$DT$6,12)),0) -> 234.59397 | Q17: =IF(13<=核心参数输入!$B$9,IF(核心参数输入!$B$64=1,SUMIFS(季度经营税费!$D$67:$DT$67,季度经营税费!$D$6:$DT$6,13),SUMIFS(季度经营税费!$D$66:$DT$66,季度经营税费!$D$6:$DT$6,13)),0) -> 251.85103 | R17: =IF(14<=核心参数输入!$B$9,IF(核心参数输入!$B$64=1,SUMIFS(季度经营税费!$D$67:$DT$67,季度经营税费!$D$6:$DT$6,14),SUMIFS(季度经营税费!$D$66:$DT$66,季度经营税费!$D$6:$DT$6,14)),0) -> 240.33912 | S17: =IF(15<=核心参数输入!$B$9,IF(核心参数输入!$B$64=1,SUMIFS(季度经营税费!$D$67:$DT$67,季度经营税费!$D$6:$DT$6,15),SUMIFS(季度经营税费!$D$66:$DT$66,季度经营税费!$D$6:$DT$6,15)),0) -> 215.27919 | T17: =IF(16<=核心参数输入!$B$9,IF(核心参数输入!$B$64=1,SUMIFS(季度经营税费!$D$67:$DT$67,季度经营税费!$D$6:$DT$6,16),SUMIFS(季度经营税费!$D$66:$DT$66,季度经营税费!$D$6:$DT$6,16)),0) -> 228.73131 | U17: =IF(17<=核心参数输入!$B$9,IF(核心参数输入!$B$64=1,SUMIFS(季度经营税费!$D$67:$DT$67,季度经营税费!$D$6:$DT$6,17),SUMIFS(季度经营税费!$D$66:$DT$66,季度经营税费!$D$6:$DT$6,17)),0) -> 242.35723 | V17: =IF(18<=核心参数输入!$B$9,IF(核心参数输入!$B$64=1,SUMIFS(季度经营税费!$D$67:$DT$67,季度经营税费!$D$6:$DT$6,18),SUMIFS(季度经营税费!$D$66:$DT$66,季度经营税费!$D$6:$DT$6,18)),0) -> 256.15901 | W17: =IF(19<=核心参数输入!$B$9,IF(核心参数输入!$B$64=1,SUMIFS(季度经营税费!$D$67:$DT$67,季度经营税费!$D$6:$DT$6,19),SUMIFS(季度经营税费!$D$66:$DT$66,季度经营税费!$D$6:$DT$6,19)),0) -> 270.13871 | X17: =IF(20<=核心参数输入!$B$9,IF(核心参数输入!$B$64=1,SUMIFS(季度经营税费!$D$67:$DT$67,季度经营税费!$D$6:$DT$6,20),SUMIFS(季度经营税费!$D$66:$DT$66,季度经营税费!$D$6:$DT$6,20)),0) -> 284.29842 | Y17: =IF(21<=核心参数输入!$B$9,IF(核心参数输入!$B$64=1,SUMIFS(季度经营税费!$D$67:$DT$67,季度经营税费!$D$6:$DT$6,21),SUMIFS(季度经营税费!$D$66:$DT$66,季度经营税费!$D$6:$DT$6,21)),0) -> 0 | Z17: =IF(22<=核心参数输入!$B$9,IF(核心参数输入!$B$64=1,SUMIFS(季度经营税费!$D$67:$DT$67,季度经营税费!$D$6:$DT$6,22),SUMIFS(季度经营税费!$D$66:$DT$66,季度经营税费!$D$6:$DT$6,22)),0) -> 0 | AA17: =IF(23<=核心参数输入!$B$9,IF(核心参数输入!$B$64=1,SUMIFS(季度经营税费!$D$67:$DT$67,季度经营税费!$D$6:$DT$6,23),SUMIFS(季度经营税费!$D$66:$DT$66,季度经营税费!$D$6:$DT$6,23)),0) -> 0 | AB17: =IF(24<=核心参数输入!$B$9,IF(核心参数输入!$B$64=1,SUMIFS(季度经营税费!$D$67:$DT$67,季度经营税费!$D$6:$DT$6,24),SUMIFS(季度经营税费!$D$66:$DT$66,季度经营税费!$D$6:$DT$6,24)),0) -> 0 | AC17: =IF(25<=核心参数输入!$B$9,IF(核心参数输入!$B$64=1,SUMIFS(季度经营税费!$D$67:$DT$67,季度经营税费!$D$6:$DT$6,25),SUMIFS(季度经营税费!$D$66:$DT$66,季度经营税费!$D$6:$DT$6,25)),0) -> 0 | AD17: =IF(26<=核心参数输入!$B$9,IF(核心参数输入!$B$64=1,SUMIFS(季度经营税费!$D$67:$DT$67,季度经营税费!$D$6:$DT$6,26),SUMIFS(季度经营税费!$D$66:$DT$66,季度经营税费!$D$6:$DT$6,26)),0) -> 0 | AE17: =IF(27<=核心参数输入!$B$9,IF(核心参数输入!$B$64=1,SUMIFS(季度经营税费!$D$67:$DT$67,季度经营税费!$D$6:$DT$6,27),SUMIFS(季度经营税费!$D$66:$DT$66,季度经营税费!$D$6:$DT$6,27)),0) -> 0 | AF17: =IF(28<=核心参数输入!$B$9,IF(核心参数输入!$B$64=1,SUMIFS(季度经营税费!$D$67:$DT$67,季度经营税费!$D$6:$DT$6,28),SUMIFS(季度经营税费!$D$66:$DT$66,季度经营税费!$D$6:$DT$6,28)),0) -> 0 | AG17: =IF(29<=核心参数输入!$B$9,IF(核心参数输入!$B$64=1,SUMIFS(季度经营税费!$D$67:$DT$67,季度经营税费!$D$6:$DT$6,29),SUMIFS(季度经营税费!$D$66:$DT$66,季度经营税费!$D$6:$DT$6,29)),0) -> 0 | AH17: =IF(30<=核心参数输入!$B$9,IF(核心参数输入!$B$64=1,SUMIFS(季度经营税费!$D$67:$DT$67,季度经营税费!$D$6:$DT$6,30),SUMIFS(季度经营税费!$D$66:$DT$66,季度经营税费!$D$6:$DT$6,30)),0) -> 0
A18: 投资支付含资本化融资费用 | B18: 万元 | D18: =IF(0<=核心参数输入!$B$9,SUMIFS(季度投融资!$D$48:$DT$48,季度投融资!$D$6:$DT$6,0),0) -> 8000 | E18: =IF(1<=核心参数输入!$B$9,SUMIFS(季度投融资!$D$48:$DT$48,季度投融资!$D$6:$DT$6,1),0) -> 12084.188 | F18: =IF(2<=核心参数输入!$B$9,SUMIFS(季度投融资!$D$48:$DT$48,季度投融资!$D$6:$DT$6,2),0) -> 21798 | G18: =IF(3<=核心参数输入!$B$9,SUMIFS(季度投融资!$D$48:$DT$48,季度投融资!$D$6:$DT$6,3),0) -> 16947 | H18: =IF(4<=核心参数输入!$B$9,SUMIFS(季度投融资!$D$48:$DT$48,季度投融资!$D$6:$DT$6,4),0) -> 500 | I18: =IF(5<=核心参数输入!$B$9,SUMIFS(季度投融资!$D$48:$DT$48,季度投融资!$D$6:$DT$6,5),0) -> 0 | J18: =IF(6<=核心参数输入!$B$9,SUMIFS(季度投融资!$D$48:$DT$48,季度投融资!$D$6:$DT$6,6),0) -> 0 | K18: =IF(7<=核心参数输入!$B$9,SUMIFS(季度投融资!$D$48:$DT$48,季度投融资!$D$6:$DT$6,7),0) -> 0 | L18: =IF(8<=核心参数输入!$B$9,SUMIFS(季度投融资!$D$48:$DT$48,季度投融资!$D$6:$DT$6,8),0) -> 0 | M18: =IF(9<=核心参数输入!$B$9,SUMIFS(季度投融资!$D$48:$DT$48,季度投融资!$D$6:$DT$6,9),0) -> 0 | N18: =IF(10<=核心参数输入!$B$9,SUMIFS(季度投融资!$D$48:$DT$48,季度投融资!$D$6:$DT$6,10),0) -> 0 | O18: =IF(11<=核心参数输入!$B$9,SUMIFS(季度投融资!$D$48:$DT$48,季度投融资!$D$6:$DT$6,11),0) -> 0 | P18: =IF(12<=核心参数输入!$B$9,SUMIFS(季度投融资!$D$48:$DT$48,季度投融资!$D$6:$DT$6,12),0) -> 0 | Q18: =IF(13<=核心参数输入!$B$9,SUMIFS(季度投融资!$D$48:$DT$48,季度投融资!$D$6:$DT$6,13),0) -> 0 | R18: =IF(14<=核心参数输入!$B$9,SUMIFS(季度投融资!$D$48:$DT$48,季度投融资!$D$6:$DT$6,14),0) -> 0 | S18: =IF(15<=核心参数输入!$B$9,SUMIFS(季度投融资!$D$48:$DT$48,季度投融资!$D$6:$DT$6,15),0) -> 0 | T18: =IF(16<=核心参数输入!$B$9,SUMIFS(季度投融资!$D$48:$DT$48,季度投融资!$D$6:$DT$6,16),0) -> 0 | U18: =IF(17<=核心参数输入!$B$9,SUMIFS(季度投融资!$D$48:$DT$48,季度投融资!$D$6:$DT$6,17),0) -> 0 | V18: =IF(18<=核心参数输入!$B$9,SUMIFS(季度投融资!$D$48:$DT$48,季度投融资!$D$6:$DT$6,18),0) -> 0 | W18: =IF(19<=核心参数输入!$B$9,SUMIFS(季度投融资!$D$48:$DT$48,季度投融资!$D$6:$DT$6,19),0) -> 0 | X18: =IF(20<=核心参数输入!$B$9,SUMIFS(季度投融资!$D$48:$DT$48,季度投融资!$D$6:$DT$6,20),0) -> 0 | Y18: =IF(21<=核心参数输入!$B$9,SUMIFS(季度投融资!$D$48:$DT$48,季度投融资!$D$6:$DT$6,21),0) -> 0 | Z18: =IF(22<=核心参数输入!$B$9,SUMIFS(季度投融资!$D$48:$DT$48,季度投融资!$D$6:$DT$6,22),0) -> 0 | AA18: =IF(23<=核心参数输入!$B$9,SUMIFS(季度投融资!$D$48:$DT$48,季度投融资!$D$6:$DT$6,23),0) -> 0 | AB18: =IF(24<=核心参数输入!$B$9,SUMIFS(季度投融资!$D$48:$DT$48,季度投融资!$D$6:$DT$6,24),0) -> 0 | AC18: =IF(25<=核心参数输入!$B$9,SUMIFS(季度投融资!$D$48:$DT$48,季度投融资!$D$6:$DT$6,25),0) -> 0 | AD18: =IF(26<=核心参数输入!$B$9,SUMIFS(季度投融资!$D$48:$DT$48,季度投融资!$D$6:$DT$6,26),0) -> 0 | AE18: =IF(27<=核心参数输入!$B$9,SUMIFS(季度投融资!$D$48:$DT$48,季度投融资!$D$6:$DT$6,27),0) -> 0 | AF18: =IF(28<=核心参数输入!$B$9,SUMIFS(季度投融资!$D$48:$DT$48,季度投融资!$D$6:$DT$6,28),0) -> 0 | AG18: =IF(29<=核心参数输入!$B$9,SUMIFS(季度投融资!$D$48:$DT$48,季度投融资!$D$6:$DT$6,29),0) -> 0 | AH18: =IF(30<=核心参数输入!$B$9,SUMIFS(季度投融资!$D$48:$DT$48,季度投融资!$D$6:$DT$6,30),0) -> 0
A19: 贷款提款 | B19: 万元 | D19: =IF(0<=核心参数输入!$B$9,SUMIFS(季度投融资!$D$39:$DT$39,季度投融资!$D$6:$DT$6,0),0) -> 0 | E19: =IF(1<=核心参数输入!$B$9,SUMIFS(季度投融资!$D$39:$DT$39,季度投融资!$D$6:$DT$6,1),0) -> 6750 | F19: =IF(2<=核心参数输入!$B$9,SUMIFS(季度投融资!$D$39:$DT$39,季度投融资!$D$6:$DT$6,2),0) -> 12000 | G19: =IF(3<=核心参数输入!$B$9,SUMIFS(季度投融资!$D$39:$DT$39,季度投融资!$D$6:$DT$6,3),0) -> 9000 | H19: =IF(4<=核心参数输入!$B$9,SUMIFS(季度投融资!$D$39:$DT$39,季度投融资!$D$6:$DT$6,4),0) -> 0 | I19: =IF(5<=核心参数输入!$B$9,SUMIFS(季度投融资!$D$39:$DT$39,季度投融资!$D$6:$DT$6,5),0) -> 0 | J19: =IF(6<=核心参数输入!$B$9,SUMIFS(季度投融资!$D$39:$DT$39,季度投融资!$D$6:$DT$6,6),0) -> 0 | K19: =IF(7<=核心参数输入!$B$9,SUMIFS(季度投融资!$D$39:$DT$39,季度投融资!$D$6:$DT$6,7),0) -> 0 | L19: =IF(8<=核心参数输入!$B$9,SUMIFS(季度投融资!$D$39:$DT$39,季度投融资!$D$6:$DT$6,8),0) -> 0 | M19: =IF(9<=核心参数输入!$B$9,SUMIFS(季度投融资!$D$39:$DT$39,季度投融资!$D$6:$DT$6,9),0) -> 0 | N19: =IF(10<=核心参数输入!$B$9,SUMIFS(季度投融资!$D$39:$DT$39,季度投融资!$D$6:$DT$6,10),0) -> 0 | O19: =IF(11<=核心参数输入!$B$9,SUMIFS(季度投融资!$D$39:$DT$39,季度投融资!$D$6:$DT$6,11),0) -> 0 | P19: =IF(12<=核心参数输入!$B$9,SUMIFS(季度投融资!$D$39:$DT$39,季度投融资!$D$6:$DT$6,12),0) -> 0 | Q19: =IF(13<=核心参数输入!$B$9,SUMIFS(季度投融资!$D$39:$DT$39,季度投融资!$D$6:$DT$6,13),0) -> 0 | R19: =IF(14<=核心参数输入!$B$9,SUMIFS(季度投融资!$D$39:$DT$39,季度投融资!$D$6:$DT$6,14),0) -> 0 | S19: =IF(15<=核心参数输入!$B$9,SUMIFS(季度投融资!$D$39:$DT$39,季度投融资!$D$6:$DT$6,15),0) -> 0 | T19: =IF(16<=核心参数输入!$B$9,SUMIFS(季度投融资!$D$39:$DT$39,季度投融资!$D$6:$DT$6,16),0) -> 0 | U19: =IF(17<=核心参数输入!$B$9,SUMIFS(季度投融资!$D$39:$DT$39,季度投融资!$D$6:$DT$6,17),0) -> 0 | V19: =IF(18<=核心参数输入!$B$9,SUMIFS(季度投融资!$D$39:$DT$39,季度投融资!$D$6:$DT$6,18),0) -> 0 | W19: =IF(19<=核心参数输入!$B$9,SUMIFS(季度投融资!$D$39:$DT$39,季度投融资!$D$6:$DT$6,19),0) -> 0 | X19: =IF(20<=核心参数输入!$B$9,SUMIFS(季度投融资!$D$39:$DT$39,季度投融资!$D$6:$DT$6,20),0) -> 0 | Y19: =IF(21<=核心参数输入!$B$9,SUMIFS(季度投融资!$D$39:$DT$39,季度投融资!$D$6:$DT$6,21),0) -> 0 | Z19: =IF(22<=核心参数输入!$B$9,SUMIFS(季度投融资!$D$39:$DT$39,季度投融资!$D$6:$DT$6,22),0) -> 0 | AA19: =IF(23<=核心参数输入!$B$9,SUMIFS(季度投融资!$D$39:$DT$39,季度投融资!$D$6:$DT$6,23),0) -> 0 | AB19: =IF(24<=核心参数输入!$B$9,SUMIFS(季度投融资!$D$39:$DT$39,季度投融资!$D$6:$DT$6,24),0) -> 0 | AC19: =IF(25<=核心参数输入!$B$9,SUMIFS(季度投融资!$D$39:$DT$39,季度投融资!$D$6:$DT$6,25),0) -> 0 | AD19: =IF(26<=核心参数输入!$B$9,SUMIFS(季度投融资!$D$39:$DT$39,季度投融资!$D$6:$DT$6,26),0) -> 0 | AE19: =IF(27<=核心参数输入!$B$9,SUMIFS(季度投融资!$D$39:$DT$39,季度投融资!$D$6:$DT$6,27),0) -> 0 | AF19: =IF(28<=核心参数输入!$B$9,SUMIFS(季度投融资!$D$39:$DT$39,季度投融资!$D$6:$DT$6,28),0) -> 0 | AG19: =IF(29<=核心参数输入!$B$9,SUMIFS(季度投融资!$D$39:$DT$39,季度投融资!$D$6:$DT$6,29),0) -> 0 | AH19: =IF(30<=核心参数输入!$B$9,SUMIFS(季度投融资!$D$39:$DT$39,季度投融资!$D$6:$DT$6,30),0) -> 0
A20: 计划还本 | B20: 万元 | D20: =IF(0<=核心参数输入!$B$9,SUMIFS(季度投融资!$D$41:$DT$41,季度投融资!$D$6:$DT$6,0),0) -> 0 | E20: =IF(1<=核心参数输入!$B$9,SUMIFS(季度投融资!$D$41:$DT$41,季度投融资!$D$6:$DT$6,1),0) -> 0 | F20: =IF(2<=核心参数输入!$B$9,SUMIFS(季度投融资!$D$41:$DT$41,季度投融资!$D$6:$DT$6,2),0) -> 0 | G20: =IF(3<=核心参数输入!$B$9,SUMIFS(季度投融资!$D$41:$DT$41,季度投融资!$D$6:$DT$6,3),0) -> 0 | H20: =IF(4<=核心参数输入!$B$9,SUMIFS(季度投融资!$D$41:$DT$41,季度投融资!$D$6:$DT$6,4),0) -> 4285.7143 | I20: =IF(5<=核心参数输入!$B$9,SUMIFS(季度投融资!$D$41:$DT$41,季度投融资!$D$6:$DT$6,5),0) -> 4285.7143 | J20: =IF(6<=核心参数输入!$B$9,SUMIFS(季度投融资!$D$41:$DT$41,季度投融资!$D$6:$DT$6,6),0) -> 4285.7143 | K20: =IF(7<=核心参数输入!$B$9,SUMIFS(季度投融资!$D$41:$DT$41,季度投融资!$D$6:$DT$6,7),0) -> 4285.7143 | L20: =IF(8<=核心参数输入!$B$9,SUMIFS(季度投融资!$D$41:$DT$41,季度投融资!$D$6:$DT$6,8),0) -> 4285.7143 | M20: =IF(9<=核心参数输入!$B$9,SUMIFS(季度投融资!$D$41:$DT$41,季度投融资!$D$6:$DT$6,9),0) -> 4285.7143 | N20: =IF(10<=核心参数输入!$B$9,SUMIFS(季度投融资!$D$41:$DT$41,季度投融资!$D$6:$DT$6,10),0) -> 4285.7143 | O20: =IF(11<=核心参数输入!$B$9,SUMIFS(季度投融资!$D$41:$DT$41,季度投融资!$D$6:$DT$6,11),0) -> 0 | P20: =IF(12<=核心参数输入!$B$9,SUMIFS(季度投融资!$D$41:$DT$41,季度投融资!$D$6:$DT$6,12),0) -> 0 | Q20: =IF(13<=核心参数输入!$B$9,SUMIFS(季度投融资!$D$41:$DT$41,季度投融资!$D$6:$DT$6,13),0) -> 0 | R20: =IF(14<=核心参数输入!$B$9,SUMIFS(季度投融资!$D$41:$DT$41,季度投融资!$D$6:$DT$6,14),0) -> 0 | S20: =IF(15<=核心参数输入!$B$9,SUMIFS(季度投融资!$D$41:$DT$41,季度投融资!$D$6:$DT$6,15),0) -> 0 | T20: =IF(16<=核心参数输入!$B$9,SUMIFS(季度投融资!$D$41:$DT$41,季度投融资!$D$6:$DT$6,16),0) -> 0 | U20: =IF(17<=核心参数输入!$B$9,SUMIFS(季度投融资!$D$41:$DT$41,季度投融资!$D$6:$DT$6,17),0) -> 0 | V20: =IF(18<=核心参数输入!$B$9,SUMIFS(季度投融资!$D$41:$DT$41,季度投融资!$D$6:$DT$6,18),0) -> 0 | W20: =IF(19<=核心参数输入!$B$9,SUMIFS(季度投融资!$D$41:$DT$41,季度投融资!$D$6:$DT$6,19),0) -> 0 | X20: =IF(20<=核心参数输入!$B$9,SUMIFS(季度投融资!$D$41:$DT$41,季度投融资!$D$6:$DT$6,20),0) -> 0 | Y20: =IF(21<=核心参数输入!$B$9,SUMIFS(季度投融资!$D$41:$DT$41,季度投融资!$D$6:$DT$6,21),0) -> 0 | Z20: =IF(22<=核心参数输入!$B$9,SUMIFS(季度投融资!$D$41:$DT$41,季度投融资!$D$6:$DT$6,22),0) -> 0 | AA20: =IF(23<=核心参数输入!$B$9,SUMIFS(季度投融资!$D$41:$DT$41,季度投融资!$D$6:$DT$6,23),0) -> 0 | AB20: =IF(24<=核心参数输入!$B$9,SUMIFS(季度投融资!$D$41:$DT$41,季度投融资!$D$6:$DT$6,24),0) -> 0 | AC20: =IF(25<=核心参数输入!$B$9,SUMIFS(季度投融资!$D$41:$DT$41,季度投融资!$D$6:$DT$6,25),0) -> 0 | AD20: =IF(26<=核心参数输入!$B$9,SUMIFS(季度投融资!$D$41:$DT$41,季度投融资!$D$6:$DT$6,26),0) -> 0 | AE20: =IF(27<=核心参数输入!$B$9,SUMIFS(季度投融资!$D$41:$DT$41,季度投融资!$D$6:$DT$6,27),0) -> 0 | AF20: =IF(28<=核心参数输入!$B$9,SUMIFS(季度投融资!$D$41:$DT$41,季度投融资!$D$6:$DT$6,28),0) -> 0 | AG20: =IF(29<=核心参数输入!$B$9,SUMIFS(季度投融资!$D$41:$DT$41,季度投融资!$D$6:$DT$6,29),0) -> 0 | AH20: =IF(30<=核心参数输入!$B$9,SUMIFS(季度投融资!$D$41:$DT$41,季度投融资!$D$6:$DT$6,30),0) -> 0
A21: 全部利息现金 | B21: 万元 | D21: =IF(0<=核心参数输入!$B$9,SUMIFS(季度投融资!$D$42:$DT$42,季度投融资!$D$6:$DT$6,0),0) -> 0 | E21: =IF(1<=核心参数输入!$B$9,SUMIFS(季度投融资!$D$42:$DT$42,季度投融资!$D$6:$DT$6,1),0) -> 177.1875 | F21: =IF(2<=核心参数输入!$B$9,SUMIFS(季度投融资!$D$42:$DT$42,季度投融资!$D$6:$DT$6,2),0) -> 630 | G21: =IF(3<=核心参数输入!$B$9,SUMIFS(季度投融资!$D$42:$DT$42,季度投融资!$D$6:$DT$6,3),0) -> 1071 | H21: =IF(4<=核心参数输入!$B$9,SUMIFS(季度投融资!$D$42:$DT$42,季度投融资!$D$6:$DT$6,4),0) -> 1237.5 | I21: =IF(5<=核心参数输入!$B$9,SUMIFS(季度投融资!$D$42:$DT$42,季度投融资!$D$6:$DT$6,5),0) -> 1057.5 | J21: =IF(6<=核心参数输入!$B$9,SUMIFS(季度投融资!$D$42:$DT$42,季度投融资!$D$6:$DT$6,6),0) -> 877.5 | K21: =IF(7<=核心参数输入!$B$9,SUMIFS(季度投融资!$D$42:$DT$42,季度投融资!$D$6:$DT$6,7),0) -> 697.5 | L21: =IF(8<=核心参数输入!$B$9,SUMIFS(季度投融资!$D$42:$DT$42,季度投融资!$D$6:$DT$6,8),0) -> 517.5 | M21: =IF(9<=核心参数输入!$B$9,SUMIFS(季度投融资!$D$42:$DT$42,季度投融资!$D$6:$DT$6,9),0) -> 337.5 | N21: =IF(10<=核心参数输入!$B$9,SUMIFS(季度投融资!$D$42:$DT$42,季度投融资!$D$6:$DT$6,10),0) -> 157.5 | O21: =IF(11<=核心参数输入!$B$9,SUMIFS(季度投融资!$D$42:$DT$42,季度投融资!$D$6:$DT$6,11),0) -> 0 | P21: =IF(12<=核心参数输入!$B$9,SUMIFS(季度投融资!$D$42:$DT$42,季度投融资!$D$6:$DT$6,12),0) -> 0 | Q21: =IF(13<=核心参数输入!$B$9,SUMIFS(季度投融资!$D$42:$DT$42,季度投融资!$D$6:$DT$6,13),0) -> 0 | R21: =IF(14<=核心参数输入!$B$9,SUMIFS(季度投融资!$D$42:$DT$42,季度投融资!$D$6:$DT$6,14),0) -> 0 | S21: =IF(15<=核心参数输入!$B$9,SUMIFS(季度投融资!$D$42:$DT$42,季度投融资!$D$6:$DT$6,15),0) -> 0 | T21: =IF(16<=核心参数输入!$B$9,SUMIFS(季度投融资!$D$42:$DT$42,季度投融资!$D$6:$DT$6,16),0) -> 0 | U21: =IF(17<=核心参数输入!$B$9,SUMIFS(季度投融资!$D$42:$DT$42,季度投融资!$D$6:$DT$6,17),0) -> 0 | V21: =IF(18<=核心参数输入!$B$9,SUMIFS(季度投融资!$D$42:$DT$42,季度投融资!$D$6:$DT$6,18),0) -> 0 | W21: =IF(19<=核心参数输入!$B$9,SUMIFS(季度投融资!$D$42:$DT$42,季度投融资!$D$6:$DT$6,19),0) -> 0 | X21: =IF(20<=核心参数输入!$B$9,SUMIFS(季度投融资!$D$42:$DT$42,季度投融资!$D$6:$DT$6,20),0) -> 0 | Y21: =IF(21<=核心参数输入!$B$9,SUMIFS(季度投融资!$D$42:$DT$42,季度投融资!$D$6:$DT$6,21),0) -> 0 | Z21: =IF(22<=核心参数输入!$B$9,SUMIFS(季度投融资!$D$42:$DT$42,季度投融资!$D$6:$DT$6,22),0) -> 0 | AA21: =IF(23<=核心参数输入!$B$9,SUMIFS(季度投融资!$D$42:$DT$42,季度投融资!$D$6:$DT$6,23),0) -> 0 | AB21: =IF(24<=核心参数输入!$B$9,SUMIFS(季度投融资!$D$42:$DT$42,季度投融资!$D$6:$DT$6,24),0) -> 0 | AC21: =IF(25<=核心参数输入!$B$9,SUMIFS(季度投融资!$D$42:$DT$42,季度投融资!$D$6:$DT$6,25),0) -> 0 | AD21: =IF(26<=核心参数输入!$B$9,SUMIFS(季度投融资!$D$42:$DT$42,季度投融资!$D$6:$DT$6,26),0) -> 0 | AE21: =IF(27<=核心参数输入!$B$9,SUMIFS(季度投融资!$D$42:$DT$42,季度投融资!$D$6:$DT$6,27),0) -> 0 | AF21: =IF(28<=核心参数输入!$B$9,SUMIFS(季度投融资!$D$42:$DT$42,季度投融资!$D$6:$DT$6,28),0) -> 0 | AG21: =IF(29<=核心参数输入!$B$9,SUMIFS(季度投融资!$D$42:$DT$42,季度投融资!$D$6:$DT$6,29),0) -> 0 | AH21: =IF(30<=核心参数输入!$B$9,SUMIFS(季度投融资!$D$42:$DT$42,季度投融资!$D$6:$DT$6,30),0) -> 0
A22: 经营偿债现金CFADS | B22: 万元 | D22: =IF(0<=核心参数输入!$B$9,SUMIFS(季度现金流!$D$65:$DT$65,季度现金流!$D$6:$DT$6,0),0) -> 0 | E22: =IF(1<=核心参数输入!$B$9,SUMIFS(季度现金流!$D$65:$DT$65,季度现金流!$D$6:$DT$6,1),0) -> 0 | F22: =IF(2<=核心参数输入!$B$9,SUMIFS(季度现金流!$D$65:$DT$65,季度现金流!$D$6:$DT$6,2),0) -> 0 | G22: =IF(3<=核心参数输入!$B$9,SUMIFS(季度现金流!$D$65:$DT$65,季度现金流!$D$6:$DT$6,3),0) -> 0 | H22: =IF(4<=核心参数输入!$B$9,SUMIFS(季度现金流!$D$65:$DT$65,季度现金流!$D$6:$DT$6,4),0) -> 11554.939 | I22: =IF(5<=核心参数输入!$B$9,SUMIFS(季度现金流!$D$65:$DT$65,季度现金流!$D$6:$DT$6,5),0) -> 16821.455 | J22: =IF(6<=核心参数输入!$B$9,SUMIFS(季度现金流!$D$65:$DT$65,季度现金流!$D$6:$DT$6,6),0) -> 13643.414 | K22: =IF(7<=核心参数输入!$B$9,SUMIFS(季度现金流!$D$65:$DT$65,季度现金流!$D$6:$DT$6,7),0) -> 2022.6792 | L22: =IF(8<=核心参数输入!$B$9,SUMIFS(季度现金流!$D$65:$DT$65,季度现金流!$D$6:$DT$6,8),0) -> 1018.1447 | M22: =IF(9<=核心参数输入!$B$9,SUMIFS(季度现金流!$D$65:$DT$65,季度现金流!$D$6:$DT$6,9),0) -> 1037.1814 | N22: =IF(10<=核心参数输入!$B$9,SUMIFS(季度现金流!$D$65:$DT$65,季度现金流!$D$6:$DT$6,10),0) -> 1053.783 | O22: =IF(11<=核心参数输入!$B$9,SUMIFS(季度现金流!$D$65:$DT$65,季度现金流!$D$6:$DT$6,11),0) -> 1070.6005 | P22: =IF(12<=核心参数输入!$B$9,SUMIFS(季度现金流!$D$65:$DT$65,季度现金流!$D$6:$DT$6,12),0) -> 1087.6365 | Q22: =IF(13<=核心参数输入!$B$9,SUMIFS(季度现金流!$D$65:$DT$65,季度现金流!$D$6:$DT$6,13),0) -> 1104.8935 | R22: =IF(14<=核心参数输入!$B$9,SUMIFS(季度现金流!$D$65:$DT$65,季度现金流!$D$6:$DT$6,14),0) -> 1093.3816 | S22: =IF(15<=核心参数输入!$B$9,SUMIFS(季度现金流!$D$65:$DT$65,季度现金流!$D$6:$DT$6,15),0) -> 1068.3217 | T22: =IF(16<=核心参数输入!$B$9,SUMIFS(季度现金流!$D$65:$DT$65,季度现金流!$D$6:$DT$6,16),0) -> 1081.7738 | U22: =IF(17<=核心参数输入!$B$9,SUMIFS(季度现金流!$D$65:$DT$65,季度现金流!$D$6:$DT$6,17),0) -> 1095.3997 | V22: =IF(18<=核心参数输入!$B$9,SUMIFS(季度现金流!$D$65:$DT$65,季度现金流!$D$6:$DT$6,18),0) -> 1109.2015 | W22: =IF(19<=核心参数输入!$B$9,SUMIFS(季度现金流!$D$65:$DT$65,季度现金流!$D$6:$DT$6,19),0) -> 1123.1812 | X22: =IF(20<=核心参数输入!$B$9,SUMIFS(季度现金流!$D$65:$DT$65,季度现金流!$D$6:$DT$6,20),0) -> 1137.3409 | Y22: =IF(21<=核心参数输入!$B$9,SUMIFS(季度现金流!$D$65:$DT$65,季度现金流!$D$6:$DT$6,21),0) -> 0 | Z22: =IF(22<=核心参数输入!$B$9,SUMIFS(季度现金流!$D$65:$DT$65,季度现金流!$D$6:$DT$6,22),0) -> 0 | AA22: =IF(23<=核心参数输入!$B$9,SUMIFS(季度现金流!$D$65:$DT$65,季度现金流!$D$6:$DT$6,23),0) -> 0 | AB22: =IF(24<=核心参数输入!$B$9,SUMIFS(季度现金流!$D$65:$DT$65,季度现金流!$D$6:$DT$6,24),0) -> 0 | AC22: =IF(25<=核心参数输入!$B$9,SUMIFS(季度现金流!$D$65:$DT$65,季度现金流!$D$6:$DT$6,25),0) -> 0 | AD22: =IF(26<=核心参数输入!$B$9,SUMIFS(季度现金流!$D$65:$DT$65,季度现金流!$D$6:$DT$6,26),0) -> 0 | AE22: =IF(27<=核心参数输入!$B$9,SUMIFS(季度现金流!$D$65:$DT$65,季度现金流!$D$6:$DT$6,27),0) -> 0 | AF22: =IF(28<=核心参数输入!$B$9,SUMIFS(季度现金流!$D$65:$DT$65,季度现金流!$D$6:$DT$6,28),0) -> 0 | AG22: =IF(29<=核心参数输入!$B$9,SUMIFS(季度现金流!$D$65:$DT$65,季度现金流!$D$6:$DT$6,29),0) -> 0 | AH22: =IF(30<=核心参数输入!$B$9,SUMIFS(季度现金流!$D$65:$DT$65,季度现金流!$D$6:$DT$6,30),0) -> 0
A23: 合同本息 | B23: 万元 | D23: =IF(0<=核心参数输入!$B$9,SUMIFS(季度投融资!$D$46:$DT$46,季度投融资!$D$6:$DT$6,0),0) -> 0 | E23: =IF(1<=核心参数输入!$B$9,SUMIFS(季度投融资!$D$46:$DT$46,季度投融资!$D$6:$DT$6,1),0) -> 177.1875 | F23: =IF(2<=核心参数输入!$B$9,SUMIFS(季度投融资!$D$46:$DT$46,季度投融资!$D$6:$DT$6,2),0) -> 630 | G23: =IF(3<=核心参数输入!$B$9,SUMIFS(季度投融资!$D$46:$DT$46,季度投融资!$D$6:$DT$6,3),0) -> 1071 | H23: =IF(4<=核心参数输入!$B$9,SUMIFS(季度投融资!$D$46:$DT$46,季度投融资!$D$6:$DT$6,4),0) -> 5523.2143 | I23: =IF(5<=核心参数输入!$B$9,SUMIFS(季度投融资!$D$46:$DT$46,季度投融资!$D$6:$DT$6,5),0) -> 5343.2143 | J23: =IF(6<=核心参数输入!$B$9,SUMIFS(季度投融资!$D$46:$DT$46,季度投融资!$D$6:$DT$6,6),0) -> 5163.2143 | K23: =IF(7<=核心参数输入!$B$9,SUMIFS(季度投融资!$D$46:$DT$46,季度投融资!$D$6:$DT$6,7),0) -> 4983.2143 | L23: =IF(8<=核心参数输入!$B$9,SUMIFS(季度投融资!$D$46:$DT$46,季度投融资!$D$6:$DT$6,8),0) -> 4803.2143 | M23: =IF(9<=核心参数输入!$B$9,SUMIFS(季度投融资!$D$46:$DT$46,季度投融资!$D$6:$DT$6,9),0) -> 4623.2143 | N23: =IF(10<=核心参数输入!$B$9,SUMIFS(季度投融资!$D$46:$DT$46,季度投融资!$D$6:$DT$6,10),0) -> 4443.2143 | O23: =IF(11<=核心参数输入!$B$9,SUMIFS(季度投融资!$D$46:$DT$46,季度投融资!$D$6:$DT$6,11),0) -> 0 | P23: =IF(12<=核心参数输入!$B$9,SUMIFS(季度投融资!$D$46:$DT$46,季度投融资!$D$6:$DT$6,12),0) -> 0 | Q23: =IF(13<=核心参数输入!$B$9,SUMIFS(季度投融资!$D$46:$DT$46,季度投融资!$D$6:$DT$6,13),0) -> 0 | R23: =IF(14<=核心参数输入!$B$9,SUMIFS(季度投融资!$D$46:$DT$46,季度投融资!$D$6:$DT$6,14),0) -> 0 | S23: =IF(15<=核心参数输入!$B$9,SUMIFS(季度投融资!$D$46:$DT$46,季度投融资!$D$6:$DT$6,15),0) -> 0 | T23: =IF(16<=核心参数输入!$B$9,SUMIFS(季度投融资!$D$46:$DT$46,季度投融资!$D$6:$DT$6,16),0) -> 0 | U23: =IF(17<=核心参数输入!$B$9,SUMIFS(季度投融资!$D$46:$DT$46,季度投融资!$D$6:$DT$6,17),0) -> 0 | V23: =IF(18<=核心参数输入!$B$9,SUMIFS(季度投融资!$D$46:$DT$46,季度投融资!$D$6:$DT$6,18),0) -> 0 | W23: =IF(19<=核心参数输入!$B$9,SUMIFS(季度投融资!$D$46:$DT$46,季度投融资!$D$6:$DT$6,19),0) -> 0 | X23: =IF(20<=核心参数输入!$B$9,SUMIFS(季度投融资!$D$46:$DT$46,季度投融资!$D$6:$DT$6,20),0) -> 0 | Y23: =IF(21<=核心参数输入!$B$9,SUMIFS(季度投融资!$D$46:$DT$46,季度投融资!$D$6:$DT$6,21),0) -> 0 | Z23: =IF(22<=核心参数输入!$B$9,SUMIFS(季度投融资!$D$46:$DT$46,季度投融资!$D$6:$DT$6,22),0) -> 0 | AA23: =IF(23<=核心参数输入!$B$9,SUMIFS(季度投融资!$D$46:$DT$46,季度投融资!$D$6:$DT$6,23),0) -> 0 | AB23: =IF(24<=核心参数输入!$B$9,SUMIFS(季度投融资!$D$46:$DT$46,季度投融资!$D$6:$DT$6,24),0) -> 0 | AC23: =IF(25<=核心参数输入!$B$9,SUMIFS(季度投融资!$D$46:$DT$46,季度投融资!$D$6:$DT$6,25),0) -> 0 | AD23: =IF(26<=核心参数输入!$B$9,SUMIFS(季度投融资!$D$46:$DT$46,季度投融资!$D$6:$DT$6,26),0) -> 0 | AE23: =IF(27<=核心参数输入!$B$9,SUMIFS(季度投融资!$D$46:$DT$46,季度投融资!$D$6:$DT$6,27),0) -> 0 | AF23: =IF(28<=核心参数输入!$B$9,SUMIFS(季度投融资!$D$46:$DT$46,季度投融资!$D$6:$DT$6,28),0) -> 0 | AG23: =IF(29<=核心参数输入!$B$9,SUMIFS(季度投融资!$D$46:$DT$46,季度投融资!$D$6:$DT$6,29),0) -> 0 | AH23: =IF(30<=核心参数输入!$B$9,SUMIFS(季度投融资!$D$46:$DT$46,季度投融资!$D$6:$DT$6,30),0) -> 0
A24: 年度经营DSCR | B24: 倍 | D24: =IF(0<=核心参数输入!$B$9,IF(AND(0*4>核心参数输入!$B$16*4+核心参数输入!$B$148,D23>0.000001),D22/D23,""),"") | E24: =IF(1<=核心参数输入!$B$9,IF(AND(1*4>核心参数输入!$B$16*4+核心参数输入!$B$148,E23>0.000001),E22/E23,""),"") | F24: =IF(2<=核心参数输入!$B$9,IF(AND(2*4>核心参数输入!$B$16*4+核心参数输入!$B$148,F23>0.000001),F22/F23,""),"") | G24: =IF(3<=核心参数输入!$B$9,IF(AND(3*4>核心参数输入!$B$16*4+核心参数输入!$B$148,G23>0.000001),G22/G23,""),"") | H24: =IF(4<=核心参数输入!$B$9,IF(AND(4*4>核心参数输入!$B$16*4+核心参数输入!$B$148,H23>0.000001),H22/H23,""),"") -> 2.0920679 | I24: =IF(5<=核心参数输入!$B$9,IF(AND(5*4>核心参数输入!$B$16*4+核心参数输入!$B$148,I23>0.000001),I22/I23,""),"") -> 3.1481903 | J24: =IF(6<=核心参数输入!$B$9,IF(AND(6*4>核心参数输入!$B$16*4+核心参数输入!$B$148,J23>0.000001),J22/J23,""),"") -> 2.6424265 | K24: =IF(7<=核心参数输入!$B$9,IF(AND(7*4>核心参数输入!$B$16*4+核心参数输入!$B$148,K23>0.000001),K22/K23,""),"") -> 0.4058985 | L24: =IF(8<=核心参数输入!$B$9,IF(AND(8*4>核心参数输入!$B$16*4+核心参数输入!$B$148,L23>0.000001),L22/L23,""),"") -> 0.21197153 | M24: =IF(9<=核心参数输入!$B$9,IF(AND(9*4>核心参数输入!$B$16*4+核心参数输入!$B$148,M23>0.000001),M22/M23,""),"") -> 0.22434206 | N24: =IF(10<=核心参数输入!$B$9,IF(AND(10*4>核心参数输入!$B$16*4+核心参数输入!$B$148,N23>0.000001),N22/N23,""),"") -> 0.23716682 | O24: =IF(11<=核心参数输入!$B$9,IF(AND(11*4>核心参数输入!$B$16*4+核心参数输入!$B$148,O23>0.000001),O22/O23,""),"") | P24: =IF(12<=核心参数输入!$B$9,IF(AND(12*4>核心参数输入!$B$16*4+核心参数输入!$B$148,P23>0.000001),P22/P23,""),"") | Q24: =IF(13<=核心参数输入!$B$9,IF(AND(13*4>核心参数输入!$B$16*4+核心参数输入!$B$148,Q23>0.000001),Q22/Q23,""),"") | R24: =IF(14<=核心参数输入!$B$9,IF(AND(14*4>核心参数输入!$B$16*4+核心参数输入!$B$148,R23>0.000001),R22/R23,""),"") | S24: =IF(15<=核心参数输入!$B$9,IF(AND(15*4>核心参数输入!$B$16*4+核心参数输入!$B$148,S23>0.000001),S22/S23,""),"") | T24: =IF(16<=核心参数输入!$B$9,IF(AND(16*4>核心参数输入!$B$16*4+核心参数输入!$B$148,T23>0.000001),T22/T23,""),"") | U24: =IF(17<=核心参数输入!$B$9,IF(AND(17*4>核心参数输入!$B$16*4+核心参数输入!$B$148,U23>0.000001),U22/U23,""),"") | V24: =IF(18<=核心参数输入!$B$9,IF(AND(18*4>核心参数输入!$B$16*4+核心参数输入!$B$148,V23>0.000001),V22/V23,""),"") | W24: =IF(19<=核心参数输入!$B$9,IF(AND(19*4>核心参数输入!$B$16*4+核心参数输入!$B$148,W23>0.000001),W22/W23,""),"") | X24: =IF(20<=核心参数输入!$B$9,IF(AND(20*4>核心参数输入!$B$16*4+核心参数输入!$B$148,X23>0.000001),X22/X23,""),"") | Y24: =IF(21<=核心参数输入!$B$9,IF(AND(21*4>核心参数输入!$B$16*4+核心参数输入!$B$148,Y23>0.000001),Y22/Y23,""),"") | Z24: =IF(22<=核心参数输入!$B$9,IF(AND(22*4>核心参数输入!$B$16*4+核心参数输入!$B$148,Z23>0.000001),Z22/Z23,""),"") | AA24: =IF(23<=核心参数输入!$B$9,IF(AND(23*4>核心参数输入!$B$16*4+核心参数输入!$B$148,AA23>0.000001),AA22/AA23,""),"") | AB24: =IF(24<=核心参数输入!$B$9,IF(AND(24*4>核心参数输入!$B$16*4+核心参数输入!$B$148,AB23>0.000001),AB22/AB23,""),"") | AC24: =IF(25<=核心参数输入!$B$9,IF(AND(25*4>核心参数输入!$B$16*4+核心参数输入!$B$148,AC23>0.000001),AC22/AC23,""),"") | AD24: =IF(26<=核心参数输入!$B$9,IF(AND(26*4>核心参数输入!$B$16*4+核心参数输入!$B$148,AD23>0.000001),AD22/AD23,""),"") | AE24: =IF(27<=核心参数输入!$B$9,IF(AND(27*4>核心参数输入!$B$16*4+核心参数输入!$B$148,AE23>0.000001),AE22/AE23,""),"") | AF24: =IF(28<=核心参数输入!$B$9,IF(AND(28*4>核心参数输入!$B$16*4+核心参数输入!$B$148,AF23>0.000001),AF22/AF23,""),"") | AG24: =IF(29<=核心参数输入!$B$9,IF(AND(29*4>核心参数输入!$B$16*4+核心参数输入!$B$148,AG23>0.000001),AG22/AG23,""),"") | AH24: =IF(30<=核心参数输入!$B$9,IF(AND(30*4>核心参数输入!$B$16*4+核心参数输入!$B$148,AH23>0.000001),AH22/AH23,""),"")
A25: 项目投资现金流 | B25: 万元 | D25: =IF(0<=核心参数输入!$B$9,SUMIFS(季度现金流!$D$45:$DT$45,季度现金流!$D$6:$DT$6,0),0) -> -8000 | E25: =IF(1<=核心参数输入!$B$9,SUMIFS(季度现金流!$D$45:$DT$45,季度现金流!$D$6:$DT$6,1),0) -> -15876 | F25: =IF(2<=核心参数输入!$B$9,SUMIFS(季度现金流!$D$45:$DT$45,季度现金流!$D$6:$DT$6,2),0) -> -21168 | G25: =IF(3<=核心参数输入!$B$9,SUMIFS(季度现金流!$D$45:$DT$45,季度现金流!$D$6:$DT$6,3),0) -> -15876 | H25: =IF(4<=核心参数输入!$B$9,SUMIFS(季度现金流!$D$45:$DT$45,季度现金流!$D$6:$DT$6,4),0) -> 10660.869 | I25: =IF(5<=核心参数输入!$B$9,SUMIFS(季度现金流!$D$45:$DT$45,季度现金流!$D$6:$DT$6,5),0) -> 16446.397 | J25: =IF(6<=核心参数输入!$B$9,SUMIFS(季度现金流!$D$45:$DT$45,季度现金流!$D$6:$DT$6,6),0) -> 13339.344 | K25: =IF(7<=核心参数输入!$B$9,SUMIFS(季度现金流!$D$45:$DT$45,季度现金流!$D$6:$DT$6,7),0) -> 1995.0135 | L25: =IF(8<=核心参数输入!$B$9,SUMIFS(季度现金流!$D$45:$DT$45,季度现金流!$D$6:$DT$6,8),0) -> 970.136 | M25: =IF(9<=核心参数输入!$B$9,SUMIFS(季度现金流!$D$45:$DT$45,季度现金流!$D$6:$DT$6,9),0) -> 984.41355 | N25: =IF(10<=核心参数输入!$B$9,SUMIFS(季度现金流!$D$45:$DT$45,季度现金流!$D$6:$DT$6,10),0) -> 996.86475 | O25: =IF(11<=核心参数输入!$B$9,SUMIFS(季度现金流!$D$45:$DT$45,季度现金流!$D$6:$DT$6,11),0) -> 1009.4779 | P25: =IF(12<=核心参数输入!$B$9,SUMIFS(季度现金流!$D$45:$DT$45,季度现金流!$D$6:$DT$6,12),0) -> 1022.2549 | Q25: =IF(13<=核心参数输入!$B$9,SUMIFS(季度现金流!$D$45:$DT$45,季度现金流!$D$6:$DT$6,13),0) -> 1035.1976 | R25: =IF(14<=核心参数输入!$B$9,SUMIFS(季度现金流!$D$45:$DT$45,季度现金流!$D$6:$DT$6,14),0) -> 1048.3082 | S25: =IF(15<=核心参数输入!$B$9,SUMIFS(季度现金流!$D$45:$DT$45,季度现金流!$D$6:$DT$6,15),0) -> 1061.5886 | T25: =IF(16<=核心参数输入!$B$9,SUMIFS(季度现金流!$D$45:$DT$45,季度现金流!$D$6:$DT$6,16),0) -> 1075.0407 | U25: =IF(17<=核心参数输入!$B$9,SUMIFS(季度现金流!$D$45:$DT$45,季度现金流!$D$6:$DT$6,17),0) -> 1088.6666 | V25: =IF(18<=核心参数输入!$B$9,SUMIFS(季度现金流!$D$45:$DT$45,季度现金流!$D$6:$DT$6,18),0) -> 1102.4684 | W25: =IF(19<=核心参数输入!$B$9,SUMIFS(季度现金流!$D$45:$DT$45,季度现金流!$D$6:$DT$6,19),0) -> 1116.4481 | X25: =IF(20<=核心参数输入!$B$9,SUMIFS(季度现金流!$D$45:$DT$45,季度现金流!$D$6:$DT$6,20),0) -> 1130.6078 | Y25: =IF(21<=核心参数输入!$B$9,SUMIFS(季度现金流!$D$45:$DT$45,季度现金流!$D$6:$DT$6,21),0) -> 0 | Z25: =IF(22<=核心参数输入!$B$9,SUMIFS(季度现金流!$D$45:$DT$45,季度现金流!$D$6:$DT$6,22),0) -> 0 | AA25: =IF(23<=核心参数输入!$B$9,SUMIFS(季度现金流!$D$45:$DT$45,季度现金流!$D$6:$DT$6,23),0) -> 0 | AB25: =IF(24<=核心参数输入!$B$9,SUMIFS(季度现金流!$D$45:$DT$45,季度现金流!$D$6:$DT$6,24),0) -> 0 | AC25: =IF(25<=核心参数输入!$B$9,SUMIFS(季度现金流!$D$45:$DT$45,季度现金流!$D$6:$DT$6,25),0) -> 0 | AD25: =IF(26<=核心参数输入!$B$9,SUMIFS(季度现金流!$D$45:$DT$45,季度现金流!$D$6:$DT$6,26),0) -> 0 | AE25: =IF(27<=核心参数输入!$B$9,SUMIFS(季度现金流!$D$45:$DT$45,季度现金流!$D$6:$DT$6,27),0) -> 0 | AF25: =IF(28<=核心参数输入!$B$9,SUMIFS(季度现金流!$D$45:$DT$45,季度现金流!$D$6:$DT$6,28),0) -> 0 | AG25: =IF(29<=核心参数输入!$B$9,SUMIFS(季度现金流!$D$45:$DT$45,季度现金流!$D$6:$DT$6,29),0) -> 0 | AH25: =IF(30<=核心参数输入!$B$9,SUMIFS(季度现金流!$D$45:$DT$45,季度现金流!$D$6:$DT$6,30),0) -> 0
A26: 资本金现金流（完整出资） | B26: 万元 | D26: =IF(0<=核心参数输入!$B$9,SUMIFS(季度现金流!$D$47:$DT$47,季度现金流!$D$6:$DT$6,0),0) -> -8000 | E26: =IF(1<=核心参数输入!$B$9,SUMIFS(季度现金流!$D$47:$DT$47,季度现金流!$D$6:$DT$6,1),0) -> -7065 | F26: =IF(2<=核心参数输入!$B$9,SUMIFS(季度现金流!$D$47:$DT$47,季度现金流!$D$6:$DT$6,2),0) -> -9798 | G26: =IF(3<=核心参数输入!$B$9,SUMIFS(季度现金流!$D$47:$DT$47,季度现金流!$D$6:$DT$6,3),0) -> -7947 | H26: =IF(4<=核心参数输入!$B$9,SUMIFS(季度现金流!$D$47:$DT$47,季度现金流!$D$6:$DT$6,4),0) -> 5531.7249 | I26: =IF(5<=核心参数输入!$B$9,SUMIFS(季度现金流!$D$47:$DT$47,季度现金流!$D$6:$DT$6,5),0) -> 6237.3722 | J26: =IF(6<=核心参数输入!$B$9,SUMIFS(季度现金流!$D$47:$DT$47,季度现金流!$D$6:$DT$6,6),0) -> 0 | K26: =IF(7<=核心参数输入!$B$9,SUMIFS(季度现金流!$D$47:$DT$47,季度现金流!$D$6:$DT$6,7),0) -> 0 | L26: =IF(8<=核心参数输入!$B$9,SUMIFS(季度现金流!$D$47:$DT$47,季度现金流!$D$6:$DT$6,8),0) -> 0 | M26: =IF(9<=核心参数输入!$B$9,SUMIFS(季度现金流!$D$47:$DT$47,季度现金流!$D$6:$DT$6,9),0) -> 0 | N26: =IF(10<=核心参数输入!$B$9,SUMIFS(季度现金流!$D$47:$DT$47,季度现金流!$D$6:$DT$6,10),0) -> 0 | O26: =IF(11<=核心参数输入!$B$9,SUMIFS(季度现金流!$D$47:$DT$47,季度现金流!$D$6:$DT$6,11),0) -> 1070.6005 | P26: =IF(12<=核心参数输入!$B$9,SUMIFS(季度现金流!$D$47:$DT$47,季度现金流!$D$6:$DT$6,12),0) -> 1087.6365 | Q26: =IF(13<=核心参数输入!$B$9,SUMIFS(季度现金流!$D$47:$DT$47,季度现金流!$D$6:$DT$6,13),0) -> 1104.8935 | R26: =IF(14<=核心参数输入!$B$9,SUMIFS(季度现金流!$D$47:$DT$47,季度现金流!$D$6:$DT$6,14),0) -> 1093.3816 | S26: =IF(15<=核心参数输入!$B$9,SUMIFS(季度现金流!$D$47:$DT$47,季度现金流!$D$6:$DT$6,15),0) -> 1068.3217 | T26: =IF(16<=核心参数输入!$B$9,SUMIFS(季度现金流!$D$47:$DT$47,季度现金流!$D$6:$DT$6,16),0) -> 1081.7738 | U26: =IF(17<=核心参数输入!$B$9,SUMIFS(季度现金流!$D$47:$DT$47,季度现金流!$D$6:$DT$6,17),0) -> 1095.3997 | V26: =IF(18<=核心参数输入!$B$9,SUMIFS(季度现金流!$D$47:$DT$47,季度现金流!$D$6:$DT$6,18),0) -> 1109.2015 | W26: =IF(19<=核心参数输入!$B$9,SUMIFS(季度现金流!$D$47:$DT$47,季度现金流!$D$6:$DT$6,19),0) -> 1123.1812 | X26: =IF(20<=核心参数输入!$B$9,SUMIFS(季度现金流!$D$47:$DT$47,季度现金流!$D$6:$DT$6,20),0) -> 1137.3409 | Y26: =IF(21<=核心参数输入!$B$9,SUMIFS(季度现金流!$D$47:$DT$47,季度现金流!$D$6:$DT$6,21),0) -> 0 | Z26: =IF(22<=核心参数输入!$B$9,SUMIFS(季度现金流!$D$47:$DT$47,季度现金流!$D$6:$DT$6,22),0) -> 0 | AA26: =IF(23<=核心参数输入!$B$9,SUMIFS(季度现金流!$D$47:$DT$47,季度现金流!$D$6:$DT$6,23),0) -> 0 | AB26: =IF(24<=核心参数输入!$B$9,SUMIFS(季度现金流!$D$47:$DT$47,季度现金流!$D$6:$DT$6,24),0) -> 0 | AC26: =IF(25<=核心参数输入!$B$9,SUMIFS(季度现金流!$D$47:$DT$47,季度现金流!$D$6:$DT$6,25),0) -> 0 | AD26: =IF(26<=核心参数输入!$B$9,SUMIFS(季度现金流!$D$47:$DT$47,季度现金流!$D$6:$DT$6,26),0) -> 0 | AE26: =IF(27<=核心参数输入!$B$9,SUMIFS(季度现金流!$D$47:$DT$47,季度现金流!$D$6:$DT$6,27),0) -> 0 | AF26: =IF(28<=核心参数输入!$B$9,SUMIFS(季度现金流!$D$47:$DT$47,季度现金流!$D$6:$DT$6,28),0) -> 0 | AG26: =IF(29<=核心参数输入!$B$9,SUMIFS(季度现金流!$D$47:$DT$47,季度现金流!$D$6:$DT$6,29),0) -> 0 | AH26: =IF(30<=核心参数输入!$B$9,SUMIFS(季度现金流!$D$47:$DT$47,季度现金流!$D$6:$DT$6,30),0) -> 0
A27: 所需股东投入 | B27: 万元 | D27: =IF(0<=核心参数输入!$B$9,SUMIFS(季度现金流!$D$49:$DT$49,季度现金流!$D$6:$DT$6,0),0) -> 8000 | E27: =IF(1<=核心参数输入!$B$9,SUMIFS(季度现金流!$D$49:$DT$49,季度现金流!$D$6:$DT$6,1),0) -> 7065 | F27: =IF(2<=核心参数输入!$B$9,SUMIFS(季度现金流!$D$49:$DT$49,季度现金流!$D$6:$DT$6,2),0) -> 9798 | G27: =IF(3<=核心参数输入!$B$9,SUMIFS(季度现金流!$D$49:$DT$49,季度现金流!$D$6:$DT$6,3),0) -> 7947 | H27: =IF(4<=核心参数输入!$B$9,SUMIFS(季度现金流!$D$49:$DT$49,季度现金流!$D$6:$DT$6,4),0) -> 0 | I27: =IF(5<=核心参数输入!$B$9,SUMIFS(季度现金流!$D$49:$DT$49,季度现金流!$D$6:$DT$6,5),0) -> 0 | J27: =IF(6<=核心参数输入!$B$9,SUMIFS(季度现金流!$D$49:$DT$49,季度现金流!$D$6:$DT$6,6),0) -> 0 | K27: =IF(7<=核心参数输入!$B$9,SUMIFS(季度现金流!$D$49:$DT$49,季度现金流!$D$6:$DT$6,7),0) -> 0 | L27: =IF(8<=核心参数输入!$B$9,SUMIFS(季度现金流!$D$49:$DT$49,季度现金流!$D$6:$DT$6,8),0) -> 0 | M27: =IF(9<=核心参数输入!$B$9,SUMIFS(季度现金流!$D$49:$DT$49,季度现金流!$D$6:$DT$6,9),0) -> 0 | N27: =IF(10<=核心参数输入!$B$9,SUMIFS(季度现金流!$D$49:$DT$49,季度现金流!$D$6:$DT$6,10),0) -> 0 | O27: =IF(11<=核心参数输入!$B$9,SUMIFS(季度现金流!$D$49:$DT$49,季度现金流!$D$6:$DT$6,11),0) -> 0 | P27: =IF(12<=核心参数输入!$B$9,SUMIFS(季度现金流!$D$49:$DT$49,季度现金流!$D$6:$DT$6,12),0) -> 0 | Q27: =IF(13<=核心参数输入!$B$9,SUMIFS(季度现金流!$D$49:$DT$49,季度现金流!$D$6:$DT$6,13),0) -> 0 | R27: =IF(14<=核心参数输入!$B$9,SUMIFS(季度现金流!$D$49:$DT$49,季度现金流!$D$6:$DT$6,14),0) -> 0 | S27: =IF(15<=核心参数输入!$B$9,SUMIFS(季度现金流!$D$49:$DT$49,季度现金流!$D$6:$DT$6,15),0) -> 0 | T27: =IF(16<=核心参数输入!$B$9,SUMIFS(季度现金流!$D$49:$DT$49,季度现金流!$D$6:$DT$6,16),0) -> 0 | U27: =IF(17<=核心参数输入!$B$9,SUMIFS(季度现金流!$D$49:$DT$49,季度现金流!$D$6:$DT$6,17),0) -> 0 | V27: =IF(18<=核心参数输入!$B$9,SUMIFS(季度现金流!$D$49:$DT$49,季度现金流!$D$6:$DT$6,18),0) -> 0 | W27: =IF(19<=核心参数输入!$B$9,SUMIFS(季度现金流!$D$49:$DT$49,季度现金流!$D$6:$DT$6,19),0) -> 0 | X27: =IF(20<=核心参数输入!$B$9,SUMIFS(季度现金流!$D$49:$DT$49,季度现金流!$D$6:$DT$6,20),0) -> 0 | Y27: =IF(21<=核心参数输入!$B$9,SUMIFS(季度现金流!$D$49:$DT$49,季度现金流!$D$6:$DT$6,21),0) -> 0 | Z27: =IF(22<=核心参数输入!$B$9,SUMIFS(季度现金流!$D$49:$DT$49,季度现金流!$D$6:$DT$6,22),0) -> 0 | AA27: =IF(23<=核心参数输入!$B$9,SUMIFS(季度现金流!$D$49:$DT$49,季度现金流!$D$6:$DT$6,23),0) -> 0 | AB27: =IF(24<=核心参数输入!$B$9,SUMIFS(季度现金流!$D$49:$DT$49,季度现金流!$D$6:$DT$6,24),0) -> 0 | AC27: =IF(25<=核心参数输入!$B$9,SUMIFS(季度现金流!$D$49:$DT$49,季度现金流!$D$6:$DT$6,25),0) -> 0 | AD27: =IF(26<=核心参数输入!$B$9,SUMIFS(季度现金流!$D$49:$DT$49,季度现金流!$D$6:$DT$6,26),0) -> 0 | AE27: =IF(27<=核心参数输入!$B$9,SUMIFS(季度现金流!$D$49:$DT$49,季度现金流!$D$6:$DT$6,27),0) -> 0 | AF27: =IF(28<=核心参数输入!$B$9,SUMIFS(季度现金流!$D$49:$DT$49,季度现金流!$D$6:$DT$6,28),0) -> 0 | AG27: =IF(29<=核心参数输入!$B$9,SUMIFS(季度现金流!$D$49:$DT$49,季度现金流!$D$6:$DT$6,29),0) -> 0 | AH27: =IF(30<=核心参数输入!$B$9,SUMIFS(季度现金流!$D$49:$DT$49,季度现金流!$D$6:$DT$6,30),0) -> 0
A28: 理论股东分配 | B28: 万元 | D28: =IF(0<=核心参数输入!$B$9,SUMIFS(季度现金流!$D$50:$DT$50,季度现金流!$D$6:$DT$6,0),0) -> 0 | E28: =IF(1<=核心参数输入!$B$9,SUMIFS(季度现金流!$D$50:$DT$50,季度现金流!$D$6:$DT$6,1),0) -> 0 | F28: =IF(2<=核心参数输入!$B$9,SUMIFS(季度现金流!$D$50:$DT$50,季度现金流!$D$6:$DT$6,2),0) -> 0 | G28: =IF(3<=核心参数输入!$B$9,SUMIFS(季度现金流!$D$50:$DT$50,季度现金流!$D$6:$DT$6,3),0) -> 0 | H28: =IF(4<=核心参数输入!$B$9,SUMIFS(季度现金流!$D$50:$DT$50,季度现金流!$D$6:$DT$6,4),0) -> 5531.7249 | I28: =IF(5<=核心参数输入!$B$9,SUMIFS(季度现金流!$D$50:$DT$50,季度现金流!$D$6:$DT$6,5),0) -> 6237.3722 | J28: =IF(6<=核心参数输入!$B$9,SUMIFS(季度现金流!$D$50:$DT$50,季度现金流!$D$6:$DT$6,6),0) -> 0 | K28: =IF(7<=核心参数输入!$B$9,SUMIFS(季度现金流!$D$50:$DT$50,季度现金流!$D$6:$DT$6,7),0) -> 0 | L28: =IF(8<=核心参数输入!$B$9,SUMIFS(季度现金流!$D$50:$DT$50,季度现金流!$D$6:$DT$6,8),0) -> 0 | M28: =IF(9<=核心参数输入!$B$9,SUMIFS(季度现金流!$D$50:$DT$50,季度现金流!$D$6:$DT$6,9),0) -> 0 | N28: =IF(10<=核心参数输入!$B$9,SUMIFS(季度现金流!$D$50:$DT$50,季度现金流!$D$6:$DT$6,10),0) -> 0 | O28: =IF(11<=核心参数输入!$B$9,SUMIFS(季度现金流!$D$50:$DT$50,季度现金流!$D$6:$DT$6,11),0) -> 1070.6005 | P28: =IF(12<=核心参数输入!$B$9,SUMIFS(季度现金流!$D$50:$DT$50,季度现金流!$D$6:$DT$6,12),0) -> 1087.6365 | Q28: =IF(13<=核心参数输入!$B$9,SUMIFS(季度现金流!$D$50:$DT$50,季度现金流!$D$6:$DT$6,13),0) -> 1104.8935 | R28: =IF(14<=核心参数输入!$B$9,SUMIFS(季度现金流!$D$50:$DT$50,季度现金流!$D$6:$DT$6,14),0) -> 1093.3816 | S28: =IF(15<=核心参数输入!$B$9,SUMIFS(季度现金流!$D$50:$DT$50,季度现金流!$D$6:$DT$6,15),0) -> 1068.3217 | T28: =IF(16<=核心参数输入!$B$9,SUMIFS(季度现金流!$D$50:$DT$50,季度现金流!$D$6:$DT$6,16),0) -> 1081.7738 | U28: =IF(17<=核心参数输入!$B$9,SUMIFS(季度现金流!$D$50:$DT$50,季度现金流!$D$6:$DT$6,17),0) -> 1095.3997 | V28: =IF(18<=核心参数输入!$B$9,SUMIFS(季度现金流!$D$50:$DT$50,季度现金流!$D$6:$DT$6,18),0) -> 1109.2015 | W28: =IF(19<=核心参数输入!$B$9,SUMIFS(季度现金流!$D$50:$DT$50,季度现金流!$D$6:$DT$6,19),0) -> 1123.1812 | X28: =IF(20<=核心参数输入!$B$9,SUMIFS(季度现金流!$D$50:$DT$50,季度现金流!$D$6:$DT$6,20),0) -> 1137.3409 | Y28: =IF(21<=核心参数输入!$B$9,SUMIFS(季度现金流!$D$50:$DT$50,季度现金流!$D$6:$DT$6,21),0) -> 0 | Z28: =IF(22<=核心参数输入!$B$9,SUMIFS(季度现金流!$D$50:$DT$50,季度现金流!$D$6:$DT$6,22),0) -> 0 | AA28: =IF(23<=核心参数输入!$B$9,SUMIFS(季度现金流!$D$50:$DT$50,季度现金流!$D$6:$DT$6,23),0) -> 0 | AB28: =IF(24<=核心参数输入!$B$9,SUMIFS(季度现金流!$D$50:$DT$50,季度现金流!$D$6:$DT$6,24),0) -> 0 | AC28: =IF(25<=核心参数输入!$B$9,SUMIFS(季度现金流!$D$50:$DT$50,季度现金流!$D$6:$DT$6,25),0) -> 0 | AD28: =IF(26<=核心参数输入!$B$9,SUMIFS(季度现金流!$D$50:$DT$50,季度现金流!$D$6:$DT$6,26),0) -> 0 | AE28: =IF(27<=核心参数输入!$B$9,SUMIFS(季度现金流!$D$50:$DT$50,季度现金流!$D$6:$DT$6,27),0) -> 0 | AF28: =IF(28<=核心参数输入!$B$9,SUMIFS(季度现金流!$D$50:$DT$50,季度现金流!$D$6:$DT$6,28),0) -> 0 | AG28: =IF(29<=核心参数输入!$B$9,SUMIFS(季度现金流!$D$50:$DT$50,季度现金流!$D$6:$DT$6,29),0) -> 0 | AH28: =IF(30<=核心参数输入!$B$9,SUMIFS(季度现金流!$D$50:$DT$50,季度现金流!$D$6:$DT$6,30),0) -> 0
A29: 年末留存现金 | B29: 万元 | D29: =IF(0<=核心参数输入!$B$9,INDEX(季度现金流!$D$51:$DT$51,1,0*4+1),0) -> 0 | E29: =IF(1<=核心参数输入!$B$9,INDEX(季度现金流!$D$51:$DT$51,1,1*4+1),0) -> 0 | F29: =IF(2<=核心参数输入!$B$9,INDEX(季度现金流!$D$51:$DT$51,1,2*4+1),0) -> 0 | G29: =IF(3<=核心参数输入!$B$9,INDEX(季度现金流!$D$51:$DT$51,1,3*4+1),0) -> 0 | H29: =IF(4<=核心参数输入!$B$9,INDEX(季度现金流!$D$51:$DT$51,1,4*4+1),0) -> 0 | I29: =IF(5<=核心参数输入!$B$9,INDEX(季度现金流!$D$51:$DT$51,1,5*4+1),0) -> 5240.8689 | J29: =IF(6<=核心参数输入!$B$9,INDEX(季度现金流!$D$51:$DT$51,1,6*4+1),0) -> 13721.069 | K29: =IF(7<=核心参数输入!$B$9,INDEX(季度现金流!$D$51:$DT$51,1,7*4+1),0) -> 10760.534 | L29: =IF(8<=核心参数输入!$B$9,INDEX(季度现金流!$D$51:$DT$51,1,8*4+1),0) -> 6975.4642 | M29: =IF(9<=核心参数输入!$B$9,INDEX(季度现金流!$D$51:$DT$51,1,9*4+1),0) -> 3389.4313 | N29: =IF(10<=核心参数输入!$B$9,INDEX(季度现金流!$D$51:$DT$51,1,10*4+1),0) -> 0 | O29: =IF(11<=核心参数输入!$B$9,INDEX(季度现金流!$D$51:$DT$51,1,11*4+1),0) -> 0 | P29: =IF(12<=核心参数输入!$B$9,INDEX(季度现金流!$D$51:$DT$51,1,12*4+1),0) -> 0 | Q29: =IF(13<=核心参数输入!$B$9,INDEX(季度现金流!$D$51:$DT$51,1,13*4+1),0) -> 0 | R29: =IF(14<=核心参数输入!$B$9,INDEX(季度现金流!$D$51:$DT$51,1,14*4+1),0) -> 0 | S29: =IF(15<=核心参数输入!$B$9,INDEX(季度现金流!$D$51:$DT$51,1,15*4+1),0) -> 0 | T29: =IF(16<=核心参数输入!$B$9,INDEX(季度现金流!$D$51:$DT$51,1,16*4+1),0) -> 0 | U29: =IF(17<=核心参数输入!$B$9,INDEX(季度现金流!$D$51:$DT$51,1,17*4+1),0) -> 0 | V29: =IF(18<=核心参数输入!$B$9,INDEX(季度现金流!$D$51:$DT$51,1,18*4+1),0) -> 0 | W29: =IF(19<=核心参数输入!$B$9,INDEX(季度现金流!$D$51:$DT$51,1,19*4+1),0) -> 0 | X29: =IF(20<=核心参数输入!$B$9,INDEX(季度现金流!$D$51:$DT$51,1,20*4+1),0) -> 0 | Y29: =IF(21<=核心参数输入!$B$9,INDEX(季度现金流!$D$51:$DT$51,1,21*4+1),0) -> 0 | Z29: =IF(22<=核心参数输入!$B$9,INDEX(季度现金流!$D$51:$DT$51,1,22*4+1),0) -> 0 | AA29: =IF(23<=核心参数输入!$B$9,INDEX(季度现金流!$D$51:$DT$51,1,23*4+1),0) -> 0 | AB29: =IF(24<=核心参数输入!$B$9,INDEX(季度现金流!$D$51:$DT$51,1,24*4+1),0) -> 0 | AC29: =IF(25<=核心参数输入!$B$9,INDEX(季度现金流!$D$51:$DT$51,1,25*4+1),0) -> 0 | AD29: =IF(26<=核心参数输入!$B$9,INDEX(季度现金流!$D$51:$DT$51,1,26*4+1),0) -> 0 | AE29: =IF(27<=核心参数输入!$B$9,INDEX(季度现金流!$D$51:$DT$51,1,27*4+1),0) -> 0 | AF29: =IF(28<=核心参数输入!$B$9,INDEX(季度现金流!$D$51:$DT$51,1,28*4+1),0) -> 0 | AG29: =IF(29<=核心参数输入!$B$9,INDEX(季度现金流!$D$51:$DT$51,1,29*4+1),0) -> 0 | AH29: =IF(30<=核心参数输入!$B$9,INDEX(季度现金流!$D$51:$DT$51,1,30*4+1),0) -> 0
A30: 年内最大未落实缺口 | B30: 万元 | D30: =IF(0<=核心参数输入!$B$9,季度现金流!D58,0) -> 0 | E30: =IF(1<=核心参数输入!$B$9,MAX(季度现金流!$E$58:$H$58),0) -> 0 | F30: =IF(2<=核心参数输入!$B$9,MAX(季度现金流!$I$58:$L$58),0) -> 0 | G30: =IF(3<=核心参数输入!$B$9,MAX(季度现金流!$M$58:$P$58),0) -> 0 | H30: =IF(4<=核心参数输入!$B$9,MAX(季度现金流!$Q$58:$T$58),0) -> 0 | I30: =IF(5<=核心参数输入!$B$9,MAX(季度现金流!$U$58:$X$58),0) -> 0 | J30: =IF(6<=核心参数输入!$B$9,MAX(季度现金流!$Y$58:$AB$58),0) -> 0 | K30: =IF(7<=核心参数输入!$B$9,MAX(季度现金流!$AC$58:$AF$58),0) -> 0 | L30: =IF(8<=核心参数输入!$B$9,MAX(季度现金流!$AG$58:$AJ$58),0) -> 0 | M30: =IF(9<=核心参数输入!$B$9,MAX(季度现金流!$AK$58:$AN$58),0) -> 0 | N30: =IF(10<=核心参数输入!$B$9,MAX(季度现金流!$AO$58:$AR$58),0) -> 0 | O30: =IF(11<=核心参数输入!$B$9,MAX(季度现金流!$AS$58:$AV$58),0) -> 0 | P30: =IF(12<=核心参数输入!$B$9,MAX(季度现金流!$AW$58:$AZ$58),0) -> 0 | Q30: =IF(13<=核心参数输入!$B$9,MAX(季度现金流!$BA$58:$BD$58),0) -> 0 | R30: =IF(14<=核心参数输入!$B$9,MAX(季度现金流!$BE$58:$BH$58),0) -> 0 | S30: =IF(15<=核心参数输入!$B$9,MAX(季度现金流!$BI$58:$BL$58),0) -> 0 | T30: =IF(16<=核心参数输入!$B$9,MAX(季度现金流!$BM$58:$BP$58),0) -> 0 | U30: =IF(17<=核心参数输入!$B$9,MAX(季度现金流!$BQ$58:$BT$58),0) -> 0 | V30: =IF(18<=核心参数输入!$B$9,MAX(季度现金流!$BU$58:$BX$58),0) -> 0 | W30: =IF(19<=核心参数输入!$B$9,MAX(季度现金流!$BY$58:$CB$58),0) -> 0 | X30: =IF(20<=核心参数输入!$B$9,MAX(季度现金流!$CC$58:$CF$58),0) -> 0 | Y30: =IF(21<=核心参数输入!$B$9,MAX(季度现金流!$CG$58:$CJ$58),0) -> 0 | Z30: =IF(22<=核心参数输入!$B$9,MAX(季度现金流!$CK$58:$CN$58),0) -> 0 | AA30: =IF(23<=核心参数输入!$B$9,MAX(季度现金流!$CO$58:$CR$58),0) -> 0 | AB30: =IF(24<=核心参数输入!$B$9,MAX(季度现金流!$CS$58:$CV$58),0) -> 0 | AC30: =IF(25<=核心参数输入!$B$9,MAX(季度现金流!$CW$58:$CZ$58),0) -> 0 | AD30: =IF(26<=核心参数输入!$B$9,MAX(季度现金流!$DA$58:$DD$58),0) -> 0 | AE30: =IF(27<=核心参数输入!$B$9,MAX(季度现金流!$DE$58:$DH$58),0) -> 0 | AF30: =IF(28<=核心参数输入!$B$9,MAX(季度现金流!$DI$58:$DL$58),0) -> 0 | AG30: =IF(29<=核心参数输入!$B$9,MAX(季度现金流!$DM$58:$DP$58),0) -> 0 | AH30: =IF(30<=核心参数输入!$B$9,MAX(季度现金流!$DQ$58:$DT$58),0) -> 0
A31: 偿债需要其他资金支持 | B31: 万元 | D31: =IF(0<=核心参数输入!$B$9,SUMIFS(季度现金流!$D$67:$DT$67,季度现金流!$D$6:$DT$6,0),0) -> 0 | E31: =IF(1<=核心参数输入!$B$9,SUMIFS(季度现金流!$D$67:$DT$67,季度现金流!$D$6:$DT$6,1),0) -> 189 | F31: =IF(2<=核心参数输入!$B$9,SUMIFS(季度现金流!$D$67:$DT$67,季度现金流!$D$6:$DT$6,2),0) -> 630 | G31: =IF(3<=核心参数输入!$B$9,SUMIFS(季度现金流!$D$67:$DT$67,季度现金流!$D$6:$DT$6,3),0) -> 1071 | H31: =IF(4<=核心参数输入!$B$9,SUMIFS(季度现金流!$D$67:$DT$67,季度现金流!$D$6:$DT$6,4),0) -> 1396.0439 | I31: =IF(5<=核心参数输入!$B$9,SUMIFS(季度现金流!$D$67:$DT$67,季度现金流!$D$6:$DT$6,5),0) -> 566.83608 | J31: =IF(6<=核心参数输入!$B$9,SUMIFS(季度现金流!$D$67:$DT$67,季度现金流!$D$6:$DT$6,6),0) -> 1440.8865 | K31: =IF(7<=核心参数输入!$B$9,SUMIFS(季度现金流!$D$67:$DT$67,季度现金流!$D$6:$DT$6,7),0) -> 4199.8884 | L31: =IF(8<=核心参数输入!$B$9,SUMIFS(季度现金流!$D$67:$DT$67,季度现金流!$D$6:$DT$6,8),0) -> 4143.016 | M31: =IF(9<=核心参数输入!$B$9,SUMIFS(季度现金流!$D$67:$DT$67,季度现金流!$D$6:$DT$6,9),0) -> 4093.9189 | N31: =IF(10<=核心参数输入!$B$9,SUMIFS(季度现金流!$D$67:$DT$67,季度现金流!$D$6:$DT$6,10),0) -> 4044.7685 | O31: =IF(11<=核心参数输入!$B$9,SUMIFS(季度现金流!$D$67:$DT$67,季度现金流!$D$6:$DT$6,11),0) -> 0 | P31: =IF(12<=核心参数输入!$B$9,SUMIFS(季度现金流!$D$67:$DT$67,季度现金流!$D$6:$DT$6,12),0) -> 0 | Q31: =IF(13<=核心参数输入!$B$9,SUMIFS(季度现金流!$D$67:$DT$67,季度现金流!$D$6:$DT$6,13),0) -> 0 | R31: =IF(14<=核心参数输入!$B$9,SUMIFS(季度现金流!$D$67:$DT$67,季度现金流!$D$6:$DT$6,14),0) -> 0 | S31: =IF(15<=核心参数输入!$B$9,SUMIFS(季度现金流!$D$67:$DT$67,季度现金流!$D$6:$DT$6,15),0) -> 0 | T31: =IF(16<=核心参数输入!$B$9,SUMIFS(季度现金流!$D$67:$DT$67,季度现金流!$D$6:$DT$6,16),0) -> 0 | U31: =IF(17<=核心参数输入!$B$9,SUMIFS(季度现金流!$D$67:$DT$67,季度现金流!$D$6:$DT$6,17),0) -> 0 | V31: =IF(18<=核心参数输入!$B$9,SUMIFS(季度现金流!$D$67:$DT$67,季度现金流!$D$6:$DT$6,18),0) -> 0 | W31: =IF(19<=核心参数输入!$B$9,SUMIFS(季度现金流!$D$67:$DT$67,季度现金流!$D$6:$DT$6,19),0) -> 0 | X31: =IF(20<=核心参数输入!$B$9,SUMIFS(季度现金流!$D$67:$DT$67,季度现金流!$D$6:$DT$6,20),0) -> 0 | Y31: =IF(21<=核心参数输入!$B$9,SUMIFS(季度现金流!$D$67:$DT$67,季度现金流!$D$6:$DT$6,21),0) -> 0 | Z31: =IF(22<=核心参数输入!$B$9,SUMIFS(季度现金流!$D$67:$DT$67,季度现金流!$D$6:$DT$6,22),0) -> 0 | AA31: =IF(23<=核心参数输入!$B$9,SUMIFS(季度现金流!$D$67:$DT$67,季度现金流!$D$6:$DT$6,23),0) -> 0 | AB31: =IF(24<=核心参数输入!$B$9,SUMIFS(季度现金流!$D$67:$DT$67,季度现金流!$D$6:$DT$6,24),0) -> 0 | AC31: =IF(25<=核心参数输入!$B$9,SUMIFS(季度现金流!$D$67:$DT$67,季度现金流!$D$6:$DT$6,25),0) -> 0 | AD31: =IF(26<=核心参数输入!$B$9,SUMIFS(季度现金流!$D$67:$DT$67,季度现金流!$D$6:$DT$6,26),0) -> 0 | AE31: =IF(27<=核心参数输入!$B$9,SUMIFS(季度现金流!$D$67:$DT$67,季度现金流!$D$6:$DT$6,27),0) -> 0 | AF31: =IF(28<=核心参数输入!$B$9,SUMIFS(季度现金流!$D$67:$DT$67,季度现金流!$D$6:$DT$6,28),0) -> 0 | AG31: =IF(29<=核心参数输入!$B$9,SUMIFS(季度现金流!$D$67:$DT$67,季度现金流!$D$6:$DT$6,29),0) -> 0 | AH31: =IF(30<=核心参数输入!$B$9,SUMIFS(季度现金流!$D$67:$DT$67,季度现金流!$D$6:$DT$6,30),0) -> 0
A32: 年末计划贷款余额 | B32: 万元 | D32: =IF(0<=核心参数输入!$B$9,INDEX(季度投融资!$D$43:$DT$43,1,0*4+1),0) -> 0 | E32: =IF(1<=核心参数输入!$B$9,INDEX(季度投融资!$D$43:$DT$43,1,1*4+1),0) -> 9000 | F32: =IF(2<=核心参数输入!$B$9,INDEX(季度投融资!$D$43:$DT$43,1,2*4+1),0) -> 21000 | G32: =IF(3<=核心参数输入!$B$9,INDEX(季度投融资!$D$43:$DT$43,1,3*4+1),0) -> 30000 | H32: =IF(4<=核心参数输入!$B$9,INDEX(季度投融资!$D$43:$DT$43,1,4*4+1),0) -> 25714.286 | I32: =IF(5<=核心参数输入!$B$9,INDEX(季度投融资!$D$43:$DT$43,1,5*4+1),0) -> 21428.571 | J32: =IF(6<=核心参数输入!$B$9,INDEX(季度投融资!$D$43:$DT$43,1,6*4+1),0) -> 17142.857 | K32: =IF(7<=核心参数输入!$B$9,INDEX(季度投融资!$D$43:$DT$43,1,7*4+1),0) -> 12857.143 | L32: =IF(8<=核心参数输入!$B$9,INDEX(季度投融资!$D$43:$DT$43,1,8*4+1),0) -> 8571.4286 | M32: =IF(9<=核心参数输入!$B$9,INDEX(季度投融资!$D$43:$DT$43,1,9*4+1),0) -> 4285.7143 | N32: =IF(10<=核心参数输入!$B$9,INDEX(季度投融资!$D$43:$DT$43,1,10*4+1),0) -> 0 | O32: =IF(11<=核心参数输入!$B$9,INDEX(季度投融资!$D$43:$DT$43,1,11*4+1),0) -> 0 | P32: =IF(12<=核心参数输入!$B$9,INDEX(季度投融资!$D$43:$DT$43,1,12*4+1),0) -> 0 | Q32: =IF(13<=核心参数输入!$B$9,INDEX(季度投融资!$D$43:$DT$43,1,13*4+1),0) -> 0 | R32: =IF(14<=核心参数输入!$B$9,INDEX(季度投融资!$D$43:$DT$43,1,14*4+1),0) -> 0 | S32: =IF(15<=核心参数输入!$B$9,INDEX(季度投融资!$D$43:$DT$43,1,15*4+1),0) -> 0 | T32: =IF(16<=核心参数输入!$B$9,INDEX(季度投融资!$D$43:$DT$43,1,16*4+1),0) -> 0 | U32: =IF(17<=核心参数输入!$B$9,INDEX(季度投融资!$D$43:$DT$43,1,17*4+1),0) -> 0 | V32: =IF(18<=核心参数输入!$B$9,INDEX(季度投融资!$D$43:$DT$43,1,18*4+1),0) -> 0 | W32: =IF(19<=核心参数输入!$B$9,INDEX(季度投融资!$D$43:$DT$43,1,19*4+1),0) -> 0 | X32: =IF(20<=核心参数输入!$B$9,INDEX(季度投融资!$D$43:$DT$43,1,20*4+1),0) -> 0 | Y32: =IF(21<=核心参数输入!$B$9,INDEX(季度投融资!$D$43:$DT$43,1,21*4+1),0) -> 0 | Z32: =IF(22<=核心参数输入!$B$9,INDEX(季度投融资!$D$43:$DT$43,1,22*4+1),0) -> 0 | AA32: =IF(23<=核心参数输入!$B$9,INDEX(季度投融资!$D$43:$DT$43,1,23*4+1),0) -> 0 | AB32: =IF(24<=核心参数输入!$B$9,INDEX(季度投融资!$D$43:$DT$43,1,24*4+1),0) -> 0 | AC32: =IF(25<=核心参数输入!$B$9,INDEX(季度投融资!$D$43:$DT$43,1,25*4+1),0) -> 0 | AD32: =IF(26<=核心参数输入!$B$9,INDEX(季度投融资!$D$43:$DT$43,1,26*4+1),0) -> 0 | AE32: =IF(27<=核心参数输入!$B$9,INDEX(季度投融资!$D$43:$DT$43,1,27*4+1),0) -> 0 | AF32: =IF(28<=核心参数输入!$B$9,INDEX(季度投融资!$D$43:$DT$43,1,28*4+1),0) -> 0 | AG32: =IF(29<=核心参数输入!$B$9,INDEX(季度投融资!$D$43:$DT$43,1,29*4+1),0) -> 0 | AH32: =IF(30<=核心参数输入!$B$9,INDEX(季度投融资!$D$43:$DT$43,1,30*4+1),0) -> 0
A33: 累计项目现金流 | B33: 万元 | D33: =IF(0<=核心参数输入!$B$9,INDEX(季度现金流!$D$68:$DT$68,1,0*4+1),0) -> -8000 | E33: =IF(1<=核心参数输入!$B$9,INDEX(季度现金流!$D$68:$DT$68,1,1*4+1),0) -> -23876 | F33: =IF(2<=核心参数输入!$B$9,INDEX(季度现金流!$D$68:$DT$68,1,2*4+1),0) -> -45044 | G33: =IF(3<=核心参数输入!$B$9,INDEX(季度现金流!$D$68:$DT$68,1,3*4+1),0) -> -60920 | H33: =IF(4<=核心参数输入!$B$9,INDEX(季度现金流!$D$68:$DT$68,1,4*4+1),0) -> -50259.131 | I33: =IF(5<=核心参数输入!$B$9,INDEX(季度现金流!$D$68:$DT$68,1,5*4+1),0) -> -33812.734 | J33: =IF(6<=核心参数输入!$B$9,INDEX(季度现金流!$D$68:$DT$68,1,6*4+1),0) -> -20473.391 | K33: =IF(7<=核心参数输入!$B$9,INDEX(季度现金流!$D$68:$DT$68,1,7*4+1),0) -> -18478.377 | L33: =IF(8<=核心参数输入!$B$9,INDEX(季度现金流!$D$68:$DT$68,1,8*4+1),0) -> -17508.241 | M33: =IF(9<=核心参数输入!$B$9,INDEX(季度现金流!$D$68:$DT$68,1,9*4+1),0) -> -16523.828 | N33: =IF(10<=核心参数输入!$B$9,INDEX(季度现金流!$D$68:$DT$68,1,10*4+1),0) -> -15526.963 | O33: =IF(11<=核心参数输入!$B$9,INDEX(季度现金流!$D$68:$DT$68,1,11*4+1),0) -> -14517.485 | P33: =IF(12<=核心参数输入!$B$9,INDEX(季度现金流!$D$68:$DT$68,1,12*4+1),0) -> -13495.23 | Q33: =IF(13<=核心参数输入!$B$9,INDEX(季度现金流!$D$68:$DT$68,1,13*4+1),0) -> -12460.032 | R33: =IF(14<=核心参数输入!$B$9,INDEX(季度现金流!$D$68:$DT$68,1,14*4+1),0) -> -11411.724 | S33: =IF(15<=核心参数输入!$B$9,INDEX(季度现金流!$D$68:$DT$68,1,15*4+1),0) -> -10350.136 | T33: =IF(16<=核心参数输入!$B$9,INDEX(季度现金流!$D$68:$DT$68,1,16*4+1),0) -> -9275.0949 | U33: =IF(17<=核心参数输入!$B$9,INDEX(季度现金流!$D$68:$DT$68,1,17*4+1),0) -> -8186.4283 | V33: =IF(18<=核心参数输入!$B$9,INDEX(季度现金流!$D$68:$DT$68,1,18*4+1),0) -> -7083.9599 | W33: =IF(19<=核心参数输入!$B$9,INDEX(季度现金流!$D$68:$DT$68,1,19*4+1),0) -> -5967.5118 | X33: =IF(20<=核心参数输入!$B$9,INDEX(季度现金流!$D$68:$DT$68,1,20*4+1),0) -> -4836.904 | Y33: =IF(21<=核心参数输入!$B$9,INDEX(季度现金流!$D$68:$DT$68,1,21*4+1),0) -> 0 | Z33: =IF(22<=核心参数输入!$B$9,INDEX(季度现金流!$D$68:$DT$68,1,22*4+1),0) -> 0 | AA33: =IF(23<=核心参数输入!$B$9,INDEX(季度现金流!$D$68:$DT$68,1,23*4+1),0) -> 0 | AB33: =IF(24<=核心参数输入!$B$9,INDEX(季度现金流!$D$68:$DT$68,1,24*4+1),0) -> 0 | AC33: =IF(25<=核心参数输入!$B$9,INDEX(季度现金流!$D$68:$DT$68,1,25*4+1),0) -> 0 | AD33: =IF(26<=核心参数输入!$B$9,INDEX(季度现金流!$D$68:$DT$68,1,26*4+1),0) -> 0 | AE33: =IF(27<=核心参数输入!$B$9,INDEX(季度现金流!$D$68:$DT$68,1,27*4+1),0) -> 0 | AF33: =IF(28<=核心参数输入!$B$9,INDEX(季度现金流!$D$68:$DT$68,1,28*4+1),0) -> 0 | AG33: =IF(29<=核心参数输入!$B$9,INDEX(季度现金流!$D$68:$DT$68,1,29*4+1),0) -> 0 | AH33: =IF(30<=核心参数输入!$B$9,INDEX(季度现金流!$D$68:$DT$68,1,30*4+1),0) -> 0
A34: 本年项目折现现金流 | B34: 万元 | D34: =IF(0<=核心参数输入!$B$9,SUMIFS(季度现金流!$D$69:$DT$69,季度现金流!$D$6:$DT$6,0),0) -> -8000 | E34: =IF(1<=核心参数输入!$B$9,SUMIFS(季度现金流!$D$69:$DT$69,季度现金流!$D$6:$DT$6,1),0) -> -15133.93 | F34: =IF(2<=核心参数输入!$B$9,SUMIFS(季度现金流!$D$69:$DT$69,季度现金流!$D$6:$DT$6,2),0) -> -18683.864 | G34: =IF(3<=核心参数输入!$B$9,SUMIFS(季度现金流!$D$69:$DT$69,季度现金流!$D$6:$DT$6,3),0) -> -12974.906 | H34: =IF(4<=核心参数输入!$B$9,SUMIFS(季度现金流!$D$69:$DT$69,季度现金流!$D$6:$DT$6,4),0) -> 8039.3312 | I34: =IF(5<=核心参数输入!$B$9,SUMIFS(季度现金流!$D$69:$DT$69,季度现金流!$D$6:$DT$6,5),0) -> 11531.788 | J34: =IF(6<=核心参数输入!$B$9,SUMIFS(季度现金流!$D$69:$DT$69,季度现金流!$D$6:$DT$6,6),0) -> 8673.015 | K34: =IF(7<=核心参数输入!$B$9,SUMIFS(季度现金流!$D$69:$DT$69,季度现金流!$D$6:$DT$6,7),0) -> 1217.4626 | L34: =IF(8<=核心参数输入!$B$9,SUMIFS(季度现金流!$D$69:$DT$69,季度现金流!$D$6:$DT$6,8),0) -> 540.32911 | M34: =IF(9<=核心参数输入!$B$9,SUMIFS(季度现金流!$D$69:$DT$69,季度现金流!$D$6:$DT$6,9),0) -> 507.76778 | N34: =IF(10<=核心参数输入!$B$9,SUMIFS(季度现金流!$D$69:$DT$69,季度现金流!$D$6:$DT$6,10),0) -> 476.14966 | O34: =IF(11<=核心参数输入!$B$9,SUMIFS(季度现金流!$D$69:$DT$69,季度现金流!$D$6:$DT$6,11),0) -> 446.50179 | P34: =IF(12<=核心参数输入!$B$9,SUMIFS(季度现金流!$D$69:$DT$69,季度现金流!$D$6:$DT$6,12),0) -> 418.7012 | Q34: =IF(13<=核心参数输入!$B$9,SUMIFS(季度现金流!$D$69:$DT$69,季度现金流!$D$6:$DT$6,13),0) -> 392.63264 | R34: =IF(14<=核心参数输入!$B$9,SUMIFS(季度现金流!$D$69:$DT$69,季度现金流!$D$6:$DT$6,14),0) -> 368.18807 | S34: =IF(15<=核心参数输入!$B$9,SUMIFS(季度现金流!$D$69:$DT$69,季度现金流!$D$6:$DT$6,15),0) -> 345.26617 | T34: =IF(16<=核心参数输入!$B$9,SUMIFS(季度现金流!$D$69:$DT$69,季度现金流!$D$6:$DT$6,16),0) -> 323.77199 | U34: =IF(17<=核心参数输入!$B$9,SUMIFS(季度现金流!$D$69:$DT$69,季度现金流!$D$6:$DT$6,17),0) -> 303.61649 | V34: =IF(18<=核心参数输入!$B$9,SUMIFS(季度现金流!$D$69:$DT$69,季度现金流!$D$6:$DT$6,18),0) -> 284.7162 | W34: =IF(19<=核心参数输入!$B$9,SUMIFS(季度现金流!$D$69:$DT$69,季度现金流!$D$6:$DT$6,19),0) -> 266.99287 | X34: =IF(20<=核心参数输入!$B$9,SUMIFS(季度现金流!$D$69:$DT$69,季度现金流!$D$6:$DT$6,20),0) -> 250.37313 | Y34: =IF(21<=核心参数输入!$B$9,SUMIFS(季度现金流!$D$69:$DT$69,季度现金流!$D$6:$DT$6,21),0) -> 0 | Z34: =IF(22<=核心参数输入!$B$9,SUMIFS(季度现金流!$D$69:$DT$69,季度现金流!$D$6:$DT$6,22),0) -> 0 | AA34: =IF(23<=核心参数输入!$B$9,SUMIFS(季度现金流!$D$69:$DT$69,季度现金流!$D$6:$DT$6,23),0) -> 0 | AB34: =IF(24<=核心参数输入!$B$9,SUMIFS(季度现金流!$D$69:$DT$69,季度现金流!$D$6:$DT$6,24),0) -> 0 | AC34: =IF(25<=核心参数输入!$B$9,SUMIFS(季度现金流!$D$69:$DT$69,季度现金流!$D$6:$DT$6,25),0) -> 0 | AD34: =IF(26<=核心参数输入!$B$9,SUMIFS(季度现金流!$D$69:$DT$69,季度现金流!$D$6:$DT$6,26),0) -> 0 | AE34: =IF(27<=核心参数输入!$B$9,SUMIFS(季度现金流!$D$69:$DT$69,季度现金流!$D$6:$DT$6,27),0) -> 0 | AF34: =IF(28<=核心参数输入!$B$9,SUMIFS(季度现金流!$D$69:$DT$69,季度现金流!$D$6:$DT$6,28),0) -> 0 | AG34: =IF(29<=核心参数输入!$B$9,SUMIFS(季度现金流!$D$69:$DT$69,季度现金流!$D$6:$DT$6,29),0) -> 0 | AH34: =IF(30<=核心参数输入!$B$9,SUMIFS(季度现金流!$D$69:$DT$69,季度现金流!$D$6:$DT$6,30),0) -> 0
A35: 累计项目折现现金流 | B35: 万元 | D35: =IF(0<=核心参数输入!$B$9,INDEX(季度现金流!$D$70:$DT$70,1,0*4+1),0) -> -8000 | E35: =IF(1<=核心参数输入!$B$9,INDEX(季度现金流!$D$70:$DT$70,1,1*4+1),0) -> -23133.93 | F35: =IF(2<=核心参数输入!$B$9,INDEX(季度现金流!$D$70:$DT$70,1,2*4+1),0) -> -41817.794 | G35: =IF(3<=核心参数输入!$B$9,INDEX(季度现金流!$D$70:$DT$70,1,3*4+1),0) -> -54792.7 | H35: =IF(4<=核心参数输入!$B$9,INDEX(季度现金流!$D$70:$DT$70,1,4*4+1),0) -> -46753.368 | I35: =IF(5<=核心参数输入!$B$9,INDEX(季度现金流!$D$70:$DT$70,1,5*4+1),0) -> -35221.58 | J35: =IF(6<=核心参数输入!$B$9,INDEX(季度现金流!$D$70:$DT$70,1,6*4+1),0) -> -26548.565 | K35: =IF(7<=核心参数输入!$B$9,INDEX(季度现金流!$D$70:$DT$70,1,7*4+1),0) -> -25331.103 | L35: =IF(8<=核心参数输入!$B$9,INDEX(季度现金流!$D$70:$DT$70,1,8*4+1),0) -> -24790.773 | M35: =IF(9<=核心参数输入!$B$9,INDEX(季度现金流!$D$70:$DT$70,1,9*4+1),0) -> -24283.006 | N35: =IF(10<=核心参数输入!$B$9,INDEX(季度现金流!$D$70:$DT$70,1,10*4+1),0) -> -23806.856 | O35: =IF(11<=核心参数输入!$B$9,INDEX(季度现金流!$D$70:$DT$70,1,11*4+1),0) -> -23360.354 | P35: =IF(12<=核心参数输入!$B$9,INDEX(季度现金流!$D$70:$DT$70,1,12*4+1),0) -> -22941.653 | Q35: =IF(13<=核心参数输入!$B$9,INDEX(季度现金流!$D$70:$DT$70,1,13*4+1),0) -> -22549.02 | R35: =IF(14<=核心参数输入!$B$9,INDEX(季度现金流!$D$70:$DT$70,1,14*4+1),0) -> -22180.832 | S35: =IF(15<=核心参数输入!$B$9,INDEX(季度现金流!$D$70:$DT$70,1,15*4+1),0) -> -21835.566 | T35: =IF(16<=核心参数输入!$B$9,INDEX(季度现金流!$D$70:$DT$70,1,16*4+1),0) -> -21511.794 | U35: =IF(17<=核心参数输入!$B$9,INDEX(季度现金流!$D$70:$DT$70,1,17*4+1),0) -> -21208.178 | V35: =IF(18<=核心参数输入!$B$9,INDEX(季度现金流!$D$70:$DT$70,1,18*4+1),0) -> -20923.461 | W35: =IF(19<=核心参数输入!$B$9,INDEX(季度现金流!$D$70:$DT$70,1,19*4+1),0) -> -20656.469 | X35: =IF(20<=核心参数输入!$B$9,INDEX(季度现金流!$D$70:$DT$70,1,20*4+1),0) -> -20406.095 | Y35: =IF(21<=核心参数输入!$B$9,INDEX(季度现金流!$D$70:$DT$70,1,21*4+1),0) -> 0 | Z35: =IF(22<=核心参数输入!$B$9,INDEX(季度现金流!$D$70:$DT$70,1,22*4+1),0) -> 0 | AA35: =IF(23<=核心参数输入!$B$9,INDEX(季度现金流!$D$70:$DT$70,1,23*4+1),0) -> 0 | AB35: =IF(24<=核心参数输入!$B$9,INDEX(季度现金流!$D$70:$DT$70,1,24*4+1),0) -> 0 | AC35: =IF(25<=核心参数输入!$B$9,INDEX(季度现金流!$D$70:$DT$70,1,25*4+1),0) -> 0 | AD35: =IF(26<=核心参数输入!$B$9,INDEX(季度现金流!$D$70:$DT$70,1,26*4+1),0) -> 0 | AE35: =IF(27<=核心参数输入!$B$9,INDEX(季度现金流!$D$70:$DT$70,1,27*4+1),0) -> 0 | AF35: =IF(28<=核心参数输入!$B$9,INDEX(季度现金流!$D$70:$DT$70,1,28*4+1),0) -> 0 | AG35: =IF(29<=核心参数输入!$B$9,INDEX(季度现金流!$D$70:$DT$70,1,29*4+1),0) -> 0 | AH35: =IF(30<=核心参数输入!$B$9,INDEX(季度现金流!$D$70:$DT$70,1,30*4+1),0) -> 0
A36: 持有期末账面净值 | B36: 万元 | D36: =IF(0<=核心参数输入!$B$9,INDEX(季度经营税费!$D$56:$DT$56,1,0*4+1),0) -> 3600 | E36: =IF(1<=核心参数输入!$B$9,INDEX(季度经营税费!$D$56:$DT$56,1,1*4+1),0) -> 10829.25 | F36: =IF(2<=核心参数输入!$B$9,INDEX(季度经营税费!$D$56:$DT$56,1,2*4+1),0) -> 20638.35 | G36: =IF(3<=核心参数输入!$B$9,INDEX(季度经营税费!$D$56:$DT$56,1,3*4+1),0) -> 28264.5 | H36: =IF(4<=核心参数输入!$B$9,INDEX(季度经营税费!$D$56:$DT$56,1,4*4+1),0) -> 27411.457 | I36: =IF(5<=核心参数输入!$B$9,INDEX(季度经营税费!$D$56:$DT$56,1,5*4+1),0) -> 26558.415 | J36: =IF(6<=核心参数输入!$B$9,INDEX(季度经营税费!$D$56:$DT$56,1,6*4+1),0) -> 25705.372 | K36: =IF(7<=核心参数输入!$B$9,INDEX(季度经营税费!$D$56:$DT$56,1,7*4+1),0) -> 24852.33 | L36: =IF(8<=核心参数输入!$B$9,INDEX(季度经营税费!$D$56:$DT$56,1,8*4+1),0) -> 23999.287 | M36: =IF(9<=核心参数输入!$B$9,INDEX(季度经营税费!$D$56:$DT$56,1,9*4+1),0) -> 23146.245 | N36: =IF(10<=核心参数输入!$B$9,INDEX(季度经营税费!$D$56:$DT$56,1,10*4+1),0) -> 22293.202 | O36: =IF(11<=核心参数输入!$B$9,INDEX(季度经营税费!$D$56:$DT$56,1,11*4+1),0) -> 21440.16 | P36: =IF(12<=核心参数输入!$B$9,INDEX(季度经营税费!$D$56:$DT$56,1,12*4+1),0) -> 20587.117 | Q36: =IF(13<=核心参数输入!$B$9,INDEX(季度经营税费!$D$56:$DT$56,1,13*4+1),0) -> 19734.075 | R36: =IF(14<=核心参数输入!$B$9,INDEX(季度经营税费!$D$56:$DT$56,1,14*4+1),0) -> 18881.032 | S36: =IF(15<=核心参数输入!$B$9,INDEX(季度经营税费!$D$56:$DT$56,1,15*4+1),0) -> 18027.99 | T36: =IF(16<=核心参数输入!$B$9,INDEX(季度经营税费!$D$56:$DT$56,1,16*4+1),0) -> 17174.947 | U36: =IF(17<=核心参数输入!$B$9,INDEX(季度经营税费!$D$56:$DT$56,1,17*4+1),0) -> 16321.905 | V36: =IF(18<=核心参数输入!$B$9,INDEX(季度经营税费!$D$56:$DT$56,1,18*4+1),0) -> 15468.862 | W36: =IF(19<=核心参数输入!$B$9,INDEX(季度经营税费!$D$56:$DT$56,1,19*4+1),0) -> 14615.82 | X36: =IF(20<=核心参数输入!$B$9,INDEX(季度经营税费!$D$56:$DT$56,1,20*4+1),0) -> 13762.777 | Y36: =IF(21<=核心参数输入!$B$9,INDEX(季度经营税费!$D$56:$DT$56,1,21*4+1),0) -> 0 | Z36: =IF(22<=核心参数输入!$B$9,INDEX(季度经营税费!$D$56:$DT$56,1,22*4+1),0) -> 0 | AA36: =IF(23<=核心参数输入!$B$9,INDEX(季度经营税费!$D$56:$DT$56,1,23*4+1),0) -> 0 | AB36: =IF(24<=核心参数输入!$B$9,INDEX(季度经营税费!$D$56:$DT$56,1,24*4+1),0) -> 0 | AC36: =IF(25<=核心参数输入!$B$9,INDEX(季度经营税费!$D$56:$DT$56,1,25*4+1),0) -> 0 | AD36: =IF(26<=核心参数输入!$B$9,INDEX(季度经营税费!$D$56:$DT$56,1,26*4+1),0) -> 0 | AE36: =IF(27<=核心参数输入!$B$9,INDEX(季度经营税费!$D$56:$DT$56,1,27*4+1),0) -> 0 | AF36: =IF(28<=核心参数输入!$B$9,INDEX(季度经营税费!$D$56:$DT$56,1,28*4+1),0) -> 0 | AG36: =IF(29<=核心参数输入!$B$9,INDEX(季度经营税费!$D$56:$DT$56,1,29*4+1),0) -> 0 | AH36: =IF(30<=核心参数输入!$B$9,INDEX(季度经营税费!$D$56:$DT$56,1,30*4+1),0) -> 0
A37: 年末销售应收 | B37: 万元 | D37: =IF(0<=核心参数输入!$B$9,INDEX(季度经营税费!$D$13:$DT$13,1,0*4+1),0) -> 0 | E37: =IF(1<=核心参数输入!$B$9,INDEX(季度经营税费!$D$13:$DT$13,1,1*4+1),0) -> 0 | F37: =IF(2<=核心参数输入!$B$9,INDEX(季度经营税费!$D$13:$DT$13,1,2*4+1),0) -> 0 | G37: =IF(3<=核心参数输入!$B$9,INDEX(季度经营税费!$D$13:$DT$13,1,3*4+1),0) -> 0 | H37: =IF(4<=核心参数输入!$B$9,INDEX(季度经营税费!$D$13:$DT$13,1,4*4+1),0) -> 1085.9062 | I37: =IF(5<=核心参数输入!$B$9,INDEX(季度经营税费!$D$13:$DT$13,1,5*4+1),0) -> 1447.875 | J37: =IF(6<=核心参数输入!$B$9,INDEX(季度经营税费!$D$13:$DT$13,1,6*4+1),0) -> 1085.9062 | K37: =IF(7<=核心参数输入!$B$9,INDEX(季度经营税费!$D$13:$DT$13,1,7*4+1),0) -> 0 | L37: =IF(8<=核心参数输入!$B$9,INDEX(季度经营税费!$D$13:$DT$13,1,8*4+1),0) -> 0 | M37: =IF(9<=核心参数输入!$B$9,INDEX(季度经营税费!$D$13:$DT$13,1,9*4+1),0) -> 0 | N37: =IF(10<=核心参数输入!$B$9,INDEX(季度经营税费!$D$13:$DT$13,1,10*4+1),0) -> 0 | O37: =IF(11<=核心参数输入!$B$9,INDEX(季度经营税费!$D$13:$DT$13,1,11*4+1),0) -> 0 | P37: =IF(12<=核心参数输入!$B$9,INDEX(季度经营税费!$D$13:$DT$13,1,12*4+1),0) -> 0 | Q37: =IF(13<=核心参数输入!$B$9,INDEX(季度经营税费!$D$13:$DT$13,1,13*4+1),0) -> 0 | R37: =IF(14<=核心参数输入!$B$9,INDEX(季度经营税费!$D$13:$DT$13,1,14*4+1),0) -> 0 | S37: =IF(15<=核心参数输入!$B$9,INDEX(季度经营税费!$D$13:$DT$13,1,15*4+1),0) -> 0 | T37: =IF(16<=核心参数输入!$B$9,INDEX(季度经营税费!$D$13:$DT$13,1,16*4+1),0) -> 0 | U37: =IF(17<=核心参数输入!$B$9,INDEX(季度经营税费!$D$13:$DT$13,1,17*4+1),0) -> 0 | V37: =IF(18<=核心参数输入!$B$9,INDEX(季度经营税费!$D$13:$DT$13,1,18*4+1),0) -> 0 | W37: =IF(19<=核心参数输入!$B$9,INDEX(季度经营税费!$D$13:$DT$13,1,19*4+1),0) -> 0 | X37: =IF(20<=核心参数输入!$B$9,INDEX(季度经营税费!$D$13:$DT$13,1,20*4+1),0) -> 0 | Y37: =IF(21<=核心参数输入!$B$9,INDEX(季度经营税费!$D$13:$DT$13,1,21*4+1),0) -> 0 | Z37: =IF(22<=核心参数输入!$B$9,INDEX(季度经营税费!$D$13:$DT$13,1,22*4+1),0) -> 0 | AA37: =IF(23<=核心参数输入!$B$9,INDEX(季度经营税费!$D$13:$DT$13,1,23*4+1),0) -> 0 | AB37: =IF(24<=核心参数输入!$B$9,INDEX(季度经营税费!$D$13:$DT$13,1,24*4+1),0) -> 0 | AC37: =IF(25<=核心参数输入!$B$9,INDEX(季度经营税费!$D$13:$DT$13,1,25*4+1),0) -> 0 | AD37: =IF(26<=核心参数输入!$B$9,INDEX(季度经营税费!$D$13:$DT$13,1,26*4+1),0) -> 0 | AE37: =IF(27<=核心参数输入!$B$9,INDEX(季度经营税费!$D$13:$DT$13,1,27*4+1),0) -> 0 | AF37: =IF(28<=核心参数输入!$B$9,INDEX(季度经营税费!$D$13:$DT$13,1,28*4+1),0) -> 0 | AG37: =IF(29<=核心参数输入!$B$9,INDEX(季度经营税费!$D$13:$DT$13,1,29*4+1),0) -> 0 | AH37: =IF(30<=核心参数输入!$B$9,INDEX(季度经营税费!$D$13:$DT$13,1,30*4+1),0) -> 0
A38: 年末进项税留抵 | B38: 万元 | D38: =IF(0<=核心参数输入!$B$9,INDEX(季度经营税费!$D$52:$DT$52,1,0*4+1),0) -> 0 | E38: =IF(1<=核心参数输入!$B$9,INDEX(季度经营税费!$D$52:$DT$52,1,1*4+1),0) -> 0 | F38: =IF(2<=核心参数输入!$B$9,INDEX(季度经营税费!$D$52:$DT$52,1,2*4+1),0) -> 0 | G38: =IF(3<=核心参数输入!$B$9,INDEX(季度经营税费!$D$52:$DT$52,1,3*4+1),0) -> 0 | H38: =IF(4<=核心参数输入!$B$9,INDEX(季度经营税费!$D$52:$DT$52,1,4*4+1),0) -> 0 | I38: =IF(5<=核心参数输入!$B$9,INDEX(季度经营税费!$D$52:$DT$52,1,5*4+1),0) -> 0 | J38: =IF(6<=核心参数输入!$B$9,INDEX(季度经营税费!$D$52:$DT$52,1,6*4+1),0) -> 0 | K38: =IF(7<=核心参数输入!$B$9,INDEX(季度经营税费!$D$52:$DT$52,1,7*4+1),0) -> 0 | L38: =IF(8<=核心参数输入!$B$9,INDEX(季度经营税费!$D$52:$DT$52,1,8*4+1),0) -> 0 | M38: =IF(9<=核心参数输入!$B$9,INDEX(季度经营税费!$D$52:$DT$52,1,9*4+1),0) -> 0 | N38: =IF(10<=核心参数输入!$B$9,INDEX(季度经营税费!$D$52:$DT$52,1,10*4+1),0) -> 0 | O38: =IF(11<=核心参数输入!$B$9,INDEX(季度经营税费!$D$52:$DT$52,1,11*4+1),0) -> 0 | P38: =IF(12<=核心参数输入!$B$9,INDEX(季度经营税费!$D$52:$DT$52,1,12*4+1),0) -> 0 | Q38: =IF(13<=核心参数输入!$B$9,INDEX(季度经营税费!$D$52:$DT$52,1,13*4+1),0) -> 0 | R38: =IF(14<=核心参数输入!$B$9,INDEX(季度经营税费!$D$52:$DT$52,1,14*4+1),0) -> 0 | S38: =IF(15<=核心参数输入!$B$9,INDEX(季度经营税费!$D$52:$DT$52,1,15*4+1),0) -> 0 | T38: =IF(16<=核心参数输入!$B$9,INDEX(季度经营税费!$D$52:$DT$52,1,16*4+1),0) -> 0 | U38: =IF(17<=核心参数输入!$B$9,INDEX(季度经营税费!$D$52:$DT$52,1,17*4+1),0) -> 0 | V38: =IF(18<=核心参数输入!$B$9,INDEX(季度经营税费!$D$52:$DT$52,1,18*4+1),0) -> 0 | W38: =IF(19<=核心参数输入!$B$9,INDEX(季度经营税费!$D$52:$DT$52,1,19*4+1),0) -> 0 | X38: =IF(20<=核心参数输入!$B$9,INDEX(季度经营税费!$D$52:$DT$52,1,20*4+1),0) -> 0 | Y38: =IF(21<=核心参数输入!$B$9,INDEX(季度经营税费!$D$52:$DT$52,1,21*4+1),0) -> 0 | Z38: =IF(22<=核心参数输入!$B$9,INDEX(季度经营税费!$D$52:$DT$52,1,22*4+1),0) -> 0 | AA38: =IF(23<=核心参数输入!$B$9,INDEX(季度经营税费!$D$52:$DT$52,1,23*4+1),0) -> 0 | AB38: =IF(24<=核心参数输入!$B$9,INDEX(季度经营税费!$D$52:$DT$52,1,24*4+1),0) -> 0 | AC38: =IF(25<=核心参数输入!$B$9,INDEX(季度经营税费!$D$52:$DT$52,1,25*4+1),0) -> 0 | AD38: =IF(26<=核心参数输入!$B$9,INDEX(季度经营税费!$D$52:$DT$52,1,26*4+1),0) -> 0 | AE38: =IF(27<=核心参数输入!$B$9,INDEX(季度经营税费!$D$52:$DT$52,1,27*4+1),0) -> 0 | AF38: =IF(28<=核心参数输入!$B$9,INDEX(季度经营税费!$D$52:$DT$52,1,28*4+1),0) -> 0 | AG38: =IF(29<=核心参数输入!$B$9,INDEX(季度经营税费!$D$52:$DT$52,1,29*4+1),0) -> 0 | AH38: =IF(30<=核心参数输入!$B$9,INDEX(季度经营税费!$D$52:$DT$52,1,30*4+1),0) -> 0
A39: 周转资金回收 | B39: 万元 | D39: =IF(0<=核心参数输入!$B$9,IF(核心参数输入!$B$64=1,SUMIFS(季度现金流!$D$17:$DT$17,季度现金流!$D$6:$DT$6,0),SUMIFS(季度现金流!$D$16:$DT$16,季度现金流!$D$6:$DT$6,0)),0) -> 0 | E39: =IF(1<=核心参数输入!$B$9,IF(核心参数输入!$B$64=1,SUMIFS(季度现金流!$D$17:$DT$17,季度现金流!$D$6:$DT$6,1),SUMIFS(季度现金流!$D$16:$DT$16,季度现金流!$D$6:$DT$6,1)),0) -> 0 | F39: =IF(2<=核心参数输入!$B$9,IF(核心参数输入!$B$64=1,SUMIFS(季度现金流!$D$17:$DT$17,季度现金流!$D$6:$DT$6,2),SUMIFS(季度现金流!$D$16:$DT$16,季度现金流!$D$6:$DT$6,2)),0) -> 0 | G39: =IF(3<=核心参数输入!$B$9,IF(核心参数输入!$B$64=1,SUMIFS(季度现金流!$D$17:$DT$17,季度现金流!$D$6:$DT$6,3),SUMIFS(季度现金流!$D$16:$DT$16,季度现金流!$D$6:$DT$6,3)),0) -> 0 | H39: =IF(4<=核心参数输入!$B$9,IF(核心参数输入!$B$64=1,SUMIFS(季度现金流!$D$17:$DT$17,季度现金流!$D$6:$DT$6,4),SUMIFS(季度现金流!$D$16:$DT$16,季度现金流!$D$6:$DT$6,4)),0) -> 0 | I39: =IF(5<=核心参数输入!$B$9,IF(核心参数输入!$B$64=1,SUMIFS(季度现金流!$D$17:$DT$17,季度现金流!$D$6:$DT$6,5),SUMIFS(季度现金流!$D$16:$DT$16,季度现金流!$D$6:$DT$6,5)),0) -> 0 | J39: =IF(6<=核心参数输入!$B$9,IF(核心参数输入!$B$64=1,SUMIFS(季度现金流!$D$17:$DT$17,季度现金流!$D$6:$DT$6,6),SUMIFS(季度现金流!$D$16:$DT$16,季度现金流!$D$6:$DT$6,6)),0) -> 0 | K39: =IF(7<=核心参数输入!$B$9,IF(核心参数输入!$B$64=1,SUMIFS(季度现金流!$D$17:$DT$17,季度现金流!$D$6:$DT$6,7),SUMIFS(季度现金流!$D$16:$DT$16,季度现金流!$D$6:$DT$6,7)),0) -> 0 | L39: =IF(8<=核心参数输入!$B$9,IF(核心参数输入!$B$64=1,SUMIFS(季度现金流!$D$17:$DT$17,季度现金流!$D$6:$DT$6,8),SUMIFS(季度现金流!$D$16:$DT$16,季度现金流!$D$6:$DT$6,8)),0) -> 0 | M39: =IF(9<=核心参数输入!$B$9,IF(核心参数输入!$B$64=1,SUMIFS(季度现金流!$D$17:$DT$17,季度现金流!$D$6:$DT$6,9),SUMIFS(季度现金流!$D$16:$DT$16,季度现金流!$D$6:$DT$6,9)),0) -> 0 | N39: =IF(10<=核心参数输入!$B$9,IF(核心参数输入!$B$64=1,SUMIFS(季度现金流!$D$17:$DT$17,季度现金流!$D$6:$DT$6,10),SUMIFS(季度现金流!$D$16:$DT$16,季度现金流!$D$6:$DT$6,10)),0) -> 0 | O39: =IF(11<=核心参数输入!$B$9,IF(核心参数输入!$B$64=1,SUMIFS(季度现金流!$D$17:$DT$17,季度现金流!$D$6:$DT$6,11),SUMIFS(季度现金流!$D$16:$DT$16,季度现金流!$D$6:$DT$6,11)),0) -> 0 | P39: =IF(12<=核心参数输入!$B$9,IF(核心参数输入!$B$64=1,SUMIFS(季度现金流!$D$17:$DT$17,季度现金流!$D$6:$DT$6,12),SUMIFS(季度现金流!$D$16:$DT$16,季度现金流!$D$6:$DT$6,12)),0) -> 0 | Q39: =IF(13<=核心参数输入!$B$9,IF(核心参数输入!$B$64=1,SUMIFS(季度现金流!$D$17:$DT$17,季度现金流!$D$6:$DT$6,13),SUMIFS(季度现金流!$D$16:$DT$16,季度现金流!$D$6:$DT$6,13)),0) -> 0 | R39: =IF(14<=核心参数输入!$B$9,IF(核心参数输入!$B$64=1,SUMIFS(季度现金流!$D$17:$DT$17,季度现金流!$D$6:$DT$6,14),SUMIFS(季度现金流!$D$16:$DT$16,季度现金流!$D$6:$DT$6,14)),0) -> 0 | S39: =IF(15<=核心参数输入!$B$9,IF(核心参数输入!$B$64=1,SUMIFS(季度现金流!$D$17:$DT$17,季度现金流!$D$6:$DT$6,15),SUMIFS(季度现金流!$D$16:$DT$16,季度现金流!$D$6:$DT$6,15)),0) -> 0 | T39: =IF(16<=核心参数输入!$B$9,IF(核心参数输入!$B$64=1,SUMIFS(季度现金流!$D$17:$DT$17,季度现金流!$D$6:$DT$6,16),SUMIFS(季度现金流!$D$16:$DT$16,季度现金流!$D$6:$DT$6,16)),0) -> 0 | U39: =IF(17<=核心参数输入!$B$9,IF(核心参数输入!$B$64=1,SUMIFS(季度现金流!$D$17:$DT$17,季度现金流!$D$6:$DT$6,17),SUMIFS(季度现金流!$D$16:$DT$16,季度现金流!$D$6:$DT$6,17)),0) -> 0 | V39: =IF(18<=核心参数输入!$B$9,IF(核心参数输入!$B$64=1,SUMIFS(季度现金流!$D$17:$DT$17,季度现金流!$D$6:$DT$6,18),SUMIFS(季度现金流!$D$16:$DT$16,季度现金流!$D$6:$DT$6,18)),0) -> 0 | W39: =IF(19<=核心参数输入!$B$9,IF(核心参数输入!$B$64=1,SUMIFS(季度现金流!$D$17:$DT$17,季度现金流!$D$6:$DT$6,19),SUMIFS(季度现金流!$D$16:$DT$16,季度现金流!$D$6:$DT$6,19)),0) -> 0 | X39: =IF(20<=核心参数输入!$B$9,IF(核心参数输入!$B$64=1,SUMIFS(季度现金流!$D$17:$DT$17,季度现金流!$D$6:$DT$6,20),SUMIFS(季度现金流!$D$16:$DT$16,季度现金流!$D$6:$DT$6,20)),0) -> 0 | Y39: =IF(21<=核心参数输入!$B$9,IF(核心参数输入!$B$64=1,SUMIFS(季度现金流!$D$17:$DT$17,季度现金流!$D$6:$DT$6,21),SUMIFS(季度现金流!$D$16:$DT$16,季度现金流!$D$6:$DT$6,21)),0) -> 0 | Z39: =IF(22<=核心参数输入!$B$9,IF(核心参数输入!$B$64=1,SUMIFS(季度现金流!$D$17:$DT$17,季度现金流!$D$6:$DT$6,22),SUMIFS(季度现金流!$D$16:$DT$16,季度现金流!$D$6:$DT$6,22)),0) -> 0 | AA39: =IF(23<=核心参数输入!$B$9,IF(核心参数输入!$B$64=1,SUMIFS(季度现金流!$D$17:$DT$17,季度现金流!$D$6:$DT$6,23),SUMIFS(季度现金流!$D$16:$DT$16,季度现金流!$D$6:$DT$6,23)),0) -> 0 | AB39: =IF(24<=核心参数输入!$B$9,IF(核心参数输入!$B$64=1,SUMIFS(季度现金流!$D$17:$DT$17,季度现金流!$D$6:$DT$6,24),SUMIFS(季度现金流!$D$16:$DT$16,季度现金流!$D$6:$DT$6,24)),0) -> 0 | AC39: =IF(25<=核心参数输入!$B$9,IF(核心参数输入!$B$64=1,SUMIFS(季度现金流!$D$17:$DT$17,季度现金流!$D$6:$DT$6,25),SUMIFS(季度现金流!$D$16:$DT$16,季度现金流!$D$6:$DT$6,25)),0) -> 0 | AD39: =IF(26<=核心参数输入!$B$9,IF(核心参数输入!$B$64=1,SUMIFS(季度现金流!$D$17:$DT$17,季度现金流!$D$6:$DT$6,26),SUMIFS(季度现金流!$D$16:$DT$16,季度现金流!$D$6:$DT$6,26)),0) -> 0 | AE39: =IF(27<=核心参数输入!$B$9,IF(核心参数输入!$B$64=1,SUMIFS(季度现金流!$D$17:$DT$17,季度现金流!$D$6:$DT$6,27),SUMIFS(季度现金流!$D$16:$DT$16,季度现金流!$D$6:$DT$6,27)),0) -> 0 | AF39: =IF(28<=核心参数输入!$B$9,IF(核心参数输入!$B$64=1,SUMIFS(季度现金流!$D$17:$DT$17,季度现金流!$D$6:$DT$6,28),SUMIFS(季度现金流!$D$16:$DT$16,季度现金流!$D$6:$DT$6,28)),0) -> 0 | AG39: =IF(29<=核心参数输入!$B$9,IF(核心参数输入!$B$64=1,SUMIFS(季度现金流!$D$17:$DT$17,季度现金流!$D$6:$DT$6,29),SUMIFS(季度现金流!$D$16:$DT$16,季度现金流!$D$6:$DT$6,29)),0) -> 0 | AH39: =IF(30<=核心参数输入!$B$9,IF(核心参数输入!$B$64=1,SUMIFS(季度现金流!$D$17:$DT$17,季度现金流!$D$6:$DT$6,30),SUMIFS(季度现金流!$D$16:$DT$16,季度现金流!$D$6:$DT$6,30)),0) -> 0
A40: 持有物业出售净现金 | B40: 万元 | D40: =IF(0<=核心参数输入!$B$9,IF(核心参数输入!$B$64=1,SUMIFS(季度经营税费!$D$59:$DT$59,季度经营税费!$D$6:$DT$6,0),0),0) -> 0 | E40: =IF(1<=核心参数输入!$B$9,IF(核心参数输入!$B$64=1,SUMIFS(季度经营税费!$D$59:$DT$59,季度经营税费!$D$6:$DT$6,1),0),0) -> 0 | F40: =IF(2<=核心参数输入!$B$9,IF(核心参数输入!$B$64=1,SUMIFS(季度经营税费!$D$59:$DT$59,季度经营税费!$D$6:$DT$6,2),0),0) -> 0 | G40: =IF(3<=核心参数输入!$B$9,IF(核心参数输入!$B$64=1,SUMIFS(季度经营税费!$D$59:$DT$59,季度经营税费!$D$6:$DT$6,3),0),0) -> 0 | H40: =IF(4<=核心参数输入!$B$9,IF(核心参数输入!$B$64=1,SUMIFS(季度经营税费!$D$59:$DT$59,季度经营税费!$D$6:$DT$6,4),0),0) -> 0 | I40: =IF(5<=核心参数输入!$B$9,IF(核心参数输入!$B$64=1,SUMIFS(季度经营税费!$D$59:$DT$59,季度经营税费!$D$6:$DT$6,5),0),0) -> 0 | J40: =IF(6<=核心参数输入!$B$9,IF(核心参数输入!$B$64=1,SUMIFS(季度经营税费!$D$59:$DT$59,季度经营税费!$D$6:$DT$6,6),0),0) -> 0 | K40: =IF(7<=核心参数输入!$B$9,IF(核心参数输入!$B$64=1,SUMIFS(季度经营税费!$D$59:$DT$59,季度经营税费!$D$6:$DT$6,7),0),0) -> 0 | L40: =IF(8<=核心参数输入!$B$9,IF(核心参数输入!$B$64=1,SUMIFS(季度经营税费!$D$59:$DT$59,季度经营税费!$D$6:$DT$6,8),0),0) -> 0 | M40: =IF(9<=核心参数输入!$B$9,IF(核心参数输入!$B$64=1,SUMIFS(季度经营税费!$D$59:$DT$59,季度经营税费!$D$6:$DT$6,9),0),0) -> 0 | N40: =IF(10<=核心参数输入!$B$9,IF(核心参数输入!$B$64=1,SUMIFS(季度经营税费!$D$59:$DT$59,季度经营税费!$D$6:$DT$6,10),0),0) -> 0 | O40: =IF(11<=核心参数输入!$B$9,IF(核心参数输入!$B$64=1,SUMIFS(季度经营税费!$D$59:$DT$59,季度经营税费!$D$6:$DT$6,11),0),0) -> 0 | P40: =IF(12<=核心参数输入!$B$9,IF(核心参数输入!$B$64=1,SUMIFS(季度经营税费!$D$59:$DT$59,季度经营税费!$D$6:$DT$6,12),0),0) -> 0 | Q40: =IF(13<=核心参数输入!$B$9,IF(核心参数输入!$B$64=1,SUMIFS(季度经营税费!$D$59:$DT$59,季度经营税费!$D$6:$DT$6,13),0),0) -> 0 | R40: =IF(14<=核心参数输入!$B$9,IF(核心参数输入!$B$64=1,SUMIFS(季度经营税费!$D$59:$DT$59,季度经营税费!$D$6:$DT$6,14),0),0) -> 0 | S40: =IF(15<=核心参数输入!$B$9,IF(核心参数输入!$B$64=1,SUMIFS(季度经营税费!$D$59:$DT$59,季度经营税费!$D$6:$DT$6,15),0),0) -> 0 | T40: =IF(16<=核心参数输入!$B$9,IF(核心参数输入!$B$64=1,SUMIFS(季度经营税费!$D$59:$DT$59,季度经营税费!$D$6:$DT$6,16),0),0) -> 0 | U40: =IF(17<=核心参数输入!$B$9,IF(核心参数输入!$B$64=1,SUMIFS(季度经营税费!$D$59:$DT$59,季度经营税费!$D$6:$DT$6,17),0),0) -> 0 | V40: =IF(18<=核心参数输入!$B$9,IF(核心参数输入!$B$64=1,SUMIFS(季度经营税费!$D$59:$DT$59,季度经营税费!$D$6:$DT$6,18),0),0) -> 0 | W40: =IF(19<=核心参数输入!$B$9,IF(核心参数输入!$B$64=1,SUMIFS(季度经营税费!$D$59:$DT$59,季度经营税费!$D$6:$DT$6,19),0),0) -> 0 | X40: =IF(20<=核心参数输入!$B$9,IF(核心参数输入!$B$64=1,SUMIFS(季度经营税费!$D$59:$DT$59,季度经营税费!$D$6:$DT$6,20),0),0) -> 0 | Y40: =IF(21<=核心参数输入!$B$9,IF(核心参数输入!$B$64=1,SUMIFS(季度经营税费!$D$59:$DT$59,季度经营税费!$D$6:$DT$6,21),0),0) -> 0 | Z40: =IF(22<=核心参数输入!$B$9,IF(核心参数输入!$B$64=1,SUMIFS(季度经营税费!$D$59:$DT$59,季度经营税费!$D$6:$DT$6,22),0),0) -> 0 | AA40: =IF(23<=核心参数输入!$B$9,IF(核心参数输入!$B$64=1,SUMIFS(季度经营税费!$D$59:$DT$59,季度经营税费!$D$6:$DT$6,23),0),0) -> 0 | AB40: =IF(24<=核心参数输入!$B$9,IF(核心参数输入!$B$64=1,SUMIFS(季度经营税费!$D$59:$DT$59,季度经营税费!$D$6:$DT$6,24),0),0) -> 0 | AC40: =IF(25<=核心参数输入!$B$9,IF(核心参数输入!$B$64=1,SUMIFS(季度经营税费!$D$59:$DT$59,季度经营税费!$D$6:$DT$6,25),0),0) -> 0 | AD40: =IF(26<=核心参数输入!$B$9,IF(核心参数输入!$B$64=1,SUMIFS(季度经营税费!$D$59:$DT$59,季度经营税费!$D$6:$DT$6,26),0),0) -> 0 | AE40: =IF(27<=核心参数输入!$B$9,IF(核心参数输入!$B$64=1,SUMIFS(季度经营税费!$D$59:$DT$59,季度经营税费!$D$6:$DT$6,27),0),0) -> 0 | AF40: =IF(28<=核心参数输入!$B$9,IF(核心参数输入!$B$64=1,SUMIFS(季度经营税费!$D$59:$DT$59,季度经营税费!$D$6:$DT$6,28),0),0) -> 0 | AG40: =IF(29<=核心参数输入!$B$9,IF(核心参数输入!$B$64=1,SUMIFS(季度经营税费!$D$59:$DT$59,季度经营税费!$D$6:$DT$6,29),0),0) -> 0 | AH40: =IF(30<=核心参数输入!$B$9,IF(核心参数输入!$B$64=1,SUMIFS(季度经营税费!$D$59:$DT$59,季度经营税费!$D$6:$DT$6,30),0),0) -> 0
A41: 期末税款及负债结算 | B41: 万元 | D41: =IF(0<=核心参数输入!$B$9,SUMIFS(季度经营税费!$D$73:$DT$73,季度经营税费!$D$6:$DT$6,0)+SUMIFS(季度经营税费!$D$74:$DT$74,季度经营税费!$D$6:$DT$6,0)+IF(核心参数输入!$B$64=1,0,SUMIFS(季度经营税费!$D$76:$DT$76,季度经营税费!$D$6:$DT$6,0)),0) -> 0 | E41: =IF(1<=核心参数输入!$B$9,SUMIFS(季度经营税费!$D$73:$DT$73,季度经营税费!$D$6:$DT$6,1)+SUMIFS(季度经营税费!$D$74:$DT$74,季度经营税费!$D$6:$DT$6,1)+IF(核心参数输入!$B$64=1,0,SUMIFS(季度经营税费!$D$76:$DT$76,季度经营税费!$D$6:$DT$6,1)),0) -> 0 | F41: =IF(2<=核心参数输入!$B$9,SUMIFS(季度经营税费!$D$73:$DT$73,季度经营税费!$D$6:$DT$6,2)+SUMIFS(季度经营税费!$D$74:$DT$74,季度经营税费!$D$6:$DT$6,2)+IF(核心参数输入!$B$64=1,0,SUMIFS(季度经营税费!$D$76:$DT$76,季度经营税费!$D$6:$DT$6,2)),0) -> 0 | G41: =IF(3<=核心参数输入!$B$9,SUMIFS(季度经营税费!$D$73:$DT$73,季度经营税费!$D$6:$DT$6,3)+SUMIFS(季度经营税费!$D$74:$DT$74,季度经营税费!$D$6:$DT$6,3)+IF(核心参数输入!$B$64=1,0,SUMIFS(季度经营税费!$D$76:$DT$76,季度经营税费!$D$6:$DT$6,3)),0) -> 0 | H41: =IF(4<=核心参数输入!$B$9,SUMIFS(季度经营税费!$D$73:$DT$73,季度经营税费!$D$6:$DT$6,4)+SUMIFS(季度经营税费!$D$74:$DT$74,季度经营税费!$D$6:$DT$6,4)+IF(核心参数输入!$B$64=1,0,SUMIFS(季度经营税费!$D$76:$DT$76,季度经营税费!$D$6:$DT$6,4)),0) -> 0 | I41: =IF(5<=核心参数输入!$B$9,SUMIFS(季度经营税费!$D$73:$DT$73,季度经营税费!$D$6:$DT$6,5)+SUMIFS(季度经营税费!$D$74:$DT$74,季度经营税费!$D$6:$DT$6,5)+IF(核心参数输入!$B$64=1,0,SUMIFS(季度经营税费!$D$76:$DT$76,季度经营税费!$D$6:$DT$6,5)),0) -> 0 | J41: =IF(6<=核心参数输入!$B$9,SUMIFS(季度经营税费!$D$73:$DT$73,季度经营税费!$D$6:$DT$6,6)+SUMIFS(季度经营税费!$D$74:$DT$74,季度经营税费!$D$6:$DT$6,6)+IF(核心参数输入!$B$64=1,0,SUMIFS(季度经营税费!$D$76:$DT$76,季度经营税费!$D$6:$DT$6,6)),0) -> 0 | K41: =IF(7<=核心参数输入!$B$9,SUMIFS(季度经营税费!$D$73:$DT$73,季度经营税费!$D$6:$DT$6,7)+SUMIFS(季度经营税费!$D$74:$DT$74,季度经营税费!$D$6:$DT$6,7)+IF(核心参数输入!$B$64=1,0,SUMIFS(季度经营税费!$D$76:$DT$76,季度经营税费!$D$6:$DT$6,7)),0) -> 0 | L41: =IF(8<=核心参数输入!$B$9,SUMIFS(季度经营税费!$D$73:$DT$73,季度经营税费!$D$6:$DT$6,8)+SUMIFS(季度经营税费!$D$74:$DT$74,季度经营税费!$D$6:$DT$6,8)+IF(核心参数输入!$B$64=1,0,SUMIFS(季度经营税费!$D$76:$DT$76,季度经营税费!$D$6:$DT$6,8)),0) -> 0 | M41: =IF(9<=核心参数输入!$B$9,SUMIFS(季度经营税费!$D$73:$DT$73,季度经营税费!$D$6:$DT$6,9)+SUMIFS(季度经营税费!$D$74:$DT$74,季度经营税费!$D$6:$DT$6,9)+IF(核心参数输入!$B$64=1,0,SUMIFS(季度经营税费!$D$76:$DT$76,季度经营税费!$D$6:$DT$6,9)),0) -> 0 | N41: =IF(10<=核心参数输入!$B$9,SUMIFS(季度经营税费!$D$73:$DT$73,季度经营税费!$D$6:$DT$6,10)+SUMIFS(季度经营税费!$D$74:$DT$74,季度经营税费!$D$6:$DT$6,10)+IF(核心参数输入!$B$64=1,0,SUMIFS(季度经营税费!$D$76:$DT$76,季度经营税费!$D$6:$DT$6,10)),0) -> 0 | O41: =IF(11<=核心参数输入!$B$9,SUMIFS(季度经营税费!$D$73:$DT$73,季度经营税费!$D$6:$DT$6,11)+SUMIFS(季度经营税费!$D$74:$DT$74,季度经营税费!$D$6:$DT$6,11)+IF(核心参数输入!$B$64=1,0,SUMIFS(季度经营税费!$D$76:$DT$76,季度经营税费!$D$6:$DT$6,11)),0) -> 0 | P41: =IF(12<=核心参数输入!$B$9,SUMIFS(季度经营税费!$D$73:$DT$73,季度经营税费!$D$6:$DT$6,12)+SUMIFS(季度经营税费!$D$74:$DT$74,季度经营税费!$D$6:$DT$6,12)+IF(核心参数输入!$B$64=1,0,SUMIFS(季度经营税费!$D$76:$DT$76,季度经营税费!$D$6:$DT$6,12)),0) -> 0 | Q41: =IF(13<=核心参数输入!$B$9,SUMIFS(季度经营税费!$D$73:$DT$73,季度经营税费!$D$6:$DT$6,13)+SUMIFS(季度经营税费!$D$74:$DT$74,季度经营税费!$D$6:$DT$6,13)+IF(核心参数输入!$B$64=1,0,SUMIFS(季度经营税费!$D$76:$DT$76,季度经营税费!$D$6:$DT$6,13)),0) -> 0 | R41: =IF(14<=核心参数输入!$B$9,SUMIFS(季度经营税费!$D$73:$DT$73,季度经营税费!$D$6:$DT$6,14)+SUMIFS(季度经营税费!$D$74:$DT$74,季度经营税费!$D$6:$DT$6,14)+IF(核心参数输入!$B$64=1,0,SUMIFS(季度经营税费!$D$76:$DT$76,季度经营税费!$D$6:$DT$6,14)),0) -> 0 | S41: =IF(15<=核心参数输入!$B$9,SUMIFS(季度经营税费!$D$73:$DT$73,季度经营税费!$D$6:$DT$6,15)+SUMIFS(季度经营税费!$D$74:$DT$74,季度经营税费!$D$6:$DT$6,15)+IF(核心参数输入!$B$64=1,0,SUMIFS(季度经营税费!$D$76:$DT$76,季度经营税费!$D$6:$DT$6,15)),0) -> 0 | T41: =IF(16<=核心参数输入!$B$9,SUMIFS(季度经营税费!$D$73:$DT$73,季度经营税费!$D$6:$DT$6,16)+SUMIFS(季度经营税费!$D$74:$DT$74,季度经营税费!$D$6:$DT$6,16)+IF(核心参数输入!$B$64=1,0,SUMIFS(季度经营税费!$D$76:$DT$76,季度经营税费!$D$6:$DT$6,16)),0) -> 0 | U41: =IF(17<=核心参数输入!$B$9,SUMIFS(季度经营税费!$D$73:$DT$73,季度经营税费!$D$6:$DT$6,17)+SUMIFS(季度经营税费!$D$74:$DT$74,季度经营税费!$D$6:$DT$6,17)+IF(核心参数输入!$B$64=1,0,SUMIFS(季度经营税费!$D$76:$DT$76,季度经营税费!$D$6:$DT$6,17)),0) -> 0 | V41: =IF(18<=核心参数输入!$B$9,SUMIFS(季度经营税费!$D$73:$DT$73,季度经营税费!$D$6:$DT$6,18)+SUMIFS(季度经营税费!$D$74:$DT$74,季度经营税费!$D$6:$DT$6,18)+IF(核心参数输入!$B$64=1,0,SUMIFS(季度经营税费!$D$76:$DT$76,季度经营税费!$D$6:$DT$6,18)),0) -> 0 | W41: =IF(19<=核心参数输入!$B$9,SUMIFS(季度经营税费!$D$73:$DT$73,季度经营税费!$D$6:$DT$6,19)+SUMIFS(季度经营税费!$D$74:$DT$74,季度经营税费!$D$6:$DT$6,19)+IF(核心参数输入!$B$64=1,0,SUMIFS(季度经营税费!$D$76:$DT$76,季度经营税费!$D$6:$DT$6,19)),0) -> 0 | X41: =IF(20<=核心参数输入!$B$9,SUMIFS(季度经营税费!$D$73:$DT$73,季度经营税费!$D$6:$DT$6,20)+SUMIFS(季度经营税费!$D$74:$DT$74,季度经营税费!$D$6:$DT$6,20)+IF(核心参数输入!$B$64=1,0,SUMIFS(季度经营税费!$D$76:$DT$76,季度经营税费!$D$6:$DT$6,20)),0) -> 0 | Y41: =IF(21<=核心参数输入!$B$9,SUMIFS(季度经营税费!$D$73:$DT$73,季度经营税费!$D$6:$DT$6,21)+SUMIFS(季度经营税费!$D$74:$DT$74,季度经营税费!$D$6:$DT$6,21)+IF(核心参数输入!$B$64=1,0,SUMIFS(季度经营税费!$D$76:$DT$76,季度经营税费!$D$6:$DT$6,21)),0) -> 0 | Z41: =IF(22<=核心参数输入!$B$9,SUMIFS(季度经营税费!$D$73:$DT$73,季度经营税费!$D$6:$DT$6,22)+SUMIFS(季度经营税费!$D$74:$DT$74,季度经营税费!$D$6:$DT$6,22)+IF(核心参数输入!$B$64=1,0,SUMIFS(季度经营税费!$D$76:$DT$76,季度经营税费!$D$6:$DT$6,22)),0) -> 0 | AA41: =IF(23<=核心参数输入!$B$9,SUMIFS(季度经营税费!$D$73:$DT$73,季度经营税费!$D$6:$DT$6,23)+SUMIFS(季度经营税费!$D$74:$DT$74,季度经营税费!$D$6:$DT$6,23)+IF(核心参数输入!$B$64=1,0,SUMIFS(季度经营税费!$D$76:$DT$76,季度经营税费!$D$6:$DT$6,23)),0) -> 0 | AB41: =IF(24<=核心参数输入!$B$9,SUMIFS(季度经营税费!$D$73:$DT$73,季度经营税费!$D$6:$DT$6,24)+SUMIFS(季度经营税费!$D$74:$DT$74,季度经营税费!$D$6:$DT$6,24)+IF(核心参数输入!$B$64=1,0,SUMIFS(季度经营税费!$D$76:$DT$76,季度经营税费!$D$6:$DT$6,24)),0) -> 0 | AC41: =IF(25<=核心参数输入!$B$9,SUMIFS(季度经营税费!$D$73:$DT$73,季度经营税费!$D$6:$DT$6,25)+SUMIFS(季度经营税费!$D$74:$DT$74,季度经营税费!$D$6:$DT$6,25)+IF(核心参数输入!$B$64=1,0,SUMIFS(季度经营税费!$D$76:$DT$76,季度经营税费!$D$6:$DT$6,25)),0) -> 0 | AD41: =IF(26<=核心参数输入!$B$9,SUMIFS(季度经营税费!$D$73:$DT$73,季度经营税费!$D$6:$DT$6,26)+SUMIFS(季度经营税费!$D$74:$DT$74,季度经营税费!$D$6:$DT$6,26)+IF(核心参数输入!$B$64=1,0,SUMIFS(季度经营税费!$D$76:$DT$76,季度经营税费!$D$6:$DT$6,26)),0) -> 0 | AE41: =IF(27<=核心参数输入!$B$9,SUMIFS(季度经营税费!$D$73:$DT$73,季度经营税费!$D$6:$DT$6,27)+SUMIFS(季度经营税费!$D$74:$DT$74,季度经营税费!$D$6:$DT$6,27)+IF(核心参数输入!$B$64=1,0,SUMIFS(季度经营税费!$D$76:$DT$76,季度经营税费!$D$6:$DT$6,27)),0) -> 0 | AF41: =IF(28<=核心参数输入!$B$9,SUMIFS(季度经营税费!$D$73:$DT$73,季度经营税费!$D$6:$DT$6,28)+SUMIFS(季度经营税费!$D$74:$DT$74,季度经营税费!$D$6:$DT$6,28)+IF(核心参数输入!$B$64=1,0,SUMIFS(季度经营税费!$D$76:$DT$76,季度经营税费!$D$6:$DT$6,28)),0) -> 0 | AG41: =IF(29<=核心参数输入!$B$9,SUMIFS(季度经营税费!$D$73:$DT$73,季度经营税费!$D$6:$DT$6,29)+SUMIFS(季度经营税费!$D$74:$DT$74,季度经营税费!$D$6:$DT$6,29)+IF(核心参数输入!$B$64=1,0,SUMIFS(季度经营税费!$D$76:$DT$76,季度经营税费!$D$6:$DT$6,29)),0) -> 0 | AH41: =IF(30<=核心参数输入!$B$9,SUMIFS(季度经营税费!$D$73:$DT$73,季度经营税费!$D$6:$DT$6,30)+SUMIFS(季度经营税费!$D$74:$DT$74,季度经营税费!$D$6:$DT$6,30)+IF(核心参数输入!$B$64=1,0,SUMIFS(季度经营税费!$D$76:$DT$76,季度经营税费!$D$6:$DT$6,30)),0) -> 0
A42: 最低DSCR辅助筛选 | B42: 倍 | D42: =IF(0<=核心参数输入!$B$9,IF(ISNUMBER(D24),D24,1E+99),1E+99) -> 1e+99 | E42: =IF(1<=核心参数输入!$B$9,IF(ISNUMBER(E24),E24,1E+99),1E+99) -> 1e+99 | F42: =IF(2<=核心参数输入!$B$9,IF(ISNUMBER(F24),F24,1E+99),1E+99) -> 1e+99 | G42: =IF(3<=核心参数输入!$B$9,IF(ISNUMBER(G24),G24,1E+99),1E+99) -> 1e+99 | H42: =IF(4<=核心参数输入!$B$9,IF(ISNUMBER(H24),H24,1E+99),1E+99) -> 2.0920679 | I42: =IF(5<=核心参数输入!$B$9,IF(ISNUMBER(I24),I24,1E+99),1E+99) -> 3.1481903 | J42: =IF(6<=核心参数输入!$B$9,IF(ISNUMBER(J24),J24,1E+99),1E+99) -> 2.6424265 | K42: =IF(7<=核心参数输入!$B$9,IF(ISNUMBER(K24),K24,1E+99),1E+99) -> 0.4058985 | L42: =IF(8<=核心参数输入!$B$9,IF(ISNUMBER(L24),L24,1E+99),1E+99) -> 0.21197153 | M42: =IF(9<=核心参数输入!$B$9,IF(ISNUMBER(M24),M24,1E+99),1E+99) -> 0.22434206 | N42: =IF(10<=核心参数输入!$B$9,IF(ISNUMBER(N24),N24,1E+99),1E+99) -> 0.23716682 | O42: =IF(11<=核心参数输入!$B$9,IF(ISNUMBER(O24),O24,1E+99),1E+99) -> 1e+99 | P42: =IF(12<=核心参数输入!$B$9,IF(ISNUMBER(P24),P24,1E+99),1E+99) -> 1e+99 | Q42: =IF(13<=核心参数输入!$B$9,IF(ISNUMBER(Q24),Q24,1E+99),1E+99) -> 1e+99 | R42: =IF(14<=核心参数输入!$B$9,IF(ISNUMBER(R24),R24,1E+99),1E+99) -> 1e+99 | S42: =IF(15<=核心参数输入!$B$9,IF(ISNUMBER(S24),S24,1E+99),1E+99) -> 1e+99 | T42: =IF(16<=核心参数输入!$B$9,IF(ISNUMBER(T24),T24,1E+99),1E+99) -> 1e+99 | U42: =IF(17<=核心参数输入!$B$9,IF(ISNUMBER(U24),U24,1E+99),1E+99) -> 1e+99 | V42: =IF(18<=核心参数输入!$B$9,IF(ISNUMBER(V24),V24,1E+99),1E+99) -> 1e+99 | W42: =IF(19<=核心参数输入!$B$9,IF(ISNUMBER(W24),W24,1E+99),1E+99) -> 1e+99 | X42: =IF(20<=核心参数输入!$B$9,IF(ISNUMBER(X24),X24,1E+99),1E+99) -> 1e+99 | Y42: =IF(21<=核心参数输入!$B$9,IF(ISNUMBER(Y24),Y24,1E+99),1E+99) -> 1e+99 | Z42: =IF(22<=核心参数输入!$B$9,IF(ISNUMBER(Z24),Z24,1E+99),1E+99) -> 1e+99 | AA42: =IF(23<=核心参数输入!$B$9,IF(ISNUMBER(AA24),AA24,1E+99),1E+99) -> 1e+99 | AB42: =IF(24<=核心参数输入!$B$9,IF(ISNUMBER(AB24),AB24,1E+99),1E+99) -> 1e+99 | AC42: =IF(25<=核心参数输入!$B$9,IF(ISNUMBER(AC24),AC24,1E+99),1E+99) -> 1e+99 | AD42: =IF(26<=核心参数输入!$B$9,IF(ISNUMBER(AD24),AD24,1E+99),1E+99) -> 1e+99 | AE42: =IF(27<=核心参数输入!$B$9,IF(ISNUMBER(AE24),AE24,1E+99),1E+99) -> 1e+99 | AF42: =IF(28<=核心参数输入!$B$9,IF(ISNUMBER(AF24),AF24,1E+99),1E+99) -> 1e+99 | AG42: =IF(29<=核心参数输入!$B$9,IF(ISNUMBER(AG24),AG24,1E+99),1E+99) -> 1e+99 | AH42: =IF(30<=核心参数输入!$B$9,IF(ISNUMBER(AH24),AH24,1E+99),1E+99) -> 1e+99
A68: 组合压力 · 年度汇总
A70: 销售收入（利润口径） | B70: 万元 | D70: =IF(0<=核心参数输入!$B$9,SUMIFS(季度经营税费!$D$142:$DT$142,季度经营税费!$D$6:$DT$6,0),0) -> 0 | E70: =IF(1<=核心参数输入!$B$9,SUMIFS(季度经营税费!$D$142:$DT$142,季度经营税费!$D$6:$DT$6,1),0) -> 0 | F70: =IF(2<=核心参数输入!$B$9,SUMIFS(季度经营税费!$D$142:$DT$142,季度经营税费!$D$6:$DT$6,2),0) -> 0 | G70: =IF(3<=核心参数输入!$B$9,SUMIFS(季度经营税费!$D$142:$DT$142,季度经营税费!$D$6:$DT$6,3),0) -> 0 | H70: =IF(4<=核心参数输入!$B$9,SUMIFS(季度经营税费!$D$142:$DT$142,季度经营税费!$D$6:$DT$6,4),0) -> 13030.875 | I70: =IF(5<=核心参数输入!$B$9,SUMIFS(季度经营税费!$D$142:$DT$142,季度经营税费!$D$6:$DT$6,5),0) -> 17374.5 | J70: =IF(6<=核心参数输入!$B$9,SUMIFS(季度经营税费!$D$142:$DT$142,季度经营税费!$D$6:$DT$6,6),0) -> 13030.875 | K70: =IF(7<=核心参数输入!$B$9,SUMIFS(季度经营税费!$D$142:$DT$142,季度经营税费!$D$6:$DT$6,7),0) -> 0 | L70: =IF(8<=核心参数输入!$B$9,SUMIFS(季度经营税费!$D$142:$DT$142,季度经营税费!$D$6:$DT$6,8),0) -> 0 | M70: =IF(9<=核心参数输入!$B$9,SUMIFS(季度经营税费!$D$142:$DT$142,季度经营税费!$D$6:$DT$6,9),0) -> 0 | N70: =IF(10<=核心参数输入!$B$9,SUMIFS(季度经营税费!$D$142:$DT$142,季度经营税费!$D$6:$DT$6,10),0) -> 0 | O70: =IF(11<=核心参数输入!$B$9,SUMIFS(季度经营税费!$D$142:$DT$142,季度经营税费!$D$6:$DT$6,11),0) -> 0 | P70: =IF(12<=核心参数输入!$B$9,SUMIFS(季度经营税费!$D$142:$DT$142,季度经营税费!$D$6:$DT$6,12),0) -> 0 | Q70: =IF(13<=核心参数输入!$B$9,SUMIFS(季度经营税费!$D$142:$DT$142,季度经营税费!$D$6:$DT$6,13),0) -> 0 | R70: =IF(14<=核心参数输入!$B$9,SUMIFS(季度经营税费!$D$142:$DT$142,季度经营税费!$D$6:$DT$6,14),0) -> 0 | S70: =IF(15<=核心参数输入!$B$9,SUMIFS(季度经营税费!$D$142:$DT$142,季度经营税费!$D$6:$DT$6,15),0) -> 0 | T70: =IF(16<=核心参数输入!$B$9,SUMIFS(季度经营税费!$D$142:$DT$142,季度经营税费!$D$6:$DT$6,16),0) -> 0 | U70: =IF(17<=核心参数输入!$B$9,SUMIFS(季度经营税费!$D$142:$DT$142,季度经营税费!$D$6:$DT$6,17),0) -> 0 | V70: =IF(18<=核心参数输入!$B$9,SUMIFS(季度经营税费!$D$142:$DT$142,季度经营税费!$D$6:$DT$6,18),0) -> 0 | W70: =IF(19<=核心参数输入!$B$9,SUMIFS(季度经营税费!$D$142:$DT$142,季度经营税费!$D$6:$DT$6,19),0) -> 0 | X70: =IF(20<=核心参数输入!$B$9,SUMIFS(季度经营税费!$D$142:$DT$142,季度经营税费!$D$6:$DT$6,20),0) -> 0 | Y70: =IF(21<=核心参数输入!$B$9,SUMIFS(季度经营税费!$D$142:$DT$142,季度经营税费!$D$6:$DT$6,21),0) -> 0 | Z70: =IF(22<=核心参数输入!$B$9,SUMIFS(季度经营税费!$D$142:$DT$142,季度经营税费!$D$6:$DT$6,22),0) -> 0 | AA70: =IF(23<=核心参数输入!$B$9,SUMIFS(季度经营税费!$D$142:$DT$142,季度经营税费!$D$6:$DT$6,23),0) -> 0 | AB70: =IF(24<=核心参数输入!$B$9,SUMIFS(季度经营税费!$D$142:$DT$142,季度经营税费!$D$6:$DT$6,24),0) -> 0 | AC70: =IF(25<=核心参数输入!$B$9,SUMIFS(季度经营税费!$D$142:$DT$142,季度经营税费!$D$6:$DT$6,25),0) -> 0 | AD70: =IF(26<=核心参数输入!$B$9,SUMIFS(季度经营税费!$D$142:$DT$142,季度经营税费!$D$6:$DT$6,26),0) -> 0 | AE70: =IF(27<=核心参数输入!$B$9,SUMIFS(季度经营税费!$D$142:$DT$142,季度经营税费!$D$6:$DT$6,27),0) -> 0 | AF70: =IF(28<=核心参数输入!$B$9,SUMIFS(季度经营税费!$D$142:$DT$142,季度经营税费!$D$6:$DT$6,28),0) -> 0 | AG70: =IF(29<=核心参数输入!$B$9,SUMIFS(季度经营税费!$D$142:$DT$142,季度经营税费!$D$6:$DT$6,29),0) -> 0 | AH70: =IF(30<=核心参数输入!$B$9,SUMIFS(季度经营税费!$D$142:$DT$142,季度经营税费!$D$6:$DT$6,30),0) -> 0
A71: 持有收入（利润口径） | B71: 万元 | D71: =IF(0<=核心参数输入!$B$9,SUMIFS(季度经营税费!$D$143:$DT$143,季度经营税费!$D$6:$DT$6,0),0) -> 0 | E71: =IF(1<=核心参数输入!$B$9,SUMIFS(季度经营税费!$D$143:$DT$143,季度经营税费!$D$6:$DT$6,1),0) -> 0 | F71: =IF(2<=核心参数输入!$B$9,SUMIFS(季度经营税费!$D$143:$DT$143,季度经营税费!$D$6:$DT$6,2),0) -> 0 | G71: =IF(3<=核心参数输入!$B$9,SUMIFS(季度经营税费!$D$143:$DT$143,季度经营税费!$D$6:$DT$6,3),0) -> 0 | H71: =IF(4<=核心参数输入!$B$9,SUMIFS(季度经营税费!$D$143:$DT$143,季度经营税费!$D$6:$DT$6,4),0) -> 201.3128 | I71: =IF(5<=核心参数输入!$B$9,SUMIFS(季度经营税费!$D$143:$DT$143,季度经营税费!$D$6:$DT$6,5),0) -> 805.97818 | J71: =IF(6<=核心参数输入!$B$9,SUMIFS(季度经营税费!$D$143:$DT$143,季度经营税费!$D$6:$DT$6,6),0) -> 1172.3719 | K71: =IF(7<=核心参数输入!$B$9,SUMIFS(季度经营税费!$D$143:$DT$143,季度经营税费!$D$6:$DT$6,7),0) -> 1420.932 | L71: =IF(8<=核心参数输入!$B$9,SUMIFS(季度经营税费!$D$143:$DT$143,季度经营税费!$D$6:$DT$6,8),0) -> 1516.4356 | M71: =IF(9<=核心参数输入!$B$9,SUMIFS(季度经营税费!$D$143:$DT$143,季度经营税费!$D$6:$DT$6,9),0) -> 1542.1942 | N71: =IF(10<=核心参数输入!$B$9,SUMIFS(季度经营税费!$D$143:$DT$143,季度经营税费!$D$6:$DT$6,10),0) -> 1565.3271 | O71: =IF(11<=核心参数输入!$B$9,SUMIFS(季度经营税费!$D$143:$DT$143,季度经营税费!$D$6:$DT$6,11),0) -> 1588.807 | P71: =IF(12<=核心参数输入!$B$9,SUMIFS(季度经营税费!$D$143:$DT$143,季度经营税费!$D$6:$DT$6,12),0) -> 1612.6391 | Q71: =IF(13<=核心参数输入!$B$9,SUMIFS(季度经营税费!$D$143:$DT$143,季度经营税费!$D$6:$DT$6,13),0) -> 1636.8287 | R71: =IF(14<=核心参数输入!$B$9,SUMIFS(季度经营税费!$D$143:$DT$143,季度经营税费!$D$6:$DT$6,14),0) -> 1661.3812 | S71: =IF(15<=核心参数输入!$B$9,SUMIFS(季度经营税费!$D$143:$DT$143,季度经营税费!$D$6:$DT$6,15),0) -> 1686.3019 | T71: =IF(16<=核心参数输入!$B$9,SUMIFS(季度经营税费!$D$143:$DT$143,季度经营税费!$D$6:$DT$6,16),0) -> 1711.5964 | U71: =IF(17<=核心参数输入!$B$9,SUMIFS(季度经营税费!$D$143:$DT$143,季度经营税费!$D$6:$DT$6,17),0) -> 1737.2704 | V71: =IF(18<=核心参数输入!$B$9,SUMIFS(季度经营税费!$D$143:$DT$143,季度经营税费!$D$6:$DT$6,18),0) -> 1763.3294 | W71: =IF(19<=核心参数输入!$B$9,SUMIFS(季度经营税费!$D$143:$DT$143,季度经营税费!$D$6:$DT$6,19),0) -> 1789.7794 | X71: =IF(20<=核心参数输入!$B$9,SUMIFS(季度经营税费!$D$143:$DT$143,季度经营税费!$D$6:$DT$6,20),0) -> 1816.626 | Y71: =IF(21<=核心参数输入!$B$9,SUMIFS(季度经营税费!$D$143:$DT$143,季度经营税费!$D$6:$DT$6,21),0) -> 0 | Z71: =IF(22<=核心参数输入!$B$9,SUMIFS(季度经营税费!$D$143:$DT$143,季度经营税费!$D$6:$DT$6,22),0) -> 0 | AA71: =IF(23<=核心参数输入!$B$9,SUMIFS(季度经营税费!$D$143:$DT$143,季度经营税费!$D$6:$DT$6,23),0) -> 0 | AB71: =IF(24<=核心参数输入!$B$9,SUMIFS(季度经营税费!$D$143:$DT$143,季度经营税费!$D$6:$DT$6,24),0) -> 0 | AC71: =IF(25<=核心参数输入!$B$9,SUMIFS(季度经营税费!$D$143:$DT$143,季度经营税费!$D$6:$DT$6,25),0) -> 0 | AD71: =IF(26<=核心参数输入!$B$9,SUMIFS(季度经营税费!$D$143:$DT$143,季度经营税费!$D$6:$DT$6,26),0) -> 0 | AE71: =IF(27<=核心参数输入!$B$9,SUMIFS(季度经营税费!$D$143:$DT$143,季度经营税费!$D$6:$DT$6,27),0) -> 0 | AF71: =IF(28<=核心参数输入!$B$9,SUMIFS(季度经营税费!$D$143:$DT$143,季度经营税费!$D$6:$DT$6,28),0) -> 0 | AG71: =IF(29<=核心参数输入!$B$9,SUMIFS(季度经营税费!$D$143:$DT$143,季度经营税费!$D$6:$DT$6,29),0) -> 0 | AH71: =IF(30<=核心参数输入!$B$9,SUMIFS(季度经营税费!$D$143:$DT$143,季度经营税费!$D$6:$DT$6,30),0) -> 0
A72: 销售实收现金 | B72: 万元 | D72: =IF(0<=核心参数输入!$B$9,SUMIFS(季度经营税费!$D$122:$DT$122,季度经营税费!$D$6:$DT$6,0),0) -> 0 | E72: =IF(1<=核心参数输入!$B$9,SUMIFS(季度经营税费!$D$122:$DT$122,季度经营税费!$D$6:$DT$6,1),0) -> 0 | F72: =IF(2<=核心参数输入!$B$9,SUMIFS(季度经营税费!$D$122:$DT$122,季度经营税费!$D$6:$DT$6,2),0) -> 0 | G72: =IF(3<=核心参数输入!$B$9,SUMIFS(季度经营税费!$D$122:$DT$122,季度经营税费!$D$6:$DT$6,3),0) -> 0 | H72: =IF(4<=核心参数输入!$B$9,SUMIFS(季度经营税费!$D$122:$DT$122,季度经营税费!$D$6:$DT$6,4),0) -> 12053.559 | I72: =IF(5<=核心参数输入!$B$9,SUMIFS(季度经营税费!$D$122:$DT$122,季度经营税费!$D$6:$DT$6,5),0) -> 17048.728 | J72: =IF(6<=核心参数输入!$B$9,SUMIFS(季度经营税费!$D$122:$DT$122,季度经营税费!$D$6:$DT$6,6),0) -> 13356.647 | K72: =IF(7<=核心参数输入!$B$9,SUMIFS(季度经营税费!$D$122:$DT$122,季度经营税费!$D$6:$DT$6,7),0) -> 977.31563 | L72: =IF(8<=核心参数输入!$B$9,SUMIFS(季度经营税费!$D$122:$DT$122,季度经营税费!$D$6:$DT$6,8),0) -> 0 | M72: =IF(9<=核心参数输入!$B$9,SUMIFS(季度经营税费!$D$122:$DT$122,季度经营税费!$D$6:$DT$6,9),0) -> 0 | N72: =IF(10<=核心参数输入!$B$9,SUMIFS(季度经营税费!$D$122:$DT$122,季度经营税费!$D$6:$DT$6,10),0) -> 0 | O72: =IF(11<=核心参数输入!$B$9,SUMIFS(季度经营税费!$D$122:$DT$122,季度经营税费!$D$6:$DT$6,11),0) -> 0 | P72: =IF(12<=核心参数输入!$B$9,SUMIFS(季度经营税费!$D$122:$DT$122,季度经营税费!$D$6:$DT$6,12),0) -> 0 | Q72: =IF(13<=核心参数输入!$B$9,SUMIFS(季度经营税费!$D$122:$DT$122,季度经营税费!$D$6:$DT$6,13),0) -> 0 | R72: =IF(14<=核心参数输入!$B$9,SUMIFS(季度经营税费!$D$122:$DT$122,季度经营税费!$D$6:$DT$6,14),0) -> 0 | S72: =IF(15<=核心参数输入!$B$9,SUMIFS(季度经营税费!$D$122:$DT$122,季度经营税费!$D$6:$DT$6,15),0) -> 0 | T72: =IF(16<=核心参数输入!$B$9,SUMIFS(季度经营税费!$D$122:$DT$122,季度经营税费!$D$6:$DT$6,16),0) -> 0 | U72: =IF(17<=核心参数输入!$B$9,SUMIFS(季度经营税费!$D$122:$DT$122,季度经营税费!$D$6:$DT$6,17),0) -> 0 | V72: =IF(18<=核心参数输入!$B$9,SUMIFS(季度经营税费!$D$122:$DT$122,季度经营税费!$D$6:$DT$6,18),0) -> 0 | W72: =IF(19<=核心参数输入!$B$9,SUMIFS(季度经营税费!$D$122:$DT$122,季度经营税费!$D$6:$DT$6,19),0) -> 0 | X72: =IF(20<=核心参数输入!$B$9,SUMIFS(季度经营税费!$D$122:$DT$122,季度经营税费!$D$6:$DT$6,20),0) -> 0 | Y72: =IF(21<=核心参数输入!$B$9,SUMIFS(季度经营税费!$D$122:$DT$122,季度经营税费!$D$6:$DT$6,21),0) -> 0 | Z72: =IF(22<=核心参数输入!$B$9,SUMIFS(季度经营税费!$D$122:$DT$122,季度经营税费!$D$6:$DT$6,22),0) -> 0 | AA72: =IF(23<=核心参数输入!$B$9,SUMIFS(季度经营税费!$D$122:$DT$122,季度经营税费!$D$6:$DT$6,23),0) -> 0 | AB72: =IF(24<=核心参数输入!$B$9,SUMIFS(季度经营税费!$D$122:$DT$122,季度经营税费!$D$6:$DT$6,24),0) -> 0 | AC72: =IF(25<=核心参数输入!$B$9,SUMIFS(季度经营税费!$D$122:$DT$122,季度经营税费!$D$6:$DT$6,25),0) -> 0 | AD72: =IF(26<=核心参数输入!$B$9,SUMIFS(季度经营税费!$D$122:$DT$122,季度经营税费!$D$6:$DT$6,26),0) -> 0 | AE72: =IF(27<=核心参数输入!$B$9,SUMIFS(季度经营税费!$D$122:$DT$122,季度经营税费!$D$6:$DT$6,27),0) -> 0 | AF72: =IF(28<=核心参数输入!$B$9,SUMIFS(季度经营税费!$D$122:$DT$122,季度经营税费!$D$6:$DT$6,28),0) -> 0 | AG72: =IF(29<=核心参数输入!$B$9,SUMIFS(季度经营税费!$D$122:$DT$122,季度经营税费!$D$6:$DT$6,29),0) -> 0 | AH72: =IF(30<=核心参数输入!$B$9,SUMIFS(季度经营税费!$D$122:$DT$122,季度经营税费!$D$6:$DT$6,30),0) -> 0
A73: 租金实收现金 | B73: 万元 | D73: =IF(0<=核心参数输入!$B$9,SUMIFS(季度经营税费!$D$136:$DT$136,季度经营税费!$D$6:$DT$6,0),0) -> 0 | E73: =IF(1<=核心参数输入!$B$9,SUMIFS(季度经营税费!$D$136:$DT$136,季度经营税费!$D$6:$DT$6,1),0) -> 0 | F73: =IF(2<=核心参数输入!$B$9,SUMIFS(季度经营税费!$D$136:$DT$136,季度经营税费!$D$6:$DT$6,2),0) -> 0 | G73: =IF(3<=核心参数输入!$B$9,SUMIFS(季度经营税费!$D$136:$DT$136,季度经营税费!$D$6:$DT$6,3),0) -> 0 | H73: =IF(4<=核心参数输入!$B$9,SUMIFS(季度经营税费!$D$136:$DT$136,季度经营税费!$D$6:$DT$6,4),0) -> 188.07107 | I73: =IF(5<=核心参数输入!$B$9,SUMIFS(季度经营税费!$D$136:$DT$136,季度经营税费!$D$6:$DT$6,5),0) -> 752.96341 | J73: =IF(6<=核心参数输入!$B$9,SUMIFS(季度经营税费!$D$136:$DT$136,季度经营税费!$D$6:$DT$6,6),0) -> 1095.2569 | K73: =IF(7<=核心参数输入!$B$9,SUMIFS(季度经营税费!$D$136:$DT$136,季度经营税费!$D$6:$DT$6,7),0) -> 1327.4675 | L73: =IF(8<=核心参数输入!$B$9,SUMIFS(季度经营税费!$D$136:$DT$136,季度经营税费!$D$6:$DT$6,8),0) -> 1416.6891 | M73: =IF(9<=核心参数输入!$B$9,SUMIFS(季度经营税费!$D$136:$DT$136,季度经营税费!$D$6:$DT$6,9),0) -> 1440.7534 | N73: =IF(10<=核心参数输入!$B$9,SUMIFS(季度经营税费!$D$136:$DT$136,季度经营税费!$D$6:$DT$6,10),0) -> 1462.3647 | O73: =IF(11<=核心参数输入!$B$9,SUMIFS(季度经营税费!$D$136:$DT$136,季度经营税费!$D$6:$DT$6,11),0) -> 1484.3002 | P73: =IF(12<=核心参数输入!$B$9,SUMIFS(季度经营税费!$D$136:$DT$136,季度经营税费!$D$6:$DT$6,12),0) -> 1506.5647 | Q73: =IF(13<=核心参数输入!$B$9,SUMIFS(季度经营税费!$D$136:$DT$136,季度经营税费!$D$6:$DT$6,13),0) -> 1529.1632 | R73: =IF(14<=核心参数输入!$B$9,SUMIFS(季度经营税费!$D$136:$DT$136,季度经营税费!$D$6:$DT$6,14),0) -> 1552.1006 | S73: =IF(15<=核心参数输入!$B$9,SUMIFS(季度经营税费!$D$136:$DT$136,季度经营税费!$D$6:$DT$6,15),0) -> 1575.3821 | T73: =IF(16<=核心参数输入!$B$9,SUMIFS(季度经营税费!$D$136:$DT$136,季度经营税费!$D$6:$DT$6,16),0) -> 1599.0129 | U73: =IF(17<=核心参数输入!$B$9,SUMIFS(季度经营税费!$D$136:$DT$136,季度经营税费!$D$6:$DT$6,17),0) -> 1622.998 | V73: =IF(18<=核心参数输入!$B$9,SUMIFS(季度经营税费!$D$136:$DT$136,季度经营税费!$D$6:$DT$6,18),0) -> 1647.343 | W73: =IF(19<=核心参数输入!$B$9,SUMIFS(季度经营税费!$D$136:$DT$136,季度经营税费!$D$6:$DT$6,19),0) -> 1672.0532 | X73: =IF(20<=核心参数输入!$B$9,SUMIFS(季度经营税费!$D$136:$DT$136,季度经营税费!$D$6:$DT$6,20),0) -> 1697.134 | Y73: =IF(21<=核心参数输入!$B$9,SUMIFS(季度经营税费!$D$136:$DT$136,季度经营税费!$D$6:$DT$6,21),0) -> 0 | Z73: =IF(22<=核心参数输入!$B$9,SUMIFS(季度经营税费!$D$136:$DT$136,季度经营税费!$D$6:$DT$6,22),0) -> 0 | AA73: =IF(23<=核心参数输入!$B$9,SUMIFS(季度经营税费!$D$136:$DT$136,季度经营税费!$D$6:$DT$6,23),0) -> 0 | AB73: =IF(24<=核心参数输入!$B$9,SUMIFS(季度经营税费!$D$136:$DT$136,季度经营税费!$D$6:$DT$6,24),0) -> 0 | AC73: =IF(25<=核心参数输入!$B$9,SUMIFS(季度经营税费!$D$136:$DT$136,季度经营税费!$D$6:$DT$6,25),0) -> 0 | AD73: =IF(26<=核心参数输入!$B$9,SUMIFS(季度经营税费!$D$136:$DT$136,季度经营税费!$D$6:$DT$6,26),0) -> 0 | AE73: =IF(27<=核心参数输入!$B$9,SUMIFS(季度经营税费!$D$136:$DT$136,季度经营税费!$D$6:$DT$6,27),0) -> 0 | AF73: =IF(28<=核心参数输入!$B$9,SUMIFS(季度经营税费!$D$136:$DT$136,季度经营税费!$D$6:$DT$6,28),0) -> 0 | AG73: =IF(29<=核心参数输入!$B$9,SUMIFS(季度经营税费!$D$136:$DT$136,季度经营税费!$D$6:$DT$6,29),0) -> 0 | AH73: =IF(30<=核心参数输入!$B$9,SUMIFS(季度经营税费!$D$136:$DT$136,季度经营税费!$D$6:$DT$6,30),0) -> 0
A74: 其他经营实收现金 | B74: 万元 | D74: =IF(0<=核心参数输入!$B$9,SUMIFS(季度经营税费!$D$138:$DT$138,季度经营税费!$D$6:$DT$6,0),0) -> 0 | E74: =IF(1<=核心参数输入!$B$9,SUMIFS(季度经营税费!$D$138:$DT$138,季度经营税费!$D$6:$DT$6,1),0) -> 0 | F74: =IF(2<=核心参数输入!$B$9,SUMIFS(季度经营税费!$D$138:$DT$138,季度经营税费!$D$6:$DT$6,2),0) -> 0 | G74: =IF(3<=核心参数输入!$B$9,SUMIFS(季度经营税费!$D$138:$DT$138,季度经营税费!$D$6:$DT$6,3),0) -> 0 | H74: =IF(4<=核心参数输入!$B$9,SUMIFS(季度经营税费!$D$138:$DT$138,季度经营税费!$D$6:$DT$6,4),0) -> 9.4035533 | I74: =IF(5<=核心参数输入!$B$9,SUMIFS(季度经营税费!$D$138:$DT$138,季度经营税费!$D$6:$DT$6,5),0) -> 37.64817 | J74: =IF(6<=核心参数输入!$B$9,SUMIFS(季度经营税费!$D$138:$DT$138,季度经营税费!$D$6:$DT$6,6),0) -> 54.762843 | K74: =IF(7<=核心参数输入!$B$9,SUMIFS(季度经营税费!$D$138:$DT$138,季度经营税费!$D$6:$DT$6,7),0) -> 66.373373 | L74: =IF(8<=核心参数输入!$B$9,SUMIFS(季度经营税费!$D$138:$DT$138,季度经营税费!$D$6:$DT$6,8),0) -> 70.834456 | M74: =IF(9<=核心参数输入!$B$9,SUMIFS(季度经营税费!$D$138:$DT$138,季度经营税费!$D$6:$DT$6,9),0) -> 72.037671 | N74: =IF(10<=核心参数输入!$B$9,SUMIFS(季度经营税费!$D$138:$DT$138,季度经营税费!$D$6:$DT$6,10),0) -> 73.118236 | O74: =IF(11<=核心参数输入!$B$9,SUMIFS(季度经营税费!$D$138:$DT$138,季度经营税费!$D$6:$DT$6,11),0) -> 74.21501 | P74: =IF(12<=核心参数输入!$B$9,SUMIFS(季度经营税费!$D$138:$DT$138,季度经营税费!$D$6:$DT$6,12),0) -> 75.328235 | Q74: =IF(13<=核心参数输入!$B$9,SUMIFS(季度经营税费!$D$138:$DT$138,季度经营税费!$D$6:$DT$6,13),0) -> 76.458158 | R74: =IF(14<=核心参数输入!$B$9,SUMIFS(季度经营税费!$D$138:$DT$138,季度经营税费!$D$6:$DT$6,14),0) -> 77.605031 | S74: =IF(15<=核心参数输入!$B$9,SUMIFS(季度经营税费!$D$138:$DT$138,季度经营税费!$D$6:$DT$6,15),0) -> 78.769106 | T74: =IF(16<=核心参数输入!$B$9,SUMIFS(季度经营税费!$D$138:$DT$138,季度经营税费!$D$6:$DT$6,16),0) -> 79.950643 | U74: =IF(17<=核心参数输入!$B$9,SUMIFS(季度经营税费!$D$138:$DT$138,季度经营税费!$D$6:$DT$6,17),0) -> 81.149902 | V74: =IF(18<=核心参数输入!$B$9,SUMIFS(季度经营税费!$D$138:$DT$138,季度经营税费!$D$6:$DT$6,18),0) -> 82.367151 | W74: =IF(19<=核心参数输入!$B$9,SUMIFS(季度经营税费!$D$138:$DT$138,季度经营税费!$D$6:$DT$6,19),0) -> 83.602658 | X74: =IF(20<=核心参数输入!$B$9,SUMIFS(季度经营税费!$D$138:$DT$138,季度经营税费!$D$6:$DT$6,20),0) -> 84.856698 | Y74: =IF(21<=核心参数输入!$B$9,SUMIFS(季度经营税费!$D$138:$DT$138,季度经营税费!$D$6:$DT$6,21),0) -> 0 | Z74: =IF(22<=核心参数输入!$B$9,SUMIFS(季度经营税费!$D$138:$DT$138,季度经营税费!$D$6:$DT$6,22),0) -> 0 | AA74: =IF(23<=核心参数输入!$B$9,SUMIFS(季度经营税费!$D$138:$DT$138,季度经营税费!$D$6:$DT$6,23),0) -> 0 | AB74: =IF(24<=核心参数输入!$B$9,SUMIFS(季度经营税费!$D$138:$DT$138,季度经营税费!$D$6:$DT$6,24),0) -> 0 | AC74: =IF(25<=核心参数输入!$B$9,SUMIFS(季度经营税费!$D$138:$DT$138,季度经营税费!$D$6:$DT$6,25),0) -> 0 | AD74: =IF(26<=核心参数输入!$B$9,SUMIFS(季度经营税费!$D$138:$DT$138,季度经营税费!$D$6:$DT$6,26),0) -> 0 | AE74: =IF(27<=核心参数输入!$B$9,SUMIFS(季度经营税费!$D$138:$DT$138,季度经营税费!$D$6:$DT$6,27),0) -> 0 | AF74: =IF(28<=核心参数输入!$B$9,SUMIFS(季度经营税费!$D$138:$DT$138,季度经营税费!$D$6:$DT$6,28),0) -> 0 | AG74: =IF(29<=核心参数输入!$B$9,SUMIFS(季度经营税费!$D$138:$DT$138,季度经营税费!$D$6:$DT$6,29),0) -> 0 | AH74: =IF(30<=核心参数输入!$B$9,SUMIFS(季度经营税费!$D$138:$DT$138,季度经营税费!$D$6:$DT$6,30),0) -> 0
A75: 现金成本及流转税 | B75: 万元 | D75: =IF(0<=核心参数输入!$B$9,SUMIFS(季度经营税费!$D$179:$DT$179,季度经营税费!$D$6:$DT$6,0),0) -> 0 | E75: =IF(1<=核心参数输入!$B$9,SUMIFS(季度经营税费!$D$179:$DT$179,季度经营税费!$D$6:$DT$6,1),0) -> 0 | F75: =IF(2<=核心参数输入!$B$9,SUMIFS(季度经营税费!$D$179:$DT$179,季度经营税费!$D$6:$DT$6,2),0) -> 0 | G75: =IF(3<=核心参数输入!$B$9,SUMIFS(季度经营税费!$D$179:$DT$179,季度经营税费!$D$6:$DT$6,3),0) -> 0 | H75: =IF(4<=核心参数输入!$B$9,SUMIFS(季度经营税费!$D$179:$DT$179,季度经营税费!$D$6:$DT$6,4),0) -> 1884.0176 | I75: =IF(5<=核心参数输入!$B$9,SUMIFS(季度经营税费!$D$179:$DT$179,季度经营税费!$D$6:$DT$6,5),0) -> 2453.5546 | J75: =IF(6<=核心参数输入!$B$9,SUMIFS(季度经营税费!$D$179:$DT$179,季度经营税费!$D$6:$DT$6,6),0) -> 2068.7066 | K75: =IF(7<=核心参数输入!$B$9,SUMIFS(季度经营税费!$D$179:$DT$179,季度经营税费!$D$6:$DT$6,7),0) -> 750.87922 | L75: =IF(8<=核心参数输入!$B$9,SUMIFS(季度经营税费!$D$179:$DT$179,季度经营税费!$D$6:$DT$6,8),0) -> 774.21861 | M75: =IF(9<=核心参数输入!$B$9,SUMIFS(季度经营税费!$D$179:$DT$179,季度经营税费!$D$6:$DT$6,9),0) -> 785.29083 | N75: =IF(10<=核心参数输入!$B$9,SUMIFS(季度经营税费!$D$179:$DT$179,季度经营税费!$D$6:$DT$6,10),0) -> 796.02631 | O75: =IF(11<=核心参数输入!$B$9,SUMIFS(季度经营税费!$D$179:$DT$179,季度经营税费!$D$6:$DT$6,11),0) -> 806.95595 | P75: =IF(12<=核心参数输入!$B$9,SUMIFS(季度经营税费!$D$179:$DT$179,季度经营税费!$D$6:$DT$6,12),0) -> 818.08332 | Q75: =IF(13<=核心参数输入!$B$9,SUMIFS(季度经营税费!$D$179:$DT$179,季度经营税费!$D$6:$DT$6,13),0) -> 829.41205 | R75: =IF(14<=核心参数输入!$B$9,SUMIFS(季度经营税费!$D$179:$DT$179,季度经营税费!$D$6:$DT$6,14),0) -> 840.94587 | S75: =IF(15<=核心参数输入!$B$9,SUMIFS(季度经营税费!$D$179:$DT$179,季度经营税费!$D$6:$DT$6,15),0) -> 852.68855 | T75: =IF(16<=核心参数输入!$B$9,SUMIFS(季度经营税费!$D$179:$DT$179,季度经营税费!$D$6:$DT$6,16),0) -> 864.64394 | U75: =IF(17<=核心参数输入!$B$9,SUMIFS(季度经营税费!$D$179:$DT$179,季度经营税费!$D$6:$DT$6,17),0) -> 876.81596 | V75: =IF(18<=核心参数输入!$B$9,SUMIFS(季度经营税费!$D$179:$DT$179,季度经营税费!$D$6:$DT$6,18),0) -> 889.20861 | W75: =IF(19<=核心参数输入!$B$9,SUMIFS(季度经营税费!$D$179:$DT$179,季度经营税费!$D$6:$DT$6,19),0) -> 901.82596 | X75: =IF(20<=核心参数输入!$B$9,SUMIFS(季度经营税费!$D$179:$DT$179,季度经营税费!$D$6:$DT$6,20),0) -> 914.67215 | Y75: =IF(21<=核心参数输入!$B$9,SUMIFS(季度经营税费!$D$179:$DT$179,季度经营税费!$D$6:$DT$6,21),0) -> 0 | Z75: =IF(22<=核心参数输入!$B$9,SUMIFS(季度经营税费!$D$179:$DT$179,季度经营税费!$D$6:$DT$6,22),0) -> 0 | AA75: =IF(23<=核心参数输入!$B$9,SUMIFS(季度经营税费!$D$179:$DT$179,季度经营税费!$D$6:$DT$6,23),0) -> 0 | AB75: =IF(24<=核心参数输入!$B$9,SUMIFS(季度经营税费!$D$179:$DT$179,季度经营税费!$D$6:$DT$6,24),0) -> 0 | AC75: =IF(25<=核心参数输入!$B$9,SUMIFS(季度经营税费!$D$179:$DT$179,季度经营税费!$D$6:$DT$6,25),0) -> 0 | AD75: =IF(26<=核心参数输入!$B$9,SUMIFS(季度经营税费!$D$179:$DT$179,季度经营税费!$D$6:$DT$6,26),0) -> 0 | AE75: =IF(27<=核心参数输入!$B$9,SUMIFS(季度经营税费!$D$179:$DT$179,季度经营税费!$D$6:$DT$6,27),0) -> 0 | AF75: =IF(28<=核心参数输入!$B$9,SUMIFS(季度经营税费!$D$179:$DT$179,季度经营税费!$D$6:$DT$6,28),0) -> 0 | AG75: =IF(29<=核心参数输入!$B$9,SUMIFS(季度经营税费!$D$179:$DT$179,季度经营税费!$D$6:$DT$6,29),0) -> 0 | AH75: =IF(30<=核心参数输入!$B$9,SUMIFS(季度经营税费!$D$179:$DT$179,季度经营税费!$D$6:$DT$6,30),0) -> 0
A76: 融资所得税现金 | B76: 万元 | D76: =IF(0<=核心参数输入!$B$9,IF(核心参数输入!$B$64=1,SUMIFS(季度经营税费!$D$175:$DT$175,季度经营税费!$D$6:$DT$6,0),SUMIFS(季度经营税费!$D$174:$DT$174,季度经营税费!$D$6:$DT$6,0)),0) -> 0 | E76: =IF(1<=核心参数输入!$B$9,IF(核心参数输入!$B$64=1,SUMIFS(季度经营税费!$D$175:$DT$175,季度经营税费!$D$6:$DT$6,1),SUMIFS(季度经营税费!$D$174:$DT$174,季度经营税费!$D$6:$DT$6,1)),0) -> 0 | F76: =IF(2<=核心参数输入!$B$9,IF(核心参数输入!$B$64=1,SUMIFS(季度经营税费!$D$175:$DT$175,季度经营税费!$D$6:$DT$6,2),SUMIFS(季度经营税费!$D$174:$DT$174,季度经营税费!$D$6:$DT$6,2)),0) -> 0 | G76: =IF(3<=核心参数输入!$B$9,IF(核心参数输入!$B$64=1,SUMIFS(季度经营税费!$D$175:$DT$175,季度经营税费!$D$6:$DT$6,3),SUMIFS(季度经营税费!$D$174:$DT$174,季度经营税费!$D$6:$DT$6,3)),0) -> 0 | H76: =IF(4<=核心参数输入!$B$9,IF(核心参数输入!$B$64=1,SUMIFS(季度经营税费!$D$175:$DT$175,季度经营税费!$D$6:$DT$6,4),SUMIFS(季度经营税费!$D$174:$DT$174,季度经营税费!$D$6:$DT$6,4)),0) -> 0 | I76: =IF(5<=核心参数输入!$B$9,IF(核心参数输入!$B$64=1,SUMIFS(季度经营税费!$D$175:$DT$175,季度经营税费!$D$6:$DT$6,5),SUMIFS(季度经营税费!$D$174:$DT$174,季度经营税费!$D$6:$DT$6,5)),0) -> 0 | J76: =IF(6<=核心参数输入!$B$9,IF(核心参数输入!$B$64=1,SUMIFS(季度经营税费!$D$175:$DT$175,季度经营税费!$D$6:$DT$6,6),SUMIFS(季度经营税费!$D$174:$DT$174,季度经营税费!$D$6:$DT$6,6)),0) -> 0 | K76: =IF(7<=核心参数输入!$B$9,IF(核心参数输入!$B$64=1,SUMIFS(季度经营税费!$D$175:$DT$175,季度经营税费!$D$6:$DT$6,7),SUMIFS(季度经营税费!$D$174:$DT$174,季度经营税费!$D$6:$DT$6,7)),0) -> 0 | L76: =IF(8<=核心参数输入!$B$9,IF(核心参数输入!$B$64=1,SUMIFS(季度经营税费!$D$175:$DT$175,季度经营税费!$D$6:$DT$6,8),SUMIFS(季度经营税费!$D$174:$DT$174,季度经营税费!$D$6:$DT$6,8)),0) -> 0 | M76: =IF(9<=核心参数输入!$B$9,IF(核心参数输入!$B$64=1,SUMIFS(季度经营税费!$D$175:$DT$175,季度经营税费!$D$6:$DT$6,9),SUMIFS(季度经营税费!$D$174:$DT$174,季度经营税费!$D$6:$DT$6,9)),0) -> 0 | N76: =IF(10<=核心参数输入!$B$9,IF(核心参数输入!$B$64=1,SUMIFS(季度经营税费!$D$175:$DT$175,季度经营税费!$D$6:$DT$6,10),SUMIFS(季度经营税费!$D$174:$DT$174,季度经营税费!$D$6:$DT$6,10)),0) -> 0 | O76: =IF(11<=核心参数输入!$B$9,IF(核心参数输入!$B$64=1,SUMIFS(季度经营税费!$D$175:$DT$175,季度经营税费!$D$6:$DT$6,11),SUMIFS(季度经营税费!$D$174:$DT$174,季度经营税费!$D$6:$DT$6,11)),0) -> 0 | P76: =IF(12<=核心参数输入!$B$9,IF(核心参数输入!$B$64=1,SUMIFS(季度经营税费!$D$175:$DT$175,季度经营税费!$D$6:$DT$6,12),SUMIFS(季度经营税费!$D$174:$DT$174,季度经营税费!$D$6:$DT$6,12)),0) -> 0 | Q76: =IF(13<=核心参数输入!$B$9,IF(核心参数输入!$B$64=1,SUMIFS(季度经营税费!$D$175:$DT$175,季度经营税费!$D$6:$DT$6,13),SUMIFS(季度经营税费!$D$174:$DT$174,季度经营税费!$D$6:$DT$6,13)),0) -> 0 | R76: =IF(14<=核心参数输入!$B$9,IF(核心参数输入!$B$64=1,SUMIFS(季度经营税费!$D$175:$DT$175,季度经营税费!$D$6:$DT$6,14),SUMIFS(季度经营税费!$D$174:$DT$174,季度经营税费!$D$6:$DT$6,14)),0) -> 0 | S76: =IF(15<=核心参数输入!$B$9,IF(核心参数输入!$B$64=1,SUMIFS(季度经营税费!$D$175:$DT$175,季度经营税费!$D$6:$DT$6,15),SUMIFS(季度经营税费!$D$174:$DT$174,季度经营税费!$D$6:$DT$6,15)),0) -> 0 | T76: =IF(16<=核心参数输入!$B$9,IF(核心参数输入!$B$64=1,SUMIFS(季度经营税费!$D$175:$DT$175,季度经营税费!$D$6:$DT$6,16),SUMIFS(季度经营税费!$D$174:$DT$174,季度经营税费!$D$6:$DT$6,16)),0) -> 0 | U76: =IF(17<=核心参数输入!$B$9,IF(核心参数输入!$B$64=1,SUMIFS(季度经营税费!$D$175:$DT$175,季度经营税费!$D$6:$DT$6,17),SUMIFS(季度经营税费!$D$174:$DT$174,季度经营税费!$D$6:$DT$6,17)),0) -> 0 | V76: =IF(18<=核心参数输入!$B$9,IF(核心参数输入!$B$64=1,SUMIFS(季度经营税费!$D$175:$DT$175,季度经营税费!$D$6:$DT$6,18),SUMIFS(季度经营税费!$D$174:$DT$174,季度经营税费!$D$6:$DT$6,18)),0) -> 0 | W76: =IF(19<=核心参数输入!$B$9,IF(核心参数输入!$B$64=1,SUMIFS(季度经营税费!$D$175:$DT$175,季度经营税费!$D$6:$DT$6,19),SUMIFS(季度经营税费!$D$174:$DT$174,季度经营税费!$D$6:$DT$6,19)),0) -> 0 | X76: =IF(20<=核心参数输入!$B$9,IF(核心参数输入!$B$64=1,SUMIFS(季度经营税费!$D$175:$DT$175,季度经营税费!$D$6:$DT$6,20),SUMIFS(季度经营税费!$D$174:$DT$174,季度经营税费!$D$6:$DT$6,20)),0) -> 0 | Y76: =IF(21<=核心参数输入!$B$9,IF(核心参数输入!$B$64=1,SUMIFS(季度经营税费!$D$175:$DT$175,季度经营税费!$D$6:$DT$6,21),SUMIFS(季度经营税费!$D$174:$DT$174,季度经营税费!$D$6:$DT$6,21)),0) -> 0 | Z76: =IF(22<=核心参数输入!$B$9,IF(核心参数输入!$B$64=1,SUMIFS(季度经营税费!$D$175:$DT$175,季度经营税费!$D$6:$DT$6,22),SUMIFS(季度经营税费!$D$174:$DT$174,季度经营税费!$D$6:$DT$6,22)),0) -> 0 | AA76: =IF(23<=核心参数输入!$B$9,IF(核心参数输入!$B$64=1,SUMIFS(季度经营税费!$D$175:$DT$175,季度经营税费!$D$6:$DT$6,23),SUMIFS(季度经营税费!$D$174:$DT$174,季度经营税费!$D$6:$DT$6,23)),0) -> 0 | AB76: =IF(24<=核心参数输入!$B$9,IF(核心参数输入!$B$64=1,SUMIFS(季度经营税费!$D$175:$DT$175,季度经营税费!$D$6:$DT$6,24),SUMIFS(季度经营税费!$D$174:$DT$174,季度经营税费!$D$6:$DT$6,24)),0) -> 0 | AC76: =IF(25<=核心参数输入!$B$9,IF(核心参数输入!$B$64=1,SUMIFS(季度经营税费!$D$175:$DT$175,季度经营税费!$D$6:$DT$6,25),SUMIFS(季度经营税费!$D$174:$DT$174,季度经营税费!$D$6:$DT$6,25)),0) -> 0 | AD76: =IF(26<=核心参数输入!$B$9,IF(核心参数输入!$B$64=1,SUMIFS(季度经营税费!$D$175:$DT$175,季度经营税费!$D$6:$DT$6,26),SUMIFS(季度经营税费!$D$174:$DT$174,季度经营税费!$D$6:$DT$6,26)),0) -> 0 | AE76: =IF(27<=核心参数输入!$B$9,IF(核心参数输入!$B$64=1,SUMIFS(季度经营税费!$D$175:$DT$175,季度经营税费!$D$6:$DT$6,27),SUMIFS(季度经营税费!$D$174:$DT$174,季度经营税费!$D$6:$DT$6,27)),0) -> 0 | AF76: =IF(28<=核心参数输入!$B$9,IF(核心参数输入!$B$64=1,SUMIFS(季度经营税费!$D$175:$DT$175,季度经营税费!$D$6:$DT$6,28),SUMIFS(季度经营税费!$D$174:$DT$174,季度经营税费!$D$6:$DT$6,28)),0) -> 0 | AG76: =IF(29<=核心参数输入!$B$9,IF(核心参数输入!$B$64=1,SUMIFS(季度经营税费!$D$175:$DT$175,季度经营税费!$D$6:$DT$6,29),SUMIFS(季度经营税费!$D$174:$DT$174,季度经营税费!$D$6:$DT$6,29)),0) -> 0 | AH76: =IF(30<=核心参数输入!$B$9,IF(核心参数输入!$B$64=1,SUMIFS(季度经营税费!$D$175:$DT$175,季度经营税费!$D$6:$DT$6,30),SUMIFS(季度经营税费!$D$174:$DT$174,季度经营税费!$D$6:$DT$6,30)),0) -> 0
A77: 净利润 | B77: 万元 | D77: =IF(0<=核心参数输入!$B$9,IF(核心参数输入!$B$64=1,SUMIFS(季度经营税费!$D$177:$DT$177,季度经营税费!$D$6:$DT$6,0),SUMIFS(季度经营税费!$D$176:$DT$176,季度经营税费!$D$6:$DT$6,0)),0) -> 0 | E77: =IF(1<=核心参数输入!$B$9,IF(核心参数输入!$B$64=1,SUMIFS(季度经营税费!$D$177:$DT$177,季度经营税费!$D$6:$DT$6,1),SUMIFS(季度经营税费!$D$176:$DT$176,季度经营税费!$D$6:$DT$6,1)),0) -> 0 | F77: =IF(2<=核心参数输入!$B$9,IF(核心参数输入!$B$64=1,SUMIFS(季度经营税费!$D$177:$DT$177,季度经营税费!$D$6:$DT$6,2),SUMIFS(季度经营税费!$D$176:$DT$176,季度经营税费!$D$6:$DT$6,2)),0) -> 0 | G77: =IF(3<=核心参数输入!$B$9,IF(核心参数输入!$B$64=1,SUMIFS(季度经营税费!$D$177:$DT$177,季度经营税费!$D$6:$DT$6,3),SUMIFS(季度经营税费!$D$176:$DT$176,季度经营税费!$D$6:$DT$6,3)),0) -> 0 | H77: =IF(4<=核心参数输入!$B$9,IF(核心参数输入!$B$64=1,SUMIFS(季度经营税费!$D$177:$DT$177,季度经营税费!$D$6:$DT$6,4),SUMIFS(季度经营税费!$D$176:$DT$176,季度经营税费!$D$6:$DT$6,4)),0) -> -2058.4515 | I77: =IF(5<=核心参数输入!$B$9,IF(核心参数输入!$B$64=1,SUMIFS(季度经营税费!$D$177:$DT$177,季度经营税费!$D$6:$DT$6,5),SUMIFS(季度经营税费!$D$176:$DT$176,季度经营税费!$D$6:$DT$6,5)),0) -> -1256.8365 | J77: =IF(6<=核心参数输入!$B$9,IF(核心参数输入!$B$64=1,SUMIFS(季度经营税费!$D$177:$DT$177,季度经营税费!$D$6:$DT$6,6),SUMIFS(季度经营税费!$D$176:$DT$176,季度经营税费!$D$6:$DT$6,6)),0) -> -930.59535 | K77: =IF(7<=核心参数输入!$B$9,IF(核心参数输入!$B$64=1,SUMIFS(季度经营税费!$D$177:$DT$177,季度经营税费!$D$6:$DT$6,7),SUMIFS(季度经营税费!$D$176:$DT$176,季度经营税费!$D$6:$DT$6,7)),0) -> -982.99189 | L77: =IF(8<=核心参数输入!$B$9,IF(核心参数输入!$B$64=1,SUMIFS(季度经营税费!$D$177:$DT$177,季度经营税费!$D$6:$DT$6,8),SUMIFS(季度经营税费!$D$176:$DT$176,季度经营税费!$D$6:$DT$6,8)),0) -> -732.64854 | M77: =IF(9<=核心参数输入!$B$9,IF(核心参数输入!$B$64=1,SUMIFS(季度经营税费!$D$177:$DT$177,季度经营税费!$D$6:$DT$6,9),SUMIFS(季度经营税费!$D$176:$DT$176,季度经营税费!$D$6:$DT$6,9)),0) -> -538.45323 | N77: =IF(10<=核心参数输入!$B$9,IF(核心参数输入!$B$64=1,SUMIFS(季度经营税费!$D$177:$DT$177,季度经营税费!$D$6:$DT$6,10),SUMIFS(季度经营税费!$D$176:$DT$176,季度经营税费!$D$6:$DT$6,10)),0) -> -346.49685 | O77: =IF(11<=核心参数输入!$B$9,IF(核心参数输入!$B$64=1,SUMIFS(季度经营税费!$D$177:$DT$177,季度经营税费!$D$6:$DT$6,11),SUMIFS(季度经营税费!$D$176:$DT$176,季度经营税费!$D$6:$DT$6,11)),0) -> -176.89424 | P77: =IF(12<=核心参数输入!$B$9,IF(核心参数输入!$B$64=1,SUMIFS(季度经营税费!$D$177:$DT$177,季度经营税费!$D$6:$DT$6,12),SUMIFS(季度经营税费!$D$176:$DT$176,季度经营税费!$D$6:$DT$6,12)),0) -> -164.64388 | Q77: =IF(13<=核心参数输入!$B$9,IF(核心参数输入!$B$64=1,SUMIFS(季度经营税费!$D$177:$DT$177,季度经营税费!$D$6:$DT$6,13),SUMIFS(季度经营税费!$D$176:$DT$176,季度经营税费!$D$6:$DT$6,13)),0) -> -152.24423 | R77: =IF(14<=核心参数输入!$B$9,IF(核心参数输入!$B$64=1,SUMIFS(季度经营税费!$D$177:$DT$177,季度经营税费!$D$6:$DT$6,14),SUMIFS(季度经营税费!$D$176:$DT$176,季度经营税费!$D$6:$DT$6,14)),0) -> -139.69373 | S77: =IF(15<=核心参数输入!$B$9,IF(核心参数输入!$B$64=1,SUMIFS(季度经营税费!$D$177:$DT$177,季度经营税费!$D$6:$DT$6,15),SUMIFS(季度经营税费!$D$176:$DT$176,季度经营税费!$D$6:$DT$6,15)),0) -> -126.99082 | T77: =IF(16<=核心参数输入!$B$9,IF(核心参数输入!$B$64=1,SUMIFS(季度经营税费!$D$177:$DT$177,季度经营税费!$D$6:$DT$6,16),SUMIFS(季度经营税费!$D$176:$DT$176,季度经营税费!$D$6:$DT$6,16)),0) -> -114.13394 | U77: =IF(17<=核心参数输入!$B$9,IF(核心参数输入!$B$64=1,SUMIFS(季度经营税费!$D$177:$DT$177,季度经营税费!$D$6:$DT$6,17),SUMIFS(季度经营税费!$D$176:$DT$176,季度经营税费!$D$6:$DT$6,17)),0) -> -101.12151 | V77: =IF(18<=核心参数输入!$B$9,IF(核心参数输入!$B$64=1,SUMIFS(季度经营税费!$D$177:$DT$177,季度经营税费!$D$6:$DT$6,18),SUMIFS(季度经营税费!$D$176:$DT$176,季度经营税费!$D$6:$DT$6,18)),0) -> -87.951944 | W77: =IF(19<=核心参数输入!$B$9,IF(核心参数输入!$B$64=1,SUMIFS(季度经营税费!$D$177:$DT$177,季度经营税费!$D$6:$DT$6,19),SUMIFS(季度经营税费!$D$176:$DT$176,季度经营税费!$D$6:$DT$6,19)),0) -> -74.623639 | X77: =IF(20<=核心参数输入!$B$9,IF(核心参数输入!$B$64=1,SUMIFS(季度经营税费!$D$177:$DT$177,季度经营税费!$D$6:$DT$6,20),SUMIFS(季度经营税费!$D$176:$DT$176,季度经营税费!$D$6:$DT$6,20)),0) -> -61.134993 | Y77: =IF(21<=核心参数输入!$B$9,IF(核心参数输入!$B$64=1,SUMIFS(季度经营税费!$D$177:$DT$177,季度经营税费!$D$6:$DT$6,21),SUMIFS(季度经营税费!$D$176:$DT$176,季度经营税费!$D$6:$DT$6,21)),0) -> 0 | Z77: =IF(22<=核心参数输入!$B$9,IF(核心参数输入!$B$64=1,SUMIFS(季度经营税费!$D$177:$DT$177,季度经营税费!$D$6:$DT$6,22),SUMIFS(季度经营税费!$D$176:$DT$176,季度经营税费!$D$6:$DT$6,22)),0) -> 0 | AA77: =IF(23<=核心参数输入!$B$9,IF(核心参数输入!$B$64=1,SUMIFS(季度经营税费!$D$177:$DT$177,季度经营税费!$D$6:$DT$6,23),SUMIFS(季度经营税费!$D$176:$DT$176,季度经营税费!$D$6:$DT$6,23)),0) -> 0 | AB77: =IF(24<=核心参数输入!$B$9,IF(核心参数输入!$B$64=1,SUMIFS(季度经营税费!$D$177:$DT$177,季度经营税费!$D$6:$DT$6,24),SUMIFS(季度经营税费!$D$176:$DT$176,季度经营税费!$D$6:$DT$6,24)),0) -> 0 | AC77: =IF(25<=核心参数输入!$B$9,IF(核心参数输入!$B$64=1,SUMIFS(季度经营税费!$D$177:$DT$177,季度经营税费!$D$6:$DT$6,25),SUMIFS(季度经营税费!$D$176:$DT$176,季度经营税费!$D$6:$DT$6,25)),0) -> 0 | AD77: =IF(26<=核心参数输入!$B$9,IF(核心参数输入!$B$64=1,SUMIFS(季度经营税费!$D$177:$DT$177,季度经营税费!$D$6:$DT$6,26),SUMIFS(季度经营税费!$D$176:$DT$176,季度经营税费!$D$6:$DT$6,26)),0) -> 0 | AE77: =IF(27<=核心参数输入!$B$9,IF(核心参数输入!$B$64=1,SUMIFS(季度经营税费!$D$177:$DT$177,季度经营税费!$D$6:$DT$6,27),SUMIFS(季度经营税费!$D$176:$DT$176,季度经营税费!$D$6:$DT$6,27)),0) -> 0 | AF77: =IF(28<=核心参数输入!$B$9,IF(核心参数输入!$B$64=1,SUMIFS(季度经营税费!$D$177:$DT$177,季度经营税费!$D$6:$DT$6,28),SUMIFS(季度经营税费!$D$176:$DT$176,季度经营税费!$D$6:$DT$6,28)),0) -> 0 | AG77: =IF(29<=核心参数输入!$B$9,IF(核心参数输入!$B$64=1,SUMIFS(季度经营税费!$D$177:$DT$177,季度经营税费!$D$6:$DT$6,29),SUMIFS(季度经营税费!$D$176:$DT$176,季度经营税费!$D$6:$DT$6,29)),0) -> 0 | AH77: =IF(30<=核心参数输入!$B$9,IF(核心参数输入!$B$64=1,SUMIFS(季度经营税费!$D$177:$DT$177,季度经营税费!$D$6:$DT$6,30),SUMIFS(季度经营税费!$D$176:$DT$176,季度经营税费!$D$6:$DT$6,30)),0) -> 0
A78: 投资支付含资本化融资费用 | B78: 万元 | D78: =IF(0<=核心参数输入!$B$9,SUMIFS(季度投融资!$D$158:$DT$158,季度投融资!$D$6:$DT$6,0),0) -> 8000 | E78: =IF(1<=核心参数输入!$B$9,SUMIFS(季度投融资!$D$158:$DT$158,季度投融资!$D$6:$DT$6,1),0) -> 13274.887 | F78: =IF(2<=核心参数输入!$B$9,SUMIFS(季度投融资!$D$158:$DT$158,季度投融资!$D$6:$DT$6,2),0) -> 23914.8 | G78: =IF(3<=核心参数输入!$B$9,SUMIFS(季度投融资!$D$158:$DT$158,季度投融资!$D$6:$DT$6,3),0) -> 18534.6 | H78: =IF(4<=核心参数输入!$B$9,SUMIFS(季度投融资!$D$158:$DT$158,季度投融资!$D$6:$DT$6,4),0) -> 500 | I78: =IF(5<=核心参数输入!$B$9,SUMIFS(季度投融资!$D$158:$DT$158,季度投融资!$D$6:$DT$6,5),0) -> 0 | J78: =IF(6<=核心参数输入!$B$9,SUMIFS(季度投融资!$D$158:$DT$158,季度投融资!$D$6:$DT$6,6),0) -> 0 | K78: =IF(7<=核心参数输入!$B$9,SUMIFS(季度投融资!$D$158:$DT$158,季度投融资!$D$6:$DT$6,7),0) -> 0 | L78: =IF(8<=核心参数输入!$B$9,SUMIFS(季度投融资!$D$158:$DT$158,季度投融资!$D$6:$DT$6,8),0) -> 0 | M78: =IF(9<=核心参数输入!$B$9,SUMIFS(季度投融资!$D$158:$DT$158,季度投融资!$D$6:$DT$6,9),0) -> 0 | N78: =IF(10<=核心参数输入!$B$9,SUMIFS(季度投融资!$D$158:$DT$158,季度投融资!$D$6:$DT$6,10),0) -> 0 | O78: =IF(11<=核心参数输入!$B$9,SUMIFS(季度投融资!$D$158:$DT$158,季度投融资!$D$6:$DT$6,11),0) -> 0 | P78: =IF(12<=核心参数输入!$B$9,SUMIFS(季度投融资!$D$158:$DT$158,季度投融资!$D$6:$DT$6,12),0) -> 0 | Q78: =IF(13<=核心参数输入!$B$9,SUMIFS(季度投融资!$D$158:$DT$158,季度投融资!$D$6:$DT$6,13),0) -> 0 | R78: =IF(14<=核心参数输入!$B$9,SUMIFS(季度投融资!$D$158:$DT$158,季度投融资!$D$6:$DT$6,14),0) -> 0 | S78: =IF(15<=核心参数输入!$B$9,SUMIFS(季度投融资!$D$158:$DT$158,季度投融资!$D$6:$DT$6,15),0) -> 0 | T78: =IF(16<=核心参数输入!$B$9,SUMIFS(季度投融资!$D$158:$DT$158,季度投融资!$D$6:$DT$6,16),0) -> 0 | U78: =IF(17<=核心参数输入!$B$9,SUMIFS(季度投融资!$D$158:$DT$158,季度投融资!$D$6:$DT$6,17),0) -> 0 | V78: =IF(18<=核心参数输入!$B$9,SUMIFS(季度投融资!$D$158:$DT$158,季度投融资!$D$6:$DT$6,18),0) -> 0 | W78: =IF(19<=核心参数输入!$B$9,SUMIFS(季度投融资!$D$158:$DT$158,季度投融资!$D$6:$DT$6,19),0) -> 0 | X78: =IF(20<=核心参数输入!$B$9,SUMIFS(季度投融资!$D$158:$DT$158,季度投融资!$D$6:$DT$6,20),0) -> 0 | Y78: =IF(21<=核心参数输入!$B$9,SUMIFS(季度投融资!$D$158:$DT$158,季度投融资!$D$6:$DT$6,21),0) -> 0 | Z78: =IF(22<=核心参数输入!$B$9,SUMIFS(季度投融资!$D$158:$DT$158,季度投融资!$D$6:$DT$6,22),0) -> 0 | AA78: =IF(23<=核心参数输入!$B$9,SUMIFS(季度投融资!$D$158:$DT$158,季度投融资!$D$6:$DT$6,23),0) -> 0 | AB78: =IF(24<=核心参数输入!$B$9,SUMIFS(季度投融资!$D$158:$DT$158,季度投融资!$D$6:$DT$6,24),0) -> 0 | AC78: =IF(25<=核心参数输入!$B$9,SUMIFS(季度投融资!$D$158:$DT$158,季度投融资!$D$6:$DT$6,25),0) -> 0 | AD78: =IF(26<=核心参数输入!$B$9,SUMIFS(季度投融资!$D$158:$DT$158,季度投融资!$D$6:$DT$6,26),0) -> 0 | AE78: =IF(27<=核心参数输入!$B$9,SUMIFS(季度投融资!$D$158:$DT$158,季度投融资!$D$6:$DT$6,27),0) -> 0 | AF78: =IF(28<=核心参数输入!$B$9,SUMIFS(季度投融资!$D$158:$DT$158,季度投融资!$D$6:$DT$6,28),0) -> 0 | AG78: =IF(29<=核心参数输入!$B$9,SUMIFS(季度投融资!$D$158:$DT$158,季度投融资!$D$6:$DT$6,29),0) -> 0 | AH78: =IF(30<=核心参数输入!$B$9,SUMIFS(季度投融资!$D$158:$DT$158,季度投融资!$D$6:$DT$6,30),0) -> 0
A79: 贷款提款 | B79: 万元 | D79: =IF(0<=核心参数输入!$B$9,SUMIFS(季度投融资!$D$149:$DT$149,季度投融资!$D$6:$DT$6,0),0) -> 0 | E79: =IF(1<=核心参数输入!$B$9,SUMIFS(季度投融资!$D$149:$DT$149,季度投融资!$D$6:$DT$6,1),0) -> 6750 | F79: =IF(2<=核心参数输入!$B$9,SUMIFS(季度投融资!$D$149:$DT$149,季度投融资!$D$6:$DT$6,2),0) -> 12000 | G79: =IF(3<=核心参数输入!$B$9,SUMIFS(季度投融资!$D$149:$DT$149,季度投融资!$D$6:$DT$6,3),0) -> 9000 | H79: =IF(4<=核心参数输入!$B$9,SUMIFS(季度投融资!$D$149:$DT$149,季度投融资!$D$6:$DT$6,4),0) -> 0 | I79: =IF(5<=核心参数输入!$B$9,SUMIFS(季度投融资!$D$149:$DT$149,季度投融资!$D$6:$DT$6,5),0) -> 0 | J79: =IF(6<=核心参数输入!$B$9,SUMIFS(季度投融资!$D$149:$DT$149,季度投融资!$D$6:$DT$6,6),0) -> 0 | K79: =IF(7<=核心参数输入!$B$9,SUMIFS(季度投融资!$D$149:$DT$149,季度投融资!$D$6:$DT$6,7),0) -> 0 | L79: =IF(8<=核心参数输入!$B$9,SUMIFS(季度投融资!$D$149:$DT$149,季度投融资!$D$6:$DT$6,8),0) -> 0 | M79: =IF(9<=核心参数输入!$B$9,SUMIFS(季度投融资!$D$149:$DT$149,季度投融资!$D$6:$DT$6,9),0) -> 0 | N79: =IF(10<=核心参数输入!$B$9,SUMIFS(季度投融资!$D$149:$DT$149,季度投融资!$D$6:$DT$6,10),0) -> 0 | O79: =IF(11<=核心参数输入!$B$9,SUMIFS(季度投融资!$D$149:$DT$149,季度投融资!$D$6:$DT$6,11),0) -> 0 | P79: =IF(12<=核心参数输入!$B$9,SUMIFS(季度投融资!$D$149:$DT$149,季度投融资!$D$6:$DT$6,12),0) -> 0 | Q79: =IF(13<=核心参数输入!$B$9,SUMIFS(季度投融资!$D$149:$DT$149,季度投融资!$D$6:$DT$6,13),0) -> 0 | R79: =IF(14<=核心参数输入!$B$9,SUMIFS(季度投融资!$D$149:$DT$149,季度投融资!$D$6:$DT$6,14),0) -> 0 | S79: =IF(15<=核心参数输入!$B$9,SUMIFS(季度投融资!$D$149:$DT$149,季度投融资!$D$6:$DT$6,15),0) -> 0 | T79: =IF(16<=核心参数输入!$B$9,SUMIFS(季度投融资!$D$149:$DT$149,季度投融资!$D$6:$DT$6,16),0) -> 0 | U79: =IF(17<=核心参数输入!$B$9,SUMIFS(季度投融资!$D$149:$DT$149,季度投融资!$D$6:$DT$6,17),0) -> 0 | V79: =IF(18<=核心参数输入!$B$9,SUMIFS(季度投融资!$D$149:$DT$149,季度投融资!$D$6:$DT$6,18),0) -> 0 | W79: =IF(19<=核心参数输入!$B$9,SUMIFS(季度投融资!$D$149:$DT$149,季度投融资!$D$6:$DT$6,19),0) -> 0 | X79: =IF(20<=核心参数输入!$B$9,SUMIFS(季度投融资!$D$149:$DT$149,季度投融资!$D$6:$DT$6,20),0) -> 0 | Y79: =IF(21<=核心参数输入!$B$9,SUMIFS(季度投融资!$D$149:$DT$149,季度投融资!$D$6:$DT$6,21),0) -> 0 | Z79: =IF(22<=核心参数输入!$B$9,SUMIFS(季度投融资!$D$149:$DT$149,季度投融资!$D$6:$DT$6,22),0) -> 0 | AA79: =IF(23<=核心参数输入!$B$9,SUMIFS(季度投融资!$D$149:$DT$149,季度投融资!$D$6:$DT$6,23),0) -> 0 | AB79: =IF(24<=核心参数输入!$B$9,SUMIFS(季度投融资!$D$149:$DT$149,季度投融资!$D$6:$DT$6,24),0) -> 0 | AC79: =IF(25<=核心参数输入!$B$9,SUMIFS(季度投融资!$D$149:$DT$149,季度投融资!$D$6:$DT$6,25),0) -> 0 | AD79: =IF(26<=核心参数输入!$B$9,SUMIFS(季度投融资!$D$149:$DT$149,季度投融资!$D$6:$DT$6,26),0) -> 0 | AE79: =IF(27<=核心参数输入!$B$9,SUMIFS(季度投融资!$D$149:$DT$149,季度投融资!$D$6:$DT$6,27),0) -> 0 | AF79: =IF(28<=核心参数输入!$B$9,SUMIFS(季度投融资!$D$149:$DT$149,季度投融资!$D$6:$DT$6,28),0) -> 0 | AG79: =IF(29<=核心参数输入!$B$9,SUMIFS(季度投融资!$D$149:$DT$149,季度投融资!$D$6:$DT$6,29),0) -> 0 | AH79: =IF(30<=核心参数输入!$B$9,SUMIFS(季度投融资!$D$149:$DT$149,季度投融资!$D$6:$DT$6,30),0) -> 0
A80: 计划还本 | B80: 万元 | D80: =IF(0<=核心参数输入!$B$9,SUMIFS(季度投融资!$D$151:$DT$151,季度投融资!$D$6:$DT$6,0),0) -> 0 | E80: =IF(1<=核心参数输入!$B$9,SUMIFS(季度投融资!$D$151:$DT$151,季度投融资!$D$6:$DT$6,1),0) -> 0 | F80: =IF(2<=核心参数输入!$B$9,SUMIFS(季度投融资!$D$151:$DT$151,季度投融资!$D$6:$DT$6,2),0) -> 0 | G80: =IF(3<=核心参数输入!$B$9,SUMIFS(季度投融资!$D$151:$DT$151,季度投融资!$D$6:$DT$6,3),0) -> 0 | H80: =IF(4<=核心参数输入!$B$9,SUMIFS(季度投融资!$D$151:$DT$151,季度投融资!$D$6:$DT$6,4),0) -> 4285.7143 | I80: =IF(5<=核心参数输入!$B$9,SUMIFS(季度投融资!$D$151:$DT$151,季度投融资!$D$6:$DT$6,5),0) -> 4285.7143 | J80: =IF(6<=核心参数输入!$B$9,SUMIFS(季度投融资!$D$151:$DT$151,季度投融资!$D$6:$DT$6,6),0) -> 4285.7143 | K80: =IF(7<=核心参数输入!$B$9,SUMIFS(季度投融资!$D$151:$DT$151,季度投融资!$D$6:$DT$6,7),0) -> 4285.7143 | L80: =IF(8<=核心参数输入!$B$9,SUMIFS(季度投融资!$D$151:$DT$151,季度投融资!$D$6:$DT$6,8),0) -> 4285.7143 | M80: =IF(9<=核心参数输入!$B$9,SUMIFS(季度投融资!$D$151:$DT$151,季度投融资!$D$6:$DT$6,9),0) -> 4285.7143 | N80: =IF(10<=核心参数输入!$B$9,SUMIFS(季度投融资!$D$151:$DT$151,季度投融资!$D$6:$DT$6,10),0) -> 4285.7143 | O80: =IF(11<=核心参数输入!$B$9,SUMIFS(季度投融资!$D$151:$DT$151,季度投融资!$D$6:$DT$6,11),0) -> 0 | P80: =IF(12<=核心参数输入!$B$9,SUMIFS(季度投融资!$D$151:$DT$151,季度投融资!$D$6:$DT$6,12),0) -> 0 | Q80: =IF(13<=核心参数输入!$B$9,SUMIFS(季度投融资!$D$151:$DT$151,季度投融资!$D$6:$DT$6,13),0) -> 0 | R80: =IF(14<=核心参数输入!$B$9,SUMIFS(季度投融资!$D$151:$DT$151,季度投融资!$D$6:$DT$6,14),0) -> 0 | S80: =IF(15<=核心参数输入!$B$9,SUMIFS(季度投融资!$D$151:$DT$151,季度投融资!$D$6:$DT$6,15),0) -> 0 | T80: =IF(16<=核心参数输入!$B$9,SUMIFS(季度投融资!$D$151:$DT$151,季度投融资!$D$6:$DT$6,16),0) -> 0 | U80: =IF(17<=核心参数输入!$B$9,SUMIFS(季度投融资!$D$151:$DT$151,季度投融资!$D$6:$DT$6,17),0) -> 0 | V80: =IF(18<=核心参数输入!$B$9,SUMIFS(季度投融资!$D$151:$DT$151,季度投融资!$D$6:$DT$6,18),0) -> 0 | W80: =IF(19<=核心参数输入!$B$9,SUMIFS(季度投融资!$D$151:$DT$151,季度投融资!$D$6:$DT$6,19),0) -> 0 | X80: =IF(20<=核心参数输入!$B$9,SUMIFS(季度投融资!$D$151:$DT$151,季度投融资!$D$6:$DT$6,20),0) -> 0 | Y80: =IF(21<=核心参数输入!$B$9,SUMIFS(季度投融资!$D$151:$DT$151,季度投融资!$D$6:$DT$6,21),0) -> 0 | Z80: =IF(22<=核心参数输入!$B$9,SUMIFS(季度投融资!$D$151:$DT$151,季度投融资!$D$6:$DT$6,22),0) -> 0 | AA80: =IF(23<=核心参数输入!$B$9,SUMIFS(季度投融资!$D$151:$DT$151,季度投融资!$D$6:$DT$6,23),0) -> 0 | AB80: =IF(24<=核心参数输入!$B$9,SUMIFS(季度投融资!$D$151:$DT$151,季度投融资!$D$6:$DT$6,24),0) -> 0 | AC80: =IF(25<=核心参数输入!$B$9,SUMIFS(季度投融资!$D$151:$DT$151,季度投融资!$D$6:$DT$6,25),0) -> 0 | AD80: =IF(26<=核心参数输入!$B$9,SUMIFS(季度投融资!$D$151:$DT$151,季度投融资!$D$6:$DT$6,26),0) -> 0 | AE80: =IF(27<=核心参数输入!$B$9,SUMIFS(季度投融资!$D$151:$DT$151,季度投融资!$D$6:$DT$6,27),0) -> 0 | AF80: =IF(28<=核心参数输入!$B$9,SUMIFS(季度投融资!$D$151:$DT$151,季度投融资!$D$6:$DT$6,28),0) -> 0 | AG80: =IF(29<=核心参数输入!$B$9,SUMIFS(季度投融资!$D$151:$DT$151,季度投融资!$D$6:$DT$6,29),0) -> 0 | AH80: =IF(30<=核心参数输入!$B$9,SUMIFS(季度投融资!$D$151:$DT$151,季度投融资!$D$6:$DT$6,30),0) -> 0
A81: 全部利息现金 | B81: 万元 | D81: =IF(0<=核心参数输入!$B$9,SUMIFS(季度投融资!$D$152:$DT$152,季度投融资!$D$6:$DT$6,0),0) -> 0 | E81: =IF(1<=核心参数输入!$B$9,SUMIFS(季度投融资!$D$152:$DT$152,季度投融资!$D$6:$DT$6,1),0) -> 177.1875 | F81: =IF(2<=核心参数输入!$B$9,SUMIFS(季度投融资!$D$152:$DT$152,季度投融资!$D$6:$DT$6,2),0) -> 630 | G81: =IF(3<=核心参数输入!$B$9,SUMIFS(季度投融资!$D$152:$DT$152,季度投融资!$D$6:$DT$6,3),0) -> 1071 | H81: =IF(4<=核心参数输入!$B$9,SUMIFS(季度投融资!$D$152:$DT$152,季度投融资!$D$6:$DT$6,4),0) -> 1237.5 | I81: =IF(5<=核心参数输入!$B$9,SUMIFS(季度投融资!$D$152:$DT$152,季度投融资!$D$6:$DT$6,5),0) -> 1057.5 | J81: =IF(6<=核心参数输入!$B$9,SUMIFS(季度投融资!$D$152:$DT$152,季度投融资!$D$6:$DT$6,6),0) -> 877.5 | K81: =IF(7<=核心参数输入!$B$9,SUMIFS(季度投融资!$D$152:$DT$152,季度投融资!$D$6:$DT$6,7),0) -> 697.5 | L81: =IF(8<=核心参数输入!$B$9,SUMIFS(季度投融资!$D$152:$DT$152,季度投融资!$D$6:$DT$6,8),0) -> 517.5 | M81: =IF(9<=核心参数输入!$B$9,SUMIFS(季度投融资!$D$152:$DT$152,季度投融资!$D$6:$DT$6,9),0) -> 337.5 | N81: =IF(10<=核心参数输入!$B$9,SUMIFS(季度投融资!$D$152:$DT$152,季度投融资!$D$6:$DT$6,10),0) -> 157.5 | O81: =IF(11<=核心参数输入!$B$9,SUMIFS(季度投融资!$D$152:$DT$152,季度投融资!$D$6:$DT$6,11),0) -> 0 | P81: =IF(12<=核心参数输入!$B$9,SUMIFS(季度投融资!$D$152:$DT$152,季度投融资!$D$6:$DT$6,12),0) -> 0 | Q81: =IF(13<=核心参数输入!$B$9,SUMIFS(季度投融资!$D$152:$DT$152,季度投融资!$D$6:$DT$6,13),0) -> 0 | R81: =IF(14<=核心参数输入!$B$9,SUMIFS(季度投融资!$D$152:$DT$152,季度投融资!$D$6:$DT$6,14),0) -> 0 | S81: =IF(15<=核心参数输入!$B$9,SUMIFS(季度投融资!$D$152:$DT$152,季度投融资!$D$6:$DT$6,15),0) -> 0 | T81: =IF(16<=核心参数输入!$B$9,SUMIFS(季度投融资!$D$152:$DT$152,季度投融资!$D$6:$DT$6,16),0) -> 0 | U81: =IF(17<=核心参数输入!$B$9,SUMIFS(季度投融资!$D$152:$DT$152,季度投融资!$D$6:$DT$6,17),0) -> 0 | V81: =IF(18<=核心参数输入!$B$9,SUMIFS(季度投融资!$D$152:$DT$152,季度投融资!$D$6:$DT$6,18),0) -> 0 | W81: =IF(19<=核心参数输入!$B$9,SUMIFS(季度投融资!$D$152:$DT$152,季度投融资!$D$6:$DT$6,19),0) -> 0 | X81: =IF(20<=核心参数输入!$B$9,SUMIFS(季度投融资!$D$152:$DT$152,季度投融资!$D$6:$DT$6,20),0) -> 0 | Y81: =IF(21<=核心参数输入!$B$9,SUMIFS(季度投融资!$D$152:$DT$152,季度投融资!$D$6:$DT$6,21),0) -> 0 | Z81: =IF(22<=核心参数输入!$B$9,SUMIFS(季度投融资!$D$152:$DT$152,季度投融资!$D$6:$DT$6,22),0) -> 0 | AA81: =IF(23<=核心参数输入!$B$9,SUMIFS(季度投融资!$D$152:$DT$152,季度投融资!$D$6:$DT$6,23),0) -> 0 | AB81: =IF(24<=核心参数输入!$B$9,SUMIFS(季度投融资!$D$152:$DT$152,季度投融资!$D$6:$DT$6,24),0) -> 0 | AC81: =IF(25<=核心参数输入!$B$9,SUMIFS(季度投融资!$D$152:$DT$152,季度投融资!$D$6:$DT$6,25),0) -> 0 | AD81: =IF(26<=核心参数输入!$B$9,SUMIFS(季度投融资!$D$152:$DT$152,季度投融资!$D$6:$DT$6,26),0) -> 0 | AE81: =IF(27<=核心参数输入!$B$9,SUMIFS(季度投融资!$D$152:$DT$152,季度投融资!$D$6:$DT$6,27),0) -> 0 | AF81: =IF(28<=核心参数输入!$B$9,SUMIFS(季度投融资!$D$152:$DT$152,季度投融资!$D$6:$DT$6,28),0) -> 0 | AG81: =IF(29<=核心参数输入!$B$9,SUMIFS(季度投融资!$D$152:$DT$152,季度投融资!$D$6:$DT$6,29),0) -> 0 | AH81: =IF(30<=核心参数输入!$B$9,SUMIFS(季度投融资!$D$152:$DT$152,季度投融资!$D$6:$DT$6,30),0) -> 0
A82: 经营偿债现金CFADS | B82: 万元 | D82: =IF(0<=核心参数输入!$B$9,SUMIFS(季度现金流!$D$175:$DT$175,季度现金流!$D$6:$DT$6,0),0) -> 0 | E82: =IF(1<=核心参数输入!$B$9,SUMIFS(季度现金流!$D$175:$DT$175,季度现金流!$D$6:$DT$6,1),0) -> 0 | F82: =IF(2<=核心参数输入!$B$9,SUMIFS(季度现金流!$D$175:$DT$175,季度现金流!$D$6:$DT$6,2),0) -> 0 | G82: =IF(3<=核心参数输入!$B$9,SUMIFS(季度现金流!$D$175:$DT$175,季度现金流!$D$6:$DT$6,3),0) -> 0 | H82: =IF(4<=核心参数输入!$B$9,SUMIFS(季度现金流!$D$175:$DT$175,季度现金流!$D$6:$DT$6,4),0) -> 10367.016 | I82: =IF(5<=核心参数输入!$B$9,SUMIFS(季度现金流!$D$175:$DT$175,季度现金流!$D$6:$DT$6,5),0) -> 15385.785 | J82: =IF(6<=核心参数输入!$B$9,SUMIFS(季度现金流!$D$175:$DT$175,季度现金流!$D$6:$DT$6,6),0) -> 12437.96 | K82: =IF(7<=核心参数输入!$B$9,SUMIFS(季度现金流!$D$175:$DT$175,季度现金流!$D$6:$DT$6,7),0) -> 1620.2772 | L82: =IF(8<=核心参数输入!$B$9,SUMIFS(季度现金流!$D$175:$DT$175,季度现金流!$D$6:$DT$6,8),0) -> 713.30496 | M82: =IF(9<=核心参数输入!$B$9,SUMIFS(季度现金流!$D$175:$DT$175,季度现金流!$D$6:$DT$6,9),0) -> 727.50027 | N82: =IF(10<=核心参数输入!$B$9,SUMIFS(季度现金流!$D$175:$DT$175,季度现金流!$D$6:$DT$6,10),0) -> 739.45665 | O82: =IF(11<=核心参数输入!$B$9,SUMIFS(季度现金流!$D$175:$DT$175,季度现金流!$D$6:$DT$6,11),0) -> 751.55926 | P82: =IF(12<=核心参数输入!$B$9,SUMIFS(季度现金流!$D$175:$DT$175,季度现金流!$D$6:$DT$6,12),0) -> 763.80962 | Q82: =IF(13<=核心参数输入!$B$9,SUMIFS(季度现金流!$D$175:$DT$175,季度现金流!$D$6:$DT$6,13),0) -> 776.20927 | R82: =IF(14<=核心参数输入!$B$9,SUMIFS(季度现金流!$D$175:$DT$175,季度现金流!$D$6:$DT$6,14),0) -> 788.75977 | S82: =IF(15<=核心参数输入!$B$9,SUMIFS(季度现金流!$D$175:$DT$175,季度现金流!$D$6:$DT$6,15),0) -> 801.46268 | T82: =IF(16<=核心参数输入!$B$9,SUMIFS(季度现金流!$D$175:$DT$175,季度现金流!$D$6:$DT$6,16),0) -> 814.31956 | U82: =IF(17<=核心参数输入!$B$9,SUMIFS(季度现金流!$D$175:$DT$175,季度现金流!$D$6:$DT$6,17),0) -> 827.33199 | V82: =IF(18<=核心参数输入!$B$9,SUMIFS(季度现金流!$D$175:$DT$175,季度现金流!$D$6:$DT$6,18),0) -> 840.50156 | W82: =IF(19<=核心参数输入!$B$9,SUMIFS(季度现金流!$D$175:$DT$175,季度现金流!$D$6:$DT$6,19),0) -> 853.82986 | X82: =IF(20<=核心参数输入!$B$9,SUMIFS(季度现金流!$D$175:$DT$175,季度现金流!$D$6:$DT$6,20),0) -> 867.31851 | Y82: =IF(21<=核心参数输入!$B$9,SUMIFS(季度现金流!$D$175:$DT$175,季度现金流!$D$6:$DT$6,21),0) -> 0 | Z82: =IF(22<=核心参数输入!$B$9,SUMIFS(季度现金流!$D$175:$DT$175,季度现金流!$D$6:$DT$6,22),0) -> 0 | AA82: =IF(23<=核心参数输入!$B$9,SUMIFS(季度现金流!$D$175:$DT$175,季度现金流!$D$6:$DT$6,23),0) -> 0 | AB82: =IF(24<=核心参数输入!$B$9,SUMIFS(季度现金流!$D$175:$DT$175,季度现金流!$D$6:$DT$6,24),0) -> 0 | AC82: =IF(25<=核心参数输入!$B$9,SUMIFS(季度现金流!$D$175:$DT$175,季度现金流!$D$6:$DT$6,25),0) -> 0 | AD82: =IF(26<=核心参数输入!$B$9,SUMIFS(季度现金流!$D$175:$DT$175,季度现金流!$D$6:$DT$6,26),0) -> 0 | AE82: =IF(27<=核心参数输入!$B$9,SUMIFS(季度现金流!$D$175:$DT$175,季度现金流!$D$6:$DT$6,27),0) -> 0 | AF82: =IF(28<=核心参数输入!$B$9,SUMIFS(季度现金流!$D$175:$DT$175,季度现金流!$D$6:$DT$6,28),0) -> 0 | AG82: =IF(29<=核心参数输入!$B$9,SUMIFS(季度现金流!$D$175:$DT$175,季度现金流!$D$6:$DT$6,29),0) -> 0 | AH82: =IF(30<=核心参数输入!$B$9,SUMIFS(季度现金流!$D$175:$DT$175,季度现金流!$D$6:$DT$6,30),0) -> 0
A83: 合同本息 | B83: 万元 | D83: =IF(0<=核心参数输入!$B$9,SUMIFS(季度投融资!$D$156:$DT$156,季度投融资!$D$6:$DT$6,0),0) -> 0 | E83: =IF(1<=核心参数输入!$B$9,SUMIFS(季度投融资!$D$156:$DT$156,季度投融资!$D$6:$DT$6,1),0) -> 177.1875 | F83: =IF(2<=核心参数输入!$B$9,SUMIFS(季度投融资!$D$156:$DT$156,季度投融资!$D$6:$DT$6,2),0) -> 630 | G83: =IF(3<=核心参数输入!$B$9,SUMIFS(季度投融资!$D$156:$DT$156,季度投融资!$D$6:$DT$6,3),0) -> 1071 | H83: =IF(4<=核心参数输入!$B$9,SUMIFS(季度投融资!$D$156:$DT$156,季度投融资!$D$6:$DT$6,4),0) -> 5523.2143 | I83: =IF(5<=核心参数输入!$B$9,SUMIFS(季度投融资!$D$156:$DT$156,季度投融资!$D$6:$DT$6,5),0) -> 5343.2143 | J83: =IF(6<=核心参数输入!$B$9,SUMIFS(季度投融资!$D$156:$DT$156,季度投融资!$D$6:$DT$6,6),0) -> 5163.2143 | K83: =IF(7<=核心参数输入!$B$9,SUMIFS(季度投融资!$D$156:$DT$156,季度投融资!$D$6:$DT$6,7),0) -> 4983.2143 | L83: =IF(8<=核心参数输入!$B$9,SUMIFS(季度投融资!$D$156:$DT$156,季度投融资!$D$6:$DT$6,8),0) -> 4803.2143 | M83: =IF(9<=核心参数输入!$B$9,SUMIFS(季度投融资!$D$156:$DT$156,季度投融资!$D$6:$DT$6,9),0) -> 4623.2143 | N83: =IF(10<=核心参数输入!$B$9,SUMIFS(季度投融资!$D$156:$DT$156,季度投融资!$D$6:$DT$6,10),0) -> 4443.2143 | O83: =IF(11<=核心参数输入!$B$9,SUMIFS(季度投融资!$D$156:$DT$156,季度投融资!$D$6:$DT$6,11),0) -> 0 | P83: =IF(12<=核心参数输入!$B$9,SUMIFS(季度投融资!$D$156:$DT$156,季度投融资!$D$6:$DT$6,12),0) -> 0 | Q83: =IF(13<=核心参数输入!$B$9,SUMIFS(季度投融资!$D$156:$DT$156,季度投融资!$D$6:$DT$6,13),0) -> 0 | R83: =IF(14<=核心参数输入!$B$9,SUMIFS(季度投融资!$D$156:$DT$156,季度投融资!$D$6:$DT$6,14),0) -> 0 | S83: =IF(15<=核心参数输入!$B$9,SUMIFS(季度投融资!$D$156:$DT$156,季度投融资!$D$6:$DT$6,15),0) -> 0 | T83: =IF(16<=核心参数输入!$B$9,SUMIFS(季度投融资!$D$156:$DT$156,季度投融资!$D$6:$DT$6,16),0) -> 0 | U83: =IF(17<=核心参数输入!$B$9,SUMIFS(季度投融资!$D$156:$DT$156,季度投融资!$D$6:$DT$6,17),0) -> 0 | V83: =IF(18<=核心参数输入!$B$9,SUMIFS(季度投融资!$D$156:$DT$156,季度投融资!$D$6:$DT$6,18),0) -> 0 | W83: =IF(19<=核心参数输入!$B$9,SUMIFS(季度投融资!$D$156:$DT$156,季度投融资!$D$6:$DT$6,19),0) -> 0 | X83: =IF(20<=核心参数输入!$B$9,SUMIFS(季度投融资!$D$156:$DT$156,季度投融资!$D$6:$DT$6,20),0) -> 0 | Y83: =IF(21<=核心参数输入!$B$9,SUMIFS(季度投融资!$D$156:$DT$156,季度投融资!$D$6:$DT$6,21),0) -> 0 | Z83: =IF(22<=核心参数输入!$B$9,SUMIFS(季度投融资!$D$156:$DT$156,季度投融资!$D$6:$DT$6,22),0) -> 0 | AA83: =IF(23<=核心参数输入!$B$9,SUMIFS(季度投融资!$D$156:$DT$156,季度投融资!$D$6:$DT$6,23),0) -> 0 | AB83: =IF(24<=核心参数输入!$B$9,SUMIFS(季度投融资!$D$156:$DT$156,季度投融资!$D$6:$DT$6,24),0) -> 0 | AC83: =IF(25<=核心参数输入!$B$9,SUMIFS(季度投融资!$D$156:$DT$156,季度投融资!$D$6:$DT$6,25),0) -> 0 | AD83: =IF(26<=核心参数输入!$B$9,SUMIFS(季度投融资!$D$156:$DT$156,季度投融资!$D$6:$DT$6,26),0) -> 0 | AE83: =IF(27<=核心参数输入!$B$9,SUMIFS(季度投融资!$D$156:$DT$156,季度投融资!$D$6:$DT$6,27),0) -> 0 | AF83: =IF(28<=核心参数输入!$B$9,SUMIFS(季度投融资!$D$156:$DT$156,季度投融资!$D$6:$DT$6,28),0) -> 0 | AG83: =IF(29<=核心参数输入!$B$9,SUMIFS(季度投融资!$D$156:$DT$156,季度投融资!$D$6:$DT$6,29),0) -> 0 | AH83: =IF(30<=核心参数输入!$B$9,SUMIFS(季度投融资!$D$156:$DT$156,季度投融资!$D$6:$DT$6,30),0) -> 0
A84: 年度经营DSCR | B84: 倍 | D84: =IF(0<=核心参数输入!$B$9,IF(AND(0*4>核心参数输入!$B$16*4+核心参数输入!$B$148+核心参数输入!$B$124,D83>0.000001),D82/D83,""),"") | E84: =IF(1<=核心参数输入!$B$9,IF(AND(1*4>核心参数输入!$B$16*4+核心参数输入!$B$148+核心参数输入!$B$124,E83>0.000001),E82/E83,""),"") | F84: =IF(2<=核心参数输入!$B$9,IF(AND(2*4>核心参数输入!$B$16*4+核心参数输入!$B$148+核心参数输入!$B$124,F83>0.000001),F82/F83,""),"") | G84: =IF(3<=核心参数输入!$B$9,IF(AND(3*4>核心参数输入!$B$16*4+核心参数输入!$B$148+核心参数输入!$B$124,G83>0.000001),G82/G83,""),"") | H84: =IF(4<=核心参数输入!$B$9,IF(AND(4*4>核心参数输入!$B$16*4+核心参数输入!$B$148+核心参数输入!$B$124,H83>0.000001),H82/H83,""),"") -> 1.8769897 | I84: =IF(5<=核心参数输入!$B$9,IF(AND(5*4>核心参数输入!$B$16*4+核心参数输入!$B$148+核心参数输入!$B$124,I83>0.000001),I82/I83,""),"") -> 2.8794999 | J84: =IF(6<=核心参数输入!$B$9,IF(AND(6*4>核心参数输入!$B$16*4+核心参数输入!$B$148+核心参数输入!$B$124,J83>0.000001),J82/J83,""),"") -> 2.4089568 | K84: =IF(7<=核心参数输入!$B$9,IF(AND(7*4>核心参数输入!$B$16*4+核心参数输入!$B$148+核心参数输入!$B$124,K83>0.000001),K82/K83,""),"") -> 0.32514701 | L84: =IF(8<=核心参数输入!$B$9,IF(AND(8*4>核心参数输入!$B$16*4+核心参数输入!$B$148+核心参数输入!$B$124,L83>0.000001),L82/L83,""),"") -> 0.14850575 | M84: =IF(9<=核心参数输入!$B$9,IF(AND(9*4>核心参数输入!$B$16*4+核心参数输入!$B$148+核心参数输入!$B$124,M83>0.000001),M82/M83,""),"") -> 0.15735811 | N84: =IF(10<=核心参数输入!$B$9,IF(AND(10*4>核心参数输入!$B$16*4+核心参数输入!$B$148+核心参数输入!$B$124,N83>0.000001),N82/N83,""),"") -> 0.16642381 | O84: =IF(11<=核心参数输入!$B$9,IF(AND(11*4>核心参数输入!$B$16*4+核心参数输入!$B$148+核心参数输入!$B$124,O83>0.000001),O82/O83,""),"") | P84: =IF(12<=核心参数输入!$B$9,IF(AND(12*4>核心参数输入!$B$16*4+核心参数输入!$B$148+核心参数输入!$B$124,P83>0.000001),P82/P83,""),"") | Q84: =IF(13<=核心参数输入!$B$9,IF(AND(13*4>核心参数输入!$B$16*4+核心参数输入!$B$148+核心参数输入!$B$124,Q83>0.000001),Q82/Q83,""),"") | R84: =IF(14<=核心参数输入!$B$9,IF(AND(14*4>核心参数输入!$B$16*4+核心参数输入!$B$148+核心参数输入!$B$124,R83>0.000001),R82/R83,""),"") | S84: =IF(15<=核心参数输入!$B$9,IF(AND(15*4>核心参数输入!$B$16*4+核心参数输入!$B$148+核心参数输入!$B$124,S83>0.000001),S82/S83,""),"") | T84: =IF(16<=核心参数输入!$B$9,IF(AND(16*4>核心参数输入!$B$16*4+核心参数输入!$B$148+核心参数输入!$B$124,T83>0.000001),T82/T83,""),"") | U84: =IF(17<=核心参数输入!$B$9,IF(AND(17*4>核心参数输入!$B$16*4+核心参数输入!$B$148+核心参数输入!$B$124,U83>0.000001),U82/U83,""),"") | V84: =IF(18<=核心参数输入!$B$9,IF(AND(18*4>核心参数输入!$B$16*4+核心参数输入!$B$148+核心参数输入!$B$124,V83>0.000001),V82/V83,""),"") | W84: =IF(19<=核心参数输入!$B$9,IF(AND(19*4>核心参数输入!$B$16*4+核心参数输入!$B$148+核心参数输入!$B$124,W83>0.000001),W82/W83,""),"") | X84: =IF(20<=核心参数输入!$B$9,IF(AND(20*4>核心参数输入!$B$16*4+核心参数输入!$B$148+核心参数输入!$B$124,X83>0.000001),X82/X83,""),"") | Y84: =IF(21<=核心参数输入!$B$9,IF(AND(21*4>核心参数输入!$B$16*4+核心参数输入!$B$148+核心参数输入!$B$124,Y83>0.000001),Y82/Y83,""),"") | Z84: =IF(22<=核心参数输入!$B$9,IF(AND(22*4>核心参数输入!$B$16*4+核心参数输入!$B$148+核心参数输入!$B$124,Z83>0.000001),Z82/Z83,""),"") | AA84: =IF(23<=核心参数输入!$B$9,IF(AND(23*4>核心参数输入!$B$16*4+核心参数输入!$B$148+核心参数输入!$B$124,AA83>0.000001),AA82/AA83,""),"") | AB84: =IF(24<=核心参数输入!$B$9,IF(AND(24*4>核心参数输入!$B$16*4+核心参数输入!$B$148+核心参数输入!$B$124,AB83>0.000001),AB82/AB83,""),"") | AC84: =IF(25<=核心参数输入!$B$9,IF(AND(25*4>核心参数输入!$B$16*4+核心参数输入!$B$148+核心参数输入!$B$124,AC83>0.000001),AC82/AC83,""),"") | AD84: =IF(26<=核心参数输入!$B$9,IF(AND(26*4>核心参数输入!$B$16*4+核心参数输入!$B$148+核心参数输入!$B$124,AD83>0.000001),AD82/AD83,""),"") | AE84: =IF(27<=核心参数输入!$B$9,IF(AND(27*4>核心参数输入!$B$16*4+核心参数输入!$B$148+核心参数输入!$B$124,AE83>0.000001),AE82/AE83,""),"") | AF84: =IF(28<=核心参数输入!$B$9,IF(AND(28*4>核心参数输入!$B$16*4+核心参数输入!$B$148+核心参数输入!$B$124,AF83>0.000001),AF82/AF83,""),"") | AG84: =IF(29<=核心参数输入!$B$9,IF(AND(29*4>核心参数输入!$B$16*4+核心参数输入!$B$148+核心参数输入!$B$124,AG83>0.000001),AG82/AG83,""),"") | AH84: =IF(30<=核心参数输入!$B$9,IF(AND(30*4>核心参数输入!$B$16*4+核心参数输入!$B$148+核心参数输入!$B$124,AH83>0.000001),AH82/AH83,""),"")
A85: 项目投资现金流 | B85: 万元 | D85: =IF(0<=核心参数输入!$B$9,SUMIFS(季度现金流!$D$155:$DT$155,季度现金流!$D$6:$DT$6,0),0) -> -8000 | E85: =IF(1<=核心参数输入!$B$9,SUMIFS(季度现金流!$D$155:$DT$155,季度现金流!$D$6:$DT$6,1),0) -> -17463.6 | F85: =IF(2<=核心参数输入!$B$9,SUMIFS(季度现金流!$D$155:$DT$155,季度现金流!$D$6:$DT$6,2),0) -> -23284.8 | G85: =IF(3<=核心参数输入!$B$9,SUMIFS(季度现金流!$D$155:$DT$155,季度现金流!$D$6:$DT$6,3),0) -> -17463.6 | H85: =IF(4<=核心参数输入!$B$9,SUMIFS(季度现金流!$D$155:$DT$155,季度现金流!$D$6:$DT$6,4),0) -> 9867.0164 | I85: =IF(5<=核心参数输入!$B$9,SUMIFS(季度现金流!$D$155:$DT$155,季度现金流!$D$6:$DT$6,5),0) -> 15385.785 | J85: =IF(6<=核心参数输入!$B$9,SUMIFS(季度现金流!$D$155:$DT$155,季度现金流!$D$6:$DT$6,6),0) -> 12426.231 | K85: =IF(7<=核心参数输入!$B$9,SUMIFS(季度现金流!$D$155:$DT$155,季度现金流!$D$6:$DT$6,7),0) -> 1620.2772 | L85: =IF(8<=核心参数输入!$B$9,SUMIFS(季度现金流!$D$155:$DT$155,季度现金流!$D$6:$DT$6,8),0) -> 713.30496 | M85: =IF(9<=核心参数输入!$B$9,SUMIFS(季度现金流!$D$155:$DT$155,季度现金流!$D$6:$DT$6,9),0) -> 727.50027 | N85: =IF(10<=核心参数输入!$B$9,SUMIFS(季度现金流!$D$155:$DT$155,季度现金流!$D$6:$DT$6,10),0) -> 739.45665 | O85: =IF(11<=核心参数输入!$B$9,SUMIFS(季度现金流!$D$155:$DT$155,季度现金流!$D$6:$DT$6,11),0) -> 751.55926 | P85: =IF(12<=核心参数输入!$B$9,SUMIFS(季度现金流!$D$155:$DT$155,季度现金流!$D$6:$DT$6,12),0) -> 763.80962 | Q85: =IF(13<=核心参数输入!$B$9,SUMIFS(季度现金流!$D$155:$DT$155,季度现金流!$D$6:$DT$6,13),0) -> 776.20927 | R85: =IF(14<=核心参数输入!$B$9,SUMIFS(季度现金流!$D$155:$DT$155,季度现金流!$D$6:$DT$6,14),0) -> 788.75977 | S85: =IF(15<=核心参数输入!$B$9,SUMIFS(季度现金流!$D$155:$DT$155,季度现金流!$D$6:$DT$6,15),0) -> 801.46268 | T85: =IF(16<=核心参数输入!$B$9,SUMIFS(季度现金流!$D$155:$DT$155,季度现金流!$D$6:$DT$6,16),0) -> 814.31956 | U85: =IF(17<=核心参数输入!$B$9,SUMIFS(季度现金流!$D$155:$DT$155,季度现金流!$D$6:$DT$6,17),0) -> 827.33199 | V85: =IF(18<=核心参数输入!$B$9,SUMIFS(季度现金流!$D$155:$DT$155,季度现金流!$D$6:$DT$6,18),0) -> 840.50156 | W85: =IF(19<=核心参数输入!$B$9,SUMIFS(季度现金流!$D$155:$DT$155,季度现金流!$D$6:$DT$6,19),0) -> 853.82986 | X85: =IF(20<=核心参数输入!$B$9,SUMIFS(季度现金流!$D$155:$DT$155,季度现金流!$D$6:$DT$6,20),0) -> 867.31851 | Y85: =IF(21<=核心参数输入!$B$9,SUMIFS(季度现金流!$D$155:$DT$155,季度现金流!$D$6:$DT$6,21),0) -> 0 | Z85: =IF(22<=核心参数输入!$B$9,SUMIFS(季度现金流!$D$155:$DT$155,季度现金流!$D$6:$DT$6,22),0) -> 0 | AA85: =IF(23<=核心参数输入!$B$9,SUMIFS(季度现金流!$D$155:$DT$155,季度现金流!$D$6:$DT$6,23),0) -> 0 | AB85: =IF(24<=核心参数输入!$B$9,SUMIFS(季度现金流!$D$155:$DT$155,季度现金流!$D$6:$DT$6,24),0) -> 0 | AC85: =IF(25<=核心参数输入!$B$9,SUMIFS(季度现金流!$D$155:$DT$155,季度现金流!$D$6:$DT$6,25),0) -> 0 | AD85: =IF(26<=核心参数输入!$B$9,SUMIFS(季度现金流!$D$155:$DT$155,季度现金流!$D$6:$DT$6,26),0) -> 0 | AE85: =IF(27<=核心参数输入!$B$9,SUMIFS(季度现金流!$D$155:$DT$155,季度现金流!$D$6:$DT$6,27),0) -> 0 | AF85: =IF(28<=核心参数输入!$B$9,SUMIFS(季度现金流!$D$155:$DT$155,季度现金流!$D$6:$DT$6,28),0) -> 0 | AG85: =IF(29<=核心参数输入!$B$9,SUMIFS(季度现金流!$D$155:$DT$155,季度现金流!$D$6:$DT$6,29),0) -> 0 | AH85: =IF(30<=核心参数输入!$B$9,SUMIFS(季度现金流!$D$155:$DT$155,季度现金流!$D$6:$DT$6,30),0) -> 0
A86: 资本金现金流（完整出资） | B86: 万元 | D86: =IF(0<=核心参数输入!$B$9,SUMIFS(季度现金流!$D$157:$DT$157,季度现金流!$D$6:$DT$6,0),0) -> -8000 | E86: =IF(1<=核心参数输入!$B$9,SUMIFS(季度现金流!$D$157:$DT$157,季度现金流!$D$6:$DT$6,1),0) -> -8652.6 | F86: =IF(2<=核心参数输入!$B$9,SUMIFS(季度现金流!$D$157:$DT$157,季度现金流!$D$6:$DT$6,2),0) -> -11914.8 | G86: =IF(3<=核心参数输入!$B$9,SUMIFS(季度现金流!$D$157:$DT$157,季度现金流!$D$6:$DT$6,3),0) -> -9534.6 | H86: =IF(4<=核心参数输入!$B$9,SUMIFS(季度现金流!$D$157:$DT$157,季度现金流!$D$6:$DT$6,4),0) -> 4343.8021 | I86: =IF(5<=核心参数输入!$B$9,SUMIFS(季度现金流!$D$157:$DT$157,季度现金流!$D$6:$DT$6,5),0) -> 2264.9985 | J86: =IF(6<=核心参数输入!$B$9,SUMIFS(季度现金流!$D$157:$DT$157,季度现金流!$D$6:$DT$6,6),0) -> 0 | K86: =IF(7<=核心参数输入!$B$9,SUMIFS(季度现金流!$D$157:$DT$157,季度现金流!$D$6:$DT$6,7),0) -> 0 | L86: =IF(8<=核心参数输入!$B$9,SUMIFS(季度现金流!$D$157:$DT$157,季度现金流!$D$6:$DT$6,8),0) -> 0 | M86: =IF(9<=核心参数输入!$B$9,SUMIFS(季度现金流!$D$157:$DT$157,季度现金流!$D$6:$DT$6,9),0) -> 0 | N86: =IF(10<=核心参数输入!$B$9,SUMIFS(季度现金流!$D$157:$DT$157,季度现金流!$D$6:$DT$6,10),0) -> 0 | O86: =IF(11<=核心参数输入!$B$9,SUMIFS(季度现金流!$D$157:$DT$157,季度现金流!$D$6:$DT$6,11),0) -> 751.55926 | P86: =IF(12<=核心参数输入!$B$9,SUMIFS(季度现金流!$D$157:$DT$157,季度现金流!$D$6:$DT$6,12),0) -> 763.80962 | Q86: =IF(13<=核心参数输入!$B$9,SUMIFS(季度现金流!$D$157:$DT$157,季度现金流!$D$6:$DT$6,13),0) -> 776.20927 | R86: =IF(14<=核心参数输入!$B$9,SUMIFS(季度现金流!$D$157:$DT$157,季度现金流!$D$6:$DT$6,14),0) -> 788.75977 | S86: =IF(15<=核心参数输入!$B$9,SUMIFS(季度现金流!$D$157:$DT$157,季度现金流!$D$6:$DT$6,15),0) -> 801.46268 | T86: =IF(16<=核心参数输入!$B$9,SUMIFS(季度现金流!$D$157:$DT$157,季度现金流!$D$6:$DT$6,16),0) -> 814.31956 | U86: =IF(17<=核心参数输入!$B$9,SUMIFS(季度现金流!$D$157:$DT$157,季度现金流!$D$6:$DT$6,17),0) -> 827.33199 | V86: =IF(18<=核心参数输入!$B$9,SUMIFS(季度现金流!$D$157:$DT$157,季度现金流!$D$6:$DT$6,18),0) -> 840.50156 | W86: =IF(19<=核心参数输入!$B$9,SUMIFS(季度现金流!$D$157:$DT$157,季度现金流!$D$6:$DT$6,19),0) -> 853.82986 | X86: =IF(20<=核心参数输入!$B$9,SUMIFS(季度现金流!$D$157:$DT$157,季度现金流!$D$6:$DT$6,20),0) -> 867.31851 | Y86: =IF(21<=核心参数输入!$B$9,SUMIFS(季度现金流!$D$157:$DT$157,季度现金流!$D$6:$DT$6,21),0) -> 0 | Z86: =IF(22<=核心参数输入!$B$9,SUMIFS(季度现金流!$D$157:$DT$157,季度现金流!$D$6:$DT$6,22),0) -> 0 | AA86: =IF(23<=核心参数输入!$B$9,SUMIFS(季度现金流!$D$157:$DT$157,季度现金流!$D$6:$DT$6,23),0) -> 0 | AB86: =IF(24<=核心参数输入!$B$9,SUMIFS(季度现金流!$D$157:$DT$157,季度现金流!$D$6:$DT$6,24),0) -> 0 | AC86: =IF(25<=核心参数输入!$B$9,SUMIFS(季度现金流!$D$157:$DT$157,季度现金流!$D$6:$DT$6,25),0) -> 0 | AD86: =IF(26<=核心参数输入!$B$9,SUMIFS(季度现金流!$D$157:$DT$157,季度现金流!$D$6:$DT$6,26),0) -> 0 | AE86: =IF(27<=核心参数输入!$B$9,SUMIFS(季度现金流!$D$157:$DT$157,季度现金流!$D$6:$DT$6,27),0) -> 0 | AF86: =IF(28<=核心参数输入!$B$9,SUMIFS(季度现金流!$D$157:$DT$157,季度现金流!$D$6:$DT$6,28),0) -> 0 | AG86: =IF(29<=核心参数输入!$B$9,SUMIFS(季度现金流!$D$157:$DT$157,季度现金流!$D$6:$DT$6,29),0) -> 0 | AH86: =IF(30<=核心参数输入!$B$9,SUMIFS(季度现金流!$D$157:$DT$157,季度现金流!$D$6:$DT$6,30),0) -> 0
A87: 所需股东投入 | B87: 万元 | D87: =IF(0<=核心参数输入!$B$9,SUMIFS(季度现金流!$D$159:$DT$159,季度现金流!$D$6:$DT$6,0),0) -> 8000 | E87: =IF(1<=核心参数输入!$B$9,SUMIFS(季度现金流!$D$159:$DT$159,季度现金流!$D$6:$DT$6,1),0) -> 8652.6 | F87: =IF(2<=核心参数输入!$B$9,SUMIFS(季度现金流!$D$159:$DT$159,季度现金流!$D$6:$DT$6,2),0) -> 11914.8 | G87: =IF(3<=核心参数输入!$B$9,SUMIFS(季度现金流!$D$159:$DT$159,季度现金流!$D$6:$DT$6,3),0) -> 9534.6 | H87: =IF(4<=核心参数输入!$B$9,SUMIFS(季度现金流!$D$159:$DT$159,季度现金流!$D$6:$DT$6,4),0) -> 0 | I87: =IF(5<=核心参数输入!$B$9,SUMIFS(季度现金流!$D$159:$DT$159,季度现金流!$D$6:$DT$6,5),0) -> 0 | J87: =IF(6<=核心参数输入!$B$9,SUMIFS(季度现金流!$D$159:$DT$159,季度现金流!$D$6:$DT$6,6),0) -> 0 | K87: =IF(7<=核心参数输入!$B$9,SUMIFS(季度现金流!$D$159:$DT$159,季度现金流!$D$6:$DT$6,7),0) -> 0 | L87: =IF(8<=核心参数输入!$B$9,SUMIFS(季度现金流!$D$159:$DT$159,季度现金流!$D$6:$DT$6,8),0) -> 0 | M87: =IF(9<=核心参数输入!$B$9,SUMIFS(季度现金流!$D$159:$DT$159,季度现金流!$D$6:$DT$6,9),0) -> 0 | N87: =IF(10<=核心参数输入!$B$9,SUMIFS(季度现金流!$D$159:$DT$159,季度现金流!$D$6:$DT$6,10),0) -> 0 | O87: =IF(11<=核心参数输入!$B$9,SUMIFS(季度现金流!$D$159:$DT$159,季度现金流!$D$6:$DT$6,11),0) -> 0 | P87: =IF(12<=核心参数输入!$B$9,SUMIFS(季度现金流!$D$159:$DT$159,季度现金流!$D$6:$DT$6,12),0) -> 0 | Q87: =IF(13<=核心参数输入!$B$9,SUMIFS(季度现金流!$D$159:$DT$159,季度现金流!$D$6:$DT$6,13),0) -> 0 | R87: =IF(14<=核心参数输入!$B$9,SUMIFS(季度现金流!$D$159:$DT$159,季度现金流!$D$6:$DT$6,14),0) -> 0 | S87: =IF(15<=核心参数输入!$B$9,SUMIFS(季度现金流!$D$159:$DT$159,季度现金流!$D$6:$DT$6,15),0) -> 0 | T87: =IF(16<=核心参数输入!$B$9,SUMIFS(季度现金流!$D$159:$DT$159,季度现金流!$D$6:$DT$6,16),0) -> 0 | U87: =IF(17<=核心参数输入!$B$9,SUMIFS(季度现金流!$D$159:$DT$159,季度现金流!$D$6:$DT$6,17),0) -> 0 | V87: =IF(18<=核心参数输入!$B$9,SUMIFS(季度现金流!$D$159:$DT$159,季度现金流!$D$6:$DT$6,18),0) -> 0 | W87: =IF(19<=核心参数输入!$B$9,SUMIFS(季度现金流!$D$159:$DT$159,季度现金流!$D$6:$DT$6,19),0) -> 0 | X87: =IF(20<=核心参数输入!$B$9,SUMIFS(季度现金流!$D$159:$DT$159,季度现金流!$D$6:$DT$6,20),0) -> 0 | Y87: =IF(21<=核心参数输入!$B$9,SUMIFS(季度现金流!$D$159:$DT$159,季度现金流!$D$6:$DT$6,21),0) -> 0 | Z87: =IF(22<=核心参数输入!$B$9,SUMIFS(季度现金流!$D$159:$DT$159,季度现金流!$D$6:$DT$6,22),0) -> 0 | AA87: =IF(23<=核心参数输入!$B$9,SUMIFS(季度现金流!$D$159:$DT$159,季度现金流!$D$6:$DT$6,23),0) -> 0 | AB87: =IF(24<=核心参数输入!$B$9,SUMIFS(季度现金流!$D$159:$DT$159,季度现金流!$D$6:$DT$6,24),0) -> 0 | AC87: =IF(25<=核心参数输入!$B$9,SUMIFS(季度现金流!$D$159:$DT$159,季度现金流!$D$6:$DT$6,25),0) -> 0 | AD87: =IF(26<=核心参数输入!$B$9,SUMIFS(季度现金流!$D$159:$DT$159,季度现金流!$D$6:$DT$6,26),0) -> 0 | AE87: =IF(27<=核心参数输入!$B$9,SUMIFS(季度现金流!$D$159:$DT$159,季度现金流!$D$6:$DT$6,27),0) -> 0 | AF87: =IF(28<=核心参数输入!$B$9,SUMIFS(季度现金流!$D$159:$DT$159,季度现金流!$D$6:$DT$6,28),0) -> 0 | AG87: =IF(29<=核心参数输入!$B$9,SUMIFS(季度现金流!$D$159:$DT$159,季度现金流!$D$6:$DT$6,29),0) -> 0 | AH87: =IF(30<=核心参数输入!$B$9,SUMIFS(季度现金流!$D$159:$DT$159,季度现金流!$D$6:$DT$6,30),0) -> 0
A88: 理论股东分配 | B88: 万元 | D88: =IF(0<=核心参数输入!$B$9,SUMIFS(季度现金流!$D$160:$DT$160,季度现金流!$D$6:$DT$6,0),0) -> 0 | E88: =IF(1<=核心参数输入!$B$9,SUMIFS(季度现金流!$D$160:$DT$160,季度现金流!$D$6:$DT$6,1),0) -> 0 | F88: =IF(2<=核心参数输入!$B$9,SUMIFS(季度现金流!$D$160:$DT$160,季度现金流!$D$6:$DT$6,2),0) -> 0 | G88: =IF(3<=核心参数输入!$B$9,SUMIFS(季度现金流!$D$160:$DT$160,季度现金流!$D$6:$DT$6,3),0) -> 0 | H88: =IF(4<=核心参数输入!$B$9,SUMIFS(季度现金流!$D$160:$DT$160,季度现金流!$D$6:$DT$6,4),0) -> 4343.8021 | I88: =IF(5<=核心参数输入!$B$9,SUMIFS(季度现金流!$D$160:$DT$160,季度现金流!$D$6:$DT$6,5),0) -> 2264.9985 | J88: =IF(6<=核心参数输入!$B$9,SUMIFS(季度现金流!$D$160:$DT$160,季度现金流!$D$6:$DT$6,6),0) -> 0 | K88: =IF(7<=核心参数输入!$B$9,SUMIFS(季度现金流!$D$160:$DT$160,季度现金流!$D$6:$DT$6,7),0) -> 0 | L88: =IF(8<=核心参数输入!$B$9,SUMIFS(季度现金流!$D$160:$DT$160,季度现金流!$D$6:$DT$6,8),0) -> 0 | M88: =IF(9<=核心参数输入!$B$9,SUMIFS(季度现金流!$D$160:$DT$160,季度现金流!$D$6:$DT$6,9),0) -> 0 | N88: =IF(10<=核心参数输入!$B$9,SUMIFS(季度现金流!$D$160:$DT$160,季度现金流!$D$6:$DT$6,10),0) -> 0 | O88: =IF(11<=核心参数输入!$B$9,SUMIFS(季度现金流!$D$160:$DT$160,季度现金流!$D$6:$DT$6,11),0) -> 751.55926 | P88: =IF(12<=核心参数输入!$B$9,SUMIFS(季度现金流!$D$160:$DT$160,季度现金流!$D$6:$DT$6,12),0) -> 763.80962 | Q88: =IF(13<=核心参数输入!$B$9,SUMIFS(季度现金流!$D$160:$DT$160,季度现金流!$D$6:$DT$6,13),0) -> 776.20927 | R88: =IF(14<=核心参数输入!$B$9,SUMIFS(季度现金流!$D$160:$DT$160,季度现金流!$D$6:$DT$6,14),0) -> 788.75977 | S88: =IF(15<=核心参数输入!$B$9,SUMIFS(季度现金流!$D$160:$DT$160,季度现金流!$D$6:$DT$6,15),0) -> 801.46268 | T88: =IF(16<=核心参数输入!$B$9,SUMIFS(季度现金流!$D$160:$DT$160,季度现金流!$D$6:$DT$6,16),0) -> 814.31956 | U88: =IF(17<=核心参数输入!$B$9,SUMIFS(季度现金流!$D$160:$DT$160,季度现金流!$D$6:$DT$6,17),0) -> 827.33199 | V88: =IF(18<=核心参数输入!$B$9,SUMIFS(季度现金流!$D$160:$DT$160,季度现金流!$D$6:$DT$6,18),0) -> 840.50156 | W88: =IF(19<=核心参数输入!$B$9,SUMIFS(季度现金流!$D$160:$DT$160,季度现金流!$D$6:$DT$6,19),0) -> 853.82986 | X88: =IF(20<=核心参数输入!$B$9,SUMIFS(季度现金流!$D$160:$DT$160,季度现金流!$D$6:$DT$6,20),0) -> 867.31851 | Y88: =IF(21<=核心参数输入!$B$9,SUMIFS(季度现金流!$D$160:$DT$160,季度现金流!$D$6:$DT$6,21),0) -> 0 | Z88: =IF(22<=核心参数输入!$B$9,SUMIFS(季度现金流!$D$160:$DT$160,季度现金流!$D$6:$DT$6,22),0) -> 0 | AA88: =IF(23<=核心参数输入!$B$9,SUMIFS(季度现金流!$D$160:$DT$160,季度现金流!$D$6:$DT$6,23),0) -> 0 | AB88: =IF(24<=核心参数输入!$B$9,SUMIFS(季度现金流!$D$160:$DT$160,季度现金流!$D$6:$DT$6,24),0) -> 0 | AC88: =IF(25<=核心参数输入!$B$9,SUMIFS(季度现金流!$D$160:$DT$160,季度现金流!$D$6:$DT$6,25),0) -> 0 | AD88: =IF(26<=核心参数输入!$B$9,SUMIFS(季度现金流!$D$160:$DT$160,季度现金流!$D$6:$DT$6,26),0) -> 0 | AE88: =IF(27<=核心参数输入!$B$9,SUMIFS(季度现金流!$D$160:$DT$160,季度现金流!$D$6:$DT$6,27),0) -> 0 | AF88: =IF(28<=核心参数输入!$B$9,SUMIFS(季度现金流!$D$160:$DT$160,季度现金流!$D$6:$DT$6,28),0) -> 0 | AG88: =IF(29<=核心参数输入!$B$9,SUMIFS(季度现金流!$D$160:$DT$160,季度现金流!$D$6:$DT$6,29),0) -> 0 | AH88: =IF(30<=核心参数输入!$B$9,SUMIFS(季度现金流!$D$160:$DT$160,季度现金流!$D$6:$DT$6,30),0) -> 0
